Workbook

Sheet MT.ROCK (PURCHASED & SF)
A2: DATE | B2: SERVICE FEES/DELIVERY | C2: GROSS AMOUNT BILLED | D2: NET OF VAT | F2: DATE | G2: INVOICES/DELIVERY | H2: GROSS AMOUNT BILLED | I2: NET OF VAT
A3: 44230 | B3: SI1125 | C3: =178716.38+21445.97 -> 200162.35 | D3: =C3/1.12 -> 178716.38 | F3: 44226 | G3: SI1125 | H3: =3574327.08+428919.25 -> 4003246.3 | I3: =H3/1.12 -> 3574327.1
A4: 44260 | B4: SI1148 | C4: =168569.96+20228.39 -> 188798.35 | D4: =C4/1.12 -> 168569.96 | F4: 44246 | G4: SI1148 | H4: =3371400.4+404568.04 -> 3775968.4 | I4: =H4/1.12 -> 3371400.4
A5: 44260 | B5: SI1140 | C5: =257303.97+30876.48 -> 288180.45 | D5: =C5/1.12 -> 257303.97 | F5: 44239 | G5: SI1140 | H5: =5146078.47+617592.42 -> 5763670.9 | I5: =H5/1.12 -> 5146134.7
A6: 44289 | B6: CI1166 | C6: =111814.51+13417.74 -> 125232.25 | D6: =C6/1.12 -> 111814.51 | F6: 44258 | G6: SI1166 | H6: 2236290 | I6: =H6/1.12 -> 1996687.5
A7: 44289 | B7: CI1179 | C7: =127662.01+15319.44 -> 142981.45 | D7: =C7/1.12 -> 127662.01 | F7: 44272 | G7: SI1179 | H7: =2553239.67+306388.76 -> 2859628.4 | I7: =H7/1.12 -> 2553239.7
A8: 44289 | B8: SI1176 | C8: =128845.04+15461.41 -> 144306.45 | D8: =C8/1.12 -> 128845.04 | F8: 44266 | G8: SI1176 | H8: =2576900.37+309228.04 -> 2886128.4 | I8: =H8/1.12 -> 2576900.4
A9: 44319 | B9: SI1203 | C9: =95812.66+11497.52 -> 107310.18 | D9: =C9/1.12 -> 95812.661 | F9: 44305 | G9: SI1203 | H9: =1916252.88+229950.35 -> 2146203.2 | I9: =H9/1.12 -> 1916252.9
A10: 44319 | B10: SI1187 | C10: =116967.26+14036.07 -> 131003.33 | D10: =C10/1.12 -> 116967.26 | F10: 44280 | G10: SI1187 | H10: =2339344.91+280721.39 -> 2620066.3 | I10: =H10/1.12 -> 2339344.9
A11: 44340 | B11: SI1232 | C11: =77569.29+9308.31 -> 86877.6 | D11: =C11/1.12 -> 77569.286 | F11: 44326 | G11: SI1232 | H11: =1551385.33+186166.24 -> 1737551.6 | I11: =H11/1.12 -> 1551385.3
A12: 44340 | B12: SI1211 | C12: =125946.99+15113.64 -> 141060.63 | D12: =C12/1.12 -> 125946.99 | F12: 44313 | G12: SI1211 | H12: =2518939.35+302272.73 -> 2821212.1 | I12: =H12/1.12 -> 2518939.4
A13: 44347 | B13: SI1238 | C13: =147525.67+17703.08 -> 165228.75 | D13: =C13/1.12 -> 147525.67 | F13: 44331 | G13: SI1238 | H13: =2842834.37+341140.13 -> 3183974.5 | I13: =H13/1.12 -> 2842834.4
A14: 44355 | B14: SI1245 | C14: =150070.31+18008.44 -> 168078.75 | D14: =C14/1.12 -> 150070.31 | F14: 44337 | G14: SI1245 | H14: =2678369.72+321404.37 -> 2999774.1 | I14: =H14/1.12 -> 2678369.7
A15: 44368 | B15: SI1257 | C15: =202801.65+24336.2 -> 227137.85 | D15: =C15/1.12 -> 202801.65 | F15: 44355 | G15: SI1257 | H15: =4056032.75+486723.93 -> 4542756.7 | I15: =H15/1.12 -> 4056032.7
A16: 44364 | B16: SI1256 | C16: 180327.25 | D16: =C16/1.12 -> 161006.47 | F16: 44350 | G16: SI1256 | H16: =3220130.69+386415.69 -> 3606546.4 | I16: =H16/1.12 -> 3220130.7
A17: 44385 | B17: SI1273/BS3 | C17: =102076.59+12249.19 -> 114325.78 | D17: =C17/1.12 -> 102076.59 | F17: 44372 | G17: SI1273 | H17: =2041529.94+244983.59 -> 2286513.5 | I17: =H17/1.12 -> 2041529.9
A18: 44393 | B18: SI1274/BS4 | C18: =81336.61+9760.39 -> 91097 | D18: =C18/1.12 -> 81336.607 | F18: 44379 | G18: SI274 | H18: =1626731.62+195207.8 -> 1821939.4 | I18: =H18/1.12 -> 1626731.6
A19: 44393 | B19: SI1285/BS7 | C19: =53792.32+6455.08 -> 60247.4 | D19: =C19/1.12 -> 53792.321 | F19: 44385 | G19: SI1285 | H19: =1075845.83+129101.5 -> 1204947.3 | I19: =H19/1.12 -> 1075845.8
A20: 44407 | B20: SI1300/BS12 | C20: =122184.73+14662.17 -> 136846.9 | D20: =C20/1.12 -> 122184.73 | F20: 44398 | G20: SI1300 | H20: =2443695.2+293243.42 -> 2736938.6 | I20: =H20/1.12 -> 2443695.2
A21: 44413 | B21: SI1308/BS16 | C21: =106722.44+12806.69 -> 119529.13 | D21: =C21/1.12 -> 106722.44 | F21: 44406 | G21: SI1308 | H21: =2134448.35+256133.8 -> 2390582.1 | I21: =H21/1.12 -> 2134448.3
A22: 44427 | B22: SI1322/BS18 | C22: =151117.62+18134.11 -> 169251.73 | D22: =C22/1.12 -> 151117.62 | F22: 44413 | G22: SI1322 | H22: =3022351.9+362682.23 -> 3385034.1 | I22: =H22/1.12 -> 3022351.9
A23: 44439 | B23: SI1340/BS24 | C23: =143693.3+17243.2 -> 160936.5 | D23: =C23/1.12 -> 143693.3 | F23: 44426 | G23: SI1340 | H23: =2873865.14+344863.82 -> 3218729 | I23: =H23/1.12 -> 2873865.1
A24: 44439 | B24: SI1327/BS20 | C24: =146455.58+17574.67 -> 164030.25 | D24: =C24/1.12 -> 146455.58 | F24: 44420 | G24: SI1327 | H24: =2929111.36+351493.37 -> 3280604.7 | I24: =H24/1.12 -> 2929111.4
A25: 44455 | B25: SI1351/BS31 | C25: =153671.54+18440.58 -> 172112.12 | D25: =C25/1.12 -> 153671.54 | F25: 44441 | G25: SI1351 | H25: =3073431.97+368811.84 -> 3442243.8 | I25: =H25/1.12 -> 3073432
A26: 44463 | B26: SI1369/BS37 | C26: =114479.13+13737.5 -> 128216.63 | D26: =C26/1.12 -> 114479.13 | F26: 44447 | G26: SI1369 | H26: =2289581.89+274749.82 -> 2564331.7 | I26: =H26/1.12 -> 2289581.9
A27: 44487 | B27: SI1392/BS48 | C27: =212107.71+25452.93 -> 237560.64 | D27: =C27/1.12 -> 212107.71 | F27: 44462 | G27: SI1392 | H27: =4242154.83+509058.59 -> 4751213.4 | I27: =H27/1.12 -> 4242154.8
A28: 44483 | B28: SI1398/BS50 | C28: =101471.3+12176.56 -> 113647.86 | D28: =C28/1.12 -> 101471.3 | F28: 44468 | G28: SI1398 | H28: =2029426.55+243531.19 -> 2272957.7 | I28: =H28/1.12 -> 2029426.6
A29: 44477 | B29: BS48 | C29: 237560.64 | D29: 212107.71
A30: 44494 | B30: SI1417/BS56 | C30: =154464.87+18535.78 -> 173000.65 | D30: =C30/1.12 -> 154464.87 | F30: 44476 | G30: SI1247 | H30: =3089296.45+370715.57 -> 3460012 | I30: =H30/1.12 -> 3089296.4
A31: 44510 | B31: SI1450/BS91 | C31: =84066.47+10087.98 -> 94154.45 | D31: =C31/1.12 -> 84066.473 | F31: 44496 | G31: SI1450 | H31: =1681329.5+201759.54 -> 1883089 | I31: =H31/1.12 -> 1681329.5
A32: 44522 | B32: SI1457/BS105 | C32: =75519.96+9062.4 -> 84582.36 | D32: =C32/1.12 -> 75519.964 | F32: 44511 | G32: SI1457 | H32: =1510399.12+181247.89 -> 1691647 | I32: =H32/1.12 -> 1510399.1
A33: 44539 | B33: SI1456/BS122 | C33: =60004.33+7200.52 -> 67204.85 | D33: =C33/1.12 -> 60004.33 | F33: 44530 | G33: SI1456 | H33: =1200086.62+144010.38 -> 1344097 | I33: =H33/1.12 -> 1200086.6
A34: 44561 | B34: SI1509/BS152 | C34: =61187.37+7342.48 -> 68529.85 | D34: =C34/1.12 -> 61187.366 | F34: 44543 | G34: SI1509 | H34: =1223747.37+146849.69 -> 1370597.1 | I34: =H34/1.12 -> 1223747.4
A35: 44561 | B35: SI1510/BS153 | C35: =61187.37+7342.48 -> 68529.85 | D35: =C35/1.12 -> 61187.366 | F35: 44551 | G35: SI1510 | H35: =1223747.37+146849.69 -> 1370597.1 | I35: =H35/1.12 -> 1223747.4
A36: 44561 | B36: SI1512/BS154 | C36: =27733.13+3327.98 -> 31061.11 | D36: =C36/1.12 -> 27733.134 | F36: 44551 | G36: SI1512 | H36: =554662.47+66559.5 -> 621221.97 | I36: =H36/1.12 -> 554662.47
A37: 44601 | B37: SI1546/BS189 | C37: =91669.78+11000.37 -> 102670.15 | D37: =C37/1.12 -> 91669.777 | F37: 44581 | G37: SI1546 | H37: =1833395.56+220007.46 -> 2053403 | I37: =H37/1.12 -> 1833395.6
A38: 44614 | B38: SI1548/BS191 | C38: =60640.31+7276.84 -> 67917.15 | D38: =C38/1.12 -> 60640.312 | F38: 44588 | G38: SI1548 | H38: =1212806.37+145536.76 -> 1358343.1 | I38: =H38/1.12 -> 1212806.4
A39: 44615 | B39: SI1549/BS192 | C39: =35909.6+4309.15 -> 40218.75 | D39: =C39/1.12 -> 35909.598 | F39: 44595 | G39: SI1549 | H39: =718192+86183.04 -> 804375.04 | I39: =H39/1.12 -> 718192
A40: 44615 | B40: SI1550/BS203 | C40: =15184.15+1822.1 -> 17006.25 | D40: =C40/1.12 -> 15184.152 | F40: 44602 | G40: SI1550 | H40: =303683+36441.96 -> 340124.96 | I40: =H40/1.12 -> 303683
A41: 44628 | B41: SI1565/BS221 | C41: =4821.43+578.57 -> 5400 | D41: =C41/1.12 -> 4821.4286 | F41: 44616 | G41: SI1565 | H41: =96428.5+11571.42 -> 107999.92 | I41: =H41/1.12 -> 96428.5
A42: 44638 | B42: SI1566/BS222 | C42: =4821.43+578.57 -> 5400 | D42: =C42/1.12 -> 4821.4286 | F42: 44623 | G42: SI1566 | H42: =96428.5+11571.42 -> 107999.92 | I42: =H42/1.12 -> 96428.5
A43: 44639 | B43: SI1567/BS226 | C43: =4821.43+43+578.57 -> 5443 | D43: =C43/1.12 -> 4859.8214 | F43: 44629 | G43: SI1567 | H43: =96428.5+11571.42 -> 107999.92 | I43: =H43/1.12 -> 96428.5
A44: 44651 | B44: SI1581/BS246 | C44: =36545.76+730.92 -> 37276.68 | D44: =C44/1.12 -> 33282.75 | F44: 44623 | G44: SI1581 | H44: =659933.1+79191.97 -> 739125.07 | I44: =H44/1.12 -> 659933.1
A45: 44671 | B45: SI1587/BS253 | C45: =30728.24+3687.39 -> 34415.63 | D45: =C45/1.12 -> 30728.241 | F45: 44658 | G45: SI1587 | H45: =543582.65+65229.92 -> 608812.57 | I45: =H45/1.12 -> 543582.65
A46: 44653 | B46: SI582/BS248 | C46: =30728.24+3687.39 -> 34415.63 | D46: =C46/1.12 -> 30728.241 | F46: 44651 | G46: SI1582 | H46: =614564.75+73747.77 -> 688312.52 | I46: =H46/1.12 -> 614564.75
D47: =C47/1.12 -> 0 | F47: 44623 | G47: DR444 | H47: =3572765.7+428731.88 -> 4001497.6 | I47: =H47/1.12 -> 3572765.7
A48: 44700 | B48: SI1604/BS268 | C48: =5457.59+654.91 -> 6112.5 | D48: =C48/1.12 -> 5457.5893 | F48: 44678 | G48: SI1604 | H48: =109151.7+13098.2 -> 122249.9 | I48: =H48/1.12 -> 109151.7
A49: 44748 | B49: BS287 | C49: =16691.76+2003.01 -> 18694.77 | D49: =C49/1.12 -> 16691.759
A50: 44749 | B50: SI1638/BS318 | C50: =45195+5423.4 -> 50618.4 | D50: =C50/1.12 -> 45195 | F50: 44629 | G50: SI1638 | H50: 1012368 | I50: =H50/1.12 -> 903900
A51: 44749 | B51: SI1627/BS306 | C51: =26672.5+3200.7 -> 29873.2 | D51: =C51/1.12 -> 26672.5 | F51: 44714 | G51: SI1627 | H51: 597464 | I51: =H51/1.12 -> 533450
A52: 44750 | B52: SI615/BS284 | C52: =62089.76+7450.77 -> 69540.53 | D52: =C52/1.12 -> 62089.759 | F52: 44693 | G52: SI1615 | H52: =818625+98235 -> 916860 | I52: =H52/1.12 -> 818625
A53: 44784 | B53: BS349 | C53: =32624.33+3914.92 -> 36539.25 | D53: =C53/1.12 -> 32624.33 | F53: 44712 | G53: SI1618/1615 | H53: =634755+76170.6+14670.1 -> 725595.7 | I53: =H53/1.12 -> 647853.3
A54: 44756 | B54: SI1639/BS319 | C54: =20189.5+2422.74 -> 22612.24 | D54: =C54/1.12 -> 20189.5 | F54: 44728 | G54: SI1639-B | H54: =269290+32314.8+134500+16140 -> 452244.8 | I54: =H54/1.12 -> 403790
A55: 44809 | B55: SI1665/BS350 | C55: =7276.79+873.21 -> 8150 | D55: =C55/1.12 -> 7276.7857 | F55: 44768 | G55: SI1665 | H55: =132812.4+15937.49 -> 148749.89 | I55: =H55/1.12 -> 132812.4
D56: =C56/1.12 -> 0 | F56: 44741 | G56: SI1648 | H56: =134500+16140 -> 150640 | I56: =H56/1.12 -> 134500
A57: 44811 | B57: SI1682/BS371 | C57: =6640.63+796.88 -> 7437.51 | D57: =C57/1.12 -> 6640.6339 | F57: 44774 | G57: SI1682 | H57: =132812.4+15937.49 -> 148749.89 | I57: =H57/1.12 -> 132812.4
A58: 44811 | B58: SI1681/BS370 | C58: =6004.46+720.54 -> 6725 | D58: =C58/1.12 -> 6004.4643 | F58: 44791 | G58: SI1681 | H58: =120089.2+14410.71 -> 134499.91 | I58: =H58/1.12 -> 120089.21
A59: 44811 | B59: SI1680/BS369 | C59: =7276.79+873.21 -> 8150 | D59: =C59/1.12 -> 7276.7857 | F59: 44777 | G59: SI1680 | H59: =145535.6+17464.28 -> 162999.88 | I59: =H59/1.12 -> 145535.61
A60: 44839 | B60: SI1685/BS376 | C60: =6004.46+720.54 -> 6725 | D60: =C60/1.12 -> 6004.4643 | F60: 44805 | G60: SI1685 | H60: =120089.2+14410.71 -> 134499.91 | I60: =H60/1.12 -> 120089.21
A61: 44839 | B61: SI1693/BS384 | C61: =37957.59+4554.91 -> 42512.5 | D61: =C61/1.12 -> 37957.589 | F61: 44817 | G61: SI1693 | H61: =759151.55+91098.19 -> 850249.74 | I61: =H61/1.12 -> 759151.55
A62: 44848 | B62: SI1707/BS399 | C62: =4274.55+512.95 -> 4787.5 | D62: =C62/1.12 -> 4274.5536 | F62: 44833 | G62: SI1707 | H62: =85491+10258.92 -> 95749.92 | I62: =H62/1.12 -> 85491
A63: 44851 | B63: SI1667/BS352 | C63: =6640.63+796.88 -> 7437.51 | D63: =C63/1.12 -> 6640.6339 | F63: 44798 | G63: SI1667 | H63: =132812.4+15937.49 -> 148749.89 | I63: =H63/1.12 -> 132812.4
A64: 44851 | B64: SI1702/BS355 | C64: =3638.39+436.61 -> 4075 | D64: =C64/1.12 -> 3638.3929 | F64: 44825 | G64: SI1702 | H64: =72767.8+8732.14 -> 81499.94 | I64: =H64/1.12 -> 72767.804
A65: 44869 | B65: SI1720/BS416 | C65: =152806.26+18336.75 -> 171143.01 | D65: =C65/1.12 -> 152806.26 | F65: 44854 | G65: SI1720 | H65: =3056125.73+366735.09 -> 3422860.8 | I65: =H65/1.12 -> 3056125.7
A66: 44869 | B66: SI1717/BS407 | C66: =126754.46+15210.54 -> 141965 | D66: =C66/1.12 -> 126754.46 | F66: 44847 | G66: SI1717 | H66: =2535090.6+304210.87 -> 2839301.5 | I66: =H66/1.12 -> 2535090.6
A67: 44881 | B67: SI1732/BS432 | C67: =101951.12+12234.13 -> 114185.25 | D67: =C67/1.12 -> 101951.12 | F67: 44875 | G67: SI1732 | H67: =2039022.74+244682.73 -> 2283705.5 | I67: =H67/1.12 -> 2039022.7
A68: 44895 | B68: SI1737/BS438 | C68: =170126.12+20415.13 -> 190541.25 | D68: =C68/1.12 -> 170126.12 | F68: 44889 | G68: SI1737 | H68: =3402302.69+408302.69 -> 3810605.4 | I68: =H68/1.12 -> 3402326.2
A69: 44910 | B69: SI1746/BS452 | C69: =87973.44+10556.81 -> 98530.25 | D69: =C69/1.12 -> 87973.437 | F69: 44897 | G69: SI1740 | H69: =1757237.11+210868.46 -> 1968105.6 | I69: =H69/1.12 -> 1757237.1
A70: 44926 | B70: SI1754/BS460 | C70: =76763.84+9211.66 -> 85975.5 | D70: =C70/1.12 -> 76763.839 | F70: 44909 | G70: SI1754 | H70: =1535276.61+184233.19 -> 1719509.8 | I70: =H70/1.12 -> 1535276.6
A71: 44926 | B71: SI1749/BS455 | C71: =87499.33+10499.92 -> 97999.25 | D71: =C71/1.12 -> 87499.33 | F71: 44903 | G71: SI1749 | H71: =1749987.13+209998.45 -> 1959985.6 | I71: =H71/1.12 -> 1749987.1
A72: 44967 | B72: SI1770/BS489 | C72: =148185.27+17782.23 -> 165967.5 | D72: =C72/1.12 -> 148185.27 | F72: 44945 | G72: SI1770 | H72: =2963704.84+355644.58 -> 3319349.4 | I72: =H72/1.12 -> 2963704.8
A73: 45007 | B73: SI1777/BS500 | C73: =147585.27+17710.23 -> 165295.5 | D73: =C73/1.12 -> 147585.27 | F73: 44966 | G73: SI1777 | H73: =2951704.63+354204.55 -> 3305909.2 | I73: =H73/1.12 -> 2951704.6
F74: 44973 | G74: SI1782 | H74: =4388382.85+526605.94 -> 4914988.8 | I74: =H74/1.12 -> 4388382.8
A75: 45027 | B75: SI1802/BS538 | C75: =239011.16+28681.34 -> 267692.5 | D75: =C75/1.12 -> 239011.16 | F75: 44994 | G75: SI1802 | H75: =4780221.98+573626.64 -> 5353848.6 | I75: =H75/1.12 -> 4780222
A76: 45027 | B76: SI1800/BS535 | C76: =116508.04+13980.96 -> 130489 | D76: =C76/1.12 -> 116508.04 | F76: 44988 | G76: SI1800 | H76: =2330160.09+279619.21 -> 2609779.3 | I76: =H76/1.12 -> 2330160.1
A77: 45046 | B77: SI1816/BS558 | C77: =123371.88+14804.63 -> 138176.51 | D77: =C77/1.12 -> 123371.88 | F77: 45027 | G77: SI1816 | H77: =2467436.84+296092.42 -> 2763529.3 | I77: =H77/1.12 -> 2467436.8
A78: 45057 | B78: SI1827/BS572 | C78: =94496.88+11339.63 -> 105836.51 | D78: =C78/1.12 -> 94496.884 | F78: 45041 | G78: SI1827 | H78: =1889937.08+226792.45 -> 2116729.5 | I78: =H78/1.12 -> 1889937.1
A79: 45091 | B79: SI1855/BS613 | C79: =5178.57+621.43 -> 5800 | D79: =C79/1.12 -> 5178.5714 | F79: 45050 | G79: SI1855 | H79: =103571.4+12428.57 -> 115999.97 | I79: =H79/1.12 -> 103571.4
A80: 45091 | B80: SI1866/BS628 | C80: =85546.88+10265.63 -> 95812.51 | D80: =C80/1.12 -> 85546.884 | F80: 45085 | G80: SI1866 | H80: =1710937.35+205312.48 -> 1916249.8 | I80: =H80/1.12 -> 1710937.3
A81: 45091 | B81: SI1865/BS627 | C81: =98667.41+11840.09 -> 110507.5 | D81: =C81/1.12 -> 98667.411 | F81: 45078 | G81: SI1865 | H81: =1973348.05+236801.77 -> 2210149.8 | I81: =H81/1.12 -> 1973348.1
A82: 45091 | B82: SI1856/BS614 | C82: =150209.82+18025.18 -> 168235 | D82: =C82/1.12 -> 150209.82 | F82: 45078 | G82: SI1856 | H82: =3004196.3+360503.56 -> 3364699.9 | I82: =H82/1.12 -> 3004196.3
A83: 45124 | B83: SI1875/BS647 | C83: =163253.13+19590.38 -> 182843.51 | D83: =C83/1.12 -> 163253.13 | F83: 45098 | G83: SI1875 | H83: =3265061.93+391807.43 -> 3656869.4 | I83: =H83/1.12 -> 3265061.9
A84: 45124 | B84: SI1884/BS663 | C84: =163664.29+19639.71 -> 183304 | D84: =C84/1.12 -> 163664.29 | F84: 45112 | G84: SI1884 | H84: 3666079.4 | I84: =H84/1.12 -> 3273285.2
A85: 45127 | B85: SI1889/BS668 | C85: =140817.41+16898.09 -> 157715.5 | D85: =C85/1.12 -> 140817.41 | F85: 45120 | G85: SI1889 | H85: =2816347.45+337961.69 -> 3154309.1 | I85: =H85/1.12 -> 2816347.4
A86: 45150 | B86: SI1897/BS680 | C86: =131028.57+15723.43 -> 146752 | D86: =C86/1.12 -> 131028.57 | F86: 45132 | G86: SI1897 | H86: =2620570.49+314468.46 -> 2935039 | I86: =H86/1.12 -> 2620570.5
A87: 45161 | B87: SI1901/BS684 | C87: =102215.18+12265.82 -> 114481 | D87: =C87/1.12 -> 102215.18 | F87: 45140 | G87: SI1901 | H87: =2044302.68+245316.32 -> 2289619 | I87: =H87/1.12 -> 2044302.7
A88: 45163 | B88: SI1914/BS700 | C88: =151489.73+18178.77 -> 169668.5 | D88: =C88/1.12 -> 151489.73 | F88: 45154 | G88: SI1914 | H88: =3029795.11+363575.41 -> 3393370.5 | I88: =H88/1.12 -> 3029795.1
A89: 45163 | B89: SI1905/BS693 | C89: =149666.29+17959.95 -> 167626.24 | D89: =C89/1.12 -> 149666.29 | F89: 45147 | G89: SI1905 | H89: =2993325.73+359199.08 -> 3352524.8 | I89: =H89/1.12 -> 2993325.7
A90: 45209 | B90: SI1928/BS722 | C90: =124066.07+14887.93 -> 138954 | D90: =C90/1.12 -> 124066.07 | F90: 45170 | G90: SI1928 | H90: 2779080.5 | I90: =H90/1.12 -> 2481321.9
A91: 45209 | B91: SI1931/BS725 | C91: =118682.37+14241.88 -> 132924.25 | D91: =C91/1.12 -> 118682.37 | F91: 45170 | G91: SI1931 | H91: =2373647.74+284837.73 -> 2658485.5 | I91: =H91/1.12 -> 2373647.7
A92: 45209 | B92: SI1930/BS724 | C92: =188049.55+22565.95 -> 210615.5 | D92: =C92/1.12 -> 188049.55 | F92: 45183 | G92: SI1930 | H92: 4212310.7 | I92: =H92/1.12 -> 3760991.7
A93: 45222 | B93: SI1934/BS735 | C93: =89654.02+10758.48 -> 100412.5 | D93: =C93/1.12 -> 89654.018 | F93: 45199 | G93: SI1934 | H93: 2008251.1 | I93: =H93/1.12 -> 1793081.3
A94: 45258 | B94: SI1945/BS748 | C94: =16738.84+2008.66 -> 18747.5 | D94: =C94/1.12 -> 16738.839 | F94: 45211 | G94: SI1945 | H94: 374950.4 | I94: =H94/1.12 -> 334777.14
A95: 45251 | B95: SI1937/BS739 | C95: =78301.9+9396.23 -> 87698.13 | D95: =C95/1.12 -> 78301.902 | F95: 45206 | G95: SI1937 | H95: 1753963.3 | I95: =H95/1.12 -> 1566038.6
A96: 45275 | B96: SI1968/BS774 | C96: =26686.38+3202.37 -> 29888.75 | D96: =C96/1.12 -> 26686.384 | F96: 45237 | G96: SI1968 | H96: 597767.82 | I96: =H96/1.12 -> 533721.27
A97: 45275 | B97: SI1972/BS793 | C97: =23574.78+2828.97 -> 26403.75 | D97: =C97/1.12 -> 23574.777 | F97: 45253 | G97: SI1972 | H97: 528074.03 | I97: =H97/1.12 -> 471494.67
A98: 45308 | B98: SI1986/BS817 | C98: =19850.45+2382.05 -> 22232.5 | D98: =C98/1.12 -> 19850.446 | F98: 45267 | G98: SI1986 | H98: 444650.47 | I98: =H98/1.12 -> 397009.35
A99: 45301 | B99: SI1985/BS816 | C99: =26005.58+3120.67 -> 29126.25 | D99: =C99/1.12 -> 26005.58 | F99: 45261 | G99: SI1985 | H99: 582525.62 | I99: =H99/1.12 -> 520112.16
A100: 45377 | B100: SI2000/BS838 | C100: =21167.41+2540.09 -> 23707.5 | D100: =C100/1.12 -> 21167.411 | F100: 45302 | G100: SI2000 | H100: 474150.36 | I100: =H100/1.12 -> 423348.54
A101: 45322 | B101: SI2006/BS846 | C101: =136978.57+16437.43 -> 153416 | D101: =C101/1.12 -> 136978.57 | F101: 45315 | G101: SI2006 | H101: 3068320 | I101: =H101/1.12 -> 2739571.5
...

Sheet EXPEDITION (PURCHASED & SF)
A2: DATE | B2: SERVICE FEES/DELIVERY | C2: GROSS AMOUNT BILLED | D2: NET OF VAT | F2: DATE | G2: INVOICES/DELIVERY | H2: GROSS AMOUNT BILLED | I2: NET OF VAT
A3: 44237 | B3: CI3273 | C3: =177736.61+21328.39 -> 199065 | D3: =C3/1.12 -> 177736.61 | F3: 44226 | G3: CI3273 | H3: =3554731.85+426567.83 -> 3981299.7 | I3: =H3/1.12 -> 3554731.9
A4: 44260 | B4: CI3274 | C4: =259390.18+31126.82 -> 290517 | D4: =C4/1.12 -> 259390.18 | F4: 44239 | G4: CI3274 | H4: =5187803.17+622536.38 -> 5810339.5 | I4: =H4/1.12 -> 5187803.2
A5: 44260 | B5: CI3275 | C5: =170235.27+20428.23 -> 190663.5 | D5: =C5/1.12 -> 170235.27 | F5: 44246 | G5: CI3275 | H5: =3404704.57+408564.55 -> 3813269.1 | I5: =H5/1.12 -> 3404704.6
A6: 44289 | B6: AP25997-CI3277 | C6: =111817.86+13418.14 -> 125236 | D6: =C6/1.12 -> 111817.86 | F6: 44258 | G6: CI3277 | H6: =2236357.06+268362.85 -> 2504719.9 | I6: =H6/1.12 -> 2236357.1
A7: 44289 | B7: AP25997-CI3279 | C7: =129317.86+15518.14 -> 144836 | D7: =C7/1.12 -> 129317.86 | F7: 44265 | G7: CI3279 | H7: =2586356.91+310362.83 -> 2896719.7 | I7: =H7/1.12 -> 2586356.9
A8: 44289 | B8: AP25997-CI3281 | C8: =131460.71+15775.29 -> 147236 | D8: =C8/1.12 -> 131460.71 | F8: 44271 | G8: CI3281 | H8: =2629214.06+315505.69 -> 2944719.8 | I8: =H8/1.12 -> 2629214.1
A9: 44319 | B9: AP25932-CI3282 | C9: =119786.61+14374.39 -> 134161 | D9: =C9/1.12 -> 119786.61 | F9: 44280 | G9: CI3282 | H9: =2395732.14+287487.87 -> 2683220 | I9: =H9/1.12 -> 2395732.2
A10: 44319 | B10: AP25932-CI3285 | C10: =96006.25+11520.75 -> 107527 | D10: =C10/1.12 -> 96006.25 | F10: 44305 | G10: CI3285 | H10: =1920124.9+230415 -> 2150539.9 | I10: =H10/1.12 -> 1920124.9
A11: 44340 | B11: AP26253-CI3291 | C11: =82063.39+9847.61 -> 91911 | D11: =C11/1.12 -> 82063.393 | F11: 44326 | G11: CI3291 | H11: =1641267.66+196952.13 -> 1838219.8 | I11: =H11/1.12 -> 1641267.7
A12: 44340 | B12: AP26253-CI3289 | C12: =141110.71+16933.29 -> 158044 | D12: =C12/1.12 -> 141110.71 | F12: 44313 | G12: CI3289 | H12: =2822214.03+338665.69 -> 3160879.7 | I12: =H12/1.12 -> 2822214
A13: 44347 | B13: AP26384-CI3292 | C13: =148151.79+17778.21 -> 165930 | D13: =C13/1.12 -> 148151.79 | F13: 44331 | G13: CI3292 | H13: =2963035.61+355564.27 -> 3318599.9 | I13: =H13/1.12 -> 2963035.6
A14: 44355 | B14: AP26549-CI3296 | C14: =147669.64+17720.36 -> 165390 | D14: =C14/1.12 -> 147669.64 | F14: 44337 | G14: CI3296 | H14: =2953392.75+354407.13 -> 3307799.9 | I14: =H14/1.12 -> 2953392.7
A15: 44364 | B15: SI03298 | C15: =158545.54+19025.46 -> 177571 | D15: =C15/1.12 -> 158545.54 | F15: 44350 | G15: CI3298 | H15: =3170910.52+380509.27 -> 3551419.8 | I15: =H15/1.12 -> 3170910.5
A16: 44368 | B16: AP26849-1_CI3301 | C16: =198718.75+23846.25 -> 222565 | D16: =C16/1.12 -> 198718.75 | F16: 44355 | G16: CI3301 | H16: =3974374.92+476924.99 -> 4451299.9 | I16: =H16/1.12 -> 3974374.9
A17: 44383 | B17: AP29470-CI3303 | C17: =101377.68+12165.32 -> 113543 | D17: =C17/1.12 -> 101377.68 | F17: 44372 | G17: CI3303 | H17: =2027553.01+243306.37 -> 2270859.4 | I17: =H17/1.12 -> 2027553
A18: 44393 | B18: AP29538-CI3308 | C18: =83035.71+9964.29 -> 93000 | D18: =C18/1.12 -> 83035.714 | F18: 44385 | G18: CI3308 | H18: =1660714.07+199285.69 -> 1859999.8 | I18: =H18/1.12 -> 1660714.1
A19: 44393 | B19: AP29538-CI3304 | C19: =99866.07+11983.93 -> 111850 | D19: =C19/1.12 -> 99866.071 | F19: 44379 | G19: CI3304 | H19: =1940535.58+232864.27+56785.73+6814.29 -> 2236999.9 | I19: =H19/1.12 -> 1997321.3
A20: 44407 | B20: AP29647-CI3309 | C20: =182790.18+21934.82 -> 204725 | D20: =C20/1.12 -> 182790.18 | F20: 44398 | G20: CI3309 | H20: =3655803.15+438696.38 -> 4094499.5 | I20: =H20/1.12 -> 3655803.2
A21: 44413 | B21: AP29728-CI3310 | C21: =103372.32+12404.68 -> 115777 | D21: =C21/1.12 -> 103372.32 | F21: 44406 | G21: CI3310 | H21: =2067446.35+248093.57 -> 2315539.9 | I21: =H21/1.12 -> 2067446.4
A22: 44427 | B22: AP29832-CI3311 | C22: =150459.82+18055.18 -> 168515 | D22: =C22/1.12 -> 150459.82 | F22: 44413 | G22: CI3311 | H22: =3009196.41+361103.57 -> 3370300 | I22: =H22/1.12 -> 3009196.4
A23: 44439 | B23: AP2982-CI3312 | C23: =143730.58+17247.67 -> 160978.25 | D23: =C23/1.12 -> 143730.58 | F23: 44420 | G23: CI3312 | H23: =2874611.49+344953.38 -> 3219564.9 | I23: =H23/1.12 -> 2874611.5
A24: 44439 | B24: AP29982-CI3313 | C24: =145599.11+17471.89 -> 163071 | D24: =C24/1.12 -> 145599.11 | F24: 44426 | G24: CI3313 | H24: =2911981.57+349437.78 -> 3261419.3 | I24: =H24/1.12 -> 2911981.6
A25: 44455 | B25: AP30118-CI3314 | C25: =154565.85+18547.9 -> 173113.75 | D25: =C25/1.12 -> 154565.85 | F25: 44441 | G25: CI3314 | H25: =3091316.38+370957.97 -> 3462274.3 | I25: =H25/1.12 -> 3091316.4
A26: 44463 | B26: AP30179-CI3315 | C26: =114243.97+13709.28 -> 127953.25 | D26: =C26/1.12 -> 114243.97 | F26: 44447 | G26: CI3315 | H26: =2284879.02+274185.49 -> 2559064.5 | I26: =H26/1.12 -> 2284879
A27: 44477 | B27: AP30306-CI3316 | C27: =211887.5+25426.5 -> 237314 | D27: =C27/1.12 -> 211887.5 | F27: 44462 | G27: CI3316 | H27: =4237749.82+508529.99 -> 4746279.8 | I27: =H27/1.12 -> 4237749.8
A28: 44483 | B28: AP30343-CI3318 | C28: =102368.97+12284.28 -> 114653.25 | D28: =C28/1.12 -> 102368.97 | F28: 44468 | G28: CI3318 | H28: =2047379.24+245685.51 -> 2293064.8 | I28: =H28/1.12 -> 2047379.2
A29: 44494 | B29: AP30424-CI3321 | C29: =225429.91+27051.59 -> 252481.5 | D29: =C29/1.12 -> 225429.91 | F29: 44476 | G29: CI3321 | H29: =4508598.83+541031.86 -> 5049630.7 | I29: =H29/1.12 -> 4508598.8
A30: 44510 | B30: AP30235-CI3322 | C30: =179708.93+21565.07 -> 201274 | D30: =C30/1.12 -> 179708.93 | F30: 44496 | G30: CI3322 | H30: =3594178.44+431301.42 -> 4025479.9 | I30: =H30/1.12 -> 3594178.4
A31: 44516 | B31: AP30631-CI3325 | C31: =175314.73+21037.77 -> 196352.5 | D31: =C31/1.12 -> 175314.73 | F31: 44511 | G31: CI3325 | H31: =3506294.5+420755.34 -> 3927049.8 | I31: =H31/1.12 -> 3506294.5
A32: 44539 | B32: AP30846-CI3326 | C32: =222651.79+26718.21 -> 249370 | D32: =C32/1.12 -> 222651.79 | F32: 44526 | G32: CI3326 | H32: =4453035.75+534364.28 -> 4987400 | I32: =H32/1.12 -> 4453035.7
A33: 44561 | B33: AP30970-CI3327 | C33: =187019.2+22442.3 -> 209461.5 | D33: =C33/1.12 -> 187019.2 | F33: 44543 | G33: CI3327 | H33: =3740382.63+448845.91 -> 4189228.5 | I33: =H33/1.12 -> 3740382.6
A34: 44561 | B34: AP30988-CI3328 | C34: =214090.63+25690.88 -> 239781.51 | D34: =C34/1.12 -> 214090.63 | F34: 44551 | G34: CI3328 | H34: =4281811.48+513817.37 -> 4795628.9 | I34: =H34/1.12 -> 4281811.5
A35: 44561 | B35: AP30988-CI3329 | C35: =133764.29+16051.71 -> 149816 | D35: =C35/1.12 -> 133764.29 | F35: 44551 | G35: CI3329 | H35: =2675285.04+321034.2 -> 2996319.2 | I35: =H35/1.12 -> 2675285
A36: 44601 | B36: AP31250-CI3333 | C36: =158620.54+19034.46 -> 177655 | D36: =C36/1.12 -> 158620.54 | F36: 44581 | G36: CI3333 | H36: =653571.75+78428.61+2518837.58+302260.52 -> 3553098.5 | I36: =H36/1.12 -> 3172409.3
A37: 44615 | B37: AP31349-CI3334 | C37: =158037.95+18964.55 -> 177002.5 | D37: =C37/1.12 -> 158037.95 | F37: 44588 | G37: CI3334 | H37: =653572.5+78428.7+2507186.15+300862.85 -> 3540050.2 | I37: =H37/1.12 -> 3160759.1
A38: 44615 | B38: AP31349-CI3335 | C38: =177832.59+21339.91 -> 199172.5 | D38: =C38/1.12 -> 177832.59 | F38: 44595 | G38: CI3335 | H38: =4233795.7+508055.49+653571.75+78428.61 -> 5473851.6 | I38: =H38/1.12 -> 4887367.5
A39: 44615 | B39: AP31349-CI3338 | C39: =372680.8+44721.7 -> 417402.5 | D39: =C39/1.12 -> 372680.8 | F39: 44602 | G39: CI3338/3337 | H39: =1089286.25+130714.35+7695046.28+923405.56 -> 9838452.4 | I39: =H39/1.12 -> 8784332.5
A40: 44624 | B40: AP31452-CI3339 | C40: =304130.58+36495.67 -> 340626.25 | D40: =C40/1.12 -> 304130.58 | F40: 44616 | G40: CI3339/3341 | H40: =1307143.5+156857.22+5806773.83+696812.87 -> 7967587.4 | I40: =H40/1.12 -> 7113917.3
A41: 44638 | B41: AP31591-CI3342 | C41: =214003.35+25680.4 -> 239683.75 | D41: =C41/1.12 -> 214003.35 | F41: 44623 | G41: CI3342/3343 | H41: =1307143.5+156857.22+4603050.22+552366.03 -> 6619417 | I41: =H41/1.12 -> 5910193.7
A42: 44638 | B42: AP31591-CI3344 | C42: =200637.28+24076.47 -> 224713.75 | D42: =C42/1.12 -> 200637.28 | F42: 44629 | G42: CI3344/3345 | H42: =4801475.78+576177.09+1307143.5+156857.22 -> 6841653.6 | I42: =H42/1.12 -> 6108619.3
A43: 44651 | B43: AP31736-CI3346 | C43: =197975.45+23757.05 -> 221732.5 | D43: =C43/1.12 -> 197975.45 | F43: 44644 | G43: CI3346/3347 | H43: =4358721.88+523046.63 -> 4881768.5 | I43: =H43/1.12 -> 4358721.9
A44: 44671 | B44: AP31945-CI3348 | C44: =245526.56+29463.19 -> 274989.75 | D44: =C44/1.12 -> 245526.56 | F44: 44651 | G44: CI3348/3349 | H44: =5110139.97+613216.8 -> 5723356.8 | I44: =H44/1.12 -> 5110140
A45: 44671 | B45: AP31945-CI3351 | C45: =144631.92+17355.83 -> 161987.75 | D45: =C45/1.12 -> 144631.92 | F45: 44658 | G45: CI3351/3352 | H45: =3125515.18+375061.83 -> 3500577 | I45: =H45/1.12 -> 3125515.2
A46: 44700 | B46: AP32271-CI3353 | C46: =274027.46+32883.3 -> 306910.76 | D46: =C46/1.12 -> 274027.46 | F46: 44678 | G46: CI3353 | H46: =5480547.5+657665.7 -> 6138213.2 | I46: =H46/1.12 -> 5480547.5
A47: 44714 | B47: AP32424-CI3354 | C47: =321828.57+38619.43 -> 360448 | D47: =C47/1.12 -> 321828.57 | F47: 44693 | G47: CI3354 | H47: =6436570.35+772388.44 -> 7208958.8 | I47: =H47/1.12 -> 6436570.3
A48: 44714 | B48: AP32424-CI3355 | C48: =300604.91+36072.59 -> 336677.5 | D48: =C48/1.12 -> 300604.91 | F48: 44701 | G48: CI3355 | H48: =6012097.9+721451.75 -> 6733549.7 | I48: =H48/1.12 -> 6012097.9
A49: 44733 | B49: AP32603-CI3356 | C49: =291422.99+34970.76 -> 326393.75 | D49: =C49/1.12 -> 291422.99 | F49: 44714 | G49: CI3356 | H49: =5828459.34+699415.12 -> 6527874.5 | I49: =H49/1.12 -> 5828459.3
A50: 44733 | B50: AP32603-CI3358 | C50: =284640.63+34156.88 -> 318797.51 | D50: =C50/1.12 -> 284640.63 | F50: 44714 | G50: CI3358 | H50: =5692812.22+683137.47 -> 6375949.7 | I50: =H50/1.12 -> 5692812.2
A51: 44742 | B51: RFP-3107-CI3360 | C51: =214032.81+25683.94 -> 239716.75 | D51: =C51/1.12 -> 214032.81 | F51: 44728 | G51: CI3359-3360 | H51: =4280656.16+513678.74 -> 4794334.9 | I51: =H51/1.12 -> 4280656.2
A52: 44757 | B52: AP32906-RFP3452 | C52: =439135.71+52696.29 -> 491832 | D52: =C52/1.12 -> 439135.71
A53: 44771 | B53: AP33031-CI3361 | C53: =254131.7+30495.8 -> 284627.5 | D53: =C53/1.12 -> 254131.7 | F53: 44741 | G53: CI3361 | H53: =5082633.95+609916.08 -> 5692550 | I53: =H53/1.12 -> 5082634
A54: 44770 | B54: AP39247-CI3363 | C54: =499911.83+59989.42 -> 559901.25 | D54: =C54/1.12 -> 499911.83 | F54: 44758 | G54: CI3363 | H54: =9998237.24+1199788.46 -> 11198026 | I54: =H54/1.12 -> 9998237.2
A55: 44784 | B55: AP33198-CI3364 | C55: =392093.3+47051.2 -> 439144.5 | D55: =C55/1.12 -> 392093.3 | F55: 44768 | G55: CI3364 | H55: =7841867.34+941024.08 -> 8782891.4 | I55: =H55/1.12 -> 7841867.3
A56: 44784 | B56: AP33198-CI3367 | C56: =293765.63+35251.88 -> 329017.51 | D56: =C56/1.12 -> 293765.63 | F56: 44777 | G56: CI3367 | H56: =5875314.78+705037.78 -> 6580352.6 | I56: =H56/1.12 -> 5875314.8
A57: 44809 | B57: AP33507-CI3368 | C57: =366813.84+44017.66 -> 410831.5 | D57: =C57/1.12 -> 366813.84 | F57: 44791 | G57: CI3368 | H57: =7336279+880353.49 -> 8216632.5 | I57: =H57/1.12 -> 7336279
A58: 44811 | B58: AP33529-CI3369 | C58: =324707.59+38964.91 -> 363672.5 | D58: =C58/1.12 -> 324707.59 | F58: 44798 | G58: CI3369 | H58: =6494154.14+779298.5 -> 7273452.6 | I58: =H58/1.12 -> 6494154.1
A59: 44819 | B59: AP33604-CI3370 | C59: =268209.15+32185.1 -> 300394.25 | D59: =C59/1.12 -> 268209.15 | F59: 44805 | G59: CI3370 | H59: =5364184.95+643702.19 -> 6007887.1 | I59: =H59/1.12 -> 5364184.9
A60: 44841 | B60: AP33838-CI3372 | C60: =343291.74+41195.01 -> 384486.75 | D60: =C60/1.12 -> 343291.74 | F60: 44817 | G60: CI3372 | H60: =6865836.03+823900.33 -> 7689736.4 | I60: =H60/1.12 -> 6865836
A61: 44841 | B61: AP33838-CI3373 | C61: =305167.41+36620.09 -> 341787.5 | D61: =C61/1.12 -> 305167.41 | F61: 44825 | G61: CI3373 | H61: =6103350.02+732402 -> 6835752 | I61: =H61/1.12 -> 6103350
A62: 44851 | B62: AP33922-CI3374 | C62: =267343.08+32081.17 -> 299424.25 | D62: =C62/1.12 -> 267343.08 | F62: 44833 | G62: CI3374 | H62: =5346863.34+641623.6 -> 5988486.9 | I62: =H62/1.12 -> 5346863.3
A63: 44867 | B63: AP34073-CI3376 | C63: =212271.43+25472.57 -> 237744 | D63: =C63/1.12 -> 212271.43 | F63: 44847 | G63: CI3376 | H63: =4245429.32+509451.53 -> 4754880.9 | I63: =H63/1.12 -> 4245429.3
A64: 44867 | B64: AP34073-CI3377/3378 | C64: =237316.96+28478.04 -> 265795 | D64: =C64/1.12 -> 237316.96 | F64: 44854 | G64: CI3377/3378 | H64: =4746339.87+569560.78 -> 5315900.7 | I64: =H64/1.12 -> 4746339.9
A65: 44881 | B65: AP34258-CI3379 | C65: =185248.66+22229.84 -> 207478.5 | D65: =C65/1.12 -> 185248.66 | F65: 44875 | G65: CI3379 | H65: =3703544.78+444425.37 -> 4147970.1 | I65: =H65/1.12 -> 3703544.8
A66: 44894 | B66: AP34325-CI3381 | C66: =271561.38+32587.37 -> 304148.75 | D66: =C66/1.12 -> 271561.38 | F66: 44889 | G66: CI3381 | H66: =5431227.47+651747.3 -> 6082974.8 | I66: =H66/1.12 -> 5431227.5
D67: =C67/1.12 -> 0 | F67: 44886 | G67: CI3382 | H67: =1428.58+171.43 -> 1600.01 | I67: =H67/1.12 -> 1428.5804 | J67: **OK
A68: 44900 | B68: AP34533-3CI3383 | C68: =182960.49+21955.26 -> 204915.75 | D68: =C68/1.12 -> 182960.49 | F68: 44896 | G68: CI3383 | H68: =3659210.03+439105.21 -> 4098315.2 | I68: =H68/1.12 -> 3659210
A69: 44926 | B69: AP34650-CI3384 | C69: =181552.46+21786.3 -> 203338.76 | D69: =C69/1.12 -> 181552.46 | F69: 44905 | G69: CI3384 | H69: =3631049.28+435725.92 -> 4066775.2 | I69: =H69/1.12 -> 3631049.3
A70: 44926 | B70: AP34650-CI3385 | C70: =202056.03+24246.72 -> 226302.75 | D70: =C70/1.12 -> 202056.03 | F70: 44909 | G70: CI3385 | H70: =4041121.42+484934.57 -> 4526056 | I70: =H70/1.12 -> 4041121.4
A71: 44957 | B71: AP34891-CI3388 | C71: =285503.35+34260.4 -> 319763.75 | D71: =C71/1.12 -> 285503.35 | F71: 44945 | G71: CI3388 | H71: =5710068.6+685208.24 -> 6395276.8 | I71: =H71/1.12 -> 5710068.6
A72: 44971 | B72: AP35042-CI3391 | C72: =217502.23+26100.27 -> 243602.5 | D72: =C72/1.12 -> 217502.23 | F72: 44966 | G72: CI3391 | H72: =4350042.19+522005.07 -> 4872047.3 | I72: =H72/1.12 -> 4350042.2
A73: 44984 | B73: AP35135-CI3392 | C73: =366631.7+43995.8 -> 410627.5 | D73: =C73/1.12 -> 366631.7 | F73: 44973 | G73: CI3392 | H73: =7332635.13+879916.22 -> 8212551.3 | I73: =H73/1.12 -> 7332635.1
A74: 45007 | B74: AP35369-CI3393 | C74: =194287.95+23314.55 -> 217602.5 | D74: =C74/1.12 -> 194287.95 | F74: 44988 | G74: CI3393 | H74: =3885760.8+466291.3 -> 4352052.1 | I74: =H74/1.12 -> 3885760.8
A75: 45016 | B75: AP35515-CI3394 | C75: =345021.65+41402.6 -> 386424.25 | D75: =C75/1.12 -> 345021.65 | F75: 44994 | G75: CI3394 | H75: =6900435.03+828052.2 -> 7728487.2 | I75: =H75/1.12 -> 6900435
A76: 45042 | B76: AP35693-CI3397 | C76: =274181.7+32901.8 -> 307083.5 | D76: =C76/1.12 -> 274181.7 | F76: 45027 | G76: CI3397 | H76: =5483636.21+658036.34 -> 6141672.5 | I76: =H76/1.12 -> 5483636.2
A77: 45062 | B77: AP35916-CI3398 | C77: =326612.95+39193.55 -> 365806.5 | D77: =C77/1.12 -> 326612.95 | F77: 45041 | G77: CI3398 | H77: =6532260.46+783871.25 -> 7316131.7 | I77: =H77/1.12 -> 6532260.5
A78: 45063 | B78: AP35929-CI3399 | C78: =392488.84+47098.66 -> 439587.5 | D78: =C78/1.12 -> 392488.84 | F78: 45050 | G78: CI3399 | H78: =7849778.82+941973.46 -> 8791752.3 | I78: =H78/1.12 -> 7849778.8
A79: 45077 | B79: AP36109-CI3400 | C79: =359073.66+43088.84 -> 402162.5 | D79: =C79/1.12 -> 359073.66 | F79: 45078 | G79: CI3400 | H79: =7181473.73+861776.85 -> 8043250.6 | I79: =H79/1.12 -> 7181473.7
A80: 45090 | B80: AP36213-CI3401 | C80: =273035.71+32764.29 -> 305800 | D80: =C80/1.12 -> 273035.71 | F80: 45078 | G80: CI3401 | H80: =5460714.67+655285.76 -> 6116000.4 | I80: =H80/1.12 -> 5460714.7
A81: 45099 | B81: AP36283-CI3403 | C81: =178147.32+21377.68 -> 199525 | D81: =C81/1.12 -> 178147.32 | F81: 45085 | G81: CI3403 | H81: =3562946.85+427553.62 -> 3990500.5 | I81: =H81/1.12 -> 3562946.8
A82: 45118 | B82: AP36490-CI3404 | C82: =173334.82+20800.18 -> 194135 | D82: =C82/1.12 -> 173334.82 | F82: 45098 | G82: CI3404 | H82: =3466697.36+416003.68 -> 3882701 | I82: =H82/1.12 -> 3466697.4
A83: 45118 | B83: AP36538-CI3406 | C83: =166819.2+20018.3 -> 186837.5 | D83: =C83/1.12 -> 166819.2 | F83: 45112 | G83: CI3406 | H83: =3336384.53+400366.14 -> 3736750.7 | I83: =H83/1.12 -> 3336384.5
A84: 45127 | B84: AP36570-CI3408 | C84: =250479.91+30057.59 -> 280537.5 | D84: =C84/1.12 -> 250479.91 | F84: 45118 | G84: CI3408 | H84: =5009598.88+601151.86 -> 5610750.7 | I84: =H84/1.12 -> 5009598.9
A85: 45150 | B85: AP36776-CI3410 | C85: =270790.18+32494.82 -> 303285 | D85: =C85/1.12 -> 270790.18 | F85: 45132 | G85: CI3410 | H85: =5415803.72+649896.45 -> 6065700.2 | I85: =H85/1.12 -> 5415803.7
A86: 45150 | B86: AP36776-CI3411 | C86: =225312.5+27037.5 -> 252350 | D86: =C86/1.12 -> 225312.5 | F86: 45140 | G86: CI3411 | H86: =4502679.53+540321.54+3571.45+428.57 -> 5047001.1 | I86: =H86/1.12 -> 4506251
A87: 45162 | B87: AP36886-CI3412 | C87: =157845.98+18941.52 -> 176787.5 | D87: =C87/1.12 -> 157845.98 | F87: 45147 | G87: CI3412 | H87: =3156920.67+378830.48 -> 3535751.1 | I87: =H87/1.12 -> 3156920.7
A88: 45170 | B88: AP36968-CI3413 | C88: =157834.82+18940.18 -> 176775 | D88: =C88/1.12 -> 157834.82 | F88: 45154 | G88: CI3413 | H88: =3156697.55+378803.71 -> 3535501.3 | I88: =H88/1.12 -> 3156697.6
A89: 45176 | B89: AP37067-CI3418 | C89: =123214.29+14785.71 -> 138000 | D89: =C89/1.12 -> 123214.29 | F89: 45161 | G89: CI3418 | H89: =2464286.68+295714.4 -> 2760001.1 | I89: =H89/1.12 -> 2464286.7
A90: 45176 | B90: AP37067-CI3419 | C90: =150290.18+18034.82 -> 168325 | D90: =C90/1.12 -> 150290.18 | F90: 45169 | G90: CI3419 | H90: =3005803.45+360696.42 -> 3366499.9 | I90: =H90/1.12 -> 3005803.5
A91: 45195 | B91: AP37244-CI3420 | C91: =313133.93+37576.07 -> 350710 | D91: =C91/1.12 -> 313133.93 | F91: 45183 | G91: CI3420 | H91: =6260535.91+751264.32+2142.87+257.14 -> 7014200.2 | I91: =H91/1.12 -> 6262678.8
A92: 45222 | B92: AP37548-CI3423 | C92: =272276.79+32673.21 -> 304950 | D92: =C92/1.12 -> 272276.79 | F92: 45199 | G92: CI3423 | H92: =5445535.88+653464.31 -> 6099000.2 | I92: =H92/1.12 -> 5445535.9
A93: 45222 | B93: AP37548-CI3424 | C93: =212294.64+25475.36 -> 237770 | D93: =C93/1.12 -> 212294.64 | F93: 45204 | G93: CI3424 | H93: =4245893.22+509507.18 -> 4755400.4 | I93: =H93/1.12 -> 4245893.2
A94: 45222 | B94: AP37548-CI3425 | C94: =191227.68+22947.32 -> 214175 | D94: =C94/1.12 -> 191227.68 | F94: 45211 | G94: CI3425 | H94: =3824554.18+458946.5 -> 4283500.7 | I94: =H94/1.12 -> 3824554.2
F95: 45237 | G95: CI3426 | H95: =5623971.85+674876.8+1964.29+235.71 -> 6301048.6 | I95: =H95/1.12 -> 5625936.3
A96: 45275 | B96: AP38121-3_CI3430 | C96: =352589.29+42310.71 -> 394900 | D96: =C96/1.12 -> 352589.29 | F96: 45253 | G96: CI3430 | H96: =9821.4+1178.57+7041961.34+845035.85 -> 7897997.2 | I96: =H96/1.12 -> 7051783.2
A97: 45291 | B97: AP38228-CI3431 | C97: =307633.93+36916.07 -> 344550 | D97: =C97/1.12 -> 307633.93 | F97: 45261 | G97: CI3431 | H97: =6152678.6+738321.43 -> 6891000 | I97: =H97/1.12 -> 6152678.6
A98: 45301 | B98: AP38346-CI3432 | C98: =227678.57+27321.43 -> 255000 | D98: =C98/1.12 -> 227678.57 | F98: 45267 | G98: CI3432 | H98: =4553571.53+546428.59 -> 5100000.1 | I98: =H98/1.12 -> 4553571.5
A99: 45321 | B99: AP38549-1_CI3435 | C99: =267276.79+32073.21 -> 299350 | D99: =C99/1.12 -> 267276.79 | F99: 45302 | G99: CI3435 | H99: =25446.43+3053.57+5320089.18+638410.73 -> 5986999.9 | I99: =H99/1.12 -> 5345535.6
A100: 45322 | B100: AP38630-CI3426 | C100: 315052.51 | D100: 281296.88
A101: 45335 | B101: AP38751-CI3428 | C101: =137622.77+16514.73 -> 154137.5 | D101: =C101/1.12 -> 137622.77 | F101: 45315 | G101: CI3428 | H101: =2752455.13+330294.62 -> 3082749.8 | I101: =H101/1.12 -> 2752455.1
...

Sheet PURCHASED & SF ANALYSIS
B2: VAT INCLUSIVE
B3: FISCAL YEAR | C3: BUDGET (VAT INCLUSIVE) | E3: ACTUAL PURCHASED | G3: ACTUAL SERVICE FEE | I3: TOTAL PURCHASED | J3: TOTAL SERVICE FEE | K3: VARIANCE PURCHASED | L3: VARIANCE SERVICE FEE | M3: VARIANCE PURCHASED (OVER BUDGET) | O3: VARIANCE SERVICE FEE (OVER BUDGET) | Q3: VARIANCE PURCHASED PERCENTAGE | R3: VARIANCE SERVICE FEE PERCENTAGE | S3: VARIANCE PURCHASED PERCENTAGE (OVER BUDGET) | U3: VARIANCE SERVICE FEE (PERCENTAGE) | W3: PERCENTAGE PURCHASED (OVER BUDGET) | Y3: PERCENTAGE SERVICE FEE (OVER BUDGET)
C4: STOCK | D4: SERVICE FEE | E4: MT. ROCK | F4: EXPEDITION | G4: MT. ROCK | H4: EXPEDITION | M4: MT. ROCK | N4: EXPEDITION | O4: MT. ROCK | P4: EXPEDITION | S4: MT. ROCK | T4: EXPEDITION | U4: MT. ROCK | V4: EXPEDITION | W4: MT. ROCK | X4: EXPEDITION | Y4: MT. ROCK | Z4: EXPEDITION
B5: 2021-2022 | C5: 2.4057859e+08 | D5: =C5*5% -> 12028930 | E5: =SUM('MT.ROCK (PURCHASED & SF)'!H18:H54) -> 57555559 | F5: =SUM('EXPEDITION (PURCHASED & SF)'!H18:H53) -> 1.6480099e+08 | G5: =SUM('MT.ROCK (PURCHASED & SF)'!C17:C48) -> 2848701.4 | H5: =SUM('EXPEDITION (PURCHASED & SF)'!C17:C51) -> 7606941 | I5: =E5+F5 -> 2.2235655e+08 | J5: =G5+H5 -> 10455642 | K5: =C5-I5 -> 18222046 | L5: =D5-J5 -> 1573287.2 | M5: =(C5/2)-E5 -> 62733737 | N5: =(C5/2)-F5 -> -44511691 | O5: =(D5/2)-G5 -> 3165763.4 | P5: =(D5/2)-H5 -> -1592476.2 | Q5: =K5/C5 -> 0.075742591 | R5: =L5/D5 -> 0.13079195 | S5: =M5/(C5/2) -> 0.52152385 | T5: =N5/(C5/2) -> -0.37003867 | U5: =O5/(D5/2) -> 0.52635828 | V5: =P5/(D5/2) -> -0.26477438 | W5: =E5/C5 -> 0.23923807 | X5: =F5/C5 -> 0.68501933 | Y5: =G5/D5 -> 0.23682086 | Z5: =H5/D5 -> 0.63238719
B6: 2022-2023 | C6: 2.7092369e+08 | D6: =C6*5% -> 13546185 | E6: =SUM('MT.ROCK (PURCHASED & SF)'!H55:H83) -> 55708566 | F6: =SUM('EXPEDITION (PURCHASED & SF)'!H54:H82) -> 1.7741011e+08 | G6: =SUM('MT.ROCK (PURCHASED & SF)'!C49:C82) -> 2578030.5 | H6: =SUM('EXPEDITION (PURCHASED & SF)'!C52:C81) -> 9452828.5 | I6: =E6+F6 -> 2.3311868e+08 | J6: =G6+H6 -> 12030859 | K6: =C6-I6 -> 37805013 | L6: =D6-J6 -> 1515325.7 | M6: =(C6/2)-E6 -> 79753280 | N6: =(C6/2)-F6 -> -41948268 | O6: =(D6/2)-G6 -> 4195061.9 | P6: =(D6/2)-H6 -> -2679736.2 | Q6: =K6/C6 -> 0.13954118 | R6: =L6/D6 -> 0.11186365 | S6: =M6/(C6/2) -> 0.58875087 | T6: =N6/(C6/2) -> -0.30966851 | U6: =O6/(D6/2) -> 0.61937172 | V6: =P6/(D6/2) -> -0.39564442 | W6: =E6/C6 -> 0.20562456 | X6: =F6/C6 -> 0.65483425 | Y6: =G6/D6 -> 0.19031414 | Z6: =H6/D6 -> 0.69782221
B7: 2023-2024 | C7: 2.9365232e+08 | D7: =C7*5% -> 14682616 | E7: =SUM('MT.ROCK (PURCHASED & SF)'!H84:H110) -> 50925072 | F7: =SUM('EXPEDITION (PURCHASED & SF)'!H83:H114) -> 1.0726831e+08 | G7: =SUM('MT.ROCK (PURCHASED & SF)'!C83:C110) -> 2729097.4 | H7: =SUM('EXPEDITION (PURCHASED & SF)'!C82:C114) -> 5557550.5 | I7: =E7+F7 -> 1.5819339e+08 | J7: =G7+H7 -> 8286647.9 | K7: =C7-I7 -> 1.3545893e+08 | L7: =D7-J7 -> 6395967.9 | M7: =(C7/2)-E7 -> 95901085 | N7: =(C7/2)-F7 -> 39557845 | O7: =(D7/2)-G7 -> 4612210.5 | P7: =(D7/2)-H7 -> 1783757.4 | Q7: =K7/C7 -> 0.46129018 | R7: =L7/D7 -> 0.43561501 | S7: =M7/(C7/2) -> 0.65316076 | T7: =N7/(C7/2) -> 0.2694196 | U7: =O7/(D7/2) -> 0.62825461 | V7: =P7/(D7/2) -> 0.24297542 | W7: =E7/C7 -> 0.17341962 | X7: =F7/C7 -> 0.3652902 | Y7: =G7/D7 -> 0.1858727 | Z7: =H7/D7 -> 0.37851229
B8: TOTAL | C8: =SUM(C5:C7) -> 8.051546e+08 | D8: =SUM(D5:D7) -> 40257730 | E8: =SUM(E5:E7) -> 1.641892e+08 | F8: =SUM(F5:F7) -> 4.4947941e+08 | G8: =SUM(G5:G7) -> 8155829.3 | H8: =SUM(H5:H7) -> 22617320 | I8: =SUM(I5:I7) -> 6.1366861e+08 | J8: =SUM(J5:J7) -> 30773149 | K8: =C8-I8 -> 1.9148599e+08 | L8: =D8-J8 -> 9484580.7 | M8: =SUM(M5:M7) -> 2.383881e+08 | N8: =SUM(N5:N7) -> -46902114 | O8: =SUM(O5:O7) -> 11973036 | P8: =SUM(P5:P7) -> -2488455 | Q8: =K8/C8 -> 0.23782512 | R8: =L8/D8 -> 0.23559651 | S8: =M8/(C8/2) -> 0.59215485 | T8: =N8/(C8/2) -> -0.11650462 | U8: =O8/(D8/2) -> 0.59481922 | V8: =P8/(D8/2) -> -0.1236262 | W8: =E8/C8 -> 0.20392257 | X8: =F8/C8 -> 0.55825231 | Y8: =G8/D8 -> 0.20259039 | Z8: =H8/D8 -> 0.5618131
B12: VAT EXCLUSIVE
B13: FISCAL YEAR | C13: BUDGET (VAT EXCLUSIVE) | E13: ACTUAL PURCHASED | G13: ACTUAL SERVICE FEE | I13: TOTAL PURCHASED | J13: TOTAL SERVICE FEE | K13: VARIANCE PURCHASED | L13: VARIANCE SERVICE FEE | M13: VARIANCE PURCHASED (OVER BUDGET) | O13: VARIANCE SERVICE FEE (OVER BUDGET) | Q13: VARIANCE PURCHASED PERCENTAGE | R13: VARIANCE SERVICE FEE PERCENTAGE | S13: VARIANCE PURCHASED PERCENTAGE (OVER BUDGET) | U13: VARIANCE SERVICE FEE (PERCENTAGE) | W13: PERCENTAGE PURCHASED (OVER BUDGET) | Y13: PERCENTAGE SERVICE FEE (OVER BUDGET)
C14: STOCK | D14: SERVICE FEE | E14: MT. ROCK | F14: EXPEDITION | G14: MT. ROCK | H14: EXPEDITION | M14: MT. ROCK | N14: EXPEDITION | O14: MT. ROCK | P14: EXPEDITION | S14: MT. ROCK | T14: EXPEDITION | U14: MT. ROCK | V14: EXPEDITION | W14: MT. ROCK | X14: EXPEDITION | Y14: MT. ROCK | Z14: EXPEDITION
B15: 2021-2022 | C15: 2.1480231e+08 | D15: =C15*5% -> 10740116 | E15: =SUM('MT.ROCK (PURCHASED & SF)'!I18:I54) -> 51388892 | F15: =SUM('EXPEDITION (PURCHASED & SF)'!I18:I53) -> 1.4714374e+08 | G15: =SUM('MT.ROCK (PURCHASED & SF)'!D17:D48) -> 2543483.4 | H15: =SUM('EXPEDITION (PURCHASED & SF)'!D17:D51) -> 6791911.6 | I15: =E15+F15 -> 1.9853263e+08 | J15: =G15+H15 -> 9335395.1 | K15: =C15-I15 -> 16269684 | L15: =D15-J15 -> 1404720.7 | M15: =(C15/2)-E15 -> 56012265 | N15: =(C15/2)-F15 -> -39742581 | O15: =(D15/2)-G15 -> 2826574.4 | P15: =(D15/2)-H15 -> -1421853.8 | Q15: =K15/C15 -> 0.075742591 | R15: =L15/D15 -> 0.13079195 | S15: =M15/(C15/2) -> 0.52152385 | T15: =N15/(C15/2) -> -0.37003867 | U15: =O15/(D15/2) -> 0.52635828 | V15: =P15/(D15/2) -> -0.26477438 | W15: =E15/C15 -> 0.23923807 | X15: =F15/C15 -> 0.68501933 | Y15: =G15/D15 -> 0.23682086 | Z15: =H15/D15 -> 0.63238719
B16: 2022-2023 | C16: 2.4189615e+08 | D16: =C16*5% -> 12094808 | E16: =SUM('MT.ROCK (PURCHASED & SF)'!I55:I83) -> 49739791 | F16: =SUM('EXPEDITION (PURCHASED & SF)'!I54:I82) -> 1.5840189e+08 | G16: =SUM('MT.ROCK (PURCHASED & SF)'!D49:D82) -> 2301812.9 | H16: =SUM('EXPEDITION (PURCHASED & SF)'!D52:D81) -> 8440025.5 | I16: =E16+F16 -> 2.0814168e+08 | J16: =G16+H16 -> 10741838 | K16: =C16-I16 -> 33754476 | L16: =D16-J16 -> 1352969.3 | M16: =(C16/2)-E16 -> 71208286 | N16: =(C16/2)-F16 -> -37453810 | O16: =(D16/2)-G16 -> 3745591 | P16: =(D16/2)-H16 -> -2392621.6 | Q16: =K16/C16 -> 0.13954118 | R16: =L16/D16 -> 0.11186365 | S16: =M16/(C16/2) -> 0.58875087 | T16: =N16/(C16/2) -> -0.30966851 | U16: =O16/(D16/2) -> 0.61937172 | V16: =P16/(D16/2) -> -0.39564442 | W16: =E16/C16 -> 0.20562456 | X16: =F16/C16 -> 0.65483425 | Y16: =G16/D16 -> 0.19031414 | Z16: =H16/D16 -> 0.69782221
B17: 2023-2024 | C17: 2.6218957e+08 | D17: =C17*5% -> 13109478 | E17: =SUM('MT.ROCK (PURCHASED & SF)'!I84:I110) -> 45468815 | F17: =SUM('EXPEDITION (PURCHASED & SF)'!I83:I114) -> 95775280 | G17: =SUM('MT.ROCK (PURCHASED & SF)'!D83:D110) -> 2436694.1 | H17: =SUM('EXPEDITION (PURCHASED & SF)'!D82:D114) -> 4962098.7 | I17: =E17+F17 -> 1.4124409e+08 | J17: =G17+H17 -> 7398792.8 | K17: =C17-I17 -> 1.2094547e+08 | L17: =D17-J17 -> 5710685.6 | M17: =(C17/2)-E17 -> 85625969 | N17: =(C17/2)-F17 -> 35319504 | O17: =(D17/2)-G17 -> 4118045.1 | P17: =(D17/2)-H17 -> 1592640.5 | Q17: =K17/C17 -> 0.46129018 | R17: =L17/D17 -> 0.43561501 | S17: =M17/(C17/2) -> 0.65316076 | T17: =N17/(C17/2) -> 0.2694196 | U17: =O17/(D17/2) -> 0.62825461 | V17: =P17/(D17/2) -> 0.24297542 | W17: =E17/C17 -> 0.17341962 | X17: =F17/C17 -> 0.3652902 | Y17: =G17/D17 -> 0.1858727 | Z17: =H17/D17 -> 0.37851229
B18: TOTAL | C18: =SUM(C15:C17) -> 7.1888804e+08 | D18: =SUM(D15:D17) -> 35944402 | E18: =SUM(E15:E17) -> 1.465975e+08 | F18: =SUM(F15:F17) -> 4.0132091e+08 | G18: =SUM(G15:G17) -> 7281990.4 | H18: =SUM(H15:H17) -> 20194036 | I18: =SUM(I15:I17) -> 5.479184e+08 | J18: =SUM(J15:J17) -> 27476026 | K18: =C18-I18 -> 1.7096963e+08 | L18: =D18-J18 -> 8468375.6 | M18: =SUM(M15:M17) -> 2.1284652e+08 | N18: =SUM(N15:N17) -> -41876888 | O18: =SUM(O15:O17) -> 10690210 | P18: =SUM(P15:P17) -> -2221834.9 | Q18: =K18/C18 -> 0.23782512 | R18: =L18/D18 -> 0.23559651 | S18: =M18/(C18/2) -> 0.59215485 | T18: =N18/(C18/2) -> -0.11650462 | U18: =O18/(D18/2) -> 0.59481922 | V18: =P18/(D18/2) -> -0.1236262 | W18: =E18/C18 -> 0.20392257 | X18: =F18/C18 -> 0.55825231 | Y18: =G18/D18 -> 0.20259039 | Z18: =H18/D18 -> 0.5618131

Sheet BUDGET VS USAGE ANALYSIS
B3: 2023-2024 BUDGET | C3: 2023-2024 ACTUAL COST (As May 1) | D3: AVERAGE MONTHLY COST (From July 23-April 24) | E3: VARIANCE (As of December 1, 2024) | F3: SOH OF EXPEDITION (As of MAY 31, 2026) | G3: SOH OF MT. ROCK (MAY 31, 2026) | H3: SOH OF PMC AT MINE SITE (As of MAY 31, 2026) | I3: SOH OF PMC AND SUPPLIER (As of MAY 31,2026)
B4: =C12 -> 2.9365232e+08 | C4: ='MONTHLY COST'!U7 -> 2.1059274e+08 | D4: ='MONTHLY COST'!C8 -> 16199442 | E4: =B4-C4 -> 83059575 | F4: ='EXPEDITION '!H26 -> 68394082 | G4: =MT.ROCK!H18 -> 1488041.2 | H4: ='INVENTORY-MAY'!AV32 -> 31451671 | I4: =F4+G4+H4 -> 1.0133379e+08
B6: 2023-2024 BUDGET | C6: ESTIMATED TOTAL COST on July 1, 2024 | D6: ESTIMATED AVERAGE MONTHLY COST (From July 23-June 24) | E6: ESTIMATED VARIANCE on July 1, 2024 | F6: ESTIMATED SOH OF EXPEDITION on July 1, 2024 | G6: ESTIMATED SOH OF MT. ROCK on July 1, 2024
B7: =C12 -> 2.9365232e+08 | C7: =(C4+D7+D7) -> 2.4299162e+08 | D7: =D4 -> 16199442 | E7: =B7-C7 -> 50660691 | F7: =F4-(D7/2) -> 60294361 | G7: =G4-(D7/2) -> -6611679.6
B11: 2023-2024 BUDGET | C11: 2.6218957e+08 | D11: VAT EXCLUSIVE
C12: =C11+(C11*12%) -> 2.9365232e+08 | D12: VAT INCLUSIVE

Sheet MONTHLY COST
C3: JULY | D3: AUGUST | E3: SEPTEMBER | F3: OCTOBER | G3: NOVEMBER | H3: DECEMBER | I3: JANUARY | J3: FEBRUARY | K3: MARCH | L3: APRIL | M3: MAY | N3: JUNE | O3: JULY | P3: AUGUST | Q3: SEPTEMBER | R3: OCTOBER | S3: NOVEMBER | T3: DECEMBER | U3: TOTAL
B4: MINES | C4: 23482638 | D4: 20074334 | E4: 17770864 | F4: 17764002 | G4: 18199294 | H4: 6077470.5 | I4: 12565355 | J4: 15490003 | K4: 12563498 | L4: 14517292 | M4: 14174044 | N4: 15446444 | O4: 17354880 | U4: =SUM(C4:T4) -> 2.0548012e+08
B5: TIGERWAY | D5: 113291.3 | E5: 125798.94 | H5: 76438.06 | I5: 312951.71 | J5: 239744.38 | K5: 125298.98 | L5: 236620.18 | M5: 345838.47 | N5: 90171.48 | U5: =SUM(C5:T5) -> 1666153.5
B6: RCV PROJECT | C6: 19540.1 | D6: 111430.86 | E6: 119482.66 | F6: 405319.77 | G6: 223081.6 | H6: 163595.25 | I6: 256777.86 | J6: 234803.02 | K6: 260112.71 | L6: 357097.01 | M6: 208625.66 | N6: 589204.35 | O6: 497397.35 | U6: =SUM(C6:T6) -> 3446468.2
B7: TOTAL | C7: =SUM(C4:C6) -> 23502179 | D7: =SUM(D4:D6) -> 20299056 | E7: =SUM(E4:E6) -> 18016145 | F7: =SUM(F4:F6) -> 18169322 | G7: =SUM(G4:G6) -> 18422375 | H7: =SUM(H4:H6) -> 6317503.8 | I7: =SUM(I4:I6) -> 13135084 | J7: =SUM(J4:J6) -> 15964551 | ... O7: =SUM(O4:O6) -> 17852277 | U7: =SUM(U4:U6) -> 2.1059274e+08
B8: AVERAGE | C8: =AVERAGEA(C7:O7) -> 16199442

Sheet SOH-MAY
BL3: =SUMIF(BL11:BL33,"<0",BL11:BL34) -> -12078.02 | BM3: =SUMIF(BM11:BM33,"<0",BM11:BM34) -> -1124666.5
BL4: =SUMIF(BL11:BL33,">0",BL11:BL34) -> 5095.52 | BM4: =SUMIF(BM11:BM33,">0",BM11:BM34) -> 183245.94
BL5: =SUM(BL3:BL4) -> -6982.5 | BM5: =SUM(BM3:BM4) -> -941420.61
A6: EXPLOSIVES STOCK ON HAND/COSTING AS OF MAY 31, 2026
A7: 3
I8: DAILY ISSUANCE | AP8: ACTUAL COUNT SURFACE & UNDERGROUND | BC8: DELIVERIES | BG8: BARROWED MT. ROCK | BI8: LOGBOOK | BL8: VARIANCE | BO8: EXPLOSIVES ISSUANCE COSTING -DAILY | CT8: TOTAL COST
A9: DESCRIPTION | B9: UoM | C9: NEW PRICE 2025-2027 | D9: STOCK CODE | E9: EXPLOSIVES SOH APRIL 30, 2026 | G9: FOR DISPOSAL -SOH | I9: 46143 | J9: 46144 | K9: 46145 | L9: 46146 | M9: 46147 | N9: 46148 | O9: 46149 | P9: 46150 | Q9: 46151 | R9: 46152 | S9: 46153 | T9: 46154 | U9: 46155 | V9: 46156 | W9: 46157 | X9: 46158 | Y9: 46159 | Z9: 46160 | AA9: 46161 | AB9: 46162 | AC9: 46163 | AD9: 46164 | AE9: 46165 | AF9: 46166 | AG9: 46167 | AH9: 46168 | AI9: 46169 | AJ9: 46170 | AK9: 46171 | AL9: 46172 | AM9: 46173 | AN9: MONTHLY CONSUMPTION | AO9: MONTHLY COSTING | AP9: SURFACE AS OF MAY 31 2026 | AQ9: SINUG-ANG | AR9: MARATHON 3150 | AS9: L-5 | AT9: L-7 | AU9: L-8 | AV9: L-9 | AW9: L-10 | AX9: L-11 | AY9: L-12 | AZ9: L425 | BA9: UNDERGROUND AS OF MAY 31, 2026 | BB9: TOTAL QTY | BC9: 46162 | BD9: 46168 | BI9: REMAINING SOH AS MAY 31, 2026 | BJ9: TOTAL COST AS OF MAY 31,2026 | BO9: =I9 -> 46143 | BP9: =J9 -> 46144 | BQ9: =K9 -> 46145 | BR9: =L9 -> 46146 | BS9: =M9 -> 46147 | BT9: =N9 -> 46148 | BU9: =O9 -> 46149 | BV9: =P9 -> 46150 | ... CS9: =AM9 -> 46173
E10: QUANTITY | F10: COSTING | G10: QUANTITY | H10: COSTING | I10: QUANTITY | J10: QUANTITY | K10: QUANTITY | L10: QUANTITY | M10: QUANTITY | N10: QUANTITY | O10: QUANTITY | P10: QUANTITY | Q10: QUANTITY | R10: QUANTITY | S10: QUANTITY | T10: QUANTITY | U10: QUANTITY | V10: QUANTITY | W10: QUANTITY | X10: QUANTITY | Y10: QUANTITY | Z10: QUANTITY | AA10: QUANTITY | AB10: QUANTITY | AC10: QUANTITY | AD10: QUANTITY | AE10: QUANTITY | AF10: QUANTITY | AG10: QUANTITY | AH10: QUANTITY | AI10: QUANTITY | AJ10: QUANTITY | AK10: QUANTITY | AL10: QUANTITY | AM10: QUANTITY | AN10: QUANTITY | AO10: QUANTITY | AP10: QUANTITY | AQ10: QUANTITY | AR10: QUANTITY | AS10: QUANTITY | AT10: QUANTITY | AU10: QUANTITY | AV10: QUANTITY | AW10: QUANTITY | AX10: QUANTITY | AY10: QUANTITY | AZ10: QUANTITY | BA10: QUANTITY | BB10: QUANTITY | BC10: QUANTITY | BD10: QUANTITY | BE10: QUANTITY | BF10: QUANTITY | BG10: QUANTITY | BH10: QUANTITY | BI10: QUANTITY | BJ10: COSTING | BL10: QUANTITY | BM10: AMOUNT | BO10: FRI | BP10: SAT | BQ10: SUN | BR10: MON | BS10: TUE | BT10: WED | BU10: THU | BV10: FRI | BW10: SAT | BX10: SUN | BY10: MON | BZ10: TUE | CA10: WED | CB10: THU | CC10: FRI | CD10: SAT | CE10: SUN | CF10: MON | CG10: TUE | CH10: WED | CI10: THU | CJ10: FRI | CK10: SAT | CL10: SUN | CM10: MON | CN10: TUE | CO10: WED | CP10: THU | CQ10: FRI | CR10: SAT | CS10: SUN
A11: EM AUSTINE 200 | B11: PCS | C11: 26.2921 | E11: 0 | F11: 0 | J11: 0 | K11: 0 | L11: 0 | M11: 0 | N11: 0 | O11: 0 | P11: 0 | Q11: 0 | R11: 0 | S11: 0 | T11: 0 | U11: 0 | V11: 0 | W11: 0 | X11: 0 | Y11: 0 | Z11: 0 | AA11: 0 | AB11: 0 | AC11: 0 | AD11: 0 | AE11: 0 | AF11: 0 | AG11: 0 | AH11: 0 | AI11: 0 | AJ11: 0 | AK11: 0 | AL11: 0 | AM11: 0 | AN11: =SUM(I11:AM11) -> 0 | AO11: =C11*AN11 -> 0 | BA11: =SUM(AQ11:AY11) -> 0 | BB11: =BA11+AP11 -> 0 | BI11: =E11-I11-J11-K11-L11-M11-N11-O11-P11-Q11-R11-S11-T11-U11-V11-Y11-W11-Z11-AA11-AB11-AC11-AD11-AE11-AF11-AG11-AH11-AI11-AJ11-AK11-AM11-X11-AL11+BC11+BE11+BD11+BF11 -> 0 | BJ11: =BI11*C11 -> 0 | BL11: =BB11-BI11 -> 0 | BM11: =BL11*C11 -> 0 | BO11: =I11*C11 -> 0 | BP11: =J11*C11 -> 0 | BQ11: =K11*C11 -> 0 | BR11: =L11*C11 -> 0 | BS11: =M11*C11 -> 0 | BT11: =N11*C11 -> 0 | BU11: =O11*C11 -> 0 | BV11: =P11*C11 -> 0 | BW11: =Q11*C11 -> 0 | BX11: =R11*C11 -> 0 | BY11: =S11*C11 -> 0 | BZ11: =T11*C11 -> 0 | CA11: =U11*C11 -> 0 | CB11: =V11*C11 -> 0 | CC11: =W11*C11 -> 0 | CD11: =X11*C11 -> 0 | CE11: =C11*Y11 -> 0 | CF11: =C11*Z11 -> 0 | CG11: =AA11*C11 -> 0 | CH11: =C11*AB11 -> 0 | CI11: =C11*AC11 -> 0 | CJ11: =C11*AD11 -> 0 | CL11: =C11*AF11 -> 0 | CM11: =C11*AG11 -> 0 | CN11: =C11*AH11 -> 0 | CO11: =C11*AI11 -> 0 | CP11: =C11*AJ11 -> 0 | CQ11: =C11*AK11 -> 0 | CR11: =C11*AL11 -> 0 | CS11: =C11*AM11 -> 0
A12: DYNA NEOGEL 200 | B12: PCS | C12: 27.3438 | D12: 35245 | E12: 38714 | F12: 1559389.6 | J12: 1307 | K12: 1453 | L12: 1895 | M12: 1665 | N12: 2165 | O12: 1665 | P12: 1983 | Q12: 1996 | R12: 1611 | S12: 1697 | T12: 1731 | U12: 1811 | V12: 1339 | W12: 1513 | X12: 1192 | Y12: 1434 | Z12: 1427 | AA12: 1674 | AB12: 1779 | AC12: 1679 | AD12: 1676 | AE12: 1461 | AF12: 448 | AG12: 183 | AH12: 1626 | AI12: 1432 | AJ12: 1848 | AK12: 1795 | AL12: 1347 | AM12: 1532 | AN12: =SUM(I12:AM12) -> 46364 | AO12: =C12*AN12 -> 1267767.9 | AP12: 8000 | AY12: 9661 | AZ12: 4052 | BA12: =SUM(AQ12:AZ12) -> 13713 | BB12: =BA12+AP12 -> 21713 | BC12: 20000 | BD12: 15000 | BI12: =E12-I12-J12-K12-L12-M12-N12-O12-P12-Q12-R12-S12-T12-U12-V12-Y12-W12-Z12-AA12-AB12-AC12-AD12-AE12-AF12-AG12-AH12-AI12-AJ12-AK12-AM12-X12-AL12+BC12+BE12+BD12+BF12 -> 27350 | BJ12: =BI12*C12 -> 747852.93 | BL12: =BB12-BI12 -> -5637 | BM12: =BL12*C12 -> -154137 | BO12: =I12*C12 -> 0 | BP12: =J12*C12 -> 35738.347 | BQ12: =K12*C12 -> 39730.541 | BR12: =L12*C12 -> 51816.501 | BS12: =M12*C12 -> 45527.427 | BT12: =N12*C12 -> 59199.327 | BU12: =O12*C12 -> 45527.427 | BV12: =P12*C12 -> 54222.755 | BW12: =Q12*C12 -> 54578.225 | BX12: =R12*C12 -> 44050.862 | BY12: =S12*C12 -> 46402.429 | BZ12: =T12*C12 -> 47332.118 | CA12: =U12*C12 -> 49519.622 | CB12: =V12*C12 -> 36613.348 | CC12: =W12*C12 -> 41371.169 | CD12: =X12*C12 -> 32593.81 | CE12: =C12*Y12 -> 39211.009 | CF12: =C12*Z12 -> 39019.603 | CG12: =AA12*C12 -> 45773.521 | CH12: =C12*AB12 -> 48644.62 | CI12: =C12*AC12 -> 45910.24 | CJ12: =C12*AD12 -> 45828.209 | CK12: =C12*AE12 -> 39949.292 | CL12: =C12*AF12 -> 12250.022 | CM12: =C12*AG12 -> 5003.9154 | CN12: =C12*AH12 -> 44461.019 | CO12: =C12*AI12 -> 39156.322 | CP12: =C12*AJ12 -> 50531.342 | CQ12: =C12*AK12 -> 49082.121 | CR12: =C12*AL12 -> 36832.099 | CS12: =C12*AM12 -> 41890.702 | CT12: =SUM(BO12:CS12) -> 1267767.9 | CU12: =CT12+CT13+CT14+CT15+CT16+CT17+CT18+CT19+CT20+CT21+CT22+CT23+CT24+CT25+CT28+CT29+CT30+CT31+CT32+CT33 -> 17329054
A13: DYNAPULSAR 215 | B13: PCS | C13: 29.5639 | D13: 11082 | E13: 105602 | F13: 3595650.2 | J13: 822 | K13: 1065 | L13: 1552 | M13: 1323 | N13: 1186 | O13: 1103 | P13: 956 | Q13: 1172 | R13: 811 | S13: 1404 | T13: 1752 | U13: 1617 | V13: 1490 | W13: 926 | X13: 1081 | Y13: 1084 | Z13: 1052 | AA13: 1463 | AB13: 1644 | AC13: 1069 | AD13: 1302 | AE13: 2070 | AF13: 2127 | AG13: 2846 | AH13: 1591 | AI13: 2436 | AJ13: 1278 | AK13: 1503 | AL13: 1622 | AM13: 876 | AN13: =SUM(I13:AM13) -> 42223 | AO13: =C13*AN13 -> 1248276.5 | AP13: 59770 | AR13: 502 | AT13: 3690 | AU13: 14589 | AV13: 11133 | AW13: 9326 | AY13: 3655 | AZ13: 0 | BA13: =SUM(AQ13:AZ13) -> 42895 | BB13: =BA13+AP13 -> 102665 | BC13: 21500 | BD13: 16125 | BI13: =E13-I13-J13-K13-L13-M13-N13-O13-P13-Q13-R13-S13-T13-U13-V13-Y13-W13-Z13-AA13-AB13-AC13-AD13-AE13-AF13-AG13-AH13-AI13-AJ13-AK13-AM13-X13-AL13+BC13+BE13+BD13+BF13 -> 101004 | BJ13: =BI13*C13 -> 2986072.2 | BL13: =BB13-BI13 -> 1661 | BM13: =BL13*C13 -> 49105.638 | BO13: =I13*C13 -> 0 | BP13: =J13*C13 -> 24301.526 | BQ13: =K13*C13 -> 31485.554 | BR13: =L13*C13 -> 45883.173 | BS13: =M13*C13 -> 39113.04 | BT13: =N13*C13 -> 35062.785 | BU13: =O13*C13 -> 32608.982 | BV13: =P13*C13 -> 28263.088 | BW13: =Q13*C13 -> 34648.891 | BX13: =R13*C13 -> 23976.323 | BY13: =S13*C13 -> 41507.716 | BZ13: =T13*C13 -> 51795.953 | CA13: =U13*C13 -> 47804.826 | CB13: =V13*C13 -> 44050.211 | CC13: =W13*C13 -> 27376.171 | CD13: =X13*C13 -> 31958.576 | CE13: =C13*Y13 -> 32047.268 | CF13: =C13*Z13 -> 31101.223 | CG13: =AA13*C13 -> 43251.986 | CH13: =C13*AB13 -> 48603.052 | CI13: =C13*AC13 -> 31603.809 | CJ13: =C13*AD13 -> 38492.198 | CK13: =C13*AE13 -> 61197.273 | CL13: =C13*AF13 -> 62882.415 | CM13: =C13*AG13 -> 84138.859 | CN13: =C13*AH13 -> 47036.165 | CO13: =C13*AI13 -> 72017.66 | CP13: =C13*AJ13 -> 37782.664 | CQ13: =C13*AK13 -> 44434.542 | CR13: =C13*AL13 -> 47952.646 | CS13: =C13*AM13 -> 25897.976 | CT13: =SUM(BO13:CS13) -> 1248276.5
A14: ANFO | B14: KLS | C14: 145.88 | D14: 10128 | E14: 94798.32 | F14: 10136193 | J14: 667 | K14: 757 | L14: 1183 | M14: 1201.2 | N14: 1224 | O14: 1035.2 | P14: 1041.2 | Q14: 1028.8 | R14: 897.6 | S14: 1179 | T14: 1151.2 | U14: 1137.2 | V14: 974.6 | W14: 826.6 | X14: 757.4 | Y14: 799.5 | Z14: 988.2 | AA14: 1145.8 | AB14: 1254 | AC14: 1045 | AD14: 1166.6 | AE14: 1117.8 | AF14: 980.6 | AG14: 1160.4 | AH14: 1111.2 | AI14: 1256.4 | AJ14: 1243.8 | AK14: 939 | AL14: 915.8 | AM14: 776.4 | AN14: =SUM(I14:AM14) -> 30961.5 | AO14: =C14*AN14 -> 4516663.6 | AP14: 67600 | AR14: 195.2 | AT14: 263 | AU14: 3969 | AV14: 1436.2 | AW14: 2042.8 | AY14: 2702.6 | AZ14: 1722 | BA14: =SUM(AQ14:AZ14) -> 12330.8 | BB14: =BA14+AP14 -> 79930.8 | BC14: =350*25 -> 8750 | BD14: =350*25 -> 8750 | BI14: =E14-I14-J14-K14-L14-M14-N14-O14-P14-Q14-R14-S14-T14-U14-V14-Y14-W14-Z14-AA14-AB14-AC14-AD14-AE14-AF14-AG14-AH14-AI14-AJ14-AK14-AM14-X14-AL14+BC14+BE14+BD14+BF14 -> 81336.82 | BJ14: =BI14*C14 -> 11865415 | BL14: =BB14-BI14 -> -1406.02 | BM14: =BL14*C14 -> -205110.2 | BO14: =I14*C14 -> 0 | BP14: =J14*C14 -> 97301.96 | BQ14: =K14*C14 -> 110431.16 | BR14: =L14*C14 -> 172576.04 | BS14: =M14*C14 -> 175231.06 | BT14: =N14*C14 -> 178557.12 | BU14: =O14*C14 -> 151014.98 | BV14: =P14*C14 -> 151890.26 | BW14: =Q14*C14 -> 150081.34 | BX14: =R14*C14 -> 130941.89 | BY14: =S14*C14 -> 171992.52 | BZ14: =T14*C14 -> 167937.06 | CA14: =U14*C14 -> 165894.74 | CB14: =V14*C14 -> 142174.65 | CC14: =W14*C14 -> 120584.41 | CD14: =X14*C14 -> 110489.51 | CE14: =C14*Y14 -> 116631.06 | CF14: =C14*Z14 -> 144158.62 | CG14: =AA14*C14 -> 167149.3 | CH14: =C14*AB14 -> 182933.52 | CI14: =C14*AC14 -> 152444.6 | CJ14: =C14*AD14 -> 170183.61 | CK14: =C14*AE14 -> 163064.66 | CL14: =C14*AF14 -> 143049.93 | CM14: =C14*AG14 -> 169279.15 | CN14: =C14*AH14 -> 162101.86 | CO14: =C14*AI14 -> 183283.63 | CP14: =C14*AJ14 -> 181445.54 | CQ14: =C14*AK14 -> 136981.32 | CR14: =C14*AL14 -> 133596.9 | CS14: =C14*AM14 -> 113261.23 | CT14: =SUM(BO14:CS14) -> 4516663.6
A15: S/FUSE | B15: MTR | C15: 27.66 | D15: 12487 | E15: 23542.47 | F15: 779447.18 | J15: 240.57 | K15: 323.19 | L15: 447.12 | M15: 434.97 | N15: 425.25 | O15: 388.8 | P15: 391.23 | Q15: 413.1 | R15: 330.48 | S15: 464.13 | T15: 422.82 | U15: 456.84 | V15: 349.92 | W15: 332.91 | X15: 313.47 | Y15: 345.06 | Z15: 405.81 | AA15: 417.96 | AB15: 500.58 | AC15: 410.67 | AD15: 447.12 | AE15: 444.69 | AF15: 371.79 | AG15: 432.54 | AH15: 422.82 | AI15: 476.28 | AJ15: 490.86 | AK15: 510.3 | AL15: 425.25 | AM15: 318.33 | AN15: =SUM(I15:AM15) -> 12154.86 | AO15: =C15*AN15 -> 336203.43 | AP15: 15682.5 | AR15: =AR16*2.43 -> 546.75 | AS15: =AS16*2.43 -> 0 | AT15: =AT16*2.43 -> 422.82 | AU15: =AU16*2.43 -> 1873.53 | AV15: =AV16*2.43 -> 993.87 | AW15: =AW16*2.43 -> 879.66 | AX15: =AX16*2.43 -> 0 | AY15: =AY16*2.43 -> 1025.46 | AZ15: =AZ16*2.43 -> 189.54 | BA15: =SUM(AQ15:AZ15) -> 5931.63 | BB15: =BA15+AP15 -> 21614.13 | BC15: 4000 | BD15: 4000 | BI15: =E15-I15-J15-K15-L15-M15-N15-O15-P15-Q15-R15-S15-T15-U15-V15-Y15-W15-Z15-AA15-AB15-AC15-AD15-AE15-AF15-AG15-AH15-AI15-AJ15-AK15-AM15-X15-AL15+BC15+BE15+BD15+BF15 -> 19387.61 | BJ15: =BI15*C15 -> 536261.29 | BL15: =BB15-BI15 -> 2226.52 | BM15: =BL15*C15 -> 61585.543 | BO15: =I15*C15 -> 0 | BP15: =J15*C15 -> 6654.1662 | BQ15: =K15*C15 -> 8939.4354 | BR15: =L15*C15 -> 12367.339 | BS15: =M15*C15 -> 12031.27 | BT15: =N15*C15 -> 11762.415 | BU15: =O15*C15 -> 10754.208 | BV15: =P15*C15 -> 10821.422 | BW15: =Q15*C15 -> 11426.346 | BX15: =R15*C15 -> 9141.0768 | BY15: =S15*C15 -> 12837.836 | BZ15: =T15*C15 -> 11695.201 | CA15: =U15*C15 -> 12636.194 | CB15: =V15*C15 -> 9678.7872 | CC15: =W15*C15 -> 9208.2906 | CD15: =X15*C15 -> 8670.5802 | CE15: =C15*Y15 -> 9544.3596 | CF15: =C15*Z15 -> 11224.705 | CG15: =AA15*C15 -> 11560.774 | CH15: =C15*AB15 -> 13846.043 | CI15: =C15*AC15 -> 11359.132 | CJ15: =C15*AD15 -> 12367.339 | CK15: =C15*AE15 -> 12300.125 | CL15: =C15*AF15 -> 10283.711 | CM15: =C15*AG15 -> 11964.056 | CN15: =C15*AH15 -> 11695.201 | CO15: =C15*AI15 -> 13173.905 | CP15: =C15*AJ15 -> 13577.188 | CQ15: =C15*AK15 -> 14114.898 | CR15: =C15*AL15 -> 11762.415 | CS15: =C15*AM15 -> 8805.0078 | CT15: =SUM(BO15:CS15) -> 336203.43
A16: OBC | B16: PCS | C16: 26.25 | D16: 11966 | E16: 7429 | F16: 328282.5 | J16: 99 | K16: 133 | L16: 184 | M16: 179 | N16: 175 | O16: 160 | P16: 161 | Q16: 170 | R16: 136 | S16: 191 | T16: 174 | U16: 188 | V16: 144 | W16: 137 | X16: 129 | Y16: 142 | Z16: 167 | AA16: 172 | AB16: 206 | AC16: 169 | AD16: 184 | AE16: 183 | AF16: 153 | AG16: 178 | AH16: 174 | AI16: 196 | AJ16: 202 | AK16: 210 | AL16: 175 | AM16: 131 | AN16: =SUM(I16:AM16) -> 5002 | AO16: =C16*AN16 -> 131302.5 | AP16: 4550 | AR16: 225 | AT16: 174 | AU16: 771 | AV16: 409 | AW16: 362 | AY16: 422 | AZ16: 78 | BA16: =SUM(AQ16:AZ16) -> 2441 | BB16: =BA16+AP16 -> 6991 | BC16: 3000 | BD16: 2000 | BI16: =E16-I16-J16-K16-L16-M16-N16-O16-P16-Q16-R16-S16-T16-U16-V16-Y16-W16-Z16-AA16-AB16-AC16-AD16-AE16-AF16-AG16-AH16-AI16-AJ16-AK16-AM16-X16-AL16+BC16+BE16+BD16+BF16 -> 7427 | BJ16: =BI16*C16 -> 194958.75 | BL16: =BB16-BI16 -> -436 | BM16: =BL16*C16 -> -11445 | BO16: =I16*C16 -> 0 | BP16: =J16*C16 -> 2598.75 | BQ16: =K16*C16 -> 3491.25 | BR16: =L16*C16 -> 4830 | BS16: =M16*C16 -> 4698.75 | BT16: =N16*C16 -> 4593.75 | BU16: =O16*C16 -> 4200 | BV16: =P16*C16 -> 4226.25 | BW16: =Q16*C16 -> 4462.5 | BX16: =R16*C16 -> 3570 | BY16: =S16*C16 -> 5013.75 | BZ16: =T16*C16 -> 4567.5 | CA16: =U16*C16 -> 4935 | CB16: =V16*C16 -> 3780 | CC16: =W16*C16 -> 3596.25 | CD16: =X16*C16 -> 3386.25 | CE16: =C16*Y16 -> 3727.5 | CF16: =C16*Z16 -> 4383.75 | CG16: =AA16*C16 -> 4515 | CH16: =C16*AB16 -> 5407.5 | CI16: =C16*AC16 -> 4436.25 | CJ16: =C16*AD16 -> 4830 | CK16: =C16*AE16 -> 4803.75 | CL16: =C16*AF16 -> 4016.25 | CM16: =C16*AG16 -> 4672.5 | CN16: =C16*AH16 -> 4567.5 | CO16: =C16*AI16 -> 5145 | CP16: =C16*AJ16 -> 5302.5 | CQ16: =C16*AK16 -> 5512.5 | CR16: =C16*AL16 -> 4593.75 | CS16: =C16*AM16 -> 3438.75 | CT16: =SUM(BO16:CS16) -> 131302.5
A17: F/LIGHTER | B17: PCS | C17: 20.62 | D17: 11342 | E17: 275 | F17: 5691.12 | J17: 0 | K17: 0 | L17: 0 | M17: 0 | N17: 0 | O17: 0 | P17: 0 | Q17: 0 | R17: 0 | S17: 0 | T17: 0 | U17: 0 | V17: 0 | W17: 0 | X17: 0 | Y17: 0 | Z17: 0 | AA17: 0 | AB17: 0 | AC17: 0 | AD17: 0 | AE17: 0 | AF17: 0 | AG17: 0 | AH17: 0 | AI17: 0 | AJ17: 0 | AK17: 0 | AL17: 0 | AM17: 0 | AN17: =SUM(I17:AM17) -> 0 | AO17: =C17*AN17 -> 0 | AP17: 150 | AR17: 38 | AW17: 87 | BA17: =SUM(AQ17:AZ17) -> 125 | BB17: =BA17+AP17 -> 275 | BI17: =E17-I17-J17-K17-L17-M17-N17-O17-P17-Q17-R17-S17-T17-U17-V17-Y17-W17-Z17-AA17-AB17-AC17-AD17-AE17-AF17-AG17-AH17-AI17-AJ17-AK17-AM17-X17-AL17+BC17+BE17+BD17+BF17 -> 275 | BJ17: =BI17*C17 -> 5670.5 | BL17: =BB17-BI17 -> 0 | BM17: =BL17*C17 -> 0 | BO17: =I17*C17 -> 0 | BP17: =J17*C17 -> 0 | BQ17: =K17*C17 -> 0 | BR17: =L17*C17 -> 0 | BS17: =M17*C17 -> 0 | BT17: =N17*C17 -> 0 | BU17: =O17*C17 -> 0 | BV17: =P17*C17 -> 0 | BW17: =Q17*C17 -> 0 | BX17: =R17*C17 -> 0 | BY17: =S17*C17 -> 0 | BZ17: =T17*C17 -> 0 | CA17: =U17*C17 -> 0 | CB17: =V17*C17 -> 0 | CC17: =W17*C17 -> 0 | CD17: =X17*C17 -> 0 | CE17: =C17*Y17 -> 0 | CF17: =C17*Z17 -> 0 | CG17: =AA17*C17 -> 0 | CH17: =C17*AB17 -> 0 | CI17: =C17*AC17 -> 0 | CJ17: =C17*AD17 -> 0 | CK17: =C17*AE17 -> 0 | CL17: =C17*AF17 -> 0 | CM17: =C17*AG17 -> 0 | CN17: =C17*AH17 -> 0 | CO17: =C17*AI17 -> 0 | CP17: =C17*AJ17 -> 0 | CQ17: =C17*AK17 -> 0 | CR17: =C17*AL17 -> 0 | CS17: =C17*AM17 -> 0 | CT17: =SUM(BO17:CS17) -> 0
A18: NONEL 2.4 | B18: PCS | C18: 171.74107 | D18: 10962 | E18: 0 | F18: 0 | G18: 264 | H18: =G18*C18 -> 45339.643 | J18: 0 | K18: 0 | L18: 0 | M18: 0 | N18: 0 | O18: 0 | P18: 0 | Q18: 0 | R18: 0 | S18: 0 | T18: 0 | U18: 0 | V18: 0 | W18: 0 | X18: 0 | Y18: 0 | Z18: 0 | AA18: 0 | AB18: 0 | AC18: 0 | AD18: 0 | AE18: 0 | AF18: 0 | AG18: 0 | AH18: 0 | AI18: 0 | AJ18: 0 | AK18: 0 | AL18: 0 | AM18: 0 | AN18: =SUM(I18:AM18) -> 0 | AO18: =C18*AN18 -> 0 | AP18: 0 | BA18: =SUM(AQ18:AZ18) -> 0 | BB18: =BA18+AP18 -> 0 | BI18: =E18-I18-J18-K18-L18-M18-N18-O18-P18-Q18-R18-S18-T18-U18-V18-Y18-W18-Z18-AA18-AB18-AC18-AD18-AE18-AF18-AG18-AH18-AI18-AJ18-AK18-AM18-X18-AL18+BC18+BE18+BD18+BF18 -> 0 | BJ18: =BI18*C18 -> 0 | BL18: =BB18-BI18 -> 0 | BM18: =BL18*C18 -> 0 | BO18: =I18*C18 -> 0 | BP18: =J18*C18 -> 0 | BQ18: =K18*C18 -> 0 | BR18: =L18*C18 -> 0 | BS18: =M18*C18 -> 0 | BT18: =N18*C18 -> 0 | BU18: =O18*C18 -> 0 | BV18: =P18*C18 -> 0 | BW18: =Q18*C18 -> 0 | BX18: =R18*C18 -> 0 | BY18: =S18*C18 -> 0 | BZ18: =T18*C18 -> 0 | CA18: =U18*C18 -> 0 | CB18: =V18*C18 -> 0 | CC18: =W18*C18 -> 0 | CD18: =X18*C18 -> 0 | CE18: =C18*Y18 -> 0 | CF18: =C18*Z18 -> 0 | CG18: =AA18*C18 -> 0 | CH18: =C18*AB18 -> 0 | CI18: =C18*AC18 -> 0 | CJ18: =C18*AD18 -> 0 | CK18: =C18*AE18 -> 0 | CL18: =C18*AF18 -> 0 | CM18: =C18*AG18 -> 0 | CN18: =C18*AH18 -> 0 | CO18: =C18*AI18 -> 0 | CP18: =C18*AJ18 -> 0 | CQ18: =C18*AK18 -> 0 | CR18: =C18*AL18 -> 0 | CS18: =C18*AM18 -> 0 | CT18: =SUM(BO18:CS18) -> 0
A19: NONEL 3.6 | B19: PCS | C19: 176.78571 | D19: 15427 | E19: 0 | F19: 0 | G19: 847 | H19: =G19*C19 -> 149737.5 | J19: 0 | K19: 0 | L19: 0 | M19: 0 | N19: 0 | O19: 0 | P19: 0 | Q19: 0 | R19: 0 | S19: 0 | T19: 0 | U19: 0 | V19: 0 | W19: 0 | X19: 0 | Y19: 0 | Z19: 0 | AA19: 0 | AB19: 0 | AC19: 0 | AD19: 0 | AE19: 0 | AF19: 0 | AG19: 0 | AH19: 0 | AI19: 0 | AJ19: 0 | AK19: 0 | AL19: 0 | AM19: 0 | AN19: =SUM(I19:AM19) -> 0 | AO19: =C19*AN19 -> 0 | AP19: 0 | BA19: =SUM(AQ19:AZ19) -> 0 | BB19: =BA19+AP19 -> 0 | BI19: =E19-I19-J19-K19-L19-M19-N19-O19-P19-Q19-R19-S19-T19-U19-V19-Y19-W19-Z19-AA19-AB19-AC19-AD19-AE19-AF19-AG19-AH19-AI19-AJ19-AK19-AM19-X19-AL19+BC19+BE19+BD19+BF19 -> 0 | BJ19: =BI19*C19 -> 0 | BL19: =BB19-BI19 -> 0 | BM19: =BL19*C19 -> 0 | BO19: =I19*C19 -> 0 | BP19: =J19*C19 -> 0 | BQ19: =K19*C19 -> 0 | BR19: =L19*C19 -> 0 | BS19: =M19*C19 -> 0 | BT19: =N19*C19 -> 0 | BU19: =O19*C19 -> 0 | BV19: =P19*C19 -> 0 | BW19: =Q19*C19 -> 0 | BX19: =R19*C19 -> 0 | BY19: =S19*C19 -> 0 | BZ19: =T19*C19 -> 0 | CA19: =U19*C19 -> 0 | CB19: =V19*C19 -> 0 | CC19: =W19*C19 -> 0 | CD19: =X19*C19 -> 0 | CE19: =C19*Y19 -> 0 | CF19: =C19*Z19 -> 0 | CG19: =AA19*C19 -> 0 | CH19: =C19*AB19 -> 0 | CI19: =C19*AC19 -> 0 | CJ19: =C19*AD19 -> 0 | CK19: =C19*AE19 -> 0 | CL19: =C19*AF19 -> 0 | CM19: =C19*AG19 -> 0 | CN19: =C19*AH19 -> 0 | CO19: =C19*AI19 -> 0 | CP19: =C19*AJ19 -> 0 | CQ19: =C19*AK19 -> 0 | CR19: =C19*AL19 -> 0 | CS19: =C19*AM19 -> 0 | CT19: =SUM(BO19:CS19) -> 0
A20: SUPREME 2.4 | B20: PCS | C20: 180.35714 | D20: 16623 | E20: 16364 | F20: 2951364.3 | H20: =G20*C20 -> 0 | J20: 0 | K20: 0 | L20: 0 | M20: 0 | N20: 0 | O20: 0 | P20: 0 | Q20: 0 | R20: 0 | S20: 0 | T20: 0 | U20: 0 | V20: 0 | W20: 0 | X20: 0 | Y20: 0 | Z20: 0 | AA20: 0 | AB20: 0 | AC20: 0 | AD20: 0 | AE20: 0 | AF20: 0 | AG20: 0 | AH20: 0 | AI20: 0 | AJ20: 0 | AK20: 0 | AL20: 0 | AM20: 0 | AN20: =SUM(I20:AM20) -> 0 | AO20: =C20*AN20 -> 0 | AP20: 16361 | BA20: =SUM(AQ20:AZ20) -> 0 | BB20: =BA20+AP20 -> 16361 | BI20: =E20-I20-J20-K20-L20-M20-N20-O20-P20-Q20-R20-S20-T20-U20-V20-Y20-W20-Z20-AA20-AB20-AC20-AD20-AE20-AF20-AG20-AH20-AI20-AJ20-AK20-AM20-X20-AL20+BC20+BE20+BD20+BF20 -> 16364 | BJ20: =BI20*C20 -> 2951364.3 | BL20: =BB20-BI20 -> -3 | BM20: =BL20*C20 -> -541.07143 | BO20: =I20*C20 -> 0 | BP20: =J20*C20 -> 0 | BQ20: =K20*C20 -> 0 | BR20: =L20*C20 -> 0 | BS20: =M20*C20 -> 0 | BT20: =N20*C20 -> 0 | BU20: =O20*C20 -> 0 | BV20: =P20*C20 -> 0 | BW20: =Q20*C20 -> 0 | BX20: =R20*C20 -> 0 | BY20: =S20*C20 -> 0 | BZ20: =T20*C20 -> 0 | CA20: =U20*C20 -> 0 | CB20: =V20*C20 -> 0 | CC20: =W20*C20 -> 0 | CD20: =X20*C20 -> 0 | CE20: =C20*Y20 -> 0 | CF20: =C20*Z20 -> 0 | CG20: =AA20*C20 -> 0 | CH20: =C20*AB20 -> 0 | CI20: =C20*AC20 -> 0 | CJ20: =C20*AD20 -> 0 | CK20: =C20*AE20 -> 0 | CL20: =C20*AF20 -> 0 | CM20: =C20*AG20 -> 0 | CN20: =C20*AH20 -> 0 | CO20: =C20*AI20 -> 0 | CP20: =C20*AJ20 -> 0 | CQ20: =C20*AK20 -> 0 | CR20: =C20*AL20 -> 0 | CS20: =C20*AM20 -> 0 | CT20: =SUM(BO20:CS20) -> 0
A21: SHOCK STAR | B21: PCS | C21: 207 | E21: 0 | F21: 0 | H21: =G21*C21 -> 0 | J21: 0 | K21: 0 | L21: 0 | M21: 0 | N21: 0 | O21: 0 | P21: 0 | Q21: 0 | R21: 0 | S21: 0 | T21: 0 | U21: 0 | V21: 0 | W21: 0 | X21: 0 | Y21: 0 | Z21: 0 | AA21: 0 | AB21: 0 | AC21: 0 | AD21: 0 | AE21: 0 | AF21: 0 | AG21: 0 | AH21: 0 | AI21: 0 | AJ21: 0 | AK21: 0 | AL21: 0 | AM21: 0 | AN21: =SUM(I21:AM21) -> 0 | AO21: =C21*AN21 -> 0 | AP21: 0 | BA21: =SUM(AQ21:AZ21) -> 0 | BB21: =BA21+AP21 -> 0 | BI21: =E21-I21-J21-K21-L21-M21-N21-O21-P21-Q21-R21-S21-T21-U21-V21-Y21-W21-Z21-AA21-AB21-AC21-AD21-AE21-AF21-AG21-AH21-AI21-AJ21-AK21-AM21-X21-AL21+BC21+BE21+BD21+BF21 -> 0 | BJ21: =BI21*C21 -> 0 | BL21: =BB21-BI21 -> 0 | BM21: =BL21*C21 -> 0 | BO21: =I21*C21 -> 0 | BP21: =J21*C21 -> 0 | BQ21: =K21*C21 -> 0 | BR21: =L21*C21 -> 0 | BS21: =M21*C21 -> 0 | BT21: =N21*C21 -> 0 | BU21: =O21*C21 -> 0 | BV21: =P21*C21 -> 0 | BW21: =Q21*C21 -> 0 | BX21: =R21*C21 -> 0 | BY21: =S21*C21 -> 0 | BZ21: =T21*C21 -> 0 | CA21: =U21*C21 -> 0 | CB21: =V21*C21 -> 0 | CC21: =W21*C21 -> 0 | CD21: =X21*C21 -> 0 | CE21: =C21*Y21 -> 0 | CF21: =C21*Z21 -> 0 | CG21: =AA21*C21 -> 0 | CH21: =C21*AB21 -> 0 | CI21: =C21*AC21 -> 0 | CJ21: =C21*AD21 -> 0 | CK21: =C21*AE21 -> 0 | CL21: =C21*AF21 -> 0 | CM21: =C21*AG21 -> 0 | CN21: =C21*AH21 -> 0 | CO21: =C21*AI21 -> 0 | CP21: =C21*AJ21 -> 0 | CQ21: =C21*AK21 -> 0 | CR21: =C21*AL21 -> 0 | CS21: =C21*AM21 -> 0 | CT21: =SUM(BO21:CS21) -> 0
A22: PENTEX STOPE PREIME | B22: PCS | C22: 331 | D22: 12151 | E22: 0 | F22: 0 | G22: 95 | H22: =G22*C22 -> 31445 | AN22: =SUM(I22:AM22) -> 0 | AO22: =C22*AN22 -> 0 | AP22: 0 | BA22: =SUM(AQ22:AZ22) -> 0 | BB22: =BA22+AP22 -> 0 | BI22: =E22-I22-J22-K22-L22-M22-N22-O22-P22-Q22-R22-S22-T22-U22-V22-Y22-W22-Z22-AA22-AB22-AC22-AD22-AE22-AF22-AG22-AH22-AI22-AJ22-AK22-AM22-X22-AL22+BC22+BE22+BD22+BF22 -> 0 | BJ22: =BI22*C22 -> 0 | BL22: =BB22-BI22 -> 0 | BM22: =BL22*C22 -> 0 | BO22: =I22*C22 -> 0 | BP22: =J22*C22 -> 0 | BQ22: =K22*C22 -> 0 | BR22: =L22*C22 -> 0 | BS22: =M22*C22 -> 0 | BT22: =N22*C22 -> 0 | BU22: =O22*C22 -> 0 | BV22: =P22*C22 -> 0 | BW22: =Q22*C22 -> 0 | BX22: =R22*C22 -> 0 | BY22: =S22*C22 -> 0 | BZ22: =T22*C22 -> 0 | CA22: =U22*C22 -> 0 | CB22: =V22*C22 -> 0 | CC22: =W22*C22 -> 0 | CD22: =X22*C22 -> 0 | CE22: =C22*Y22 -> 0 | CF22: =C22*Z22 -> 0 | CG22: =AA22*C22 -> 0 | CH22: =C22*AB22 -> 0 | CI22: =C22*AC22 -> 0 | CJ22: =C22*AD22 -> 0 | CK22: =C22*AE22 -> 0 | CL22: =C22*AF22 -> 0 | CM22: =C22*AG22 -> 0 | CN22: =C22*AH22 -> 0 | CO22: =C22*AI22 -> 0 | CP22: =C22*AJ22 -> 0 | CQ22: =C22*AK22 -> 0 | CR22: =C22*AL22 -> 0 | CS22: =C22*AM22 -> 0 | CT22: =SUM(BO22:CS22) -> 0
A23: EXEL 2.4 | B23: PCS | C23: 189.38 | D23: 10965 | E23: 59481 | F23: 14524878 | H23: =G23*C23 -> 0 | J23: 1057 | K23: 1226 | L23: 1840 | M23: 1733 | N23: 1820 | O23: 1531 | P23: 1548 | Q23: 1597 | R23: 1328 | S23: 1731 | T23: 1779 | U23: 1743 | V23: 1490 | W23: 1298 | X23: 1201 | Y23: 1266 | Z23: 1450 | AA23: 1554 | AB23: 1627 | AC23: 1311 | AD23: 1432 | AE23: 1486 | AF23: 1144 | AG23: 1398 | AH23: 1398 | AI23: 1687 | AJ23: 1665 | AK23: 1406 | AL23: 1366 | AM23: 1110 | AN23: =SUM(I23:AM23) -> 44222 | AO23: =C23*AN23 -> 8374762.4 | AP23: ='EXEL 2.4 (SOH MINE)'!D20 -> 10350 | AR23: ='EXEL 2.4 (SOH MINE)'!E20 -> 2175 | AT23: ='EXEL 2.4 (SOH MINE)'!G20 -> 3650 | AU23: ='EXEL 2.4 (SOH MINE)'!H20 -> 6543 | AV23: ='EXEL 2.4 (SOH MINE)'!I20 -> 6292 | AW23: ='EXEL 2.4 (SOH MINE)'!J20 -> 5081 | AX23: ='EXEL 2.4 (SOH MINE)'!K20 -> 0 | AY23: ='EXEL 2.4 (SOH MINE)'!L20 -> 6240 | AZ23: ='EXEL 2.4 (SOH MINE)'!M20 -> 2594 | BA23: =SUM(AQ23:AZ23) -> 32575 | BB23: =BA23+AP23 -> 42925 | BC23: 25500 | BD23: 6000 | BI23: =E23-I23-J23-K23-L23-M23-N23-O23-P23-Q23-R23-S23-T23-U23-V23-Y23-W23-Z23-AA23-AB23-AC23-AD23-AE23-AF23-AG23-AH23-AI23-AJ23-AK23-AM23-X23-AL23+BC23+BE23+BD23+BF23 -> 46759 | BJ23: =BI23*C23 -> 8855219.4 | BL23: =BB23-BI23 -> -3834 | BM23: =BL23*C23 -> -726082.92 | BO23: =I23*C23 -> 0 | BP23: =J23*C23 -> 200174.66 | BQ23: =K23*C23 -> 232179.88 | BR23: =L23*C23 -> 348459.2 | BS23: =M23*C23 -> 328195.54 | BT23: =N23*C23 -> 344671.6 | BU23: =O23*C23 -> 289940.78 | BV23: =P23*C23 -> 293160.24 | BW23: =Q23*C23 -> 302439.86 | BX23: =R23*C23 -> 251496.64 | BY23: =S23*C23 -> 327816.78 | BZ23: =T23*C23 -> 336907.02 | CA23: =U23*C23 -> 330089.34 | CB23: =V23*C23 -> 282176.2 | CC23: =W23*C23 -> 245815.24 | CD23: =X23*C23 -> 227445.38 | CE23: =C23*Y23 -> 239755.08 | CF23: =C23*Z23 -> 274601 | CG23: =AA23*C23 -> 294296.52 | CH23: =C23*AB23 -> 308121.26 | CI23: =C23*AC23 -> 248277.18 | CJ23: =C23*AD23 -> 271192.16 | CK23: =C23*AE23 -> 281418.68 | CL23: =C23*AF23 -> 216650.72 | CM23: =C23*AG23 -> 264753.24 | CN23: =C23*AH23 -> 264753.24 | CO23: =C23*AI23 -> 319484.06 | CP23: =C23*AJ23 -> 315317.7 | CQ23: =C23*AK23 -> 266268.28 | CR23: =C23*AL23 -> 258693.08 | CS23: =C23*AM23 -> 210211.8 | CT23: =SUM(BO23:CS23) -> 8374762.4
A24: EXEL 4.9 | B24: PCS | C24: 195 | D24: 21809 | E24: 0 | F24: 0 | G24: 646 | H24: =G24*C24 -> 125970 | J24: 0 | K24: 0 | L24: 0 | M24: 0 | N24: 0 | O24: 0 | P24: 0 | Q24: 0 | R24: 0 | S24: 0 | T24: 0 | U24: 0 | V24: 0 | W24: 0 | X24: 0 | Y24: 0 | Z24: 0 | AA24: 0 | AB24: 0 | AC24: 0 | AD24: 0 | AE24: 0 | AF24: 0 | AG24: 0 | AH24: 0 | AI24: 0 | AJ24: 0 | AK24: 0 | AL24: 0 | AM24: 0 | AN24: =SUM(I24:AM24) -> 0 | AO24: =C24*AN24 -> 0 | AP24: 0 | BA24: =SUM(AQ24:AZ24) -> 0 | BB24: =BA24+AP24 -> 0 | BI24: =E24-I24-J24-K24-L24-M24-N24-O24-P24-Q24-R24-S24-T24-U24-V24-Y24-W24-Z24-AA24-AB24-AC24-AD24-AE24-AF24-AG24-AH24-AI24-AJ24-AK24-AM24-X24-AL24+BC24+BE24+BD24+BF24 -> 0 | BJ24: 0 | BL24: =BB24-BI24 -> 0 | BM24: =BL24*C24 -> 0 | BO24: =I24*C24 -> 0 | BP24: =J24*C24 -> 0 | BQ24: =K24*C24 -> 0 | BR24: =L24*C24 -> 0 | BS24: =M24*C24 -> 0 | BT24: =N24*C24 -> 0 | BU24: =O24*C24 -> 0 | BV24: =P24*C24 -> 0 | BW24: =Q24*C24 -> 0 | BX24: =R24*C24 -> 0 | BY24: =S24*C24 -> 0 | BZ24: =T24*C24 -> 0 | CA24: =U24*C24 -> 0 | CB24: =V24*C24 -> 0 | CC24: =W24*C24 -> 0 | CD24: =X24*C24 -> 0 | CE24: =C24*Y24 -> 0 | CF24: =C24*Z24 -> 0 | CG24: =AA24*C24 -> 0 | CH24: =C24*AB24 -> 0 | CI24: =C24*AC24 -> 0 | CJ24: =C24*AD24 -> 0 | CK24: =C24*AE24 -> 0 | CL24: =C24*AF24 -> 0 | CM24: =C24*AG24 -> 0 | CN24: =C24*AH24 -> 0 | CO24: =C24*AI24 -> 0 | CP24: =C24*AJ24 -> 0 | CQ24: =C24*AK24 -> 0 | CR24: =C24*AL24 -> 0 | CS24: =C24*AM24 -> 0 | CT24: =SUM(BO24:CS24) -> 0
A25: EXEL 3.6 | B25: PCS | C25: 195 | D25: 10966 | E25: 15644 | F25: 2275455 | H25: =G25*C25 -> 0 | J25: 13 | K25: 19 | L25: 28 | M25: 48 | N25: 65 | O25: 45 | P25: 51 | Q25: 55 | R25: 26 | S25: 39 | T25: 51 | U25: 59 | V25: 40 | W25: 26 | X25: 29 | Y25: 27 | Z25: 25 | AA25: 146 | AB25: 252 | AC25: 232 | AD25: 292 | AE25: 309 | AF25: 293 | AG25: 333 | AH25: 273 | AI25: 266 | AJ25: 128 | AK25: 122 | AL25: 98 | AM25: 63 | AN25: =SUM(I25:AM25) -> 3453 | AO25: =C25*AN25 -> 673335 | AP25: ='EXEL 3.6 (SOH MINE)'!D19 -> 8060 | AR25: ='EXEL 3.6 (SOH MINE)'!F19 -> 990 | AT25: ='EXEL 3.6 (SOH MINE)'!J19 -> 440 | AU25: ='EXEL 3.6 (SOH MINE)'!K19 -> 1162 | AV25: ='EXEL 3.6 (SOH MINE)'!L19 -> 440 | AW25: ='EXEL 3.6 (SOH MINE)'!M19 -> 493 | AX25: ='EXEL 3.6 (SOH MINE)'!N19 -> 0 | AY25: ='EXEL 3.6 (SOH MINE)'!O19 -> 668 | AZ25: ='EXEL 3.6 (SOH MINE)'!P19 -> 5 | BA25: =SUM(AQ25:AZ25) -> 4198 | BB25: =BA25+AP25 -> 12258 | BI25: =E25-I25-J25-K25-L25-M25-N25-O25-P25-Q25-R25-S25-T25-U25-V25-Y25-W25-Z25-AA25-AB25-AC25-AD25-AE25-AF25-AG25-AH25-AI25-AJ25-AK25-AM25-X25-AL25+BC25+BE25+BD25+BF25 -> 12191 | BJ25: =BI25*C25 -> 2377245 | BL25: =BB25-BI25 -> 67 | BM25: =BL25*C25 -> 13065 | BO25: =I25*C25 -> 0 | BP25: =J25*C25 -> 2535 | BQ25: =K25*C25 -> 3705 | BR25: =L25*C25 -> 5460 | BS25: =M25*C25 -> 9360 | BT25: =N25*C25 -> 12675 | BU25: =O25*C25 -> 8775 | BV25: =P25*C25 -> 9945 | BW25: =Q25*C25 -> 10725 | BX25: =R25*C25 -> 5070 | BY25: =S25*C25 -> 7605 | BZ25: =T25*C25 -> 9945 | CA25: =U25*C25 -> 11505 | CB25: =V25*C25 -> 7800 | CC25: =W25*C25 -> 5070 | CD25: =X25*C25 -> 5655 | CE25: =C25*Y25 -> 5265 | CF25: =C25*Z25 -> 4875 | CG25: =AA25*C25 -> 28470 | CH25: =C25*AB25 -> 49140 | CI25: =C25*AC25 -> 45240 | CJ25: =C25*AD25 -> 56940 | CK25: =C25*AE25 -> 60255 | CL25: =C25*AF25 -> 57135 | CM25: =C25*AG25 -> 64935 | CN25: =C25*AH25 -> 53235 | CO25: =C25*AI25 -> 51870 | CP25: =C25*AJ25 -> 24960 | CQ25: =C25*AK25 -> 23790 | CR25: =C25*AL25 -> 19110 | CS25: =C25*AM25 -> 12285 | CT25: =SUM(BO25:CS25) -> 673335
A26: MS 12 | B26: PCS | C26: 359.83 | E26: 0 | F26: 0 | H26: =G26*C26 -> 0 | AN26: =SUM(I26:AM26) -> 0 | AO26: =C26*AN26 -> 0 | AP26: 0 | BA26: =SUM(AQ26:AZ26) -> 0 | BB26: =BA26+AP26 -> 0 | BI26: =E26-I26-J26-K26-L26-M26-N26-O26-P26-Q26-R26-S26-T26-U26-V26-Y26-W26-Z26-AA26-AB26-AC26-AD26-AE26-AF26-AG26-AH26-AI26-AJ26-AK26-AM26-X26-AL26+BC26+BE26+BD26+BF26 -> 0 | BJ26: =BI26*C26 -> 0 | BL26: =BB26-BI26 -> 0 | BM26: =BL26*C26 -> 0 | BO26: =I26*C26 -> 0 | BP26: =J26*C26 -> 0 | BQ26: =K26*C26 -> 0 | BR26: =L26*C26 -> 0 | BS26: =M26*C26 -> 0 | BT26: =N26*C26 -> 0 | BU26: =O26*C26 -> 0 | BV26: =P26*C26 -> 0 | BW26: =Q26*C26 -> 0 | BX26: =R26*C26 -> 0 | BY26: =S26*C26 -> 0 | BZ26: =T26*C26 -> 0 | CA26: =U26*C26 -> 0 | CB26: =V26*C26 -> 0 | CC26: =W26*C26 -> 0 | CD26: =X26*C26 -> 0 | CE26: =C26*Y26 -> 0 | CF26: =C26*Z26 -> 0 | CG26: =AA26*C26 -> 0 | CH26: =C26*AB26 -> 0 | CI26: =C26*AC26 -> 0 | CJ26: =C26*AD26 -> 0 | CK26: =C26*AE26 -> 0 | CL26: =C26*AF26 -> 0 | CM26: =C26*AG26 -> 0 | CN26: =C26*AH26 -> 0 | CO26: =C26*AI26 -> 0 | CP26: =C26*AJ26 -> 0 | CQ26: =C26*AK26 -> 0 | CR26: =C26*AL26 -> 0 | CS26: =C26*AM26 -> 0 | CT26: =SUM(BO26:CS26) -> 0
A27: MS 18 | B27: PCS | C27: 379.46 | E27: 0 | F27: 0 | H27: =G27*C27 -> 0 | AN27: =SUM(I27:AM27) -> 0 | AO27: =C27*AN27 -> 0 | AP27: 0 | BA27: =SUM(AQ27:AZ27) -> 0 | BB27: =BA27+AP27 -> 0 | BI27: =E27-I27-J27-K27-L27-M27-N27-O27-P27-Q27-R27-S27-T27-U27-V27-Y27-W27-Z27-AA27-AB27-AC27-AD27-AE27-AF27-AG27-AH27-AI27-AJ27-AK27-AM27-X27-AL27+BC27+BE27+BD27+BF27 -> 0 | BJ27: =BI27*C27 -> 0 | BL27: =BB27-BI27 -> 0 | BM27: =BL27*C27 -> 0 | BO27: =I27*C27 -> 0 | BP27: =J27*C27 -> 0 | BQ27: =K27*C27 -> 0 | BR27: =L27*C27 -> 0 | BS27: =M27*C27 -> 0 | BT27: =N27*C27 -> 0 | BU27: =O27*C27 -> 0 | BV27: =P27*C27 -> 0 | BW27: =Q27*C27 -> 0 | BX27: =R27*C27 -> 0 | BY27: =S27*C27 -> 0 | BZ27: =T27*C27 -> 0 | CA27: =U27*C27 -> 0 | CB27: =V27*C27 -> 0 | CC27: =W27*C27 -> 0 | CD27: =X27*C27 -> 0 | CE27: =C27*Y27 -> 0 | CF27: =C27*Z27 -> 0 | CG27: =AA27*C27 -> 0 | CH27: =C27*AB27 -> 0 | CI27: =C27*AC27 -> 0 | CJ27: =C27*AD27 -> 0 | CK27: =C27*AE27 -> 0 | CL27: =C27*AF27 -> 0 | CM27: =C27*AG27 -> 0 | CN27: =C27*AH27 -> 0 | CO27: =C27*AI27 -> 0 | CP27: =C27*AJ27 -> 0 | CQ27: =C27*AK27 -> 0 | CR27: =C27*AL27 -> 0 | CS27: =C27*AM27 -> 0 | CT27: =SUM(BO27:CS27) -> 0
A28: CORDTEX 5 | B28: MTR | C28: 35.15 | D28: 10960 | E28: 17184 | F28: 1110669.7 | H28: =G28*C28 -> 0 | J28: 187 | K28: 313 | L28: 418 | M28: 396 | N28: 318 | O28: 257 | P28: 271 | Q28: 373 | R28: 509 | S28: 692 | T28: 646 | U28: 680 | V28: 591 | W28: 481 | X28: 430 | Y28: 343 | Z28: 339 | AA28: 495 | AB28: 399 | AC28: 329 | AD28: 357 | AE28: 365 | AF28: 252 | AG28: 453 | AH28: 459 | AI28: 389 | AJ28: 416 | AK28: 405 | AL28: 413 | AM28: 284 | AN28: =SUM(I28:AM28) -> 12260 | AO28: =C28*AN28 -> 430939 | AP28: 3600 | AR28: 240 | AT28: 780 | AU28: 4484 | AV28: 1601 | AW28: 597 | AY28: 0 | BA28: =SUM(AQ28:AZ28) -> 7702 | BB28: =BA28+AP28 -> 11302 | BC28: 2700 | BD28: 2700 | BI28: =E28-I28-J28-K28-L28-M28-N28-O28-P28-Q28-R28-S28-T28-U28-V28-Y28-W28-Z28-AA28-AB28-AC28-AD28-AE28-AF28-AG28-AH28-AI28-AJ28-AK28-AM28-X28-AL28+BC28+BE28+BD28+BF28 -> 10324 | BJ28: =BI28*C28 -> 362888.6 | BL28: =BB28-BI28 -> 978 | BM28: =BL28*C28 -> 34376.7 | BO28: =I28*C28 -> 0 | BP28: =J28*C28 -> 6573.05 | BQ28: =K28*C28 -> 11001.95 | BR28: =L28*C28 -> 14692.7 | BS28: =M28*C28 -> 13919.4 | BT28: =N28*C28 -> 11177.7 | BU28: =O28*C28 -> 9033.55 | BV28: =P28*C28 -> 9525.65 | BW28: =Q28*C28 -> 13110.95 | BX28: =R28*C28 -> 17891.35 | BY28: =S28*C28 -> 24323.8 | BZ28: =T28*C28 -> 22706.9 | CA28: =U28*C28 -> 23902 | CB28: =V28*C28 -> 20773.65 | CC28: =W28*C28 -> 16907.15 | CD28: =X28*C28 -> 15114.5 | CE28: =C28*Y28 -> 12056.45 | CF28: =C28*Z28 -> 11915.85 | CG28: =AA28*C28 -> 17399.25 | CH28: =C28*AB28 -> 14024.85 | CI28: =C28*AC28 -> 11564.35 | CJ28: =C28*AD28 -> 12548.55 | CK28: =C28*AE28 -> 12829.75 | CL28: =C28*AF28 -> 8857.8 | CM28: =C28*AG28 -> 15922.95 | CN28: =C28*AH28 -> 16133.85 | CO28: =C28*AI28 -> 13673.35 | CP28: =C28*AJ28 -> 14622.4 | CQ28: =C28*AK28 -> 14235.75 | CR28: =C28*AL28 -> 14516.95 | CS28: =C28*AM28 -> 9982.6 | CT28: =SUM(BO28:CS28) -> 430939
A29: CORDTEX 10 | B29: MTR | C29: 35.892857 | D29: 10961 | E29: 16123 | F29: 54987.857 | H29: =G29*C29 -> 0 | J29: 290 | K29: 239 | L29: 412 | M29: 358 | N29: 454 | O29: 422 | P29: 413 | Q29: 324 | R29: 85 | S29: 88 | T29: 104 | U29: 86 | V29: 90 | W29: 77 | X29: 85 | Y29: 218 | Z29: 272 | AA29: 269 | AB29: 423 | AC29: 364 | AD29: 387 | AE29: 437 | AF29: 384 | AG29: 333 | AH29: 314 | AI29: 452 | AJ29: 448 | AK29: 322 | AL29: 292 | AM29: 282 | AN29: =SUM(I29:AM29) -> 8724 | AO29: =C29*AN29 -> 313129.29 | AP29: 8000 | AV29: 0 | AW29: 1000 | AY29: 2396 | AZ29: 1241 | BA29: =SUM(AQ29:AZ29) -> 4637 | BB29: =BA29+AP29 -> 12637 | BC29: 3000 | BD29: 3000 | BI29: =E29-I29-J29-K29-L29-M29-N29-O29-P29-Q29-R29-S29-T29-U29-V29-Y29-W29-Z29-AA29-AB29-AC29-AD29-AE29-AF29-AG29-AH29-AI29-AJ29-AK29-AM29-X29-AL29+BC29+BE29+BD29+BF29 -> 13399 | BJ29: =BI29*C29 -> 480928.39 | BL29: =BB29-BI29 -> -762 | BM29: =BL29*C29 -> -27350.357 | BO29: =I29*C29 -> 0 | BP29: =J29*C29 -> 10408.929 | BQ29: =K29*C29 -> 8578.3929 | BR29: =L29*C29 -> 14787.857 | BS29: =M29*C29 -> 12849.643 | BT29: =N29*C29 -> 16295.357 | BU29: =O29*C29 -> 15146.786 | BV29: =P29*C29 -> 14823.75 | BW29: =Q29*C29 -> 11629.286 | BX29: =R29*C29 -> 3050.8929 | BY29: =S29*C29 -> 3158.5714 | BZ29: =T29*C29 -> 3732.8571 | CA29: =U29*C29 -> 3086.7857 | CB29: =V29*C29 -> 3230.3571 | CC29: =W29*C29 -> 2763.75 | CD29: =X29*C29 -> 3050.8929 | CE29: =C29*Y29 -> 7824.6429 | CF29: =C29*Z29 -> 9762.8571 | CG29: =AA29*C29 -> 9655.1786 | CH29: =C29*AB29 -> 15182.679 | CI29: =C29*AC29 -> 13065 | CJ29: =C29*AD29 -> 13890.536 | CK29: =C29*AE29 -> 15685.179 | CL29: =C29*AF29 -> 13782.857 | CM29: =C29*AG29 -> 11952.321 | CN29: =C29*AH29 -> 11270.357 | CO29: =C29*AI29 -> 16223.571 | CP29: =C29*AJ29 -> 16080 | CQ29: =C29*AK29 -> 11557.5 | CR29: =C29*AL29 -> 10480.714 | CS29: =C29*AM29 -> 10121.786 | CT29: =SUM(BO29:CS29) -> 313129.29
A30: DCORD I 5 | B30: MTR | C30: 37.5 | E30: 0 | F30: 29887.5 | H30: =G30*C30 -> 0 | J30: 0 | K30: 0 | L30: 0 | M30: 0 | N30: 0 | O30: 0 | P30: 0 | Q30: 0 | R30: 0 | S30: 0 | T30: 0 | U30: 0 | V30: 0 | W30: 0 | X30: 0 | Y30: 0 | Z30: 0 | AA30: 0 | AB30: 0 | AC30: 0 | AD30: 0 | AE30: 0 | AF30: 0 | AG30: 0 | AH30: 0 | AI30: 0 | AJ30: 0 | AK30: 0 | AL30: 0 | AM30: 0 | AN30: =SUM(I30:AM30) -> 0 | AO30: =C30*AN30 -> 0 | AP30: 0 | AV30: 0 | BA30: =SUM(AQ30:AZ30) -> 0 | BB30: =BA30+AP30 -> 0 | BI30: =E30-I30-J30-K30-L30-M30-N30-O30-P30-Q30-R30-S30-T30-U30-V30-Y30-W30-Z30-AA30-AB30-AC30-AD30-AE30-AF30-AG30-AH30-AI30-AJ30-AK30-AM30-X30-AL30+BC30+BE30+BD30+BF30 -> 0 | BJ30: =BI30*C30 -> 0 | BL30: =BB30-BI30 -> 0 | BM30: =BL30*C30 -> 0 | BO30: =I30*C30 -> 0 | BP30: =J30*C30 -> 0 | BQ30: =K30*C30 -> 0 | BR30: =L30*C30 -> 0 | BS30: =M30*C30 -> 0 | BT30: =N30*C30 -> 0 | BU30: =O30*C30 -> 0 | BV30: =P30*C30 -> 0 | BW30: =Q30*C30 -> 0 | BX30: =R30*C30 -> 0 | BY30: =S30*C30 -> 0 | BZ30: =T30*C30 -> 0 | CA30: =U30*C30 -> 0 | CB30: =V30*C30 -> 0 | CC30: =W30*C30 -> 0 | CD30: =X30*C30 -> 0 | CE30: =C30*Y30 -> 0 | CF30: =C30*Z30 -> 0 | CG30: =AA30*C30 -> 0 | CH30: =C30*AB30 -> 0 | CI30: =C30*AC30 -> 0 | CJ30: =C30*AD30 -> 0 | CK30: =C30*AE30 -> 0 | CL30: =C30*AF30 -> 0 | CM30: =C30*AG30 -> 0 | CN30: =C30*AH30 -> 0 | CO30: =C30*AI30 -> 0 | CP30: =C30*AJ30 -> 0 | CQ30: =C30*AK30 -> 0 | CR30: =C30*AL30 -> 0 | CS30: =C30*AM30 -> 0 | CT30: =SUM(BO30:CS30) -> 0
A31: CORDTEX 40 | B31: MTR | C31: 81.9 | D31: 10959 | E31: 0 | F31: 0 | G31: 1060 | H31: =G31*C31 -> 86814 | AN31: =SUM(I31:AM31) -> 0 | AO31: =C31*AN31 -> 0 | AP31: 0 | BA31: =SUM(AQ31:AZ31) -> 0 | BB31: =BA31+AP31 -> 0 | BI31: =E31-I31-J31-K31-L31-M31-N31-O31-P31-Q31-R31-S31-T31-U31-V31-Y31-W31-Z31-AA31-AB31-AC31-AD31-AE31-AF31-AG31-AH31-AI31-AJ31-AK31-AM31-X31-AL31+BC31+BE31+BD31+BF31 -> 0 | BJ31: =BI31*C31 -> 0 | BL31: =BB31-BI31 -> 0 | BM31: =BL31*C31 -> 0 | BO31: =I31*C31 -> 0 | BP31: =J31*C31 -> 0 | BQ31: =K31*C31 -> 0 | BR31: =L31*C31 -> 0 | BS31: =M31*C31 -> 0 | BT31: =N31*C31 -> 0 | BU31: =O31*C31 -> 0 | BV31: =P31*C31 -> 0 | BW31: =Q31*C31 -> 0 | BX31: =R31*C31 -> 0 | BY31: =S31*C31 -> 0 | BZ31: =T31*C31 -> 0 | CA31: =U31*C31 -> 0 | CB31: =V31*C31 -> 0 | CC31: =W31*C31 -> 0 | CD31: =X31*C31 -> 0 | CE31: =C31*Y31 -> 0 | CF31: =C31*Z31 -> 0 | CG31: =AA31*C31 -> 0 | CH31: =C31*AB31 -> 0 | CI31: =C31*AC31 -> 0 | CJ31: =C31*AD31 -> 0 | CK31: =C31*AE31 -> 0 | CL31: =C31*AF31 -> 0 | CM31: =C31*AG31 -> 0 | CN31: =C31*AH31 -> 0 | CO31: =C31*AI31 -> 0 | CP31: =C31*AJ31 -> 0 | CQ31: =C31*AK31 -> 0 | CR31: =C31*AL31 -> 0 | CS31: =C31*AM31 -> 0 | CT31: =SUM(BO31:CS31) -> 0
A32: BILL WIRE | B32: MTR | C32: 7.5 | D32: 16823 | E32: 2275 | F32: 16012.5 | H32: =G32*C32 -> 0 | J32: 0 | K32: 0 | L32: 0 | M32: 0 | N32: 0 | O32: 0 | P32: 0 | Q32: 0 | R32: 0 | S32: 30 | T32: 0 | U32: 0 | V32: 0 | W32: 0 | X32: 0 | Y32: 0 | Z32: 0 | AA32: 0 | AB32: 0 | AC32: 300 | AD32: 0 | AE32: 0 | AF32: 0 | AG32: 0 | AH32: 0 | AI32: 0 | AJ32: 0 | AK32: 0 | AL32: 0 | AM32: 0 | AN32: =SUM(I32:AM32) -> 330 | AO32: =C32*AN32 -> 2475 | AP32: 915 | AU32: 180 | AV32: 446 | AW32: 285 | AY32: 70 | AZ32: 120 | BA32: =SUM(AQ32:AZ32) -> 1101 | BB32: =BA32+AP32 -> 2016 | BI32: =E32-I32-J32-K32-L32-M32-N32-O32-P32-Q32-R32-S32-T32-U32-V32-Y32-W32-Z32-AA32-AB32-AC32-AD32-AE32-AF32-AG32-AH32-AI32-AJ32-AK32-AM32-X32-AL32+BC32+BE32+BD32+BF32 -> 1945 | BJ32: =BI32*C32 -> 14587.5 | BL32: =BB32-BI32 -> 71 | BM32: =BL32*C32 -> 532.5 | BO32: =I32*C32 -> 0 | BP32: =J32*C32 -> 0 | BQ32: =K32*C32 -> 0 | BR32: =L32*C32 -> 0 | BS32: =M32*C32 -> 0 | BT32: =N32*C32 -> 0 | BU32: =O32*C32 -> 0 | BV32: =P32*C32 -> 0 | BW32: =Q32*C32 -> 0 | BX32: =R32*C32 -> 0 | BY32: =S32*C32 -> 225 | BZ32: =T32*C32 -> 0 | CA32: =U32*C32 -> 0 | CB32: =V32*C32 -> 0 | CC32: =W32*C32 -> 0 | CD32: =X32*C32 -> 0 | CE32: =C32*Y32 -> 0 | CF32: =C32*Z32 -> 0 | CG32: =AA32*C32 -> 0 | CH32: =C32*AB32 -> 0 | CI32: =C32*AC32 -> 2250 | CJ32: =C32*AD32 -> 0 | CK32: =C32*AE32 -> 0 | CL32: =C32*AF32 -> 0 | CM32: =C32*AG32 -> 0 | CN32: =C32*AH32 -> 0 | CO32: =C32*AI32 -> 0 | CP32: =C32*AJ32 -> 0 | CQ32: =C32*AK32 -> 0 | CR32: =C32*AL32 -> 0 | CS32: =C32*AM32 -> 0 | CT32: =SUM(BO32:CS32) -> 2475
A33: EBC | B33: PCS | C33: 267.18 | D33: 11089 | E33: 322 | F33: 54504.72 | H33: =G33*C33 -> 0 | J33: 4 | K33: 8 | L33: 4 | M33: 8 | N33: 6 | O33: 8 | P33: 2 | Q33: 6 | R33: 4 | S33: 2 | T33: 6 | U33: 4 | V33: 6 | W33: 4 | X33: 2 | Y33: 0 | Z33: 2 | AA33: 2 | AB33: 0 | AC33: 4 | AD33: 4 | AE33: 6 | AF33: 4 | AG33: 6 | AH33: 6 | AI33: 4 | AJ33: 4 | AK33: 4 | AL33: 6 | AM33: 2 | AN33: =SUM(I33:AM33) -> 128 | AO33: =C33*AN33 -> 34199.04 | AP33: 177 | AT33: 10 | AU33: 56 | AV33: 94 | AW33: 0 | AY33: 0 | AZ33: 29 | BA33: =SUM(AQ33:AZ33) -> 189 | BB33: =BA33+AP33 -> 366 | BC33: 80 | BI33: =E33-I33-J33-K33-L33-M33-N33-O33-P33-Q33-R33-S33-T33-U33-V33-Y33-W33-Z33-AA33-AB33-AC33-AD33-AE33-AF33-AG33-AH33-AI33-AJ33-AK33-AM33-X33-AL33+BC33+BE33+BD33+BF33 -> 274 | BJ33: =BI33*C33 -> 73207.32 | BL33: =BB33-BI33 -> 92 | BM33: =BL33*C33 -> 24580.56 | BO33: =I33*C33 -> 0 | BP33: =J33*C33 -> 1068.72 | BQ33: =K33*C33 -> 2137.44 | BR33: =L33*C33 -> 1068.72 | BS33: =M33*C33 -> 2137.44 | BT33: =N33*C33 -> 1603.08 | BU33: =O33*C33 -> 2137.44 | BV33: =P33*C33 -> 534.36 | BW33: =Q33*C33 -> 1603.08 | BX33: =R33*C33 -> 1068.72 | BY33: =S33*C33 -> 534.36 | BZ33: =T33*C33 -> 1603.08 | CA33: =U33*C33 -> 1068.72 | CB33: =V33*C33 -> 1603.08 | CC33: =W33*C33 -> 1068.72 | CD33: =X33*C33 -> 534.36 | CE33: =C33*Y33 -> 0 | CF33: =C33*Z33 -> 534.36 | CG33: =AA33*C33 -> 534.36 | CH33: =C33*AB33 -> 0 | CI33: =C33*AC33 -> 1068.72 | CJ33: =C33*AD33 -> 1068.72 | CK33: =C33*AE33 -> 1603.08 | CL33: =C33*AF33 -> 1068.72 | CM33: =C33*AG33 -> 1603.08 | CN33: =C33*AH33 -> 1603.08 | CO33: =C33*AI33 -> 1068.72 | CP33: =C33*AJ33 -> 1068.72 | CQ33: =C33*AK33 -> 1068.72 | CR33: =C33*AL33 -> 1603.08 | CS33: =C33*AM33 -> 534.36 | CT33: =SUM(BO33:CS33) -> 34199.04
E34: TOTAL COST | F34: =SUM(F11:F33) -> 37422413 | G34: TOTAL COST | H34: =SUM(H11:H33) -> 439306.14 | I34: =SUM(I11:I33) -> 0 | J34: =SUM(J11:J33) -> 4686.57 | K34: =SUM(K11:K33) -> 5536.19 | L34: =SUM(L11:L33) -> 7963.12 | M34: =SUM(M11:M33) -> 7346.17 | N34: =SUM(N11:N33) -> 7838.25 | O34: =SUM(O11:O33) -> 6615 | ... AO34: =SUM(AO11:AO33) -> 17329054 | AP34: 0 | BJ34: =SUM(BJ11:BJ33) -> 31451671 | BN34: COST PER DAY | BO34: =SUM(BO11:BO33) -> 0 | BP34: =SUM(BP11:BP33) -> 387355.11 | BQ34: =SUM(BQ11:BQ33) -> 451680.6 | BR34: =SUM(BR11:BR33) -> 671941.53 | BS34: =SUM(BS11:BS33) -> 643063.57 | BT34: =SUM(BT11:BT33) -> 675598.13 | BU34: =SUM(BU11:BU33) -> 569139.15 | BV34: =SUM(BV11:BV33) -> 577412.77 | ... CS34: =SUM(CS11:CS33) -> 436429.21 | CT34: =SUM(BO34:CS34) -> 17329054
BP35: =SUM(BP12:BP34) -> 774710.21 | CA35: =BO34+BP34+BQ34+BR34+BS34+BT34+BU34+BV34+BW34+BX34+BY34+CA34+CB34+CC34 -> 7378655.5 | CB35: =CD34+CE34+CF34+CG34+CH34+CI34+CJ34+CK34+CL34+CM34+CN34+CO34+CP34+CQ34+CR34 -> 8855746.3 | CS35: NEOGEL CONSUMPTION
CC36: 1-15 | CD36: 16-30 | CS36: UNIT PRICE
CD37: =CD34+CE34+CF34+CG34+CH34+CI34+CJ34+CK34+CL34+CM34+CN34+CO34+CP34+CQ34+CR34 -> 8855746.3 | CS37: TOTAL COST
CS38: LESS NEOGEL

Sheet INVENTORY-MAY
A5: EXPLOSIVES STOCK INVENTORY
A6: ='EXPEDITION '!B3 -> DATE: MAY 31,2026 | I6: DAILY ISSUANCE | AN6: INCOMING | AS6: BARROWED MT. ROCK
A7: DESCRIPTION | B7: UoM | C7: UNIT COST | D7: FOR DISPOSAL -SOH | F7: SOH SURFACE APRIL 31,2024 | G7: SOH UNDERGROUND APRIL 31,2024 | H7: EXPLOSIVES SOH APRIL 30 ,2025 | I7: ='SOH-MAY'!I9 -> 46143 | J7: ='SOH-MAY'!J9 -> 46144 | K7: ='SOH-MAY'!K9 -> 46145 | L7: ='SOH-MAY'!L9 -> 46146 | M7: ='SOH-MAY'!M9 -> 46147 | N7: ='SOH-MAY'!N9 -> 46148 | O7: ='SOH-MAY'!O9 -> 46149 | P7: ='SOH-MAY'!P9 -> 46150 | ... AM7: ='SOH-MAY'!AM9 -> 46173 | AN7: 46162 | AO7: 46168 | AU7: REMAINING SOH AS MAY 31,2026 | AV7: TOTAL COST AS OF MAY 31, 2026 | AW7: TO BE WITHDRAWN FROM SUPPLIER MAGAZINE ON | AX7: TOTAL COST
D8: QUANTITY | E8: COSTING | F8: QUANTITY | G8: QUANTITY | H8: QUANTITY | I8: QUANTITY | J8: QUANTITY | K8: QUANTITY | L8: QUANTITY | M8: QUANTITY | N8: QUANTITY | O8: QUANTITY | P8: QUANTITY | Q8: QUANTITY | R8: QUANTITY | S8: QUANTITY | T8: QUANTITY | U8: QUANTITY | V8: QUANTITY | W8: QUANTITY | X8: QUANTITY | Y8: QUANTITY | Z8: QUANTITY | AA8: QUANTITY | AB8: QUANTITY | AC8: QUANTITY | AD8: QUANTITY | AE8: QUANTITY | AF8: QUANTITY | AG8: QUANTITY | AH8: QUANTITY | AI8: QUANTITY | AJ8: QUANTITY | AK8: QUANTITY | AL8: QUANTITY | AM8: QUANTITY | AN8: QUANTITY | AO8: QUANTITY | AP8: QUANTITY | AQ8: QUANTITY | AR8: QUANTITY | AS8: QUANTITY | AT8: QUANTITY | AU8: QUANTITY | AV8: COSTING
A9: EM AUSTINE 200 | B9: PCS | C9: 26.2921 | H9: 0 | J9: 0 | K9: 0 | L9: 0 | M9: 0 | N9: 0 | O9: 0 | P9: 0 | Q9: 0 | R9: 0 | S9: 0 | T9: 0 | U9: 0 | V9: 0 | W9: 0 | X9: 0 | Y9: 0 | Z9: 0 | AA9: 0 | AB9: 0 | AC9: 0 | AD9: 0 | AE9: 0 | AF9: 0 | AG9: 0 | AH9: 0 | AI9: 0 | AJ9: 0 | AK9: 0 | AL9: 0 | AM9: 0 | AU9: =H9-I9-J9-K9-L9-M9-N9-O9-P9-Q9-R9-S9-T9-U9-V9-W9-X9-Y9-Z9-AA9-AB9-AC9-AD9-AE9-AF9-AG9-AH9-AI9-AJ9-AK9-AL9-AM9+AN9+AQ9+AR9+AP9+AO9 -> 0 | AV9: =C9*AU9 -> 0 | AX9: =AW9*C9 -> 0
A10: DYNA NEOGEL 200 | B10: PCS | C10: 27.3438 | H10: 38714 | J10: 1307 | K10: 1453 | L10: 1895 | M10: 1665 | N10: 2165 | O10: 1665 | P10: 1983 | Q10: 1996 | R10: 1611 | S10: 1697 | T10: 1731 | U10: 1811 | V10: 1339 | W10: 1513 | X10: 1192 | Y10: 1434 | Z10: 1427 | AA10: 1674 | AB10: 1779 | AC10: 1679 | AD10: 1676 | AE10: 1461 | AF10: 448 | AG10: 183 | AH10: 1626 | AI10: 1432 | AJ10: 1848 | AK10: 1795 | AL10: 1347 | AM10: 1532 | AN10: 20000 | AO10: 15000 | AU10: =H10-I10-J10-K10-L10-M10-N10-O10-P10-Q10-R10-S10-T10-U10-V10-W10-X10-Y10-Z10-AA10-AB10-AC10-AD10-AE10-AF10-AG10-AH10-AI10-AJ10-AK10-AL10-AM10+AN10+AQ10+AR10+AP10+AO10 -> 27350 | AV10: =C10*AU10 -> 747852.93 | AX10: =AW10*C10 -> 0
A11: DYNA SENATEL PULSAR 215 | B11: PCS | C11: 29.5639 | H11: 105602 | J11: 822 | K11: 1065 | L11: 1552 | M11: 1323 | N11: 1186 | O11: 1103 | P11: 956 | Q11: 1172 | R11: 811 | S11: 1404 | T11: 1752 | U11: 1617 | V11: 1490 | W11: 926 | X11: 1081 | Y11: 1084 | Z11: 1052 | AA11: 1463 | AB11: 1644 | AC11: 1069 | AD11: 1302 | AE11: 2070 | AF11: 2127 | AG11: 2846 | AH11: 1591 | AI11: 2436 | AJ11: 1278 | AK11: 1503 | AL11: 1622 | AM11: 876 | AN11: 21500 | AO11: 16125 | AU11: =H11-I11-J11-K11-L11-M11-N11-O11-P11-Q11-R11-S11-T11-U11-V11-W11-X11-Y11-Z11-AA11-AB11-AC11-AD11-AE11-AF11-AG11-AH11-AI11-AJ11-AK11-AL11-AM11+AN11+AQ11+AR11+AP11+AO11 -> 101004 | AV11: =C11*AU11 -> 2986072.2 | AX11: =AW11*C11 -> 0
A12: ANFO | B12: KLS | C12: 145.88 | H12: 94798.32 | J12: 667 | K12: 757 | L12: 1183 | M12: 1201.2 | N12: 1224 | O12: 1035.2 | P12: 1041.2 | Q12: 1028.8 | R12: 897.6 | S12: 1179 | T12: 1151.2 | U12: 1137.2 | V12: 974.6 | W12: 826.6 | X12: 757.4 | Y12: 799.5 | Z12: 988.2 | AA12: 1145.8 | AB12: 1254 | AC12: 1045 | AD12: 1166.6 | AE12: 1117.8 | AF12: 980.6 | AG12: 1160.4 | AH12: 1111.2 | AI12: 1256.4 | AJ12: 1243.8 | AK12: 939 | AL12: 915.8 | AM12: 776.4 | AN12: 8750 | AO12: =350*25 -> 8750 | AU12: =H12-I12-J12-K12-L12-M12-N12-O12-P12-Q12-R12-S12-T12-U12-V12-W12-X12-Y12-Z12-AA12-AB12-AC12-AD12-AE12-AF12-AG12-AH12-AI12-AJ12-AK12-AL12-AM12+AN12+AQ12+AR12+AP12+AO12 -> 81336.82 | AV12: =C12*AU12 -> 11865415 | AX12: =AW12*C12 -> 0
A13: S/FUSE | B13: MTR | C13: 27.66 | H13: 23542.47 | J13: 240.57 | K13: 323.19 | L13: 447.12 | M13: 434.97 | N13: 425.25 | O13: 388.8 | P13: 391.23 | Q13: 413.1 | R13: 330.48 | S13: 464.13 | T13: 422.82 | U13: 456.84 | V13: 349.92 | W13: 332.91 | X13: 313.47 | Y13: 345.06 | Z13: 405.81 | AA13: 417.96 | AB13: 500.58 | AC13: 410.67 | AD13: 447.12 | AE13: 444.69 | AF13: 371.79 | AG13: 432.54 | AH13: 422.82 | AI13: 476.28 | AJ13: 490.86 | AK13: 510.3 | AL13: 425.25 | AM13: 318.33 | AN13: 4000 | AO13: 4000 | AU13: =H13-I13-J13-K13-L13-M13-N13-O13-P13-Q13-R13-S13-T13-U13-V13-W13-X13-Y13-Z13-AA13-AB13-AC13-AD13-AE13-AF13-AG13-AH13-AI13-AJ13-AK13-AL13-AM13+AN13+AQ13+AR13+AP13+AO13 -> 19387.61 | AV13: =C13*AU13 -> 536261.29 | AX13: =AW13*C13 -> 0
A14: OBC | B14: PCS | C14: 26.25 | H14: 7429 | J14: 99 | K14: 133 | L14: 184 | M14: 179 | N14: 175 | O14: 160 | P14: 161 | Q14: 170 | R14: 136 | S14: 191 | T14: 174 | U14: 188 | V14: 144 | W14: 137 | X14: 129 | Y14: 142 | Z14: 167 | AA14: 172 | AB14: 206 | AC14: 169 | AD14: 184 | AE14: 183 | AF14: 153 | AG14: 178 | AH14: 174 | AI14: 196 | AJ14: 202 | AK14: 210 | AL14: 175 | AM14: 131 | AN14: 3000 | AO14: 2000 | AU14: =H14-I14-J14-K14-L14-M14-N14-O14-P14-Q14-R14-S14-T14-U14-V14-W14-X14-Y14-Z14-AA14-AB14-AC14-AD14-AE14-AF14-AG14-AH14-AI14-AJ14-AK14-AL14-AM14+AN14+AQ14+AR14+AP14+AO14 -> 7427 | AV14: =C14*AU14 -> 194958.75 | AX14: =AW14*C14 -> 0
A15: F/LIGHTER | B15: PCS | C15: 20.62 | H15: 275 | J15: 0 | K15: 0 | L15: 0 | M15: 0 | N15: 0 | O15: 0 | P15: 0 | Q15: 0 | R15: 0 | S15: 0 | T15: 0 | U15: 0 | V15: 0 | W15: 0 | X15: 0 | Y15: 0 | Z15: 0 | AA15: 0 | AB15: 0 | AC15: 0 | AD15: 0 | AE15: 0 | AF15: 0 | AG15: 0 | AH15: 0 | AI15: 0 | AJ15: 0 | AK15: 0 | AL15: 0 | AM15: 0 | AU15: =H15-I15-J15-K15-L15-M15-N15-O15-P15-Q15-R15-S15-T15-U15-V15-W15-X15-Y15-Z15-AA15-AB15-AC15-AD15-AE15-AF15-AG15-AH15-AI15-AJ15-AK15-AL15-AM15+AN15+AQ15+AR15+AP15+AO15 -> 275 | AV15: =C15*AU15 -> 5670.5 | AX15: =AW15*C15 -> 0
A16: NONEL 2.4 | B16: PCS | C16: 171.74107 | D16: 264 | E16: =C16*D16 -> 45339.643 | H16: 0 | J16: 0 | K16: 0 | L16: 0 | M16: 0 | N16: 0 | O16: 0 | P16: 0 | Q16: 0 | R16: 0 | S16: 0 | T16: 0 | U16: 0 | V16: 0 | W16: 0 | X16: 0 | Y16: 0 | Z16: 0 | AA16: 0 | AB16: 0 | AC16: 0 | AD16: 0 | AE16: 0 | AF16: 0 | AG16: 0 | AH16: 0 | AI16: 0 | AJ16: 0 | AK16: 0 | AL16: 0 | AM16: 0 | AU16: =H16-I16-J16-K16-L16-M16-N16-O16-P16-Q16-R16-S16-T16-U16-V16-W16-X16-Y16-Z16-AA16-AB16-AC16-AD16-AE16-AF16-AG16-AH16-AI16-AJ16-AK16-AL16-AM16+AN16+AQ16+AR16+AP16+AO16 -> 0 | AV16: =C16*AU16 -> 0 | AX16: =AW16*C16 -> 0
A17: NONEL 3.6 | B17: PCS | C17: 176.78571 | D17: 847 | E17: =C17*D17 -> 149737.5 | H17: 0 | J17: 0 | K17: 0 | L17: 0 | M17: 0 | N17: 0 | O17: 0 | P17: 0 | Q17: 0 | R17: 0 | S17: 0 | T17: 0 | U17: 0 | V17: 0 | W17: 0 | X17: 0 | Y17: 0 | Z17: 0 | AA17: 0 | AB17: 0 | AC17: 0 | AD17: 0 | AE17: 0 | AF17: 0 | AG17: 0 | AH17: 0 | AI17: 0 | AJ17: 0 | AK17: 0 | AL17: 0 | AM17: 0 | AU17: =H17-I17-J17-K17-L17-M17-N17-O17-P17-Q17-R17-S17-T17-U17-V17-W17-X17-Y17-Z17-AA17-AB17-AC17-AD17-AE17-AF17-AG17-AH17-AI17-AJ17-AK17-AL17-AM17+AN17+AQ17+AR17+AP17+AO17 -> 0 | AV17: =C17*AU17 -> 0 | AX17: =AW17*C17 -> 0
A18: SUPREME 2.4 | B18: PCS | C18: 180.35714 | H18: 16364 | J18: 0 | K18: 0 | L18: 0 | M18: 0 | N18: 0 | O18: 0 | P18: 0 | Q18: 0 | R18: 0 | S18: 0 | T18: 0 | U18: 0 | V18: 0 | W18: 0 | X18: 0 | Y18: 0 | Z18: 0 | AA18: 0 | AB18: 0 | AC18: 0 | AD18: 0 | AE18: 0 | AF18: 0 | AG18: 0 | AH18: 0 | AI18: 0 | AJ18: 0 | AK18: 0 | AL18: 0 | AM18: 0 | AU18: =H18-I18-J18-K18-L18-M18-N18-O18-P18-Q18-R18-S18-T18-U18-V18-W18-X18-Y18-Z18-AA18-AB18-AC18-AD18-AE18-AF18-AG18-AH18-AI18-AJ18-AK18-AL18-AM18+AN18+AQ18+AR18+AP18+AO18 -> 16364 | AV18: =C18*AU18 -> 2951364.3 | AX18: =AW18*C18 -> 0
A19: SHOCK STAR | B19: PCS | C19: 207 | H19: 0 | J19: 0 | K19: 0 | L19: 0 | M19: 0 | N19: 0 | O19: 0 | P19: 0 | Q19: 0 | R19: 0 | S19: 0 | T19: 0 | U19: 0 | V19: 0 | W19: 0 | X19: 0 | Y19: 0 | Z19: 0 | AA19: 0 | AB19: 0 | AC19: 0 | AD19: 0 | AE19: 0 | AF19: 0 | AG19: 0 | AH19: 0 | AI19: 0 | AJ19: 0 | AK19: 0 | AL19: 0 | AM19: 0 | AU19: =H19-I19-J19-K19-L19-M19-N19-O19-P19-Q19-R19-S19-T19-U19-V19-W19-X19-Y19-Z19-AA19-AB19-AC19-AD19-AE19-AF19-AG19-AH19-AI19-AJ19-AK19-AL19-AM19+AN19+AQ19+AR19+AP19+AO19 -> 0 | AV19: =C19*AU19 -> 0 | AX19: =AW19*C19 -> 0
A20: PENTEX STOPE PRIME | B20: PCS | C20: 331 | D20: 95 | E20: =C20*D20 -> 31445 | H20: 0 | AU20: =H20-I20-J20-K20-L20-M20-N20-O20-P20-Q20-R20-S20-T20-U20-V20-W20-X20-Y20-Z20-AA20-AB20-AC20-AD20-AE20-AF20-AG20-AH20-AI20-AJ20-AK20-AL20-AM20+AN20+AQ20+AR20+AP20+AO20 -> 0 | AV20: =C20*AU20 -> 0 | AX20: =AW20*C20 -> 0
A21: EXEL 2.4 | B21: PCS | C21: 189.38 | H21: 59481 | J21: 1057 | K21: 1226 | L21: 1840 | M21: 1733 | N21: 1820 | O21: 1531 | P21: 1548 | Q21: 1597 | R21: 1328 | S21: 1731 | T21: 1779 | U21: 1743 | V21: 1490 | W21: 1298 | X21: 1201 | Y21: 1266 | Z21: 1450 | AA21: 1554 | AB21: 1627 | AC21: 1311 | AD21: 1432 | AE21: 1486 | AF21: 1144 | AG21: 1398 | AH21: 1398 | AI21: 1687 | AJ21: 1665 | AK21: 1406 | AL21: 1366 | AM21: 1110 | AN21: 25500 | AO21: 6000 | AU21: =H21-I21-J21-K21-L21-M21-N21-O21-P21-Q21-R21-S21-T21-U21-V21-W21-X21-Y21-Z21-AA21-AB21-AC21-AD21-AE21-AF21-AG21-AH21-AI21-AJ21-AK21-AL21-AM21+AN21+AQ21+AR21+AP21+AO21 -> 46759 | AV21: =C21*AU21 -> 8855219.4 | AX21: =AW21*C21 -> 0
A22: EXEL 4.9 | B22: PCS | C22: 207 | D22: 646 | E22: =C22*D22 -> 133722 | H22: 0 | J22: 0 | K22: 0 | L22: 0 | M22: 0 | N22: 0 | O22: 0 | P22: 0 | Q22: 0 | R22: 0 | S22: 0 | T22: 0 | U22: 0 | V22: 0 | W22: 0 | X22: 0 | Y22: 0 | Z22: 0 | AA22: 0 | AB22: 0 | AC22: 0 | AD22: 0 | AE22: 0 | AF22: 0 | AG22: 0 | AH22: 0 | AI22: 0 | AJ22: 0 | AK22: 0 | AL22: 0 | AM22: 0 | AU22: =H22-I22-J22-K22-L22-M22-N22-O22-P22-Q22-R22-S22-T22-U22-V22-W22-X22-Y22-Z22-AA22-AB22-AC22-AD22-AE22-AF22-AG22-AH22-AI22-AJ22-AK22-AL22-AM22+AN22+AQ22+AR22+AP22+AO22 -> 0 | AV22: =C22*AU22 -> 0 | AX22: =AW22*C22 -> 0
A23: EXEL 3.6 | B23: PCS | C23: 195 | H23: 15644 | J23: 13 | K23: 19 | L23: 28 | M23: 48 | N23: 65 | O23: 45 | P23: 51 | Q23: 55 | R23: 26 | S23: 39 | T23: 51 | U23: 59 | V23: 40 | W23: 26 | X23: 29 | Y23: 27 | Z23: 25 | AA23: 146 | AB23: 252 | AC23: 232 | AD23: 292 | AE23: 309 | AF23: 293 | AG23: 333 | AH23: 273 | AI23: 266 | AJ23: 128 | AK23: 122 | AL23: 98 | AM23: 63 | AU23: =H23-I23-J23-K23-L23-M23-N23-O23-P23-Q23-R23-S23-T23-U23-V23-W23-X23-Y23-Z23-AA23-AB23-AC23-AD23-AE23-AF23-AG23-AH23-AI23-AJ23-AK23-AL23-AM23+AN23+AQ23+AR23+AP23+AO23 -> 12191 | AV23: =C23*AU23 -> 2377245 | AX23: =AW23*C23 -> 0
A24: MS 12 | B24: PCS | C24: 359.83 | H24: 0 | AU24: =H24-I24-J24-K24-L24-M24-N24-O24-P24-Q24-R24-S24-T24-U24-V24-W24-X24-Y24-Z24-AA24-AB24-AC24-AD24-AE24-AF24-AG24-AH24-AI24-AJ24-AK24-AL24-AM24+AN24+AQ24+AR24+AP24+AO24 -> 0 | AV24: =C24*AU24 -> 0 | AX24: =AW24*C24 -> 0
A25: MS 18 | B25: PCS | C25: 379.46 | H25: 0 | AU25: =H25-I25-J25-K25-L25-M25-N25-O25-P25-Q25-R25-S25-T25-U25-V25-W25-X25-Y25-Z25-AA25-AB25-AC25-AD25-AE25-AF25-AG25-AH25-AI25-AJ25-AK25-AL25-AM25+AN25+AQ25+AR25+AP25+AO25 -> 0 | AV25: =C25*AU25 -> 0 | AX25: =AW25*C25 -> 0
A26: CORDTEX 5 | B26: MTR | C26: 35.15 | H26: 17184 | J26: 187 | K26: 313 | L26: 418 | M26: 396 | N26: 318 | O26: 257 | P26: 271 | Q26: 373 | R26: 509 | S26: 692 | T26: 646 | U26: 680 | V26: 591 | W26: 481 | X26: 430 | Y26: 343 | Z26: 339 | AA26: 495 | AB26: 399 | AC26: 329 | AD26: 357 | AE26: 365 | AF26: 252 | AG26: 453 | AH26: 459 | AI26: 389 | AJ26: 416 | AK26: 405 | AL26: 413 | AM26: 284 | AN26: 2700 | AO26: 2700 | AU26: =H26-I26-J26-K26-L26-M26-N26-O26-P26-Q26-R26-S26-T26-U26-V26-W26-X26-Y26-Z26-AA26-AB26-AC26-AD26-AE26-AF26-AG26-AH26-AI26-AJ26-AK26-AL26-AM26+AN26+AQ26+AR26+AP26+AO26 -> 10324 | AV26: =C26*AU26 -> 362888.6 | AX26: =AW26*C26 -> 0
A27: CORDTEX 10 | B27: MTR | C27: 35.892857 | H27: 16123 | J27: 290 | K27: 239 | L27: 412 | M27: 358 | N27: 454 | O27: 422 | P27: 413 | Q27: 324 | R27: 85 | S27: 88 | T27: 104 | U27: 86 | V27: 90 | W27: 77 | X27: 85 | Y27: 218 | Z27: 272 | AA27: 269 | AB27: 423 | AC27: 364 | AD27: 387 | AE27: 437 | AF27: 384 | AG27: 333 | AH27: 314 | AI27: 452 | AJ27: 448 | AK27: 322 | AL27: 292 | AM27: 282 | AN27: 3000 | AO27: 3000 | AU27: =H27-I27-J27-K27-L27-M27-N27-O27-P27-Q27-R27-S27-T27-U27-V27-W27-X27-Y27-Z27-AA27-AB27-AC27-AD27-AE27-AF27-AG27-AH27-AI27-AJ27-AK27-AL27-AM27+AN27+AQ27+AR27+AP27+AO27 -> 13399 | AV27: =C27*AU27 -> 480928.39 | AX27: =AW27*C27 -> 0
A28: DCORD 1 5 | B28: MTR | C28: 37.5 | H28: 0 | J28: 0 | K28: 0 | L28: 0 | M28: 0 | N28: 0 | O28: 0 | P28: 0 | Q28: 0 | R28: 0 | S28: 0 | T28: 0 | U28: 0 | V28: 0 | W28: 0 | X28: 0 | Y28: 0 | Z28: 0 | AA28: 0 | AB28: 0 | AC28: 0 | AD28: 0 | AE28: 0 | AF28: 0 | AG28: 0 | AH28: 0 | AI28: 0 | AJ28: 0 | AK28: 0 | AL28: 0 | AM28: 0 | AU28: =H28-I28-J28-K28-L28-M28-N28-O28-P28-Q28-R28-S28-T28-U28-V28-W28-X28-Y28-Z28-AA28-AB28-AC28-AD28-AE28-AF28-AG28-AH28-AI28-AJ28-AK28-AL28-AM28+AN28+AQ28+AR28+AP28+AO28 -> 0 | AV28: =C28*AU28 -> 0 | AX28: =AW28*C28 -> 0
A29: CORDTEX 40 | B29: MTR | C29: 81.9 | D29: 1060 | E29: =C29*D29 -> 86814 | H29: 0 | AU29: =H29-I29-J29-K29-L29-M29-N29-O29-P29-Q29-R29-S29-T29-U29-V29-W29-X29-Y29-Z29-AA29-AB29-AC29-AD29-AE29-AF29-AG29-AH29-AI29-AJ29-AK29-AL29-AM29+AN29+AQ29+AR29+AP29+AO29 -> 0 | AV29: =C29*AU29 -> 0 | AX29: =AW29*C29 -> 0
A30: BILL WIRE | B30: MTR | C30: 7.5 | H30: 2275 | J30: 0 | K30: 0 | L30: 0 | M30: 0 | N30: 0 | O30: 0 | P30: 0 | Q30: 0 | R30: 0 | S30: 30 | T30: 0 | U30: 0 | V30: 0 | W30: 0 | X30: 0 | Y30: 0 | Z30: 0 | AA30: 0 | AB30: 0 | AC30: 300 | AD30: 0 | AE30: 0 | AF30: 0 | AG30: 0 | AH30: 0 | AI30: 0 | AJ30: 0 | AK30: 0 | AL30: 0 | AM30: 0 | AU30: =H30-I30-J30-K30-L30-M30-N30-O30-P30-Q30-R30-S30-T30-U30-V30-W30-X30-Y30-Z30-AA30-AB30-AC30-AD30-AE30-AF30-AG30-AH30-AI30-AJ30-AK30-AL30-AM30+AN30+AQ30+AR30+AP30+AO30 -> 1945 | AV30: =C30*AU30 -> 14587.5 | AX30: =AW30*C30 -> 0
A31: EBC | B31: PCS | C31: 267.18 | H31: 322 | J31: 4 | K31: 8 | L31: 4 | M31: 8 | N31: 6 | O31: 8 | P31: 2 | Q31: 6 | R31: 4 | S31: 2 | T31: 6 | U31: 4 | V31: 6 | W31: 4 | X31: 2 | Y31: 0 | Z31: 2 | AA31: 2 | AB31: 0 | AC31: 4 | AD31: 4 | AE31: 6 | AF31: 4 | AG31: 6 | AH31: 6 | AI31: 4 | AJ31: 4 | AK31: 4 | AL31: 6 | AM31: 2 | AN31: 80 | AU31: =H31-I31-J31-K31-L31-M31-N31-O31-P31-Q31-R31-S31-T31-U31-V31-W31-X31-Y31-Z31-AA31-AB31-AC31-AD31-AE31-AF31-AG31-AH31-AI31-AJ31-AK31-AL31-AM31+AN31+AQ31+AR31+AP31+AO31 -> 274 | AV31: =C31*AU31 -> 73207.32 | AX31: =AW31*C31 -> 0
D32: TOTAL COST | E32: =SUM(E9:E31) -> 447058.14 | I32: =SUM(I9:I31) -> 0 | J32: =SUM(J9:J31) -> 4686.57 | K32: =SUM(K9:K31) -> 5536.19 | L32: =SUM(L9:L31) -> 7963.12 | M32: =SUM(M9:M31) -> 7346.17 | N32: =SUM(N9:N31) -> 7838.25 | O32: =SUM(O9:O31) -> 6615 | P32: =SUM(P9:P31) -> 6817.43 | ... AM32: =SUM(AM9:AM31) -> 5374.73 | AU32: TOTAL COST AS OF MAY 31,2026 | AV32: =SUM(AV9:AV31) -> 31451671 | AW32: TOTAL COST WITHDRAWAL | AX32: =SUM(AX9:AX31) -> 0 | AY32: =AV32+AX32 -> 31451671

Sheet EXEL 2.4 (SOH MINE)
A1: ='EXPEDITION '!B3 -> DATE: MAY 31,2026
A3: DESCRIPTION | B3: UoM | C3: UNIT COST | D3: SOH SURFACE AS OF MAY 31 2026 | E3: LEVEL 3 | F3: LEVEL 5 | G3: LEVEL 7 | H3: LEVEL 8 | I3: LEVEL 9 | J3: LEVEL 10 | K3: LEVEL 11 | L3: LEVEL 12 | M3: LEVEL 425 | N3: SOH UNDERGROUND MAY 31,2026 | O3: TOTAL | P3: TOTAL COST | Q3: ='INVENTORY-MAY'!AW7 -> TO BE WITHDRAWN FROM SUPPLIER MAGAZINE ON | R3: TOTAL COST
A4: EXEL 2.4M DELAY #
A5: 1 | B5: PCS | C5: 189.38 | D5: 750 | E5: 18 | G5: 282 | H5: 518 | I5: 470 | J5: 454 | L5: 349 | M5: 117 | N5: =SUM(E5:M5) -> 2208 | O5: =N5+D5 -> 2958 | P5: =C5*O5 -> 560186.04 | R5: =C5*Q5 -> 0
A6: 2 | B6: PCS | C6: 189.38 | D6: 250 | E6: 197 | G6: 278 | H6: 543 | I6: 486 | J6: 327 | L6: 431 | M6: 228 | N6: =SUM(E6:M6) -> 2490 | O6: =N6+D6 -> 2740 | P6: =C6*O6 -> 518901.2 | R6: =C6*Q6 -> 0
A7: 3 | B7: PCS | C7: 189.38 | D7: 750 | E7: 186 | G7: 278 | H7: 525 | I7: 467 | J7: 506 | L7: 376 | M7: 59 | N7: =SUM(E7:M7) -> 2397 | O7: =N7+D7 -> 3147 | P7: =C7*O7 -> 595978.86 | R7: =C7*Q7 -> 0
A8: 4 | B8: PCS | C8: 189.38 | D8: 500 | E8: 96 | G8: 274 | H8: 583 | I8: 424 | J8: 494 | L8: 427 | M8: 3 | N8: =SUM(E8:M8) -> 2301 | O8: =N8+D8 -> 2801 | P8: =C8*O8 -> 530453.38 | R8: =C8*Q8 -> 0
A9: 5 | B9: PCS | C9: 189.38 | D9: 410 | E9: 170 | G9: 270 | H9: 344 | I9: 386 | J9: 265 | L9: 541 | M9: 116 | N9: =SUM(E9:M9) -> 2092 | O9: =N9+D9 -> 2502 | P9: =C9*O9 -> 473828.76 | R9: =C9*Q9 -> 0
A10: 6 | B10: PCS | C10: 189.38 | D10: 410 | E10: 167 | G10: 270 | H10: 492 | I10: 367 | J10: 335 | L10: 455 | M10: 191 | N10: =SUM(E10:M10) -> 2277 | O10: =N10+D10 -> 2687 | P10: =C10*O10 -> 508864.06 | R10: =C10*Q10 -> 0
A11: 7 | B11: PCS | C11: 189.38 | D11: 850 | E11: 162 | G11: 20 | H11: 250 | I11: 344 | J11: 295 | L11: 392 | M11: 251 | N11: =SUM(E11:M11) -> 1714 | O11: =N11+D11 -> 2564 | P11: =C11*O11 -> 485570.32 | R11: =C11*Q11 -> 0
A12: 8 | B12: PCS | C12: 189.38 | D12: 360 | E12: 163 | G12: 20 | H12: 250 | I12: 371 | J12: 378 | L12: 562 | M12: 67 | N12: =SUM(E12:M12) -> 1811 | O12: =N12+D12 -> 2171 | P12: =C12*O12 -> 411143.98 | R12: =C12*Q12 -> 0
A13: 9 | B13: PCS | C13: 189.38 | D13: 90 | E13: 282 | G13: 272 | H13: 511 | I13: 159 | J13: 337 | L13: 540 | M13: 57 | N13: =SUM(E13:M13) -> 2158 | O13: =N13+D13 -> 2248 | P13: =C13*O13 -> 425726.24 | R13: =C13*Q13 -> 0
A14: 10 | B14: PCS | C14: 189.38 | D14: 620 | E14: 277 | G14: 278 | H14: 513 | I14: 327 | J14: 462 | L14: 512 | M14: 87 | N14: =SUM(E14:M14) -> 2456 | O14: =N14+D14 -> 3076 | P14: =C14*O14 -> 582532.88 | R14: =C14*Q14 -> 0
A15: 11 | B15: PCS | C15: 189.38 | D15: 1250 | E15: 110 | G15: 278 | H15: 781 | I15: 361 | J15: 343 | L15: 500 | M15: 271 | N15: =SUM(E15:M15) -> 2644 | O15: =N15+D15 -> 3894 | P15: =C15*O15 -> 737445.72 | R15: =C15*Q15 -> 0
A16: 12 | B16: PCS | C16: 189.38 | D16: 830 | E16: 166 | G16: 277 | H16: 250 | I16: 691 | J16: 239 | L16: 250 | M16: 172 | N16: =SUM(E16:M16) -> 2045 | O16: =N16+D16 -> 2875 | P16: =C16*O16 -> 544467.5 | R16: =C16*Q16 -> 0
... A18: 14 | B18: PCS | C18: 189.38 | D18: 1250 | E18: 0 | G18: 288 | H18: 285 | I18: 528 | J18: 133 | L18: 332 | M18: 277 | N18: =SUM(E18:M18) -> 1843 | O18: =N18+D18 -> 3093 | P18: =C18*O18 -> 585752.34 | R18: =C18*Q18 -> 0
A19: 15 | B19: PCS | C19: 189.38 | D19: 1500 | E19: 105 | G19: 288 | H19: 311 | I19: 499 | J19: 263 | L19: 323 | M19: 390 | N19: =SUM(E19:M19) -> 2179 | O19: =N19+D19 -> 3679 | P19: =C19*O19 -> 696729.02 | R19: =SUM(R5:R18) -> 0
A20: TOTAL CONSUMPTION | D20: =SUM(D5:D19) -> 10350 | E20: =SUM(E5:E19) -> 2175 | F20: =SUM(F5:F19) -> 0 | G20: =SUM(G5:G19) -> 3650 | H20: =SUM(H5:H19) -> 6543 | I20: =SUM(I5:I19) -> 6292 | J20: =SUM(J5:J19) -> 5081 | K20: =SUM(K5:K19) -> 0 | ... R20: =SUM(R5:R19) -> 0
N21: LOGBOOK | O21: ='SOH-MAY'!BI23 -> 46759
N22: ACTUAL | O22: =O20 -> 42925
O23: =O22-O21 -> -3834

Sheet EXEL 3.6 (SOH MINE)
A1: ='EXPEDITION '!B3 -> DATE: MAY 31,2026
A2: DESCRIPTION | B2: UoM | C2: UNIT COST | D2: ='EXEL 2.4 (SOH MINE)'!D3 -> SOH SURFACE AS OF MAY 31 2026 | E2: SINUG-ANG | F2: LEVEL 3 | G2: LEVEL 4 | H2: LEVEL 5 | I2: LEVEL 6 | J2: LEVEL 7 | K2: LEVEL 8 | L2: LEVEL 9 | M2: LEVEL 10 | N2: LEVEL 11 | O2: LEVEL 12 | P2: LEVEL 425 | Q2: ='EXEL 2.4 (SOH MINE)'!N3 -> SOH UNDERGROUND MAY 31,2026 | R2: TOTAL | S2: TOTAL COST | T2: ='EXEL 2.4 (SOH MINE)'!Q3 -> TO BE WITHDRAWN FROM SUPPLIER MAGAZINE ON | U2: TOTAL COST
A3: EXEL 3.6M DELAY #
A4: 1 | B4: PCS | C4: 195 | D4: 210 | F4: 114 | L4: 220 | Q4: =SUM(E4:P4) -> 334 | R4: =Q4+D4 -> 544 | S4: =R4*C4 -> 106080 | U4: =E4*T4 -> 0
A5: 2 | B5: PCS | C5: 195 | D5: 460 | F5: 121 | L5: 220 | Q5: =SUM(E5:P5) -> 341 | R5: =Q5+D5 -> 801 | S5: =R5*C5 -> 156195 | U5: =E5*T5 -> 0
A6: 3 | B6: PCS | C6: 195 | D6: 440 | F6: 95 | Q6: =SUM(E6:P6) -> 95 | R6: =Q6+D6 -> 535 | S6: =R6*C6 -> 104325 | U6: =E6*T6 -> 0
A7: 4 | B7: PCS | C7: 195 | D7: 440 | F7: 97 | L7: 0 | O7: 0 | Q7: =SUM(E7:P7) -> 97 | R7: =Q7+D7 -> 537 | S7: =R7*C7 -> 104715 | U7: =E7*T7 -> 0
A8: 5 | B8: PCS | C8: 195 | D8: 880 | L8: 0 | Q8: =SUM(E8:P8) -> 0 | R8: =Q8+D8 -> 880 | S8: =R8*C8 -> 171600 | U8: =E8*T8 -> 0
A9: 6 | B9: PCS | C9: 195 | D9: 660 | L9: 0 | P9: 0 | Q9: =SUM(E9:P9) -> 0 | R9: =Q9+D9 -> 660 | S9: =R9*C9 -> 128700 | U9: =E9*T9 -> 0
A10: 7 | B10: PCS | C10: 195 | D10: 440 | J10: 220 | K10: 112 | P10: 0 | Q10: =SUM(E10:P10) -> 332 | R10: =Q10+D10 -> 772 | S10: =R10*C10 -> 150540 | U10: =E10*T10 -> 0
A11: 8 | B11: PCS | C11: 195 | D11: 1100 | J11: 220 | K11: 174 | L11: 0 | P11: 0 | Q11: =SUM(E11:P11) -> 394 | R11: =Q11+D11 -> 1494 | S11: =R11*C11 -> 291330 | U11: =E11*T11 -> 0
A12: 9 | B12: PCS | C12: 195 | D12: 1320 | P12: 0 | Q12: =SUM(E12:P12) -> 0 | R12: =Q12+D12 -> 1320 | S12: =R12*C12 -> 257400 | U12: =E12*T12 -> 0
A13: 10 | B13: PCS | C13: 195 | D13: 440 | F13: 105 | O13: 0 | P13: 0 | Q13: =SUM(E13:P13) -> 105 | R13: =Q13+D13 -> 545 | S13: =R13*C13 -> 106275 | U13: =E13*T13 -> 0
A14: 11 | B14: PCS | C14: 195 | D14: 320 | F14: 93 | P14: 0 | Q14: =SUM(E14:P14) -> 93 | R14: =Q14+D14 -> 413 | S14: =R14*C14 -> 80535 | U14: =E14*T14 -> 0
A15: 12 | B15: PCS | C15: 195 | D15: 70 | F15: 96 | K15: 216 | O15: 108 | P15: 5 | Q15: =SUM(E15:P15) -> 425 | R15: =Q15+D15 -> 495 | S15: =R15*C15 -> 96525 | U15: =E15*T15 -> 0
A16: 13 | B16: PCS | C16: 195 | D16: 440 | F16: 102 | K16: 220 | M16: 53 | O16: 120 | Q16: =SUM(E16:P16) -> 495 | R16: =Q16+D16 -> 935 | S16: =R16*C16 -> 182325 | U16: =E16*T16 -> 0
A17: 14 | B17: PCS | C17: 195 | D17: 420 | F17: 85 | K17: 220 | M17: 220 | O17: 220 | Q17: =SUM(E17:P17) -> 745 | R17: =Q17+D17 -> 1165 | S17: =R17*C17 -> 227175 | U17: =E17*T17 -> 0
A18: 15 | B18: PCS | C18: 195 | D18: 420 | F18: 82 | K18: 220 | M18: 220 | O18: 220 | Q18: =SUM(E18:P18) -> 742 | R18: =Q18+D18 -> 1162 | S18: =R18*C18 -> 226590 | U18: =E18*T18 -> 0
A19: TOTAL CONSUMPTION | D19: =SUM(D4:D18) -> 8060 | E19: =SUM(E4:E18) -> 0 | F19: =SUM(F4:F18) -> 990 | G19: =SUM(G4:G18) -> 0 | H19: =SUM(H4:H18) -> 0 | I19: =SUM(I4:I18) -> 0 | J19: =SUM(J4:J18) -> 440 | K19: =SUM(K4:K18) -> 1162 | ... U19: =SUM(U4:U18) -> 0
Q20: LOGBOOK | R20: ='SOH-MAY'!BI25 -> 12191
Q21: ACTUAL | R21: =R19 -> 12258
R22: =R21-R20 -> 67

Sheet SUPREME (SOH MINE)
A1: ='EXPEDITION '!B3 -> DATE: MAY 31,2026
A2: DESCRIPTION | B2: UoM | C2: UNIT COST | D2: ='EXEL 2.4 (SOH MINE)'!D3 -> SOH SURFACE AS OF MAY 31 2026 | E2: LEVEL 4 | F2: LEVEL 5 | G2: LEVEL 6 | H2: LEVEL 7 | I2: LEVEL 8 | J2: LEVEL 9 | K2: LEVEL 10 | L2: LEVEL 12 | M2: LEVEL 11 | N2: ='EXEL 2.4 (SOH MINE)'!N3 -> SOH UNDERGROUND MAY 31,2026 | O2: TOTAL | P2: TOTAL COST | Q2: ='INVENTORY-MAY'!AW7 -> TO BE WITHDRAWN FROM SUPPLIER MAGAZINE ON | R2: TOTAL COST
A3: SUPREME 2.4M DELAY #
A4: 1 | B4: PCS | C4: 180.35714 | D4: 0 | N4: =M4+L4+J4+I4+H4+G4+F4+E4+K4 -> 0 | O4: =N4+D4 -> 0 | P4: =O4*C4 -> 0 | R4: =C4*Q4 -> 0
A5: 2 | B5: PCS | C5: 180.35714 | D5: 204 | N5: =M5+L5+J5+I5+H5+G5+F5+E5+K5 -> 0 | O5: =N5+D5 -> 204 | P5: =O5*C5 -> 36792.857 | R5: =C5*Q5 -> 0
A6: 3 | B6: PCS | C6: 180.35714 | D6: 1956 | N6: =M6+L6+J6+I6+H6+G6+F6+E6+K6 -> 0 | O6: =N6+D6 -> 1956 | P6: =O6*C6 -> 352778.57 | R6: =C6*Q6 -> 0
A7: 4 | B7: PCS | C7: 180.35714 | D7: 766 | N7: =M7+L7+J7+I7+H7+G7+F7+E7+K7 -> 0 | O7: =N7+D7 -> 766 | P7: =O7*C7 -> 138153.57 | R7: =C7*Q7 -> 0
A8: 5 | B8: PCS | C8: 180.35714 | D8: 1 | N8: =M8+L8+J8+I8+H8+G8+F8+E8+K8 -> 0 | O8: =N8+D8 -> 1 | P8: =O8*C8 -> 180.35714 | R8: =C8*Q8 -> 0
A9: 6 | B9: PCS | C9: 180.35714 | D9: 69 | N9: =M9+L9+J9+I9+H9+G9+F9+E9+K9 -> 0 | O9: =N9+D9 -> 69 | P9: =O9*C9 -> 12444.643 | R9: =C9*Q9 -> 0
A10: 7 | B10: PCS | C10: 180.35714 | D10: 217 | N10: =M10+L10+J10+I10+H10+G10+F10+E10+K10 -> 0 | O10: =N10+D10 -> 217 | P10: =O10*C10 -> 39137.5 | R10: =C10*Q10 -> 0
A11: 8 | B11: PCS | C11: 180.35714 | D11: 846 | N11: =M11+L11+J11+I11+H11+G11+F11+E11+K11 -> 0 | O11: =N11+D11 -> 846 | P11: =O11*C11 -> 152582.14 | R11: =C11*Q11 -> 0
A12: 9 | B12: PCS | C12: 180.35714 | D12: 2296 | N12: =M12+L12+J12+I12+H12+G12+F12+E12+K12 -> 0 | O12: =N12+D12 -> 2296 | P12: =O12*C12 -> 414100 | R12: =C12*Q12 -> 0
A13: 10 | B13: PCS | C13: 180.35714 | D13: 3418 | N13: =M13+L13+J13+I13+H13+G13+F13+E13+K13 -> 0 | O13: =N13+D13 -> 3418 | P13: =O13*C13 -> 616460.71 | R13: =C13*Q13 -> 0
A14: 11 | B14: PCS | C14: 180.35714 | D14: 3678 | N14: =M14+L14+J14+I14+H14+G14+F14+E14+K14 -> 0 | O14: =N14+D14 -> 3678 | P14: =O14*C14 -> 663353.57 | R14: =C14*Q14 -> 0
A15: 12 | B15: PCS | C15: 180.35714 | D15: 2908 | N15: =M15+L15+J15+I15+H15+G15+F15+E15+K15 -> 0 | O15: =N15+D15 -> 2908 | P15: =O15*C15 -> 524478.57 | R15: =C15*Q15 -> 0
... A18: 15 | B18: PCS | C18: 180.35714 | D18: 0 | N18: =M18+L18+J18+I18+H18+G18+F18+E18+K18 -> 0 | O18: =N18+D18 -> 0 | P18: =O18*C18 -> 0 | R18: =C18*Q18 -> 0
A19: TOTAL CONSUMPTION | D19: =SUM(D4:D18) -> 16359 | E19: =SUM(E4:E18) -> 0 | F19: =SUM(F4:F18) -> 0 | G19: =SUM(G4:G18) -> 0 | H19: =SUM(H4:H18) -> 0 | I19: =SUM(I4:I18) -> 0 | J19: =SUM(J4:J18) -> 0 | K19: =SUM(K4:K18) -> 0 | L19: =SUM(L4:L18) -> 0 | M19: =SUM(M4:M15) -> 0 | N19: =SUM(N4:N18) -> 0 | O19: =SUM(O4:O18) -> 16359 | P19: =SUM(P4:P18) -> 2950462.5 | Q19: =SUM(Q4:Q18) -> 0 | R19: =SUM(R4:R18) -> 0
N20: LOGBOOK | O20: ='SOH-MAY'!BI20 -> 16364
N21: ACTUAL | O21: =O19 -> 16359
O22: =O21-O20 -> -5
N40: 6 | O40: 100
N41: 11 | O41: 100

Sheet EXPEDITION 
B3: DATE: MAY 31,2026
B5: NAMELY: DYNA,OBC,SAFETY FUSE, NON-ELEC LP 2.4,ANFO
B6: NON-ELEC LP 3.6, DETCORD, EBC, FUSE LIGHTER &BELLWIRE
B8: DESCRIPTION | C8: QUANTITY | G8: UNIT PRICE | H8: COSTING
C10: BOXES/SACKS/PACK | D10: PCS | E10: KLS | F10: METERS
B11: DYNAPULSAR 215 | C11: =2392-100-75 -> 2217 | D11: =C11*215 -> 476655 | G11: 29.5639 | H11: =D11*G11 -> 14091781
B12: ANFO | C12: =5250-600-350 -> 4300 | E12: =C12*25 -> 107500 | G12: 145.88 | H12: =E12*G12 -> 15682100
B13: S/FUSE | C13: =105-4-4 -> 97 | F13: =C13*1000 -> 97000 | G13: 27.66 | H13: =F13*G13 -> 2683020
B14: OBC | C14: =355-15-10 -> 330 | D14: =C14*100 -> 33000 | G14: 26.25 | H14: =D14*G14 -> 866250
B15: F/LIGHTER | C15: 85 | D15: =C15*50 -> 4250 | G15: 20.62 | H15: =D15*G15 -> 87635
B16: EXEL 2.4 | C16: =C48 -> 548 | D16: =C16*250 -> 137000 | G16: 189.38 | H16: =D16*G16 -> 25945060
B17: EXEL 4.9 | C17: 0 | G17: 207 | H17: =D17*G17 -> 0
B18: EXEL 3.6 | C18: =C69 -> 100 | D18: =C18*220 -> 22000 | G18: 195 | H18: =D18*G18 -> 4290000
B19: MS 12 | C19: 0 | G19: 359.83 | H19: =D19*G19 -> 0
B20: MS 18 | C20: 0 | G20: 379.46 | H20: =D20*G20 -> 0
B21: CORDTEX 5 | C21: 143 | F21: =C21*900 -> 128700 | G21: 35.15 | H21: =F21*G21 -> 4523805
B22: CORDTEX 40 | C22: 0 | G22: 38.5 | H22: =F22*G22 -> 0
B23: DCORD 15 | C23: 0 | F23: =C23*150 -> 0 | G23: 37.5 | H23: =F23*G23 -> 0
B24: BILL WIRE | C24: 0 | F24: =C24*300 -> 0 | G24: 7.5 | H24: =F24*G24 -> 0
B25: EBC | C25: 840 | D25: =C25 -> 840 | G25: 267.18 | H25: =D25*G25 -> 224431.2
B26: TOTAL COST | H26: =SUM(H11:H25) -> 68394082
B29: EXEL 2.4M DELAY # | C29: MILL MAGAZINE STOCKS | D29: UNIT PRICE | E29: COSTING
C31: PCS | D31: PCS | E31: PCS
B32: 1 | C32: 10750 | D32: 189.38 | E32: =C32*D32 -> 2035835
B33: 2 | C33: 11750 | D33: 189.38 | E33: =C33*D33 -> 2225215
B34: 3 | C34: 9500 | D34: 189.38 | E34: =C34*D34 -> 1799110
B35: 4 | C35: 12750 | D35: 189.38 | E35: =C35*D35 -> 2414595
B36: 5 | C36: 11500 | D36: 189.38 | E36: =C36*D36 -> 2177870
B37: 6 | C37: 11500 | D37: 189.38 | E37: =C37*D37 -> 2177870
B38: 7 | C38: 11250 | D38: 189.38 | E38: =C38*D38 -> 2130525
B39: 8 | C39: 10250 | D39: 189.38 | E39: =C39*D39 -> 1941145
B40: 9 | C40: 10500 | D40: 189.38 | E40: =C40*D40 -> 1988490
B41: 10 | C41: 10500 | D41: 189.38 | E41: =C41*D41 -> 1988490
B42: 11 | C42: 5000 | D42: 189.38 | E42: =C42*D42 -> 946900
B43: 12 | C43: 4250 | D43: 189.38 | E43: =C43*D43 -> 804865
... B46: 15 | C46: 6250 | D46: 189.38 | E46: =C46*D46 -> 1183625
B47: TOTAL | C47: =SUM(C32:C46) -> 137000 | E47: =SUM(E32:E46) -> 25945060
C48: =C47/250 -> 548
B50: EXEL 3.6M DELAY # | C50: MILL MAGAZINE STOCKS | D50: UNIT PRICE | E50: COSTING
C52: PCS | D52: PCS | E52: PCS
B53: 1 | C53: 1760 | D53: 195 | E53: =C53*D53 -> 343200
B54: 2 | C54: 1760 | D54: 195 | E54: =C54*D54 -> 343200
B55: 3 | C55: 1760 | D55: 195 | E55: =C55*D55 -> 343200
B56: 4 | C56: 1540 | D56: 195 | E56: =C56*D56 -> 300300
B57: 5 | C57: 1320 | D57: 195 | E57: =C57*D57 -> 257400
B58: 6 | C58: 880 | D58: 195 | E58: =C58*D58 -> 171600
B59: 7 | C59: 440 | D59: 195 | E59: =C59*D59 -> 85800
B60: 8 | C60: 220 | D60: 195 | E60: =C60*D60 -> 42900
B61: 9 | C61: 660 | D61: 195 | E61: =C61*D61 -> 128700
B62: 10 | C62: 1760 | D62: 195 | E62: =C62*D62 -> 343200
B63: 11 | C63: 2200 | D63: 195 | E63: =C63*D63 -> 429000
B64: 12 | C64: 1760 | D64: 195 | E64: =C64*D64 -> 343200
... B67: 15 | C67: 1980 | D67: 195 | E67: =C67*D67 -> 386100
B68: TOTAL | C68: =SUM(C53:C67) -> 22000 | E68: =SUM(E53:E67) -> 4290000
C69: =C68/220 -> 100

Sheet MT.ROCK
B3: ='EXPEDITION '!B3 -> DATE: MAY 31,2026
B4: RE: MOUNT ROCK POWDER EXPLOSIVES STOCK INVENTORY AS OF TODAY
B5: NAMELY: DYNA,OBC,SAFETY FUSE, NON-ELEC LP 2.4, ANFO & DETCORD
B7: DESCRIPTION | C7: QUANTITY | G7: UNIT PRICE | H7: COSTING
C9: BOXES/SACKS | D9: PCS | E9: KLS | F9: METERS
B10: DYNA SUPERPOWER 208 | E10: =C10*208 -> 0 | G10: 29.45 | H10: =E10*G10 -> 0
B11: DYNA NEOGEL 200 | C11: =270-75 -> 195 | E11: =C11*200 -> 39000 | G11: 27.3438 | H11: =E11*G11 -> 1066408.2
B12: ANFO | C12: 0 | E12: =C12*25 -> 0 | G12: 155.5 | H12: =E12*G12 -> 0
B13: S/FUSE | C13: 0 | F13: =C13*1000 -> 0 | G13: 29.5 | H13: =F13*G13 -> 0
B14: OBC | C14: =25-15-10 -> 0 | D14: =C14*100 -> 0 | G14: 25.446429 | H14: =D14*G14 -> 0
B15: SUPREME 2.4 | C15: =C41 -> 6 | D15: =C15*360 -> 2160 | G15: 180.35714 | H15: =D15*G15 -> 389571.43
B16: EBC | C16: =1227-30-60-30-100-40 -> 967 | D16: 120 | G16: 267.18 | H16: =D16*G16 -> 32061.6
B17: CORDTEX 10 | C17: 0 | F17: =C17*1000 -> 0 | G17: 40.2 | H17: =F17*G17 -> 0
B18: TOTAL COST | H18: =SUM(H10:H17) -> 1488041.2
B22: SUPREME 2.4m DELAY # | C22: MILL MAGAZINE STOCKS | D22: UNIT PRICE | E22: COSTING
C24: PCS
B25: 1 | C25: 0 | D25: 202 | E25: =C25*D25 -> 0
B26: 2 | C26: 0 | D26: 202 | E26: =C26*D26 -> 0
B27: 3 | C27: 0 | D27: 202 | E27: =C27*D27 -> 0
B28: 4 | C28: 0 | D28: 202 | E28: =C28*D28 -> 0
B29: 5 | C29: 0 | D29: 202 | E29: =C29*D29 -> 0
B30: 6 | C30: 0 | D30: 202 | E30: =C30*D30 -> 0
B31: 7 | C31: 0 | D31: 202 | E31: =C31*D31 -> 0
B32: 8 | C32: 0 | D32: 202 | E32: =C32*D32 -> 0
B33: 9 | C33: 0 | D33: 202 | E33: =C33*D33 -> 0
B34: 10 | C34: 0 | D34: 202 | E34: =C34*D34 -> 0
B35: 11 | C35: 0 | D35: 202 | E35: =C35*D35 -> 0
B36: 12 | C36: 2160 | D36: 202 | E36: =C36*D36 -> 436320
B37: 13 | C37: -
B38: 14 | C38: -
B39: 15 | C39: -
B40: TOTAL | C40: =SUM(C25:C39) -> 2160 | E40: =SUM(E25:E39) -> 436320
C41: =C40/360 -> 6

Sheet TOTAL COST CY2023-2026
B2: COST PER YEAR
A3: MONTH | B3: 2023 | C3: 2024 | D3: 2025 | E3: 2026
A4: JANUARY | B4: 12269387 | C4: 13135084 | D4: 16681581 | E4: 17277309
A5: FEBRUARY | B5: 19739060 | C5: 15964551 | D5: 16174717 | E5: 15480197
A6: MARCH | B6: 22500416 | C6: 12948910 | D6: 18907293 | E6: 18856575
A7: APRIL | B7: 16014283 | C7: 15111009 | D7: 18635020 | E7: 14913522
A8: MAY | B8: 21923865 | C8: 14728509 | D8: 18119987 | E8: ='SOH-MAY'!AO34 -> 17329054 | F8: COSTING AS OF MAY 31, 2026
A9: JUNE | B9: 20994738 | C9: 16125820 | D9: 16195903
A10: JULY | B10: 23502179 | C10: 17852277 | D10: 17428371
A11: AUGUST | B11: 20299056 | C11: 18756287 | D11: 19294486
A12: SEPTEMBER | B12: 18016145 | C12: 16625137 | D12: 19214027
A13: OCTOBER | B13: 18169322 | C13: 19262802 | D13: 18072799
A14: NOVEMBER | B14: 18422375 | C14: 16297325 | D14: 19379751
A15: DECEMBER | B15: 6317503.8 | C15: 14579262 | D15: 14725661
A16: TOTAL | B16: =SUM(B4:B15) -> 2.1816833e+08 | C16: =SUM(C4:C15) -> 1.9138697e+08 | D16: =SUM(D4:D15) -> 2.128296e+08 | E16: =SUM(E4:E15) -> 83856657

Sheet FORECAST SUPPLIER AND PMC STOCK
A2: EXPEDITION
A3: MONITORING STOCK FOR SUPPLIER AND PMC STOCK
A4: As Of May 23, 2026
R6: If Mt rock arrive stock
A7: DESCRIPTION | B7: UNIT | C7: WEEKLY | D7: SURFACE | E7: SUPPLIER | F7: SINUG-AN | G7: MARATHON | H7: LEVEL 7 | I7: LEVEL 8 | J7: LEVEL 9 | K7: LEVEL 10 | L7: LEVEL 11 | M7: LEVEL 12 | N7: LEVEL 425 | O7: TOTAL | P7: WEEKS ESTIMATED | Q7: DUE UNTIL | R7: estimated weeks | S7: due until | T7: mt rock out of stock | U7: weeks | V7: due until | W7: to be deliver until last week of october
C8: CONSUMPTION | P8: CONSUMED
A9: SENATEL | B9: BOXES | C9: 50 | D9: 243 | E9: 2292 | G9: 2 | H9: 18 | I9: 58 | J9: 50 | K9: 64 | N9: 25 | O9: =D9+E9+F9+G9+H9+I9+J9+K9+L9+M9+N9 -> 2752 | P9: =O9/C9 -> 55.04 | Q9: 2nd week of june 2027
A10: ANFO | B10: SACKS | C10: 350 | D10: 2593 | E10: 4650 | G10: 8 | H10: 13 | I10: 137 | J10: 47 | K10: 159 | M10: 17 | N10: 154 | O10: =D10+E10+F10+G10+H10+I10+J10+K10+L10+M10+N10 -> 7778 | P10: =O10/C10 -> 22.222857 | Q10: last week of november 2026
A11: OBC | B11: PCS | C11: 750 | D11: 4350 | E11: 34000 | G11: 184 | H11: 182 | I11: 570 | J11: 264 | K11: 624 | M11: 152 | N11: 616 | O11: =D11+E11+F11+G11+H11+I11+J11+K11+L11+M11+N11 -> 40942 | P11: =O11/C11 -> 54.589333 | Q11: 1st week oj june 2027
A12: SAFETY FUSE | B12: MTRS | C12: 3700 | D12: 11682 | E12: 101000 | G12: 447.12 | H12: 442.26 | I12: 1385.1 | J12: 641.52 | K12: 1516.32 | M12: 609 | N12: 1496.88 | O12: =D12+E12+F12+G12+H12+I12+J12+K12+L12+M12+N12 -> 119220.2 | P12: =O12/C12 -> 32.221676 | Q12: last week of december 2026
A13: CORDTXT 5 | B13: MTRS | C13: 3000 | D13: 4500 | E13: 131400 | G13: 255 | H13: 816 | I13: 2419 | J13: 1241 | K13: 1861 | O13: =D13+E13+F13+G13+H13+I13+J13+K13+L13+M13+N13 -> 142492 | P13: =O13/C13 -> 47.497333 | Q13: 2nd weeek of april 2027
A14: EBC | B14: PCS | C14: 40 | D14: 180 | E14: 840 | H14: 10 | I14: 30 | J14: 66 | N14: 29 | O14: =D14+E14+F14+G14+H14+I14+J14+K14+L14+M14+N14 -> 1155 | P14: =O14/C14 -> 28.875 | Q14: 2nd week of may 2027
A15: BELL WIRE | B15: MTRS | D15: 915 | I15: 150 | K15: 225 | O15: =D15+E15+F15+J15+K15+L15+N15 -> 1140 | P15: =O15/C15 -> #DIV/0!
A17: DELAY | B17: UNIT | C17: WEEKLY | D17: SURFACE | E17: SUPPLIER | F17: SINUG-AN | G17: MARATHON | H17: LEVEL 7 | I17: LEVEL 8 | J17: LEVEL 9 | K17: LEVEL 10 | L17: LEVEL 11 | M17: LEVEL 12 | N17: LEVEL 425 | O17: TOTAL | P17: WEEKS ESTIMATED | Q17: DUE UNTIL | R17: if mt. rock out of stock | S17: weekly consumption | T17: estimated week consume | U17: due untl | V17: conspt util october | W17: week estimated | X17: to bedeliver/Boxes
C18: CONSUMPTION | P18: CONSUMED
A19: 1 | B19: Pcs | C19: 700 | D19: 1210 | E19: 13010 | G19: 133 | H19: 282 | I19: 467 | J19: 268 | K19: 711 | M19: 487 | N19: 582 | O19: =D19+E19+F19+G19+H19+I19+J19+K19+L19+M19+N19 -> 17150 | P19: =O19/C19 -> 24.5 | Q19: 2nd week of november | T19: =R19/S19 -> #DIV/0!
A20: 2 | B20: Pcs | C20: 700 | D20: 1460 | E20: 13510 | G20: 319 | H20: 282 | I20: 460 | J20: 284 | K20: 540 | M20: 557 | N20: 613 | O20: =D20+E20+F20+G20+H20+I20+J20+K20+L20+M20+N20 -> 18025 | P20: =O20/C20 -> 25.75 | Q20: 3rd week of november | T20: =R20/S20 -> #DIV/0!
A21: 3 | B21: Pcs | C21: 700 | D21: 1190 | E21: 11760 | G21: 282 | H21: 282 | I21: 456 | J21: 517 | K21: 728 | M21: 499 | N21: 465 | O21: =D21+E21+F21+G21+H21+I21+J21+K21+L21+M21+N21 -> 16179 | P21: =O21/C21 -> 23.112857 | Q21: 2nd week of october | T21: =R21/S21 -> #DIV/0!
A22: 4 | B22: Pcs | C22: 1000 | D22: 1190 | E22: 14790 | G22: 194 | H22: 282 | I22: 521 | J22: 472 | K22: 724 | M22: 554 | N22: 432 | O22: =D22+E22+F22+G22+H22+I22+J22+K22+L22+M22+N22 -> 19159 | P22: =O22/C22 -> 19.159 | Q22: last week of september | T22: =R22/S22 -> #DIV/0!
A23: 5 | B23: Pcs | C23: 1000 | D23: 1040 | E23: 13570 | G23: 171 | H23: 278 | I23: 284 | J23: 440 | K23: 493 | M23: 671 | N23: 564 | O23: =D23+E23+F23+G23+H23+I23+J23+K23+L23+M23+N23 -> 17511 | P23: =O23/C23 -> 17.511 | Q23: 2nd week of september | T23: =R23/S23 -> #DIV/0!
A24: 6 | B24: Pcs | C24: 1000 | D24: 1320 | E24: 12880 | G24: 168 | H24: 278 | I24: 188 | J24: 426 | K24: 561 | M24: 579 | N24: 581 | O24: =D24+E24+F24+G24+H24+I24+J24+K24+L24+M24+N24 -> 16981 | P24: =O24/C24 -> 16.981 | Q24: 2nd week of september | T24: =R24/S24 -> #DIV/0!
A25: 7 | B25: Pcs | C25: 1000 | D25: 1040 | E25: 12440 | G25: 162 | H25: 248 | I25: 266 | J25: 401 | K25: 536 | M25: 519 | N25: 618 | O25: =D25+E25+F25+G25+H25+I25+J25+K25+L25+M25+N25 -> 16230 | P25: =O25/C25 -> 16.23 | Q25: 1st week of september | T25: =R25/S25 -> #DIV/0!
A26: 8 | B26: Pcs | C26: 1000 | D26: 1710 | E26: 10970 | G26: 162 | H26: 248 | I26: 315 | J26: 425 | K26: 617 | M26: 683 | N26: 461 | O26: =D26+E26+F26+G26+H26+I26+J26+K26+L26+M26+N26 -> 15591 | P26: =O26/C26 -> 15.591 | Q26: 1st week of september | T26: =R26/S26 -> #DIV/0!
A27: 9 | B27: Pcs | C27: 1000 | D27: 1660 | E27: 11660 | G27: 282 | H27: 280 | I27: 624 | J27: 213 | K27: 543 | M27: 651 | N27: 251 | O27: =D27+E27+F27+G27+H27+I27+J27+K27+L27+M27+N27 -> 16164 | P27: =O27/C27 -> 16.164 | Q27: 1st week of september | T27: =R27/S27 -> #DIV/0!
A28: 10 | B28: Pcs | C28: 1000 | D28: 1310 | E28: 12760 | G28: 382 | H28: 286 | I28: 389 | J28: 381 | K28: 672 | M28: 623 | N28: 476 | O28: =D28+E28+F28+G28+H28+I28+J28+K28+L28+M28+N28 -> 17279 | P28: =O28/C28 -> 17.279 | Q28: 2nd week of september | T28: =R28/S28 -> #DIV/0!
A29: 11 | B29: Pcs | C29: 1000 | D29: 1570 | E29: 7700 | G29: 203 | H29: 286 | I29: 647 | J29: 409 | K29: 514 | M29: 636 | N29: 625 | O29: =D29+E29+F29+G29+H29+I29+J29+K29+L29+M29+N29 -> 12590 | P29: =O29/C29 -> 12.59 | Q29: 2nd week of august | T29: =R29/S29 -> #DIV/0!
A30: 12 | B30: Pcs | C30: 700 | D30: 1320 | E30: 6510 | G30: 262 | H30: 286 | I30: 306 | J30: 233 | K30: 411 | M30: 434 | N30: 490 | O30: =D30+E30+F30+G30+H30+I30+J30+K30+L30+M30+N30 -> 10252 | P30: =O30/C30 -> 14.645714 | Q30: last week of august | T30: =R30/S30 -> #DIV/0!
... A33: 15 | B33: Pcs | C33: 700 | D33: 2170 | E33: 8230 | G33: 187 | H33: 274 | I33: 334 | J33: 529 | K33: 555 | M33: 581 | N33: 543 | O33: =D33+E33+F33+G33+H33+I33+J33+K33+L33+M33+N33 -> 13403 | P33: =O33/C33 -> 19.147143 | Q33: last week of september | T33: =R33/S33 -> #DIV/0!
A38: MT.ROCK
A39: MONITORING STOCK FOR SUPPLIER AND PMC STOCK
A40: As Of May 23, 2026
A42: DESCRIPTION | B42: UNIT | C42: WEEKLY | D42: SURFACE | E42: SUPPLIER | F42: SINUG-AN | G42: MARATHON | H42: LEVEL 5 | I42: LEVEL 8 | J42: LEVEL 9 | K42: LEVEL 10 | L42: LEVEL 11 | M42: LEVEL 12 | N42: LEVEL 425 | O42: TOTAL | P42: WEEKS ESTIMATED | Q42: DUE UNTIL | R42: Arrival of dyna and anfo 1st week of april | S42: weeks consumed | T42: due untill
C43: CONSUMPTION
A44: 208 | B44: BOXES | C44: 50 | D44: 25 | E44: 370 | M44: 29 | N44: 19 | O44: =D44+E44+M44+N44 -> 443 | P44: =O44/C44 -> 8.86 | Q44: 3rd week of july
A45: ANFO | B45: SACKS | C45: 150 | O45: =D45+E45+F45+G45+H45+I45+J45+K45+L45+M45+N45 -> 0 | P45: =O45/C45 -> 0
A46: OBC | B46: PCS | C46: 750 | E46: 2500 | G46: 122 | H46: 95 | I46: 202 | J46: 133 | K46: 134 | L46: 0 | M46: 198 | N46: 101 | O46: =D46+E46+F46+G46+H46+I46+J46+K46+L46+M46+N46 -> 3485 | P46: =O46/C46 -> 4.6466667 | Q46: 3rd week of june
A47: SAFETY FUSE | B47: MTRS | C47: 0 | O47: =D47+E47+F47+G47+H47+I47+J47+K47+L47+M47+N47 -> 0 | P47: =O47/C47 -> #DIV/0!
A48: CORDTXT 10 | B48: MTRS | C48: 3000 | E48: 3000 | M48: 2607 | N48: 2000 | O48: =D48+E48+F48+G48+H48+I48+J48+K48+L48+M48+N48 -> 7607 | P48: =O48/C48 -> 2.5356667 | Q48: 1st week of june
A49: EBC | B49: PCS | C49: 52 | D49: 50 | E49: 120 | O49: =D49+E49+F49+G49+H49+I49+J49+K49+L49+M49+N49 -> 170 | P49: =O49/C49 -> 3.2692308 | Q49: 3rd week of july
A52: DELAY | B52: UNIT | C52: WEEKLY | D52: SURFACE | E52: SUPPLIER | F52: SINUG-AN | G52: MARATHON | H52: LEVEL 4 | I52: LEVEL 5 | J52: level 8 | K52: level 9 | L52: LEVEL 10 | M52: LEVEL 11 | O52: TOTAL | P52: WEEK ESTIMATED | Q52: DUE UNTIL
C53: CONSUMPTION | N53: LEVEL 12
A54: 1 | B54: Pcs | C54: 0 | D54: 0 | O54: =D54+E54+F54+G54+H54+I54+J54+K54+L54+M54+N54 -> 0 | P54: =O54/C54 -> #DIV/0!
A55: 2 | B55: Pcs | C55: 0 | D55: 204 | O55: =D55+E55+F55+G55+H55+I55+J55+K55+L55+M55+N55 -> 204 | P55: =O55/C55 -> #DIV/0!
A56: 3 | B56: Pcs | C56: 0 | D56: 1801 | O56: =D56+E56+F56+G56+H56+I56+J56+K56+L56+M56+N56 -> 1801 | P56: =O56/C56 -> #DIV/0!
A57: 4 | B57: Pcs | C57: 0 | D57: 766 | O57: =D57+E57+F57+G57+H57+I57+J57+K57+L57+M57+N57 -> 766 | P57: =O57/C57 -> #DIV/0!
A58: 5 | B58: Pcs | C58: 0 | D58: 1 | O58: =D58+E58+F58+G58+H58+I58+J58+K58+L58+M58+N58 -> 1 | P58: =O58/C58 -> #DIV/0!
A59: 6 | B59: Pcs | C59: 0 | D59: 64 | O59: =D59+E59+F59+G59+H59+I59+J59+K59+L59+M59+N59 -> 64 | P59: =O59/C59 -> #DIV/0!
A60: 7 | B60: Pcs | C60: 0 | D60: 217 | O60: =D60+E60+F60+G60+H60+I60+J60+K60+L60+M60+N60 -> 217 | P60: =O60/C60 -> #DIV/0!
A61: 8 | B61: Pcs | C61: 0 | D61: 848 | O61: =D61+E61+F61+G61+H61+I61+J61+K61+L61+M61+N61 -> 848 | P61: =O61/C61 -> #DIV/0!
A62: 9 | B62: Pcs | C62: 0 | D62: 2296 | O62: =D62+E62+F62+G62+H62+I62+J62+K62+L62+M62+N62 -> 2296 | P62: =O62/C62 -> #DIV/0!
A63: 10 | B63: Pcs | C63: 0 | D63: 3418 | O63: =D63+E63+F63+G63+H63+I63+J63+K63+L63+M63+N63 -> 3418 | P63: =O63/C63 -> #DIV/0!
A64: 11 | B64: Pcs | C64: 0 | D64: 2959 | O64: =D64+E64+F64+G64+H64+I64+J64+K64+L64+M64+N64 -> 2959 | P64: =O64/C64 -> #DIV/0!
A65: 12 | B65: Pcs | C65: 0 | D65: 3632 | E65: 2160 | O65: =D65+E65+F65+G65+H65+I65+J65+K65+L65+M65+N65 -> 5792 | P65: =O65/C65 -> #DIV/0!
A66: 13 | B66: Pcs | C66: 0 | D66: 0 | O66: =D66+E66+F66+G66+H66+I66+J66+K66+L66+M66+N66 -> 0 | P66: =O66/C66 -> #DIV/0!
A67: 14 | B67: Pcs | C67: 0 | D67: 0 | O67: =D67+E67+F67+G67+H67+I67+J67+K67+L67+M67+N67 -> 0 | P67: =O67/C67 -> #DIV/0!
A68: 15 | B68: Pcs | C68: 0 | D68: 0 | O68: =D68+E68+F68+G68+H68+I68+J68+K68+L68+M68+N68 -> 0 | P68: =O68/C68 -> #DIV/0!

Sheet MAGAZINE CAPACITY
A3: FORECAST - STOCK WITHDRAWAL FROM EXPEDITION MAGAZINE
A5: DESCRIPTION | B5: UNIT | C5: WEEKLY AVE. WITHDRAWAL | D5: SUPPLIER STOCK ON HAND @ MAIN MAGAZINE | E5: DATE OF WITHDRAWAL | R5: TO BE DELEVERED
E6: MARCH 12, 2026 | F6: MARCH 26, 2026 | G6: APRIL 9, 2026 | H6: APRIL 23, 2026 | I6: MAY 7, 2026 | J6: MAY 21, 2026 | K6: JUNE 4, 2026 | L6: JUNE 18 2026 | M6: REMAINING STOCK | N6: may 7 2026 | O6: may 21 2026 | P6: june 4 2026 | Q6: june 18 2026 | R6: july 9 2026 | S6: july 23 2026 | T6: aug 13 2026 | U6: aug 27 2026 | V6: sep 102026 | W6: sep 24 2026 | X6: oct 8 2026 | Y6: oct 22 2026 | Z6: nov 12 2026 | AA6: nov 26 2026 | AB6: dec 10 2026 | AC6: dec 17 2026 | AD6: TOTAL | AE6: TOTAL BOXES TO BE DELIVERED
A7: SENATEL | B7: BOXES | C7: 150 | D7: 2317 | E7: 50 | F7: 150 | G7: 150 | H7: 150 | I7: 150 | J7: 150 | K7: 150 | L7: 150 | M7: =D7-E7-F7-G7-H7-I7-J7-K7-L7 -> 1217 | AE7: 500 BOXES
A8: ANFO | B8: SACKS | C8: 600 | D8: 3425 | E8: 600 | F8: 600 | G8: 600 | H8: 600 | I8: 600 | J8: 425 | K8: 0 | L8: 0 | M8: =D8-E8-F8-G8-H8-I8-J8-K8-L8 -> 0 | O8: 200 | P8: 600 | Q8: 600 | R8: 600 | S8: 600 | T8: 600 | U8: 600 | V8: 600 | W8: 600 | X8: 600 | Y8: 600 | Z8: 600 | AA8: 600 | AB8: 600 | AC8: 600 | AD8: 8600 | AE8: 8600 SACKS
A9: OBC | B9: PCS | C9: 1000 | D9: 24100 | E9: 1000 | F9: 1000 | G9: 1000 | H9: 1000 | I9: 1000 | J9: 1000 | K9: 1000 | L9: 1000 | M9: =D9-E9-F9-G9-H9-I9-J9-K9-L9 -> 16100 | AE9: 0
A10: SAFETY FUSE | B10: MTRS | C10: 5000 | D10: 41000 | E10: 5000 | F10: 5000 | G10: 5000 | H10: 5000 | I10: 5000 | J10: 5000 | K10: 5000 | L10: 5000 | M10: =D10-E10-F10-G10-H10-I10-J10-K10-L10 -> 1000 | R10: 5000 | S10: 5000 | T10: 5000 | U10: 5000 | V10: 5000 | W10: 5000 | X10: 5000 | Y10: 5000 | Z10: 5000 | AA10: 5000 | AB10: 5000 | AC10: 5000 | AD10: 60000 | AE10: 60 BOXES
A11: CORDTXT 5 | B11: MTRS | C11: 6300 | D11: 72900 | E11: 6300 | F11: 6300 | G11: 6300 | H11: 6300 | I11: 6300 | J11: 6300 | K11: 6300 | L11: 6300 | M11: =D11-E11-F11-G11-H11-I11-J11-K11-L11 -> 22500 | V11: 6300 | W11: 6300 | X11: 6300 | Y11: 6300 | Z11: 6300 | AA11: 6300 | AB11: 6300 | AC11: 6300 | AD11: =6300*8 -> 50400 | AE11: 56 BOXES
A12: EBC | B12: PCS | C12: 60 | D12: 600 | E12: 60 | F12: 60 | G12: 60 | H12: 60 | I12: 60 | J12: 60 | K12: 60 | L12: 60 | M12: =D12-E12-F12-G12-H12-I12-J12-K12-L12 -> 120
A13: BELLWIRE | M13: =D13-E13-F13-G13-H13-I13-J13-K13-L13 -> 0
A15: DELAY # | B15: UNIT | C15: WEEKLY AVE. WITHDRAWAL | D15: ON HAND | E15: MARCH 12 2026 | F15: MARCH 19, 2026 | G15: APRIL 9, 2026 | H15: APRIL 23, 2026 | I15: MAY 7, 2026 | J15: MAY 21, 2026 | K15: JUNE 4, 2026 | L15: JUNE 18, 2026 | M15: REMAINING STOCK | N15: MAY 7 2026 | O15: MAY 21 2026 | P15: JUNE 4 2026 | Q15: JUNE 18 2026 | R15: JULY 9 2026 | S15: JULY 23 2026 | T15: AUG 13 2026 | U15: AUG 27 2026 | V15: SEPT 10 2026 | W15: SEPT 24 2026 | X15: OCT 8 2026 | Y15: OCT 22 2026 | Z15: NOV 12 2026 | AA15: NOV 26 2026 | AB15: DEC 10 2026 | AC15: DEC 17 2026 | AD15: TOTAL | AE15: TOTAL BOXES
A17: 1 | B17: Pcs | C17: 1250 | D17: 7510 | F17: 1500 | G17: 1250 | H17: 1250 | I17: 1250 | J17: 1250 | K17: 1010 | M17: =D17-E17-F17-G17-H17-I17-J17-K17-L17 -> 0 | Q17: 750 | R17: 1250 | S17: 1250 | T17: 1250 | U17: 1250 | V17: 1250 | W17: 1250 | X17: 1250 | Y17: 1250 | Z17: 1250 | AA17: 1250 | AB17: 1250 | AC17: 1250 | AD17: 15750 | AE17: 63 BOXES
A18: 2 | B18: Pcs | C18: 1250 | D18: 8510 | F18: 750 | G18: 1250 | H18: 1250 | I18: 1250 | J18: 1250 | K18: 1250 | L18: 1510 | M18: =D18-E18-F18-G18-H18-I18-J18-K18-L18 -> 0 | Q18: 500 | R18: 1250 | S18: 1250 | T18: 1250 | U18: 1250 | V18: 1250 | W18: 1250 | X18: 1250 | Y18: 1250 | Z18: 1250 | AA18: 1250 | AB18: 1250 | AC18: 1250 | AD18: 15500 | AE18: 62 BOXES
A19: 3 | B19: Pcs | C19: 1250 | D19: 6510 | F19: 1250 | G19: 1250 | H19: 1250 | I19: 1250 | J19: 1250 | K19: 260 | L19: 0 | M19: =D19-E19-F19-G19-H19-I19-J19-K19-L19 -> 0 | P19: 250 | Q19: 1250 | R19: 1250 | S19: 1250 | T19: 1250 | U19: 1250 | V19: 1250 | W19: 1250 | X19: 1250 | Y19: 1250 | Z19: 1250 | AA19: 1250 | AB19: 1250 | AC19: 1250 | AD19: =16250+500 -> 16750 | AE19: 67 BOXES
A20: 4 | B20: Pcs | C20: 2000 | D20: 7010 | F20: 1500 | G20: 2000 | H20: 2000 | I20: 1510 | K20: 0 | L20: 0 | M20: =D20-E20-F20-G20-H20-I20-J20-K20-L20 -> 0 | N20: 500 | O20: 1250 | P20: 1250 | Q20: 1250 | R20: 1250 | S20: 1250 | T20: 1250 | U20: 1250 | V20: 1250 | W20: 1250 | X20: 1250 | Y20: 1250 | Z20: 1250 | AA20: 1250 | AB20: 1250 | AC20: 1250 | AD20: =18750+500 -> 19250 | AE20: 77 BOXES
A21: 5 | B21: Pcs | C21: 2000 | D21: 6760 | F21: 1500 | G21: 2000 | H21: 2000 | I21: 1260 | J21: 0 | K21: 0 | L21: 0 | M21: =D21-E21-F21-G21-H21-I21-J21-K21-L21 -> 0 | N21: 500 | O21: 1250 | P21: 1250 | Q21: 1250 | R21: 1250 | S21: 1250 | T21: 1250 | U21: 1250 | V21: 1250 | W21: 1250 | X21: 1250 | Y21: 1250 | Z21: 1250 | AA21: 1250 | AB21: 1250 | AC21: 1250 | AD21: 19250 | AE21: 77 BOXES
A22: 6 | B22: Pcs | C22: 2000 | D22: 6510 | F22: 1500 | G22: 2000 | H22: 2010 | I22: 1000 | J22: 0 | K22: 0 | L22: 0 | M22: =D22-E22-F22-G22-H22-I22-J22-K22-L22 -> 0 | N22: 2000 | O22: 2000 | P22: 2000 | Q22: 2000 | R22: 2000 | S22: 2000 | T22: 2000 | U22: 2000 | V22: 2000 | W22: 2000 | X22: 2000 | Y22: 2000 | Z22: 2000 | AA22: 2000 | AB22: 2000 | AC22: 2000 | AD22: 32000 | AE22: 128 BOXES
A23: 7 | B23: Pcs | C23: 2000 | D23: 6260 | F23: 1500 | G23: 2000 | H23: 1760 | I23: 1000 | J23: 0 | K23: 0 | L23: 0 | M23: =D23-E23-F23-G23-H23-I23-J23-K23-L23 -> 0 | N23: 2000 | O23: 2000 | P23: 2000 | Q23: 2000 | R23: 2000 | S23: 2000 | T23: 2000 | U23: 2000 | V23: 2000 | W23: 2000 | X23: 2000 | Y23: 2000 | Z23: 2000 | AA23: 2000 | AB23: 2000 | AC23: 2000 | AD23: 32000 | AE23: 128 BOXES
A24: 8 | B24: Pcs | C24: 2000 | D24: 6010 | F24: 1500 | G24: 2000 | H24: 2010 | I24: 500 | J24: 0 | K24: 0 | L24: 0 | M24: =D24-E24-F24-G24-H24-I24-J24-K24-L24 -> 0 | N24: 2000 | O24: 2000 | P24: 2000 | Q24: 2000 | R24: 2000 | S24: 2000 | T24: 2000 | U24: 2000 | V24: 2000 | W24: 2000 | X24: 2000 | Y24: 2000 | Z24: 2000 | AA24: 2000 | AB24: 2000 | AC24: 2000 | AD24: 32000 | AE24: 128 BOXES
A25: 9 | B25: Pcs | C25: 2000 | D25: 6260 | F25: 1250 | G25: 2000 | H25: 2010 | I25: 1000 | J25: 0 | K25: 0 | L25: 0 | M25: =D25-E25-F25-G25-H25-I25-J25-K25-L25 -> 0 | N25: 2000 | O25: 2000 | P25: 2000 | Q25: 2000 | R25: 2000 | S25: 2000 | T25: 2000 | U25: 2000 | V25: 2000 | W25: 2000 | X25: 2000 | Y25: 2000 | Z25: 2000 | AA25: 2000 | AB25: 2000 | AC25: 2000 | AD25: 32000 | AE25: 128 BOXES
A26: 10 | B26: Pcs | C26: 2000 | D26: 6510 | F26: 1500 | G26: 2000 | H26: 1760 | I26: 1250 | J26: 0 | K26: 0 | L26: 0 | M26: =D26-E26-F26-G26-H26-I26-J26-K26-L26 -> 0 | N26: 2000 | O26: 2000 | P26: 2000 | Q26: 2000 | R26: 2000 | S26: 2000 | T26: 2000 | U26: 2000 | V26: 2000 | W26: 2000 | X26: 2000 | Y26: 2000 | Z26: 2000 | AA26: 2000 | AB26: 2000 | AC26: 2000 | AD26: 32000 | AE26: 128 BOXES
A27: 11 | B27: Pcs | C27: 2000 | D27: 7200 | F27: 1750 | G27: 2000 | H27: 2200 | I27: 1250 | J27: 0 | K27: 0 | L27: 0 | M27: =D27-E27-F27-G27-H27-I27-J27-K27-L27 -> 0 | N27: 2000 | O27: 2000 | P27: 2000 | Q27: 2000 | R27: 2000 | S27: 2000 | T27: 2000 | U27: 2000 | V27: 2000 | W27: 2000 | X27: 2000 | Y27: 2000 | Z27: 2000 | AA27: 2000 | AB27: 2000 | AC27: 2000 | AD27: 32000 | AE27: 128 BOXES
A28: 12 | B28: Pcs | C28: 1000 | D28: 6760 | F28: 500 | G28: 1000 | H28: 1000 | I28: 1000 | J28: 1000 | K28: 1000 | L28: 760 | M28: =D28-E28-F28-G28-H28-I28-J28-K28-L28 -> 500 | N28: 1000 | O28: 1000 | P28: 1000 | Q28: 1000 | R28: 1000 | S28: 1000 | T28: 1000 | U28: 1000 | V28: 1000 | W28: 1000 | X28: 1000 | Y28: 1000 | Z28: 1000 | AA28: 1000 | AB28: 1000 | AC28: 1000 | AD28: 16000 | AE28: 64 BOXES
A29: 13 | B29: Pcs | C29: 1000 | D29: 7230 | F29: 750 | G29: 1000 | H29: 1000 | I29: 100 | J29: 100 | K29: 1000 | L29: 1000 | M29: =D29-E29-F29-G29-H29-I29-J29-K29-L29 -> 2280 | R29: 1000 | S29: 1000 | T29: 1000 | U29: 1000 | V29: 1000 | W29: 1000 | X29: 1000 | Y29: 1000 | Z29: 1000 | AA29: 1000 | AB29: 1000 | AC29: 1000 | AD29: 12000 | AE29: 48 BOXES
A30: 14 | B30: Pcs | C30: 1000 | D30: 9730 | F30: 500 | G30: 1000 | H30: 1000 | I30: 1000 | J30: 1000 | K30: 100 | L30: 1000 | M30: =D30-E30-F30-G30-H30-I30-J30-K30-L30 -> 4130 | U30: 1000 | V30: 1000 | W30: 1000 | X30: 1000 | Y30: 1000 | Z30: 1000 | AA30: 1000 | AB30: 1000 | AC30: 1000 | AD30: 9000 | AE30: 36 BOXES
A31: 15 | B31: Pcs | C31: 1000 | D31: 9730 | F31: 250 | G31: 1000 | H31: 1000 | I31: 1000 | J31: 1000 | K31: 1000 | L31: 1000 | M31: =D31-E31-F31-G31-H31-I31-J31-K31-L31 -> 3480 | T31: 1000 | U31: 1000 | V31: 1000 | W31: 1000 | X31: 1000 | Y31: 1000 | Z31: 1000 | AA31: 1000 | AB31: 1000 | AC31: 1000 | AD31: 10000 | AE31: 40 BOXES
A32: TOTAL WITHDRAWAL | E32: =SUM(E17:E31) -> 0 | F32: =SUM(F17:F31) -> 17500 | G32: =SUM(G17:G31) -> 23750 | H32: =SUM(H17:H31) -> 23500 | I32: =SUM(I17:I31) -> 15620 | J32: =SUM(J17:J31) -> 6850 | K32: =SUM(K17:K31) -> 5620 | L32: =SUM(L17:L31) -> 5270 | AE32: 1302 BOXES | AF32: boxes
F35: DATE WITHDRAWAL
A36: DESCRIPTION | B36: UNIT | C36: WEEKLY AVE. WITHDRAWAL | D36: AVERAGE CAPACITY MAGZINE | E36: ON HAND MARCH 12 2026 | F36: MARCH 19, 2026 | G36: APRIL 9, 2026 | H36: APRIL 23, 2026 | I36: MAY 7 2026 | J36: ON HAND MAY 7 2026 | K36: DELIVERY TO MAINTAIN THE CAPACITY OF MAGAZINE
A38: SENATEL | B38: BOXES | C38: 150 | D38: 2300 | E38: 2267 | F38: 150 | G38: 150 | H38: 150 | I38: 150 | J38: =E38-F38-G38-H38-I38 -> 1667 | K38: =D38-J38 -> 633
A39: ANFO | B39: SACKS | C39: 600 | D39: 5000 | E39: 2825 | F39: 600 | G39: 600 | H39: 600 | I39: 600 | J39: =E39-F39-G39-H39-I39 -> 425 | K39: =D39-J39 -> 4575
A40: OBC | B40: PCS | C40: 1000 | D40: 30000 | E40: 23600 | F40: 1000 | G40: 1000 | H40: 1000 | I40: 1000 | J40: =E40-F40-G40-H40-I40 -> 19600 | K40: =D40-J40 -> 10400
A41: SAFETY FUSE | B41: MTRS | C41: 5000 | D41: =100*1000 -> 100000 | E41: =39*1000 -> 39000 | F41: 5000 | G41: 5000 | H41: 5000 | I41: 5000 | J41: =E41-F41-G41-H41-I41 -> 19000 | K41: =D41-J41 -> 81000
A42: CORDTXT 5 | B42: MTRS | C42: 6300 | D42: =160*900 -> 144000 | E42: =76*900 -> 68400 | F42: 6300 | G42: 6300 | H42: 6300 | I42: 6300 | J42: =E42-F42-G42-H42-I42 -> 43200 | K42: =D42-J42 -> 100800
A43: EBC | B43: PCS | C43: 60 | D43: 600 | K43: =D43-J43 -> 600
A44: BELLWIRE | K44: =D44-J44 -> 0
A46: DELAY # | B46: UNIT | C46: WEEKLY AVE. WITHDRAWAL | D46: AVERAGE CAPACITY MAGAZINE | E46: ON HAND MARCH 12 2026 | F46: MARCH 19, 2026 | G46: APRIL 9, 2026 | H46: APRIL 23, 2026 | I46: MAY 7 2026 | J46: ON HAND MAY 7 2026 | K46: TO BE DELEVERED | L46: PER BOXES
A48: 1 | B48: Pcs | C48: 1250 | D48: 16000 | E48: 7510 | F48: 1500 | G48: 1250 | H48: 1250 | I48: 1250 | J48: =E48-F48-G48-H48-I48 -> 2260 | K48: =D48-J48 -> 13740 | L48: 54
A49: 2 | B49: Pcs | C49: 1250 | D49: 16000 | E49: 8510 | F49: 750 | G49: 1250 | H49: 1250 | I49: 1250 | J49: =E49-F49-G49-H49-I49 -> 4010 | K49: =D49-J49 -> 11990 | L49: 47
A50: 3 | B50: Pcs | C50: 1250 | D50: 16000 | E50: 6510 | F50: 1250 | G50: 1250 | H50: 1250 | I50: 1250 | J50: =E50-F50-G50-H50-I50 -> 1510 | K50: =D50-J50 -> 14490 | L50: 57
A51: 4 | B51: Pcs | C51: 2000 | D51: 16000 | E51: 7010 | F51: 1500 | G51: 2000 | H51: 2000 | I51: 1510 | J51: =E51-F51-G51-H51-I51 -> 0 | K51: =D51-J51 -> 16000 | L51: 64
A52: 5 | B52: Pcs | C52: 2000 | D52: 16000 | E52: 6760 | F52: 1500 | G52: 2000 | H52: 2000 | I52: =760+500 -> 1260 | J52: =E52-F52-G52-H52-I52 -> 0 | K52: =D52-J52 -> 16000 | L52: 64
A53: 6 | B53: Pcs | C53: 2000 | D53: 16000 | E53: 6510 | F53: 1500 | G53: 2000 | H53: 2010 | I53: 1000 | J53: =E53-F53-G53-H53-I53 -> 0 | K53: =D53-J53 -> 16000 | L53: 64
A54: 7 | B54: Pcs | C54: 2000 | D54: 16000 | E54: 6260 | F54: 1500 | G54: 2000 | H54: 1760 | I54: 1000 | J54: =E54-F54-G54-H54-I54 -> 0 | K54: =D54-J54 -> 16000 | L54: 64
A55: 8 | B55: Pcs | C55: 2000 | D55: 16000 | E55: 6010 | F55: 1500 | G55: 2000 | H55: 2010 | I55: 500 | J55: =E55-F55-G55-H55-I55 -> 0 | K55: =D55-J55 -> 16000 | L55: 64
A56: 9 | B56: Pcs | C56: 2000 | D56: 16000 | E56: 6260 | F56: 1250 | G56: 2000 | H56: 2010 | I56: 1000 | J56: =E56-F56-G56-H56-I56 -> 0 | K56: =D56-J56 -> 16000 | L56: 64
A57: 10 | B57: Pcs | C57: 2000 | D57: 16000 | E57: 6510 | F57: 1500 | G57: 2000 | H57: 1760 | I57: 1250 | J57: =E57-F57-G57-H57-I57 -> 0 | K57: =D57-J57 -> 16000 | L57: 64
A58: 11 | B58: Pcs | C58: 2000 | D58: 8000 | E58: 7200 | F58: 1750 | G58: 2000 | H58: 2000 | I58: 1450 | J58: =E58-F58-G58-H58-I58 -> 0 | K58: =D58-J58 -> 8000 | L58: 32
A59: 12 | B59: Pcs | C59: 1000 | D59: 8000 | E59: 6760 | F59: 500 | G59: 1000 | H59: 1000 | I59: 1000 | J59: =E59-F59-G59-H59-I59 -> 3260 | K59: =D59-J59 -> 4740 | L59: 18
A60: 13 | B60: Pcs | C60: 1000 | D60: 8000 | E60: 7230 | F60: 750 | G60: 1000 | H60: 1000 | I60: 1000 | J60: =E60-F60-G60-H60-I60 -> 3480 | K60: =D60-J60 -> 4520 | L60: 18
A61: 14 | B61: Pcs | C61: 1000 | D61: 8000 | E61: 9730 | F61: 500 | G61: 1000 | H61: 1000 | I61: 1000 | J61: =E61-F61-G61-H61-I61 -> 6230 | K61: =D61-J61 -> 1770 | L61: 7
A62: 15 | B62: Pcs | C62: 1000 | D62: 8000 | E62: 9730 | F62: 250 | G62: 1000 | H62: 1000 | I62: 1000 | J62: =E62-F62-G62-H62-I62 -> 6480 | K62: =D62-J62 -> 1520 | L62: 6
A63: TOTAL WITHDRAWAL | E63: =SUM(E48:E62) -> 108500 | F63: =SUM(F48:F62) -> 17500 | G63: =SUM(G48:G62) -> 23750 | H63: =SUM(H48:H62) -> 23300 | I63: =SUM(I48:I62) -> 16720 | J63: =SUM(J48:J62) -> 27230 | K63: =SUM(K48:K62) -> 172770 | L63: =SUM(L48:L62) -> 687
B100: 2 | D100: 1 contauner van 200 boxes capacity | F100: 13 boxex per delay | H100: =13*4 -> 52
C101: concreet 400 boxes | F101: 26 per delay
