Workbook

Sheet FOR OMWS (2)
A1: ACTIVE | D1: STOPPED
A2: WORKING PLACES | B2: TEAM LEADER
A3: {=#REF!} -> #REF!
A20: {=#REF!} -> #REF!
A37: {=#REF!} -> #REF!
A54: {=#REF!} -> #REF!
A71: {=#REF!} -> #REF!
A88: {=#REF!} -> #REF!
A105: {=#REF!} -> #REF!
A122: {=#REF!} -> #REF!
A139: {=#REF!} -> #REF!
A154: {=#REF!} -> #REF!
A170: {=#REF!} -> #REF!
A186: {=#REF!} -> #REF!
... A1047: {=#REF!} -> #REF!

Sheet FINAL LIST WITH REMARKS
B3: STOPE PREP | E3: BREAKING | H3: PULL OUT | K3: DRIFT | N3: RAISES | Q3: WINZES | T3: CROSSCUT | W3: ROBBING / SPECIAL PROJECT
A4: LEVEL 4 | B4: L03_JV_014W_WINZE STOPE PREP | C4: FERNANDEZ, RM | D4: REPLACEMENT OF L03_JV_014W_RAISE. APPROVED ON DECEMBER 11, 2024. TEMPORARY STOPPED ON FEBRUARY 25, 2025 TO PRIORITIZE SPECIAL PROJECT AT L03_003E_ML. STOPPED ON MARCH 31, 2025. TO BE CONVERTED TO STOPE BREAKING. RESUMED AND CONVERTED TO STOPE BREAKING. APPROVED ON MARCH 31, 2025. | E4: L03_JV_014W_WINZE STOPE | F4: FERNANDEZ, RM | G4: REPLACEMENT OF L03_JV_014W_RAISE. APPROVED ON DECEMBER 11, 2024. TEMPORARY STOPPED ON FEBRUARY 25, 2025 TO PRIORITIZE SPECIAL PROJECT AT L03_003E_ML. RESUMED AND CONVERTED TO STOPE BREAKING. APPROVED ON MARCH 31, 2025. STOPPED BREAKING JULY 09,2025 DUE TO NO DATA ON THE UPPER AREA TOWARDS SMALL SCALE MINING ACTIVITIES. FOR STOPE TRAVERSE. | H4: L03_JV_014W_WINZE STOPE | I4: FERNANDEZ, RM | J4: REPLACEMENT OF L03_JV_014W_RAISE. APPROVED ON DECEMBER 11, 2024. TEMPORARY STOPPED ON FEBRUARY 25, 2025 TO PRIORITIZE SPECIAL PROJECT AT L03_003E_ML. RESUMED AND CONVERTED TO STOPE BREAKING. APPROVED ON MARCH 31, 2025. STOPPED BREAKING JULY 09, 2025 DUE TO NO DATA ON THE UPPER AREA TOWARDS SMALL SCALE MINING ACTIVITIES. FOR STOPE TRAVERSE. CONVERTED TO PULL-OUT. APPROVED ON JULY 10, 2025 3RD SHIFT.TO BE CONVERTED INTO ROBBING. STOPPED ON AUGUST 5, 2025. | K4: L03_JV_043W_DW | L4: FERNANDEZ, RM | M4: REPLACEMENT OF L03_JV_040W_ML CLEANINING. APPROVED ON OCTOBER 30, 2024. TEMPORARY STOPPED ON NOVEMBER 22, 2024 DUE TO COLLAPSED ON BAGUIO SHAFT AREA. FOR EVALUATION. RESUMED ON MAY 03, 2025. STOPPED ON JUNE 10, 2025. CHANGE STATUS TO ML CLEANING. | N4: L03_GHV_051W_RAISE | O4: FERNANDEZ 6 | P4: ADDITIONAL WORKING PLACE. MUST LIMIT BREAKING UNTIL +20m SLOPE DISTANCE. APPROVED ON SEPTEMBER 11, 2025.RENAMED FROM L03_GHV_051E_RAISE TO L03_GHV_051W_RAISE FOR PROPER POSITIONING. APPROVED ON SEPTEMBER 19, 2025. RENAMED TEAMLEADER FROM FERNANDEZ TO FERNANDEZ 6. APPROVED ON OCTOBER 13, 2025. STOPPED ON OCTOBER 24, 2025. ALREADY MADE A BREAKTHROUGH. | Q4: L03_JV_014W_WINZE | R4: FERNANDEZ, RM 6 | S4: REPLACEMENT OF L03_CTV_021W_WINZE. APPROVED ON MARCH 01, 2024.STOPPED ON MAY 10, 2024. ALREADY REACHED THE RECOMMENDED SLOPE DISTANCE. | T4: L04_NONE_026W_XCN | U4: MARTINEZ, DN 4 | V4: TARGETING CV VEIN FOR ROBBING. APPROVED ON FEB. 28, 2023.STOPPED ON MARCH 20, 2023. ALREADY FINISHED HEADING. | W4: L03_NONE_025W_XCS | X4: NITRO AV 1 | Y4: ACCESS VENTILATION SHAFT AND VENTILATION RAISE FOR INSPECTION, APPROVED ON FEB.5,2017.STOPPED ON MARCH 25, 2017 AS PER EC BAGUNO. (FINISHED). NO MEMO RECEIVED YET. RESUMED ON JULY 5, 2017 FOR THE PURPOSE OF EXTRACTING REMAINING ORES AND TO COLLAPSE THE CURRENT BACK OF THE OLD MAINLINE FOR BLOCKING PROBABLE ACCESS OF INTRUDERS. STOPPED ON JULY 17, 2017 AS PER LH FRAGINAL. REPLACED BY 38W ROBBING.resumed on august 7, 2021 for widening as access for L01 ventilation raise. TRANSFER FROM DAGAMAC 1 TO SHEPHERD AV1 ON AUGUST 6,2022.CHANGE NAME FROM L04_NONE_025W_XCS TO L03_NONE_025W_XCS DUE TO EXPLOSIVE WITHDRAWAL ISSUE.
B5: L04_JV_020W_STOPE PREP | C5: MARTINEZ, DN 4 | D5: REPLACEMENT OF L04_JV_024W_ROBBING APPROVED ON NOVEMBER 7, 2023.STOPPED ON NOVEMBER 8, 2023, MADE A BREAKTHROUGH TO AN OLD STOPE. | E5: L04_CTV_010W_WINZE STOPE | F5: MARTINEZ, DN 3 | G5: REPLACEMENT OF L04_CTV_010W_WINZE STOPE PREP. APPROVED ON NOVEMBER 28, 2023. TEMPORARILY STOPPED ON JANUARY 16, 2024. 3RD SHIFT. DUE TO LACK OF MANPOWER.RESUMED ON JANUARY 17, 2024. 3RD SHIFT.STOPPED BREAKING ON FEBRUARY 12, 2024. CONVERTED TO PULL-OUT CLEANING. | H5: L04_JVSPLIT_028E_WINZE STOPE | I5: MARTINEZ DN 2 | J5: REPLACEMENT OF L04_JVSPLIT_028E_WINZE_STOPE PREP.APPROVED ON JULY 3,2022.STOPPED ON OCTOBER 7, 2022, CONVERTED TO STOPE PULLOUT.MINED-OUT ON NOVEMBER 21, 2022 WITH 107% PULL-OUT MC. | K5: L04_CV_007E_DW_ISL | L5: MARTINEZ, DN 4 | M5: REPLACEMENT OF L04_CV_006E_DE_ISL .APPROVED ON 2/14/2023.TEMP STOPPED ON MAR 25, 2023 DUE TO MANPOWER ISSUE,RESUMED ON MARCH 28, 2023.STOPPED ON MAY 05, 2023. CONVERTED TO WINZE STOPE PREP.RESUMED ON MAY 19, 2023 AS WELL AS RENAME FROM L04_CV_006E_DW_ISL TO L04_CV_007E_DW_ISL.STOPPED ON JUNE 8, 2023. DUE TO LOW ASSAY GRADE.RESUMED ON NOVEMBER 24, 2023. AS WELL AS CHANGED TEAM LEADER FROM MARTINEZ, RON 1 TO MARTINEZ, DN 4.TEMPORARY STOPPED ON DECEMBER 6, 2023 DUE TO UNSAFE CONDITION OF THE WORKPLACE BASED ON THE JOINT EVALUATION AND ASSESSMENT OF THE CONCERNED DEPARTMENTS AFTER THE EARTHQUAKE INCIDENT. FOR FURTHER EVALUATION. STOPPED ON DECEMBER 09, 2023. MEMO FROM GEO. CURRENT FACE IS APPROACHING L05_NVN_001E_STOPE BASED ON MAP. | N5: L03_CTV_020W_RAISE | O5: FERNANDEZ, RM 2 | P5: REPLACEMENT OF L03_CTV_017W_DE. APPROVED ON APRIL 14, 2023.STOPPED ON MAY 17, 2023. MADE A BREAKTHROUGH. | Q5: L03_CTV_021W_WINZE | R5: FERNANDEZ, RM 6 | S5: REPLACEMENT OF L03_CTV_021W_ROBBING. APPROVED ON JANUARY 24, 2024.STOPPED ON FEBRUARY 29, 2024. DUE TO CONSECUTIVE LOW ASSAY GRADE ON CUT SAMPLES/BULK SAMPLES. | T5: L04_NONE_012W_XCS | U5: SHEPHERD AQ 1 | V5: CROSSCUT TO BREAKTHROUGH TO OPPOSITE MAINLINE TO TARGET BACK UP ROBBING. APPROVED ON SEPTEMBER 20,2022.STOPPED ON OCTOBER 18, 2022 ALREADY BREAKTHROUGH TO THE OLD MAINLINE. | W5: L03_GHV_053W_ROBBING | X5: FERNANDEZ 6 | Y5: REPLACEMENT OF L03_GHV_051W_RAISE. APPROVED ON OCOTBER 29, 2025. TEMPORARY STOPPED ON DECEMBER 06, 2025, DUE TO INACCESSIBILITY OF MAINLINE CAUSED BY COLLAPSED PORTION AT 5W RAISE. RESUMED FOR OPERATIONS ON MARCH 21, 2026. JOINT MANPOWER WITH L03_GHV_052E_ROBBING.
B6: L04_CV_006E_WINZE_STOPE PREP | C6: MARTINEZ, RON 1 | D6: REPLACEMENT OF L04_CV_006E_DW_ISL. APPROVED ON MAY 05, 2023.ALREADY DONE STOPE PREP ON MAY 20, 2023. CONVERT TO STOPE BREAKING. | E6: L04_CV_006E_WINZE_STOPE | F6: MARTINEZ, DN 4 | G6: REPLACEMENT OF L04_CV_006E_DW_ISL. APPROVED ON MAY 05, 2023.ALREADY DONE STOPE PREP ON MAY 20, 2023. CONVERT TO STOPE BREAKING.REPLACEMENT OF L04_CV_006E_WINZE_STOPE PREP, APPROVED ON MAY 20, 2023.TEMPORARY STOPPED ON JUNE 8, 2023 DUE TO THE UNAVAILABIILITY OF AGSAO SHAFT.RESUMED ON OCTOBER 02, 2023. AS WELL AS CHANGED TEAM LEADER FROM MARTINEZ, RON 1 TO MARTINEZ, DN 4.STOPPED BREAKING ON NOVEMBER 09, 2023. AS WELL AS TRAVERSED ON NOVEMBER 10, 2023, 2ND SHIFT. CONVERT TO PULL-OUT CLEANING. | H6: L04_CTV_022W_WINZE STOPE | I6: SHEPHERD AQ 2 | J6: REPLACEMENT ON L04_CTV_022W_WINZE STOPE PREP. APPROVED ON MAY 31,2022.STOPPED BREAKING ON SEPTEMBER 6, 2022 AND CONVERT TO PULL-OUT.MINED-OUT ON SEPTEMBER 26, 2022 WITH 105% PULL-OUT MC. | K6: L04_JVS_008W_DW | L6: MARTINEZ DN 1 | M6: REPLACEMENT OF L04_GHVFW_011E_ROBBING. APPROVED ON OCTOBER 19, 2023.STOPPED ON OCTOBER 20, 2023, TO PRIORITIZE CLEANING.. | N6: L04_CTV_023W_RAISE | O6: CAYMAN 1 | P6: RAISE ON ISL. APPROVED ON FEBRUARY 6, 2023.STOPPED ON FEBRUARY 9, 2023 . TO PROCEED TO WINZE STOPE PREP | Q6: L03_CTV_014W_WINZE | R6: FERNANDEZ, RM 4 | S6: ADDITIONAL FILL WINZE IN LEVEL 3. APPROVED ON JANUARY 08, 2024.STOPPED ON JANUARY 18 2024. ALREADY MADE A BREAKTHROUGH. | T6: L04_NONE_016E_XCN | U6: SHEPHERD AQ | V6: ADDITIONAL HORIZONTAL DEVT APPROVED ON JAN 10, 2022.STOPPED ON FEB.9,2022 | W6: L03_NONE_047E_MAINLINE CLEANING | X6: FERNANDEZ | Y6: NEW WORKING PLACE OF L03. MANPOWER FROM L03_GHV_052E_ROBBING. SPECIAL PROJECT TO ACCESS THE BACK-UP FOR ROBBING. APPROVED ON MAY 18, 2026.
B7: L04_CTV_023W_WINZE STOPE PREP | C7: CAYMAN 3 | D7: REPLACEMENT OF L04_CTV_023W_RAISE. APPROVED ON 2/10/2023.STOPPED AND CONVERT TO STOPE BREAKING ON MARCH 01, 2023.STOPPED AND CONVERT TO STOPE BREAKING ON MARCH 01, 2023. | E7: L04_CTV_023W_WINZE STOPE | F7: CAYMAN 3 | G7: REPLACEMENT OF L04_CTV_023W_WINZE STOPE APPROVED ON MARCH 01, 2023.STOPPED BREAKING ON APRIL 21, 2023. DUE TO ADJACENT STOPE BREAKTHROUGH. | H7: L04_CV_006E_STOPE | I7: MARTINEZ, RON 3 | J7: REPLACEMENT OF L04_CV_006E_STOPE PREP. APPROVED ON JUNE 22, 2022.STOPPED ON AUGUST 24, 2022 AT THE SAME TIME CONVERTED TO PULLOUT CLEANING.MINED OUT ON SEPTEMBER 12, 2022 WITH 87% PULL-OUT MC. | K7: L04_JV_020W_DE | L7: CAYMAN 1 | M7: ADDITONAL HORIZONTAL DEVELOPMENT DRIVE. APPROVED ON APRIL 26, 2023.CHANGED VEIN POSITION FROM L04_JV_027W_DE TO L04_JV_020W_DE FOR PROPER NAMING.STOPPED ON MAY 18, 2023. DUE TO CONSECUTIVE LOW ASSAY GRADE. | N7: L04_RYV_001W_RAISE | O7: APA 1 | P7: REPLACEMENT OF L04_RYV_001E_RAISE. APPROVED ON JANUARY 27,2023.STOPPED ON JAN 30, 2023. VEIN PINCHED OUT. | Q7: L04_CTV_010W_WINZE | R7: MARTINEZ, DN 3 | S7: REPLACEMENT OF L04_CTV_012W_ROBBING. APPROVED ON MAY 17, 2023.TEMPORARY STOPPED ON JUNE 8, 2023 DUE TO THE UNAVAILABIILITY OF AGSAO SHAFT.RESUMED ON OCTOBER 02, 2023.STOPPED ON OCTOBER 11, 2023.ALREADY MADE A BREAKTHROUGH. | T7: L04_NONE_028W_XCN_ISL | U7: MARTINEZ DN 1 | V7: REPLACEMENT OF L04_JVHW_027W_DW_ISL APPROVED ON SEPTEMBER 14, 2021.STOPPED ON SEMPTEBER 22, 2021 | W7: L03_NONE_045W_MAINLINE_CLEANING | X7: FERNANDEZ, RM | Y7: REPLACEMENT OF L03_NONE_043W_DW. MAILINE CLEANING ACTIVITIES INCLUDES GROUND SUPPORT INSTALLATION,CLEANING AND INSTALLATION OF RAILINGS AND WIDENINGS.APPROVED ON AUGUST 3, 2025. STOPPED ON MARCH 21, 2026. ALREADY FINISHED MAINLINE ACTIVITIES AND CLEANING.
B8: L04_GHVFW_010E_WINZE STOPE PREP | C8: MARTINEZ DN 1 | D8: REPLACEMENT OF L04_GHVFW_010E_DE_ISL APPROVED ON AUGUST 15, 2022.STOPPED AND CONVERT TO BREAKING ON AUGUST 31, 2022. | E8: L04_GHVFW_010E_WINZE STOPE | F8: MARTINEZ DN 1 | G8: REPLACEMENT OF L04_GHVFW_010E_WINZE STOPE PREP. APPROVED ON SEPTEMBER 1, 2022.CONDUCTED FILL RAISE ON OCTOBER 19, 2022. | H8: L04_CTV_021W_STOPE | I8: NOCOS 2 | J8: REPLACEMENT OF L04_CTV_021W_ROBBING APPROVED ON JULY 8,2021.stopped on oct.19 ,2021 unsafe.RESUME ON OCT.20, 2021.stopped on nov. 15,2021 converted to pull-out cleaning.TEMP STOPPED ON MARCH 16, 2022. | K8: L03_CTV_017W_DE | L8: FERNANDEZ, RM 2 | M8: REPLACEMENT OF L03_JVSPLIT_023W_ROBBING. APPROVED ON FEBRUARY 03, 2023.TEMPORARY STOPPED ON APRIL 14, 2023. TO PRIORITIZE OTHER VERTICAL DEVELOPMENT.RESUMED ON APRIL 26, 2023.STOPPED ON MAY 10, 2023. ALREADY MADE A BREAKTHROUGH. MEMO TO BE FOLLOWED.STOPPED MEMO RECEIVED ON MAY 12, 2023. | N8: L04_RYV_001E_RAISE | O8: APA 1 | P8: REPLACEMENT OF L04_RYV_001E_DW. APPROVED ON NOV 28 2022.TEMPORARILY STOPPED ON DEC 5 2022 DUE TO MAINLINE COLLAPSE.RESUMED ON DEC. 10, 2022.TEMPORARILY STOPPED ON DECEMBER 14, 2022 DUE TO LACK OF MANPOWER.RESUMED ON JANUARY 10, 2023.CHANGE NAME OF TEAM LEADER FROM SHEPHERD AR 1 TO APA 1, FULL PLEDGED TEAM LEADER APPROVED ON DECEMBER 20,2022.STOPPED ON JANUARY 25,2023 DUE TO CONSECUTIVE LOW ASSAY GRADE | Q8: L03_CTV_016W_WINZE | R8: FERNANDEZ, RM 4 | S8: REPLACEMENT OF L03_CTV_016W_ROBBING. APPROVED ON APRIL 19, 2023. FILL WINZE.STOPPED ON APRIL 21, 2023. | T8: L04_NONE_024W_XCN | U8: MARTINEZ, RONALD 2 | V8: ADDITIONAL HORIZONTAL DEVELOPMENT. APPROVED ON FEB 2 2021.CHANGE WORK HEADING INTO L04 JVSPLIT 024W DW. APPPROVED ON FEBRUARY 11,2021.STOPPED ON FEB. 11, 2021.resumed on april 16, 2021.STOPPED ON JUNE 10,2021 NOTIFY ON JUNE 15, 2021 ALREADY BREAKTHROUGH. | W8: L03_CTV_025W_RAISE | X8: FERNANDEZ, RM 5 | Y8: ADDITIONAL VERTICAL DEVELOPMENT. APPROVED ON JUNE 14, 2024. BLOCKING RAISE.RENAMED FROM L03_DPVE_025W_RAISE TO L03_CTV_025W_RAISE. FOR PROPER NAMING OF VEIN. APPROVED ON JULY 06, 2024.STOPPED ON AUGUST 01, 2024. ALREADY MADE A BREAKTHROUGH.
B9: L04_JVSPLIT_028E_WINZE_STOPE PREP | C9: MARTINEZ DN 2 | D9: REPLACEMENT OF L04_JVSPLIT_028E_DE_ISL. APPROVED ON MAY 5, 2022.STOPPED ON JULY 2,2022 CONVERT TO ACTIVE BREAKING. | E9: L04_JVSPLIT_028E_WINZE STOPE | F9: MARTINEZ DN 2 | G9: REPLACEMENT OF L04_JVSPLIT_028E_WINZE_STOPE PREP.APPROVED ON JULY 3,2022.STOPPED ON OCTOBER 7, 2022, CONVERTED TO STOPE PULLOUT. | H9: L04_GHVSPLIT_029W_STOPE | I9: SHEPHERD AQ | J9: CONVERTED TO PULL-OUT ON FEBRUARY 12, 2022. MINED-OUT ON MARCH 12, 2022 WITH 105% PULL-OUT. | K9: L03_CTV_018W_DW | L9: FERNANDEZ, RM 2 | M9: REPLACEMENT OF L03_CTV_020W_ROBBING. APPROVED ON FEBRUARY 03, 2023. RENAMED FROM L03_CTV_017W_DW TO L03_CTV_018W_DW TO AVOID MISCHARGING APPROVED ON FEBRUARY 5, 2023.STOPPED ON MARCH 1, 2023. ALREADY MADE A BREAKTHROUGH. | N9: L04_JV_042W_RAISE | O9: MARTINEZ, RON 1 | P9: REPLACEMENT OF L04_CV_006E_WINZE APPROVED ON NOVEMBER 18, 2022.STOPPED ON DEC 6 2022 (3RD SHIFT) DUE TO LOW GRADE ASSAYS. | Q9: L04_CV_006E_WINZE | R9: MARTINEZ, RON 1 | S9: REPLACEMENT OF L04_CV_009W_ROBBING. APPROVED ON SEPTEMBER 24, 2022.TEMPORARY STOPPED ON NOVEMBER 18, 2022 TO PRIORITIZE NORMAL WORKPLACES. | T9: L04_NONE_022W_XCS | U9: BAÑEZ 9 | V9: REPLACEMENT OF L04_EDVSPLIT_021W_DW. APPROVED ON OCT 15 2020. TRANSFER FROM MANZANO 2 TO MARTINEZ ON 11/5/2020. TEMP STOPPED ON DEC 21 2020 DUE TO UNSERVICEABLE AREA.resumed on March 26,2021 at the same time transfer from MARTINEZ, DN TO BANEZ. TEMPORARY STOPPED ON MARCH 27,2021 TO PRIORITIZED BY PASS FOR VENTILATION.RESUME ON 4/19/21. CHANGED NAME FROM 21E TO 22E APRIL 23, 2021. CHANGED FROM 22E TO 22W AS PER LEVEL GEO ON APRIL 23, 2021. STOPPED ON MAY 24,2021 ALREADY HIT THE TARGET. | W9: L03_JV_028W_ROBBING | X9: FERNANDEZ, RM 2 | Y9: REPLACEMENT OF L03_JVSPLIT_034W_ROBBING. APPROVED ON MAY 9, 2024. SILL.STOPPED ON AUG 1, 2024 ALREADY FINISHED ROBBING PILLAR.STOPPED ON AUG 1, 2024 ALREADY FINISHED ROBBING PILLAR.
B10: L04_CTV_022W_WINZE STOPE PREP | C10: SHEPHERD AQ3 | D10: REPLACEMENT OF L04_GHVFW_027W_ROBBING AND L04_GHVSPLIT_041W_ROBBING RESUMED APRIL 25, 2022, CHANGE TEAM LEADER FROM COMAINGKING TO SHEPHERD AQ3.STOPPED ON MAY 31,2022 ALREADY BREAKTHROUGH. | E10: L04_CTV_022W_WINZE STOPE | F10: SHEPHERD AQ 3 | G10: REPLACEMENT ON L04_CTV_022W_WINZE STOPE PREP. APPROVED ON MAY 31,2022.STOPPED BREAKING ON SEPTEMBER 6, 2022 AND CONVERT TO PULL-OUT. | H10: L04_GHVSPLIT_031W_STOPE | I10: SHEPHERD AQ | J10: CONVERTED TO PULL OUT ON DECEMBER 09, 2021. STOPPED ON JANUARY 13, 2022 MINED OUT. | K10: L04_CV_006E_DE_ISL | L10: MARTINEZ, RON 1 | M10: REPLACEMENT OF L04_CV_006E_WINZE APPROVED ON JANUARY 10, 2023.STOPPED ON FEBRUARY 10, 2023 VEIN WAS CUT BY A N-S TRENDING FAULT, PINCHED OUT VEIN. | N10: L03_JVSPLIT_016W_RAISE | O10: FERNANDEZ, RM 2 | P10: REPLACEMENT OF L03_JVSPLIT_015W_RAISE. APPROVED ON NOVEMBER 4, 2022.STOPPED ON NOVEMBER 25, 2022 TO PRIORITIZE SILL PILLAR ROBBING. | Q10: L04_CV_009W_WINZE | R10: NOCOS 2 | S10: APPROVED ON JULY 19, 2022, REPLACEMENT OF L04_CV_025W_ROBBING.STOPPED ON AUGUST 31, 2022 DUE TO UNSAFE CONDITION. | T10: L04_NONE_007W_XCN | U10: MARTINEZ, RONALD | V10: ADDITIONAL HORIZONTAL DEVELOPMENT, APPROVED ON JANUARY 11 2021 TO BE USED AS MAINLINE FOR TRAMMING.STOPPED ON MARCH 2, 2021 MADE A BREAKTHROUGH. | W10: L03_JV_029E_ROBBING | X10: FERNANDEZ, RM 3 | Y10: REPLACEMENT OF L03_JVSPLIT_011W_ROBBING. APPROVED ON JUNE 06, 2024. SILL PILLAR.STOPPED ON JUNE 18, 2024. ALREADY FINISHED HEADING.
B11: L04_JVFW_010E_STOPE PREP | C11: COMAINGKING 2 | D11: BLIND STOPE. REPLACEMENT OF L04 JVFW 014E DW. APPROVED ON NOV. 4, 2021.RENAME FROM L04_JVFW_015E_STOPE PREP TO L04_JVFW_010E_STOPE PREP. STARDTING NOVEMBER 6, 2021.STOPPED ON NOV.18,2021 | E11: L04_CTV_020W_STOPE | F11: NOCOS 1 | G11: CONVERTED FROM L04_CTV_020W_ROBBING TO STOPE. APPROVED ON MARCH 15, 2022.temp stopped on march 18,2022. | H11: L04_CV_025W_STOPE | I11: SHEPHERD AR | J11: REPLACEMENT OF L04_CV_025W_STOPE PREP. APPROVED ON SEPTEMBER 25, 2021. STOPPED BREAKING AND CONVERT TO PULL-OUT STAGE ON NOVEMBER 6, 2021. STOPPED ON NOVEMBER 23, 2021. MINED OUT | K11: L03_CTV_024W_DW | L11: FERNANDEZ, RM 4 | M11: ADDITIONAL HORIZONTAL HEADING. APPROVED ON OCTOBER 17, 2022.STOPPED ON NOVEMBER 21, 2022, PINCHED OUT VEIN. | N11: L03_JVSPLIT_015W_RAISE | O11: FERNANDEZ, RM 2 | P11: ADDITIONAL VERTICAL DEVELOPMENT. APPROVED ON SEPTEMBER 24,2022.STOPPED ON NOVEMBER 4, 2022 DUE TO UNSAFE CONDITION. | Q11: L04_GHVFW_010E_WINZE | R11: MARTINEZ DN | S11: REPLACEMENT OF L04_CTV_020W_ROBBING ON MARCH 28 2022.TEMPORARY STOPPED ON APRIL 11,2022 DUE TO TRANSITION OF MANPOWER.RESUMED APRIL 25, 2022 AS WELL AS CHANGE TEAM LEADER FROM NOCOS TO MARTINEZ DN.STOPPED ON JUNE 30, 2022, ALREADY REACHED THE RECOMMENDED STRIKE LENGTH/CROWN PILLAR. | T11: L04_NONE_022E_XCN | U11: BAÑEZ 4 | V11: ADDITIONAL. APPROVED ON OCT 16 2020. stopped on Nov. 11 2020, already hit the target vein. | W11: L04_CTV_010W_ROBBING | X11: MARTINEZ, DN 3 | Y11: REPLACEMENT OF L04_CTV_010W_WINZE STOPE. APPROVED ON FEBRUARY 21, 2024. TOPSLICE.STOPPED ON APRIL 02, 2024, WILL BE CONVERTED TO WINZE STOPE PREP.
B12: L04_GHVSPLIT_031W_STOPE PREP | C12: SHEPHERD AQ | D12: Replacement of L04_GHVSPLIT_027W_STOPE. Approved on Sept 6, 2021. STOPPED ON 10/5/2021 TO BE CONVERTED TO STOPE BREAKING. | E12: L04_GHVSPLIT_029W_STOPE | F12: SHEPHERD AQ | G12: REPLACEMENT OF L04_GHVSPLIT_029W_STOPE_PREP APPROVED ON OCTOBER 4, 2021. STOPPED STOPE BREAKING AND CONVERTED TO PULL-OUT FEB. 12, 2021. | H12: L04_JV_030E_WINZE STOPE | I12: MARTINEZ DN 2 | J12: REPLACEMENT OF L04_JV_030E_ROBBING APPROVED ON 8/19/21. CONVERTED TO ACTIVE STOPE BREAKING APPROVED ON SEPTEMBER 7, 2021.stopped breaking on Sept. 16, 2021. convert to stope pull-out starting September 17, 2021. STOPPED ON SEPTEMBER 27, 2021. FINISHED HEADING. | K12: L04_JV_040W_DW | L12: SHEPHERD AL 1 | M12: REPLACEMENT OF L04_JVSPLIT_027E_DW. APPROVED ON SEPTEMBER 12, 2022.TEMPORARY STOPPED ON SEPTEMBER 13, 2022.RESUMED ON SEPTEMBER 15, 2022.RESUMED ON SEPTEMBER 15, 2022 AT THE SAME TIME CHANGE TEAM LEADER FROM SHEPHERD AL 1 TO NOCOS.TEMPORARY STOPPED ON OCTOBER 4,2022 DUE TO LACK OF MANPOWER.RESUMED ON OCT 5, 2022. TRANSFERRED MANPOWER FROM NOCOS 2 SHEPHERD AQ 2 ON OCT 5 2022.STOPPED ON OCTOBER 19, 2022 DUE TO CONSECUTIVE LOW ASSAY GRADE.TRANSFERRED TO SHEPHERD AL. RESUMED ON OCTOBER 26. AS PER LEVEL GEO, HAS GOOD CUT SAMPLE.TEMPORARY STOPPED ON NOVEMBER 15, 2022 DUE TO INSUFFICIENT MANPOWER AND ABSENTEEISM RESULTING TO ABANDONEMENT OF WORKPLACE, THIS GROUP WILL BE MERGED TO SHEPHERD AL 1. | N12: L04_CV_007E_RAISE | O12: SHEPHERD AL 2 | P12: REPLACEMENT OF L04_CV_007E_DE. APPROVED ON SEPTEMBER 6, 2022.TEMPORARY STOPPED ON OCTOBER 11,2022. LACK OF MANPOWER. | Q12: L04_GHVFW_005W_WINZE | R12: SHEPHERD AL 2 | S12: ADDITIONAL VERTICAL DEVELOPMENT APPROVED ON MARCH 3, 2022. FILL WINZE.stopped on march 14, 2022 | T12: L04_NONE_025W_XCN | U12: MARTINEZ, RONALD | V12: SPECIAL PROJECT: COUNTER DRIVE DISTANCE TO TARGET MAINLINE FOR ROBBING AND VERTICAL DEVELOPMENT. APPROVED ON AUGUST 22 2020. TRANSFERRED TEAM LEADER ON AUGUST 27 2020, FROM BAÑEZ 4 TO MARTINEZ, RONALD. temporary stopped on Sept 6,2020 | W12: L03_GHV_024W_ROBBING | X12: FERNANDEZ, RM 1 | Y12: ADDITIONAL SOURCE OF GOOD ORE. SILL PILLAR ROBBING OF OLD STOPE. APPROVED ON MAY 13, 2024, 2ND SHIFT.TEMPORARY STOPPED ON JUNE 26, 2024. TO PRIORITIZE CLEANING AND BACKFILLING.
B13: L04_GHVFW_019E_WINZE STOPE PREP | C13: SHEPHERD AL 1 | D13: REPLACEMENT OF L04_GHVFW_018E_DE_ISL APPROVED ON JULY 1,2021.STOPPED ON 8/18/21 CONVERTED TO STOPE BREAKING | E13: L04_GHVSPLIT_031W_STOPE | F13: SHEPHERD AQ | G13: REPLACEMENT OF L04_GHVSPLIT_031W_STOPE PREP APPROVEED ON 10/5/2021. STOPPED ON DECEMBER 9, 2021 DUE TO LOW GRADE BULK SAMPLES. | H13: L04_CTV_008E_STOPE | I13: MARTINEZ, RON 3 | J13: CONVERTED TO PULL-OUT CLEANING ON SEPTEMBER 8, 2021. STOPPED ON SEPT.19,2021 DUE TO LOW QA/QC ON CUT/BULK SAMPLES WITH 61% PULL-OUT. | K13: L04_CV_005E_DE | L13: SHEPHERD AR 1 | M13: REPLACEMENT OF L04_CV_014W_ROBBING. APPROVED ON SEPTEMBER 2, 2022.TEMPORARY STOPPED ON SEPTEMBER 6, 2022 TO PRIORITIZE L04 CV 009W ROBBING.RESUMED ON SEPTEMBER 9, 2022 AS WELL AS TRANSFERRED FROM MARTINEZ, RON 1 TO SHEPHERD AR 1.TEMPORARY STOPPED ON SEPTEMBER 17, 2022 TO PRIORITIZE ANOTHER HORIZONTAL DEVELOPMENT. | N13: L04_CV_003E_RAISE | O13: SHEPHERD AL | P13: REPLACEMENT OF L04_CV_007E_DW. APPROVED ON JUNE 16, 2022.TEMPORARY STOPPED ON JUNE 20, 2022 TO PRIORITIZE THE OTHER DEVELOPMENTS AND LESSEN THE TRAFFIC OF THE MINE CARS. | Q13: L04_JVSPLIT_028E_WINZE | R13: MARTINEZ DN 2 | S13: REPLACEMENT OF L04 JV 030E ROBBING. APPROVED ON OCT 16, 2021.STOPPED ON FEB 9, 2022. ALREADY REACHED DESIRED ELEVATION, RECOMMENDED FOR ISL. RESUME ON MARCK 4, 2022.STOPPED ON MARCH 14,2022 | T13: L04_NONE_024W_XCS | U13: BAÑEZ 4 | V13: SPECIAL PROJECT: COUNTER DRIVE DISTANCE TO TARGET MAINLINE. APPROVED ON AUGUST 22 2020. TRANSFERRED TEAM LEADERON AUGUST 27 202 FROM MARTINEZ, RONALD TO BAÑEZ 4. STOPPED ON SEPT. 09 2020 3RD SHIFT. MADE A BREAKTHROUGH. | W13: L03_CTV_014W_ROBBING | X13: FERNANDEZ, RM 4 | Y13: ADDITIONAL SOURCE OF GOOD ORE. APPROVED ON NOVEMBER 17, 2023. TOPSLICE.TEMPORARY STOPPED ON DECEMBER 01, 2023. FOR AN EVALUATION OF A POSSIBLE OLD STOPE AT LEVEL 4.RESUMED ON DECEMBER 08, 2023.TEMPORARILY STOPPED ON JANAURY 08, 2024 IN ORDER TO PRIORITIZED FILL WINZE ALONG ITS MAINLINE.
B14: L04_CTV_008E_STOPE PREP | C14: MARTINEZ, RON 3 | D14: REPLACEMENT OF L08 CTV 008E DE. APPROVED ON JUNE 23 2021.STOPPED ON JULY 14, 2021.AT THE SAME TIME CONVERT TO STOPE BREAKING. | E14: L04_JV_030E_WINZE STOPE | F14: MARTINEZ DN 2 | G14: REPLACEMENT OF L04_JV_030E_ROBBING APPROVED ON 8/19/21. CONVERTED TO ACTIVE STOPE BREAKING APPROVED ON SEPTEMBER 7, 2021.stopped breaking on Sept. 16, 2021. convert to stope pull-out starting September 17, 2021. | H14: L04_CTV_025E_WINZE STOPE | I14: MARTINEZ DN 1 | J14: Replacements of L04_CTV_025E_WINZE STOPE PREP, approved on March 26, 2021.TEMPORARY STOPPED ON APRIL 7, 2021 SINGLE ENTRY. Resumed on April 9,2021. april 17, 2021 has 10m slope distance to connect to the mainline. Stopped on May 03, 2021, converted to Pull Out Cleaning.STOPPED ON MAY 17, 2021 ALREADY MINED OUT. | K14: L04_JVSPLIT_027E_DW | L14: SHEPHERD AL 1 | M14: REPLACEMENT OF L04_CV_004W_ROBBING. APPROVED ON SEPTEMBER 2, 2022. RENAME FROM L04_JV_040W_DW TO L04_JVSPLIT_027E_DW. APPROVED ON SEPTEMBER 5, 2022. STOPPED ON SEPTEMBER 12, 2022 DUE TO PINCHED OUT OF VEIN. | N14: L04_CV_002E_RAISE | O14: ANDILAB 2 | P14: REPLACEMENT OF L04_CV_002E_DE. APPROVED ON MAY 18 2022.TEmPORARILY STOPPED ON MAY 23 2022 DUE TO MANPOWER TRANSFER. | Q14: L04_CTV_008E_WINZE | R14: ANDILAB 1 | S14: REPLACEMENT OF L04 GHV 057E ROBBING. APPROVED ON JAN 24, 2022.STOPPED ON FEB.9, 2022 | T14: L04_NONE_014W_XCS | U14: NOCOS 1 | V14: TARGET CV MAINLINE FOR MAINHOLE STOPING. APPROVED ON JULY 29 2020. stopped august 23, 2020 already breakthrough. | W14: L04_JV_030E_ROBBING | X14: MARTINEZ DN 2 | Y14: REPLACEMENT OF L04_JV_030E_DW_ISL. APPROVED ON AUGUST 17, 2021.TEMPORARY STOPPED ON 19/8/21. RESUME ON SEPTEMBER 27, 2021.STOPPED ON OCT.13,2021
B15: L04_GHVSPLIT_026W_STOPE PREP | C15: BAÑEZ 5 | D15: REPLACEMNT OF L04_GHVSPLIT_026W_RAISE. APPROVED ON JUNE 15, 2021.STOPPED ON STOPE PREP ON JULY 2,2021 CONVERT TO ACTIVE BREAKING NOTIFIED ON JULY 6, 2021.STOPPED ON JULY 7, 2021 AT THE SAME TIME CONVERTED TO STOPE BREAKING. | E15: L04_GHVSPLIT_026W_STOPE | F15: BAÑEZ 5 | G15: REPLACEMNT OF L04_GHVSPLIT_026W_RAISE. APPROVED ON JUNE 15, 2021.STOPPED ON STOPE PREP ON JULY 2,2021 CONVERT TO ACTIVE BREAKING NOTIFIED ON JULY 6, 2021.STOPPED ON JULY 7, 2021 AT THE SAME TIME CONVERTED TO STOPE BREAKING. LOW DIPPING REPORTED ON JULY 20, 2021. STOPPED ON AUGUST 30, 2021 RECOMMENDED FOR ACTIVE STOPE BREAKING. | H15: L04_JVHW_014E_WINZE STOPE | I15: COMAINGKING 3 | J15: REPLACEMENT OF L04 JVHW 014E WINZE STOPE PREP. APPROVED ON JULY 11, 2020. TEMP. STOPPED ON JULY 16, 2020 TO PRIORITIZE WINZE FOR RELOCATING MANWAY. Resumed on Oct 6, 2020.MINE GEOLOGY ALREADY GUIDED SPLIT THE MINER AND OFFSET THE BLATING FF THE MASSIVE MAIN VEIN.STOPPED ON MARCH 18, 2021 CONVERT TO PULL OUT.STOPPED ON MAY 10,2021 MINED-OUT. | K15: L03_RYV_005W_DW | L15: FERNANDEZ, REX 1 | M15: REPLACEMENT OF L03_RYV_005W_DE APPROVED ON AUGUST 20, 2022.STOPPED ON SEPTEMBER 9, 2022 ALREADY REACHED THE RECOMMEND STRIKE LENGTH AS IT BREAKTHROUGH TO THE OLD MAINLINE. | N15: L04_CV_006E_RAISE | O15: MARTINEZ, RON 1 | P15: REPLACEMENT OF L04_CV_006E_DE. APPROVED ON MARCH 28 2022. JUSTIFICATION FOR ITS LOW DIPPING AT 42 DEGREES FROM 9 METER ELEVATION TO ITS CURRENT BACK (17 METERS) ON MAY 2, 2022.STOPPED ON MAY 17 2022 DUE TO PINCHING OUT OF VEIN. | Q15: L04_GHVSPLIT_041W_WINZE | R15: MARTINEZ DN 1 | S15: REPLACEMENT OF L04_JV_028W_DE_ISL.. APPROVED ON SEPTEMBER 27, 2021.STOPPED ON OCT 21, 2021. VEIN PINCHED OUT. | T15: L04_NONE_045W_XCS | U15: MARTINEZ DN.2 | V15: REPLACEMENT OF L04_GHV_045W_ROBBING APPROVED ON MARCH 23, 2020. STOPPED ON MARCH 31 2020 DUE TO MADE A BREAKTHROUGH | W15: L04_CTV_007W_ROBBING | X15: MARTINEZ, RON 1 | Y15: REPLACEMENT OF L04 NONE 007W XCN. APPROVED ON MARCH 3, 2021.RENAMED FROM CTV TO JV ON APRIL 21, 2021 AS PER LEVEL GEO.CORRECTED TO CTV ON APRIL 22, 2021 AS PER LEVEL GEO. STOPPED ON JULY 27, 2021.
B16: L04_GHVSPLIT_027W_STOPE PREP | C16: BAÑEZ 8 | D16: REPLACEMENT FROM L04_GHVSPLIT_027W_RAISE.APPROVED ON APRIL 16, 2021. temporary stopped on april 17, 2021 for grade evaluation and wireframe correction of level geo, The first wireframe used incorrect. Resumed on April 18, 2021. Design was finalized.STOPPED ON MAY 4, 2021 CONVERTED TO STOPE BREAKING. | E16: L04_GHVSPLIT_027W_STOPE | F16: BAÑEZ 8 | G16: REPLACEMENT OF L04_GHVSPLIT_027W_STOPE PREP.APPROVED ON MAY 4, 2021.recommended to continue breaking only 6m strike length form east side manway and leave the remaining length as pillar.STOPPED BREAKING ON 18/8/21 CONVERTED TO PULL-OU AT THE SAME DATE | H16: L04_GHVFW_041W_STOPE | I16: NOCOS 2 | J16: REPLACEMENT OF L04_GHVSPLIT_041W_STOPE PREP. APPROVED ON AUGUST 11 2020. Renamed from GHVSPLIT TO GHVFW ON SEPTEMBER 13,2020 AS PER MEMO OF LEVEL GEO. STOPPED BREAKING ON NOV. 30 2020 CONVERTED TO PULL OUT CLEANING. ALREADY FINISHED ON JAN 13 2021. | K16: L04_CV_007E_DW | L16: SHEPHERD AL | M16: REPLACEMENT OF L04 JVFW 012E ROBBING. APPROVED ON JAN 11, 2022.TEMP STOPPED ON JAN 14, 2022 TO REHAB MINE RAILS TOWARDS WORKING AREA.RESUMED ON JAN 19, 2022. STOPPED ON FEB. 17, 2022 DUE TO LOW GRADE.RESUMED ON MAY 11, 2022 AND TRANSFERRED FROM MARTINEZ, RON 3 TO SHEPHERD AL.TEMPORARY STOPPED ON JUNE 16, 2022 TO PRIORITIZE THE FUTURE STOPES AND REPLACE IT BY A VERTICAL DEVELOPMENT.RESUMED ON AUGUST 11, 2022.STOPPED SEPTEMBER 1, 2022 DUE TO PINCHED OUT OF VEIN. | N16: L04_CTV_022W_RAISE_ISL | O16: COMAINGKING 1 | P16: REPLACEMENT OF L04_CTV_022W_DE_ISL. APPROVED ON MARCH 2, 2022.STOPPED ON APRIL 12 2022. BREAKTHROUGH. | Q16: L04_JV_028W_WINZE | R16: MARTINEZ DN 1 | S16: REPLACEMENT of L04 CTV 025E WINZE STOPE. Approved on May 10, 2021.RENAMED FROML04_JV_027W_WINZE TO L04_JV_028W_WINZE ON MAY 11, 2021. STOPPED ON JULY 14, 2021 TO DRIVE INTERMEDIATE SUBLEVEL. | T16: L04_NONE_028W_XCN | U16: MARTINEZ, RONALD | V16: REPLACEMENT OF L04_GHV_029W_ROBBING. APPROVED ON JANUARY 13, 2020. STOPPED ON JANUARY 28 2020 DUE ALREADY BREAKTHROUGH. | W16: L04_JV_042W_ROBBING | X16: MARTINEZ, RON 2 | Y16: REPLACEMENT OF L04 CV 015W ROBBING. START JULY 14, 2021 (SILL PILLAR).STOPPED ON JULY 21, 2021. FINISHED HEADINGS.
... B32: L04_NV_011W_STOPE PREP | C32: MARTINEZ RON. 1 | D32: REPLACEMENT OF L04 NV 011E RAISE. APPROVED ON DECEMBER 15, 2018. ON WEST POSITION. STOPPED ON JANUARY 16, 2019. | E32: L04_GHVFW_017E_STOPE | F32: CABONITA 1 | G32: REPLACEMENT OF L04_GHVFW_017E_STOPE PREP. APPROVED ON JUNE 28, 2019.STOPPED CONVERT TO PULL-OUT CLEANING ON AUGUST 1, 2019. | H32: L04_JV_002E_STOPE | I32: CABONITA 1 | J32: REPLACEMENT OF L04 JV 002E STOPE PREP. APPROVED ON NOVEMBER 12, 2018. MZC. STOPPED BREAKING ON JANUARY 16, 2018. COVERTED TO PULL-OUT ON JANUARY 16, 2019. MINED-OUT ON 3/20/2019 WITH 78% PULL-OUT CLEANING. | K32: L04_CTV_010E_DW | L32: MARTINEZ DN 2 | M32: REPLACEMENTS OF L04_CTV_010E_DW APPROVE ON APRIL 16, 2021.MEMO RECEIVED ON MAY 2, 2021. Stopped on May 6,2021 notified on May 11,2021. | N32: L04_GHV_028W_RAISE | O32: MARTINEZ RON. 4 | P32: REPLACEMENT OF L04_GHV_028W_DE.APPROVED ON MARCH 26 2020. RENAMED FROM L04 GHVSPLIT 028W DE TO L04 GHV 028W RAISE ON MARCH 27, 2020. TEMP. STOPPED ON APRIL 9 DUE TO PANDEMIC. RESUMED ON JULY 7, 2020. STOPPED ON JULY 24, 2020 DUE TO PINCHED OUT OF VEIN. | Q32: L04_CV_006W_WINZE | R32: BAKAKON 1 | S32: FILL WINZE FOR WASTE PASS. APPROVED ON FEB 9, 2019. MZC. ALREADY BREAKTHROUGH STOPPED ON FEB 27, 2019. | T32: L04_NONE_023W_XCN_ISL | U32: CAYMAN 3 | V32: REPLACEMENT OF L04 CTV 023W WINZE STOPE, APPROVED ON MAY 3, 2023.STOPPED ON MAY 22, 2023 ALREADY INTERCEPTED THE TARGET VEIN. | W32: L04_CTV_011W_ROBBING | X32: NOCOS 1 | Y32: REPLACEMENT OF L04 CTV 010W DW. APPROVED ON JULY 15, 2019. AT L03. TEMPORARY STOPPED ON NOV 15, 2019 DUE TO ON GOING REGRADING AND REHAB OF MAINLINE.
B33: L04_CTV5_016E_STOPE PREP | C33: CABCAD 1 | D33: REPLACEMENT OF L04 CTV5 016E RAISE. APPROVED ON DECEMBER 10, 2018. MZC. STOPPED ON JANUARY 24, 2019. CONVERTED TO STOPE BREAKING. | E33: L04_GHVFW_005E_WINZE STOPE | F33: COMAINGKING 1 | G33: REPLACEMENT OF L04_GHVFW_005E_WINZE STOPE PREP. APPROVED ON JUNE 13, 2019. CONVERTED TO PULL-OUT ON SEPT 13, 2019. | H33: L04_CTV5_016E_STOPE | I33: CABCAD 2 | J33: REPLACEMENT OF L04 CTV5 016E RAISE. APPROVED ON DECEMBER 10, 2018. MZC. STOPPED ON JANUARY 24, 2019. CONVERTED TO STOPE BREAKING ON JANUARY 24, 2019. STOPPED BREAKING ON MARCH 31, 2019, DUE TO CONSECTUIVE LOW CUT SAMPLE; RECOMMENDED FOR STOPE CLEANING.STOP ON 4/9/19-SDNC, CONSECUTIVE LOW ASSAY GRADE RESULT. | K33: L04_JV_012W_DE | L33: ANDILAB 1 | M33: REPLACEMENT OF L04_JV_013W_WINZE APPROVED ON MARCH 19, 2021.Renamed from L04 JV 013W DE to L04 JV 012W DE on March 20,2021. Stopped on May 11,2021. | N33: L04_GHV_041W_RAISE | O33: MARTINEZ RON.3 | P33: REPLACEMENT OF L04_GHV_043W_RAISE. APPROVED ON MARCH 2 2020. STOPPED ON APRIL 8 2020 GEO RECOMMENDED TO MINIMIZE BREAKING WIDTH TO .90-1.00M DUE TO NARROW VEIN CHARACTERISTICS OF THE WORK HEADING. | Q33: L04_JV_016W_WINZE | R33: CABCAD 2 | S33: WASTEPASS, APPROVED ON 4/10/19-SDNC.ALREADY BREAKTHROUGH STOPPED ON APRIL 15, 2019 | W33: L04_RYV_010E_ROBBING | X33: NACARIO, JAIME | Y33: REPLACEMENT OF L04_CV_003W_ROBBING.APPROVED ON NOVEMBER 4, 2019.TRANSFER FROM MARTINEZ TO NACARIO ON NOV 29, 2019. STOPPED ON DEC 2, 2019 DUE TO UNSAFE CONDITION. | AD33: =+S15-'FINAL LIST WITH REMARKS'!L2375S33 -> #VALUE!
B34: L04_GHVFW_014E_STOPE PREP | C34: PARAGUYA 4 | D34: REPLACEMENT OF L04 GHVFW 014E RAISE. APPROVED ON JANUARY 31, 2019. MZC. STOPPED ON FEB 18, 2019. CONVERTED TO ACTIVE BREAKING. | E34: L04_CTV_018W_WINZE STOPE | F34: COMAINGKING 1 | G34: REPLACEMENT OF L04_CTV_018W_WINZE STOPE PREP. APPROVED ON SEPT 11, 2019. THERE'S ONLY 10 METER REMANING PILLAR BALANCE TO CONNECT W/ THE L04 MAINLINE ON OCT. 10, 2019. stopped on oct 18, 2019 convert to pull-out cleaning | H34: L04_NV_011W_STOPE | I34: MARTINEZ RON. 2 | J34: REPLACEMENT OF L04 NV 011E RAISE. APPROVED ON DECEMBER 15, 2018. ON WEST POSITION. CONVERTED TO BREAKING ON JANUARY 21, 2019. CONVERTED STOPE PULL-OUT JAN 28, 2019. DECLARED MINED-OUT MARCH 15, 2019. | K34: L04_GHVSPLIT_028W_DE | L34: BAÑEZ 5 | M34: REPLACEMENT OF L04_GHVSPLIT_028W_RAISE APPROAVED ON FEB.23,2021.STOPPED ON MAY 4, 2021. CONVERTED TO RAISE. | N34: L04_CTV_008W_RAISE | O34: NOCOS 8 | P34: REPLACEMENT OF L04_CTV_008W_DE. APPROVED ON FEBRUARY 17 2020. STOPPED ON MARCH 27 2020 UNSAFE CONDITION NO SOLID PILLAR REMAINING | Q34: L04_JV_020E_WINZE | R34: GEMENTIZA 1 | S34: FILL WINZE FOR WASTE PASS. APPROVED ON APRIL 8, 2019.RENAMED TO 20E FROM 17E ON 4/10/19-LTS. STOPPED ON APRIL 15, 2019 BECAUSE THIS WAS ALREADY BREAKTHROUGH. | W34: L04_GHVFW_008E_ROBBING | X34: COMAINGKING 4 | Y34: REPLACEMENT OF L04 GHVFW 007E DW. Approved on Oct 28, 2019. STOPPED ON DECEMBER 13, 2019 DUE TO CONSECUTIVE LOW ASSAY GRADES ON CUT SAMPLES/ BULK SAMPLES.
B35: L04_GHVFW_015E_STOPE PREP | C35: CABONITA 1 | D35: ADDITIONAL PRODUCTION. APPROVED ON MARCH 12, 2019. STOPPED ON APRIL 9, 2019. CONVERT TO BREAKING | E35: L04_JV_002E_WINZE STOPE | F35: OY-YOY 1 | G35: REPLACEMENT OF L04_JV_002E_WINZE STOPE PREP. APPROVED ON OCT 18, 2019. STOPPED ON NOV 11, 2019 DUE TO ALREADY FINISHED BREAKING AND HAS ALREADY REACHED THE DESIGN PILLAR. STOPPED BREAKING CONVERT TO PULL-OUT CLEANING ON NOV 18, 2019 | H35: L04_JV_042W_STOPE | I35: DUHIG 3 | J35: CONVERTED TO PULL-OUT ON 2/11/19.TEMP.STOP ON 4/10/19-LTS, FOR EVALUATION UNDERGROUND ONLY 78% PULL-OUT BUT ALREADY DECLARED MINED OUT. | K35: L04_CTV_025E_DW | L35: MARTINEZ DN 4 | M35: REPLACEMENT OF L04_CTV_025E_WINZE APPROAVED ON FEB.23,2021.STOPPED ON MARCH 11,2021 CONVERT TO STOPE PREPARATION. | N35: L04_JV_053W_RAISE | O35: SHEPHERD X 1 | P35: REPLACEMENT OF L04 JVSPLIT 058W RAISE. APPROVED ON APRIL 23, 2019. TEMP. STOPPED ON JUNE 20, 2019 BECAUSE THE GROUP WILL UNDERGO EXPLOSIVE SEMINAR AS PER DTAN. RESUMED OPERATION ON JUNE 26, 2019 AS THE GROUP FINISHED THEIR EXPLOSIVE SEMINAR.STOPPED ON JULY 4, 2019 DUE TO FAILURE AMIDST WIRE FRAMING & DESIGN. RESUMED ON JULY 5, 2019 TO PROCEED ON INCLINED RAISE @ EAST SIDE. STOPPED ON JULY 22, 2019 NOT PASS WIRE FRAMING (DILUTED GRADE @ 1.95.GPT) RESUMED ON FEB. 10 2020. STOPPED ON MARCH 10 2020 DUE TO CONSECUTIVE LOW ASSAY GRADES ON CUT SAMPLE. | Q35: L04_GHVFW_018E_WINZE | R35: OY-YOY 1 | S35: REPLACEMENT OF L04 CV 005W WINZE. APPROVED ON FEB 2, 2019. STOPPED ON MAY 8,2019 TO PROPOSE INTERMEDIATE SUBLEVEL. | W35: L04_JV_002E_ROBBING | X35: SHEPHERD Z | Y35: REPLACEMENT OF L04_JV_002E_WINZE STOPE APPROVED ON NOV 22, 2019. TEMPORARY STOP 12/8/19 by (WBO). Resumed on December 9 2019, In the same time Renamed from OY-YOY 1 to Shepherd Z. STOPPED ON DECEMBER 16, 2019 ALREADY REACED THE RECOMMENDED STRIKE LENGTH/CROWN PILLAR.
B36: L04_GHVFW_005E_WINZE STOPE PREP | C36: COMAINGKING 1 | D36: REPLACEMENT OF L04 GHVFW 007E DW. APPROVED ON MAY 17, 2019. MZC. CONVERT TO STOPE BREAKING ON JUNE 13, 2019. | E36: L04_CTV5_015E_WINZE STOPE | F36: BAKAKON 2 | G36: REPLACEMENT OF L04_CTV5_015E_WINZE STOPE PREP. APPROVED ON OCT 11, 2019. STOPPED ON NOV 11, 2019 ALREADY FINISHED THE DRIVING FILL RAISE AND THE SAME TIME CONVERT TO ACTIVE PULL-OUT | H36: L04_CV_011W_STOPE | I36: MARTINEZ RON. 1 | J36: REPLACEMENT OF L04 CV 011W STOPE PREP. APPROCED ON SEPT. 3, 2019.CONVERT TO PULL-OUT ON SEPT 13, 2019. STOPPED ON SEPT 15, 2019, ALREADY REACHED AGREED PULLOUT MINE CARS. | K36: L04_EDV_016W_DW | L36: BAÑEZ 4 | M36: REPLACEMENT OF L04_EDV_017W_DE, APPROVED ON FEB. 15 2021.STOPPED ON MARCH 13,2021 ALREADY BREAKTHROUGH | N36: L04_GHV_043W_RAISE | O36: MARTINEZ RON.2 | P36: ADDITIONAL INCLINED RAISE. APPROVED ON FEBRUARY 6, 2020. STOPPED ON MARCH 2 2020 DUE TO PINCHED OUT VEIN TO 0.05M | Q36: L04_GHV_045W_WINZE | R36: OY-YOY 1 | S36: ADDITIONAL,APPROVED ON MARCH 16,2016.STOPPED ON JULY 8,2016. RESUMED ON MAY 29, 2019 AT THE SAME TIME TRANSFERRED FROM ORIAS NELSON TO OY-YOY 1. STOPPED RECOMMENDS TO CONVERT THIS WORK HEADING INTO L04 JV 045W ISL DW ON JUNE 6, 2019. | W36: L04_GHV_029W_ROBBING | X36: MARTINEZ, RONALD | Y36: REPLACEMENT OF L04_NONE_028W_XCS APPROVED ON SEPT. 17, 2019. TEMP. STOPPED ON SEPT 18, 2019 UNDER REHAB. Resumed on sept. 30, 2019 to proceed in topslice. L04_GHV_029W_ROBBING TRANSFER FROM NACARIO TO MARTINEZ RONALD ON NOV 30, 2019. STOPPED ON JANUARY 13, 2020 DUE TO CONSECUTIVE LOW ASSAY GRADES ON CUT SAMPLES/ BULK SAMPLES./
B37: L04_GHVFW_017E_STOPE PREP | C37: CABONITA 1 | D37: REPLACEMENT OF L04 GHVFW 017E RAISE. APPROVED ON JUNE 8, 2019.RECOMMEND FOR ACTIVE BREAKING APPROVED ON JUNE 28, 2019. | E37: L04_CTV_018W_STOPE | F37: SHEPHERD AA2 | G37: REPLACEMENT OF L04_CTV_018W_STOPE PREP. APPROVED ON MARCH 20 2020. TEMP. STOPPED ON APRIL 9 DUE TO PANDEMIC. Permanent STOPPED ON SEPT. 30 2020. | H37: L04_JV_002E_WINZE STOPE | I37: OY-YOY 1 | J37: REPLACEMENT OF L04_JV_002E_WINZE STOPE PREP. APPROVED ON OCT 18, 2019. STOPPED ON NOV 11, 2019 DUE TO ALREADY FINISHED BREAKING ABD HAS ALREADY REACHED THE DESIGN PILLAR.STOPPED BREAKING CONVERT TO PULL-OUT CLEANING ON NOV 18, 2019 ALREADY REACHED 120% PULL-OUT. | K37: L04_EDV_022W_DW | L37: MARTINEZ DN 3 | M37: RENAME FROM L04 EDV 021W DW TO AVOID MISCHARGING. APPROVED ON FEB.11,2021.STOPPED ON MARCH 4, 2021 DUE TO LOW CONSECUTIVE LOW ASSAY GRADE. | N37: L04_JV_031E_RAISE | O37: SHEPHERD Z.2 | P37: ADDITIONAL INCLINED RAISE APPROVED ON NOV 14, 2019. STOPPED ON DEC 7, 2019 DUE TO CONSECUTIVE LOW ASSAY GRADES ON CUT SAMPLES/BULK SAMPLES. | Q37: L04_CTV5_016E_WINZE | R37: OY-YOY 1 | S37: REPLACEMENT OF L04 CTV5 17E DE, APPROVED ON 5/1/19-SDNC. TEMPORARY STOPPED ON MAY 25,2019 TO PRIORITIZE L04 GHVFW 018E DE. RESUMED ON JULY 12, 2019 AS PER SCS AND AT THE SAME TIME TRANSFER FROM CABCAD TO OY-YOY. STOPPED ON AUGUST 9, 2019 BECAUSE OF ITS PROXIMITY ABOUT PILLAR 20M BALANCE TO THE E15 SHAFT. | W37: L04_CTV_018W_ROBBING | X37: COMAINGKING 3 | Y37: REPLACEMENT OF L04_CTV_009W_RAISE. APPROVED ON DECEMBER 6, 2019. STOPPED ON JANUARY 24 2020 ALREADY FINISHED
B38: L04_CV_011W_STOPE PREP | C38: MARTINEZ RON. 1 | D38: REPLACEMENT OF L04_CV_011W_RAISE. APPROVED ON AUGUST 6, 2019. CONVERT TO ACTIVE BREAKING ON SEPT. 3, 2019. | E38: L04_GHVFW_015E_STOPE | F38: MANZANO | G38: REPLACEMENT OF L04 GHVFW 015E STOPE PREP. APPROVED ON APRIL 9, 2019-LOC.FROM GHVFW 017E RAISE 6TH FLR +10 METERS RECOMMENDED FOR IPR. STOPPED ON MAY 3,2019 DUE TO LOW GRADE NOT TO COMMENCE TO PULL-OUT/ RESUMED PULL OUT ON OCT. 20 2020 IN THE SAME TRANSFERRED FROM CABONITA TO MANZANO. | H38: L04_CTV_019W_STOPE | I38: MARTINEZ, RON 3 | J38: REPLACEMENT OF L04_CTV_019W_STOPE PREP.APPROVED ON APRIL 9, 2021.TRANSFER FROM SHEPHERD AL 1 TO MARTINEZ RON. APPROVED ON APRIL 16, 2021. CONVERTED TO PULL OUT CLEANING ON MAY 03, 2021.STOPPED ON MAY 10, 2021 MINED OUT. | K38: L04_CTV_027E_DW | L38: BAÑEZ | M38: ADDITIONAL DEVELOPMENT DRIVE. APPROVED ON NOV. 19 2020. RESUMED AND transfer from PMC MINERS 1TO BANEZ ON JAN 11 2021. stopped on january 18, 2021, recommended target length has been reached. | N38: L04_CTV_009W_RAISE | O38: COMAINGKING 3 | P38: REPLACEMENT OF L04 CTV 018W WINZE STOPE. APPROVED ON NOV. 30, 2019. INCLINED RAISE. STOPPED ON DEC 6 2019 DUE TO VEIN PINCHED OUT | Q38: L04_JV_029E_WINZE | R38: OY-YOY 1 | S38: REPLACEMENT OF L04_CTV5_015E_DE. APPROVED ON SEPT. 11, 2019. TEMP. STOPPED ON OCTOBER 10, 2019 DUE TO UNSAFE CONDITION. | W38: L04_JV_013W_ROBBING | X38: ANDILAB 1 | Y38: ADDITIONAL SOURCE OF GOOD ORE. APPROVED ON JULY 16, 2019. ON DECEMBER 12/17/ 2019 TRANSFERRED FROM MARTINEZ DN 1 TO ANDILAB GRACIANO. CONVERTED TO SILL PILLAR ON JANUARY 6, 2019. STOPPED ON FEB. 6, 2020 ALREADY REACHED THE RECOMMENDED STRIKE LENGTH FOR SILL.
B39: L04_JVHW_014E_WINZE STOPE PREP | C39: COMAINGKING 3 | D39: REPLACEMENT OF L04_JVHW_014E_DW. APPROVED ON MARCH 20 2020. STOPPED JULY 16, 2020 TO RELOCAT MANWAY FROM ADJACENT L04 JVFW 011E ROBBING MAINLINE DUE TO UNSAFE CONDITION. | E39: L04_GHVFW_041W_STOPE | F39: NOCOS 2 | G39: REPLACEMENT OF L04_GHVSPLIT_041W_STOPE PREP. APPROVED ON AUGUST 11 2020. Renamed from GHVSPLIT TO GHVFW ON SEPTEMBER 13,2020 AS PER MEMO OF LEVEL GEO. STOPPED BREAKING ON NOV. 30 2020 CONVERTED TO PULL OUT CLEANING | H39: L04_GHVFW_018E_WINZE STOPE | I39: SHEPHERD AL 1 | J39: REPLACEMENT OF L04_GHVFW_018E_WINZE STOPE PREP, APPROVED ON DEC 3 2020.TEMP. STOPPED ON MARCH 7, 2021 DUE TO MANPOWER PROBLEM.resumed on MArch 30, 2021 and transferred from Davacol Rowel 1 to Shepherd AL.STOPPED ON MAY 3, 2021 CONVERTED TO STOPE PULL-OUT.STOPPED ON MAY 17, 2021 ALREADY MINED OUT. | K39: L04_EDV_022W_DW | L39: BAÑEZ 4 | M39: REPLACEMENT OF L04 NONE 022W XCN. APPROVED ON NOV 11 2020 Stopped on Nov. 23 2020 due to consecutive low assay grades on cut samples / bulk sample. | N39: L04_CTV5_014E_RAISE | O39: BAKAKON 2 | P39: ADDITIONAL VERTICAL DEVELOPMENT. APPROVED ON OCTOBER 3, 2019. STOPPED ON OCT. 11 2019, NOT ABLE TO CONTINUE DUE TO WINZE STOPE CONDITION. | Q39: L04_JV_014E_WINZE | R39: COMAINGKING 2 | S39: REPLACEMENT OF L04 RYV 012E WINZE. APPROVED ON MARCH 16, 2019. FOR EVALUATION DUE TO LACKING OF LADDER FOR ABOUT 6 METERS.TRANSFER ON JANUARY 24 2020 FROM OY-YOY 2 TO COMAINGKING. STOPPED ON 5/30/19-LOC, CONSECUTIVE LOW GRADE RESULTS. | W39: L04_CTV5_014E_ROBBING | X39: BAKAKON 2 | Y39: REPLACEMENT OF L04_CTV5_015E_WINZE_STOPE ON NOV 26, 2019. STOPPED ON DECEMBER 13, 2019 DUE TO ALREADY REACHED THE RECOMMENDED STRIKE LENGTH/CROWN PILLAR.
B40: L04_JV_030E_WINZE STOPE PREP | C40: MARTINEZ DN 2 | D40: REPLACEMENT OF L04_JV_030E_ROBBING APPROVED ON 8/19/21. STOPPED ON SEPTEMBER 7, 2021 CONVERTED TO BREAKING. | E40: L04_CTV_019W_STOPE | F40: MARTINEZ, RON 3 | G40: REPLACEMENT OF L04_CTV_019W_STOPE PREP.APPROVED ON APRIL 9, 2021.TRANSFER FROM SHEPHERD AL 1 TO MARTINEZ RON. APPROVED ON APRIL 16, 2021. STOPPED AND CONVERTED TO PULL OUT CLEANING ON MAY 03, 2021 | H40: L04_GHVSPLIT_027W_STOPE | I40: BAÑEZ 8 | J40: REPLACEMENT OF L04_GHVSPLIT_027W_STOPE PREP.APPROVED ON MAY 4, 2021.recommended to continue breaking only 6m strike length form east side manway and leave the remaining length as pillar.STOPPED BREAKING ON 18/8/21 CONVERTED TO PULL-OU AT THE SAME DATE.STOPPED ON SEPTEMBER 7,2021 MINED OUT | K40: L04_RYV_003E_DE | L40: MANZANO 2 | M40: ADDITIONAL HORIZONTAL DEVELOPMENT. APPROVED ON NOV. 5 2020.TEMPORARY STOPPED ON NOV. 17 2020 | N40: L04_CV_008W_RAISE | O40: LERIO 5 | P40: REPLACEMENT OF L04_CV_009W_DE.APPROVED ON AUGUST 7, 2019. STOPPED ON AUGUST 14, 2019 DUE TO CONSECUTIVE LOW ASSAY GRADE AND PINCHED OUT VEIN. | Q40: L04_CV_001E_WINZE | R40: MARTINEZ RON. 1 | S40: REPLACEMENT OF L04 CV 001E ROBBING. APPROVED ON JULY 24, 2020. Temporary stopped on August 18 2020 due to no airhoist / electric hoist vailable. Resumed on August 21 2020. STOPPED ON AUGUST 28 2020 DUE TO PINCHED OUT VEIN. | W40: L04_CTV_033W_ROBBING | X40: SHEPHERD AA1 | Y40: REPLACEMENT OF L04 JV 012W RAISE. APPROVED ON JUNE 5,2019. TRANSFERRED ON DECEMBER 17, 2019 FROM MARTINEZ DN 2 TO BAKAKON. TRANSFERRED ON JANUARY 24 2020 FROM BAKAKON 1 TO SHEPHERD AA1. STOPPED ON MARCH 5 2020 DUE TO UNSAFE CONDITION.
B41: L04_CV_025W_STOPE PREP | C41: SHEPHERD AR | D41: Replacement of L04_CV_022W_DW. Approved on August 30, 2021.TRANSFER FROM BAÑEZ TO SHEPHERD AR ON SEPT.20,2021. STOPPED ON SEPTEMBER 25, 2021. | E41: L04_CTV_008E_STOPE | F41: MARTINEZ, RON 3 | G41: REPLACEMENT OF L04_CTV_008E_STOPE.APPROVED ON JULY 14, 2021. STOPPED ON SEPTEMBER 8, 2021. CONVERT TO PULL OUT CLEANING. | H41: L04_JVFW_010E_STOPE | I41: COMAINGKING 2 | J41: CONVERTED TO PULL OUT ON DECEMBER 2, 2021 STOPPED AND MINED-OUT ON DEC. 2, 2021 WITH 156% PULL-OUT. | K41: L04_JV_058W_DW | L41: MARTINEZ RONALD | M41: REPLACEMENT OF L04_JV_055W_DE, APPROVED ON APRIL 8, 2020. TEMP. STOPPED ON APRIL 9 DUE TO PANDEMIC. RESUMED ON OCT 13 2020. stopped on NOV. 16 25020. TO PRIORITY HEADINGS. | N41: L04_JV_023E_RAISE | O41: CABONITA 3 | P41: REPLACEMENT OF L04_GHV_010W_ROBBING APPROVED ON JULY 30, 2019.SDNC.STOPPED ON AUGUST 14, 2019 DUE TO ALREADY PINCHED OUT VEIN. | Q41: L04_JV_012W_WINZE | R41: ANDILAB 1 | S41: REPLACEMENT OF L04_JV_011E_ROBBING. APPROVED ON JULY 28 2020. Stopped on Sept. 12 2020 due to off vein.resumed on September 14,2020 as per Level Geologist. STOPPED ON SEPT. 29 2020 DUE TO VEIN PINCHED OUT. | W41: L04_JV_019W_ROBBING | X41: ANDILAB 1 | Y41: REPLACEMENT OF L04_JV_013W_ROBBING. APPROVED ON FEB. 20, 2020. STOPPED ON MARCH 9 2020 DUE TO CONSECUTIVE LOW ASSAY GRADE ON CUT SAMPLESS.
B42: L04_GHVSPLIT_029W_STOPE PREP | C42: SHEPHERD AQ | D42: REPLACEMENT OF L04_GHVSPLIT_026W_STOPE PREP. APPROVED ON SEPT. 13, 2021. STOPPED ON OCTOBER 4, 2021. CONVERT TO BREAKING. | E42: L04_CV_025W_STOPE | F42: SHEPHERD AR | G42: REPLACEMENT OF L04_CV_025W_STOPE PREP. APPROVED ON SEPTEMBER 25, 2021. STOPPED BREAKING AND CONVERT TO PULL-OUT STAGE ON NOVEMBER 6, 2021. | H42: L04_GHVFW_019E_WINZE STOPE | I42: SHEPHERD AL 1 | J42: REPLACEMENT OF L04_GHVFW_019E_WINZE STOPE PREP ON 8/18/21. STOPPED BREAKING ON JAN 6, 2022, NOT TRAVERSED DUE TO UNSAFE CONDITION, WITH MEMO ACKNOWLEDGED BY SAFETY, FOR PULL OUT CLEANING.MINED OUT FEB.14,2022 | K42: L04_JVSPLIT_054W_DE | L42: PMC MINERS 1 | M42: ADDITIONAL HORIZONTAL DEVELOPMENT. APPROVED ON SEPT. 24 2020. STOPPED ON OCT 15 2020 PER GEO | N42: L04_GHVFW_017E_RAISE | O42: CABONITA 1 | P42: REPLACEMENT OF L04 JV 027W STOPE. APPROVED ON DECEMBER 7,2018. TEMP STOPPED AND TRANSFER TO TAÑEZA 6 FROM PARAGUYA 1 DUE TO GOOD PERFORMANCE OF FORMER TEAM LEADER APPROVED ON MARCH 11,2019. RESUMED ON MAY 12, 2019 AND TRANSFER FROM TANEZA 6 TO CABONITA 1. STOPPED DUE TO A FAULT STRUCTURE TRANSECTING THE MOST RECENT FACE CAUSING THE VEIN TO BE DISPLACED ON JUNE 7, 2019 | Q42: L04_JV_030E_WINZE | R42: MARTINEZ DN 2 | S42: REPLACEMENT OF L04_CTV_010E_DE. APPROVED ON MAY 19,2021.SAFETY CONCER/UNSAFE CONDITION.STOPPED ON JULY 1, 2021. | W42: L04_GHV_045W_ROBBING | X42: MARTINEZ DN 4 | Y42: REPLACEMENT OF L04_GHV_042W_DW APPROVED ON NOV 12, 2019. TRANSFERRED ON DECEMBER 17, 2019 FROM BAKAKON TO MARTINEZ DANNY DUE TO ABSENTEEISM OF MEN. STOPPED ON MARCH 21 2020 ALREADY REACHED THE ALREADY REACHED THE RECOMMENDED STRIKE LENGTH/CROWN PILLAR.
B43: L04_CV_006E_STOPE PREP | C43: MARTINEZ, RON 3 | D43: REPLACEMENT OF L04_CV_006E_DE . APPROVED ON MAY 23 2022.STOPPED ON JUNE 22 2022. | E43: L04_CTV_021W_STOPE | F43: NOCOS 2 | G43: REPLACEMENT OF L04_CTV_021W_ROBBING APPROVED ON JULY 8,2021.stopped on oct.19 ,2021 unsafe.RESUME ON OCT.20, 2021.stopped on nov. 15,2021 converted to pull-out cleaning | H43: L04_CTV_023W_WINZE STOPE | I43: CAYMAN 3 | J43: PULL-OUT ON APRIL 24, 2023 AND TRAVERSED ON THE SAME DAY.ALREADY DONE STOPE PULL OUT CLEANING ON MAY 3, 2023. | K43: L04_EDV_015W_DW | L43: BAÑEZ 4 | M43: ADDITIONAL HORIZONTAL DEVELOPMENT. APPROVED ON APRIL 7 2020. TEMP. STOPPED ON APRIL 9 DUE TO PANDEMIC. Resumed on August 12 2020 In the same time transferred from Shepherd AF.3 to Bañez 4. stopped on Oct 14 2020 consecutive low assay grade | N43: L04_CV_011W_RAISE | O43: MARTINEZ RON. 1 | P43: ACCESS FOR OLD MUCK IN CV 12W ROBBING. APPROVED ON MARCH 1, 2019. STOPPED ON APRIL 11,2019 ALREADY FINISHED. | Q43: L04_JV_013W_WINZE | R43: COMAINGKING | S43: REPLACEMENT OF L04 JV 014E ROBBING. APPROVED ON SEPTEMBER 15, 2021. STOPPED ON 10/08/21 MADE A BREAKTHROUGH. | W43: L04_CTV_008W_ROBBING | X43: NOCOS 3 | Y43: REPLACEMENT OF L04_CTV_008W_ROBBING. APPROVED ON MARCH 31 2020. TEMP. STOPPED ON APRIL 9 DUE TO PANDEMIC.
B44: L04_CTV_010W_WINZE STOPE PREP | C44: MARTINEZ, DN 3 | D44: REPLACEMENT OF L04_CTV_010W_DW_ISL. APPROVED ON NOVEMBER 14, 2023.STOPPED ON NOVEMBER 28, 2023. CONVERT TO STOPE BREAKING. | E44: L04_GHVFW_019E_WINZE STOPE | F44: SHEPHERD AL 1 | G44: REPLACEMENT OF L04_GHVFW_019E_WINZE STOPE PREP ON 8/18/21. STOPPED BREAKING ON JAN 6, 2022, NOT TRAVERSED DUE TO UNSAFE CONDITION, WITH MEMO ACKNOWLEDGED BY SAFETY, FOR PULL OUT CLEANING. | H44: L04_GHVFW_010E_WINZE STOPE | I44: MARTINEZ DN 1 | J44: REPLACEMENT OF L04_GHVFW_010E_WINZE STOPE PREP. APPROVED ON SEPTEMBER 1, 2022.CONDUCTED FILL RAISE ON OCTOBER 19, 2022. STOPPED BREAKING AND CONVERT TO PULL-OUT ON NOV. 5, 2022. TRAVERSED ON NOVEMBER 4, 2022.STOPPED ON NOVERMBER 22, 2022 MINED OUT @ 94% | K44: L04_JV_056W_DW | L44: MARTINEZ DN 3 | M44: REPLACEMENT OF L04_NONE_056W_XCS, APPROVED ON APRIL 5, 2020. TEMP. STOPPED ON APRIL 9 DUE TO PANDEMIC. | N44: L04_JVSPLIT_011W_RAISE | O44: PARAGUYA 1 | P44: ADDITIONAL VERTICAL DEVELOPMENT. APPROVED ON JANUARY 11, 2019. MZC. STOPPED ON JANUARY 19, 2019 ALREADY FINISHED FILL RAISE. | Q44: L04_EDV_018W_WINZE | R44: ANDILAB 1 | S44: REPLACEMENT OF L04_JV_012W_ROBBING. APPROVED ON OCT 11, 2021. TEMP STOPPED ON NOV. 16, 2021. RESUMED ON NOVEMBER 22,2021. STOPPED ON DECEMBER 1, 2021. | W44: L04_NONE_027W_XCS | X44: DAGAMAC 6 | Y44: SPECIAL PROJECT FOR VENTILATION PURPOSES ON JUNE 4, 2019. STOPPED ON JULY 15, 2019 ALREADY ATTAINED BASED ON THE PLAN. RESUMED ON OCT. 21, 2019
B45: L04_CTV_021W_WINZE STOPE PREP | C45: MARTINEZ, DN 5 | D45: REPLACEMENT OF L04_CTV_023W_DW_ISL APPROVED ON NOVEMBER 7, 2023.TEMPORARILY STOPPED ON NOVEMBER 11, 2023 FOR SAFETY EVALUATION. RESUMED ON NOVEMBER 13, 2023, AFTER FURTHER SAFETY EVALUATION.STOPPED ON NOVEMBER 29, 2023. CONVERT TO STOPE BREAKING. | E45: L04_CV_006E_STOPE | F45: MARTINEZ, RON 3 | G45: REPLACEMENT OF L04_CV_006E_STOPE PREP. APPROVED ON JUNE 22, 2022.STOPPED ON AUGUST 24, 2022 AT THE SAME TIME CONVERTED TO PULLOUT CLEANING. | H45: L04_CV_006E_WINZE STOPE | I45: MARTINEZ, DN 4 | J45: REPLACEMENT OF L04_CV_006E_DW_ISL. APPROVED ON MAY 05, 2023.ALREADY DONE STOPE PREP ON MAY 20, 2023. CONVERT TO STOPE BREAKING.REPLACEMENT OF L04_CV_006E_WINZE_STOPE PREP, APPROVED ON MAY 20, 2023.TEMPORARY STOPPED ON JUNE 8, 2023 DUE TO THE UNAVAILABIILITY OF AGSAO SHAFT.RESUMED ON OCTOBER 02, 2023. AS WELL AS CHANGED TEAM LEADER FROM MARTINEZ, RON 1 TO MARTINEZ, DN 4.STOPPED BREAKING ON NOVEMBER 09, 2023. AS WELL AS TRAVERSED ON NOVEMBER 10, 2023, 2ND SHIFT. CONVERT TO PULL-OUT CLEANING.TEMPORARILY STOPPED ON NOVEMBER 11, 2023 FOR SAFETY EVALUATION.RESUMED ON NOVEMBER 13, 2023, AFTER FURTHER SAFETY EVALUATION.STOPPED ON NOVEMBER 22, 2023. ALREADY MINED OUT. | K45: L04_JV_055W_DE | L45: COMAINGKING 5 | M45: ADDITIONAL HORIZONTAL DEVELOPMENT. APPROVED ON MARCH 16 2020. RENAMED ON MARCH 21 2020 FROM L04_JV_005W_DE TO L04_JV_055W_DE. STOPPED ON APRIL 8 2020 DUE TO CONSECUTIVE LOW ASSAY GRADE ON CUT SAMPLE/ BULK SAMPLE. | N45: L04_NV_012W_RAISE | O45: MARTINEZ RON. 1 | P45: ADDITIONAL VERTICAL DEVELOPMENT. APPROVED ON DECEMBER 4, 2018. MZC. STOPPED ON JANUARY 29, 2019 ALREADY BREAKTHROUGH TO OLD STOPE. | Q45: L04_CTV_022W_WINZE | R45: COMAINGKING | S45: REPLACEMENT OF L04_JV_013W_WINZE. APPROVED ON OCT 13, 2021. TEMPORARY STOPPED ON 11/15/21. RESUMED ON NOV. 17, 2021. GROUP FORM L04 GHV 057W ROBBING WILL BE MERGED TO L04 CTV 022W WINZE. STOPPED ON JANUARY 25, 2022 RECOMMENDED FOR SUB LEVEL. RESUMED ON FEB 24, 2022 AS FILL WINZE . STOPPED ON FEBRUARY 28, 2022, FINISHED FILL WINZE. | W45: L04_JVFW_011E_ROBBING | X45: MARTINEZ DN 3 | Y45: REPLACEMENT OF L04 JV 005W ROBBING. APPROVED ON MARCH 6,2020. CONVERT TO SILL PILLAR ON MARCH 27, 2020. TEMPORARY STOPPED ON MARCH 31 2020 WAITING FOR CROWN PILLAR ROBBING TO BE FILLED WITH WASTE PRIOR TO SILL PILLAR ROB. RESUMED ON APRIL 3, 2020. RESUMED ON JULY 3, 2020. TEMPORARY STOPPED ON JULY 18 2020 DUE TO UNSAFE CONDITION
... B47: L03_CTV_025W_STOPE PREP | C47: FERNANDEZ, RM 5 | D47: ADDITIONAL SOURCE OF GOOD ORE. APPROVED ON AUGUST 20, 2024. STOPPED ON SEPTEMBER 17, 2024. AT THE SAME TIME CONVERT TO STOPE BREAKING. | E47: L03_CTV_025W_STOPE | F47: FERNANDEZ, RM 5 | G47: REPLACEMENT OF L03_CTV_025W_STOPE PREP. APPROVED ON SEPTEMBER 17, 2024. STOPPED BREAKING ON OCTOBER 26, 2024 DUE TO PINCHED OUT VEIN/LOW ASSAY GRADE RESULT TO ITS IPR. CONVERTED TO STOPE PULL-OUT CLEANING. | H47: L04_CTV_021W_WINZE STOPE | I47: MARTINEZ, DN 5 | J47: REPLACEMENT OF L04_CTV_021W_WINZE STOPE PREP. APPROVED ON NOVEMBER 29, 2023.STOPPED BREAKING ON FEBRUARY 10, 2024. CONVERT TO PULL-OUT CLEANING.STOPPED ON FEBRUARY 26, 2024. ALREADY MINED OUT. | K47: L04_CTV_011W_DW | L47: NOCOS 1 | M47: REPLACEMENT OF L04_CTV_011W_ROBBING APPROVED ON NOV 15, 2019. TEMPORARY STOPPED ON FEBRUARY 4 2020 DUE TO UNSERVICEABLE AREA. RESUMED ON FEB, 21 2020. STOPPED ON MARCH 26 2020 DUE TO LOW ASSAY GRADE ON CUT SAMPLE/BULK SAMPLE. | N47: L04_JV_002E_RAISE | O47: CABONITA 1 | P47: REPLACEMENT OF L04 JV 002E DW. APPROVED ON SEPT 1, 2018. STOPPED OCTOBER 12,2018. RESUMED ON JANUARY 16, 2019. STOPPED ON FEB 7, 2019 DUE TO OFF-VEIN. | Q47: L04_CV_025W_WINZE | R47: NOCOS 2 | S47: REPLACEMENT OF L04_JVFW_010E_STOPE. APPROVED ON DEC. 3, 2021.TEMP. TEMPORARY STOPPED ON JANUARY 10,2022 MEMO RECEIVED ON JANUARY 18,2022 DUE TO LACK OF MANPOWER.RESUMED ON FEB 21, 2022 AND TRANSFERRED FROM COMAINGKING 2 TO NOCOS 2.TEMP. STOPPED ON MARCH 10, 2022 INSUFFICIENT MAN POWER. RESUMED ON MARCH 15 2022.STOPPED ON MAY 3, 2022, HAS 4 METERS REMAINING DISTANCE TO CONNECT TO OLD STOPE OF LEVEL 5. | W47: L04_NONE_030E_XCS | X47: PMC MINERS 2 | Y47: FOR VENTILATION PURPOSES. APPROVED ON APRIL 7 2020. stopped on april 15 2020.
H48: L03_CTV_025W_STOPE | I48: FERNANDEZ, RM 5 | J48: REPLACEMENT OF L03_CTV_025W_STOPE PREP. APPROVED ON SEPTEMBER 17, 2024. STOPPED BREAKING ON OCTOBER 26, 2024 DUE TO PINCHED OUT VEIN/LOW ASSAY GRADE RESULT TO ITS IPR. CONVERTED TO STOPE PULL-OUT CLEANING. STOPPED ON NOVEMBER 08, 2024. DUE TO CONSECUTIVE LOW ASSAY GRADE. | K48: L04_GHV_028W_DW | L48: MARTINEZ, RONALD | M48: REPLACEMENT OF L04_NONE_028W_XCS. APPROVED ON JANUARY 30 2020. STOPPED ON MARCH 10 2020 DUE TO CONSECUTIVE LOW ASSAY GRADE ON CUT SAMPLES/ BULK SAMPLES. | N48: L04_CV_008W_RAISE | O48: MARTINEZ RON. 1 | P48: REPLACEMENT OF L04 CV 008W DE ON AUGUST 1, 2018/LTS.STOPPE ON AUGUST 28, 2018. RESUMED ON OCTOBER 18,2018 TO CONTINUE ADVANCE UNTIL IT BREAKTHROUGH AT L03 AS PER RDPARONDA.STOPPED DUE TO UNSAFE CONDITION ON OCTOBER 19, 2018 | Q48: L04_GHVFW_008W_WINZE | R48: SHEPHERD AR 1 | S48: REPLACEMENT OF L04_EDV_018W_DE_ISL. APPROVED ON APRIL 6 2022.STOPPED ON JUNE 9, 2022 DUE TO CONSECUTIVE LOW ASSAY GRADES ON CUT SAMPLES/BULK SAMPLE. | W48: L04_CTV_026E_ROBBING | X48: MARTINEZ DN 4 | Y48: REPLACEMENT OF L04_CTVSPLIT_026E_ROBBING. APPROVED ON AUGUST 10 2020. Start Robbing on August 18 2020.STOPPED ON AUGUST 26,2020.DUE TO POOR VIEN MENERALIZATION.
K49: L04_JVHW_014E_DE | L49: COMAINGKING 3 | M49: REPLACEMENT OF L04 JVFW_14E_WINZE.APPROVED ON MAY 31, 2019/ TEMP. STOPPED ON JUNE 17, 2019 DUE TO LACK OF MANPOWER. RESUMED ON FEBRUARY 4, 2020 AS WELL AS TRANSFER FROM OY-YOY 2 TO COMAINGKING 3. STOPPED ON MARCH 6 2020 DUE TO PINCHED OUT VEIN. | N49: L04_RYV_010E_RAISE | O49: MARTINEZ DN 3 | P49: REPLACEMENT OF L04 RYV 010E DW. APPROVED ON JANUARY 19, 2019. MZC. DRIVING INCLINED RAISE TOWARDS WEST ON FEB 25, 2019. STOPPED ON MARCH 14, 2019 DUE TO PINCHED OUT OF VEIN. | Q49: L03_RYV_007W_WINZE | R49: FERNANDEZ, RM 5 | S49: ADDITIONAL VERTICAL DEVELOPMENT APPROVED ON JANUARY 20, 2023.STOPPED ON FEBRUARY 23, 2023 DUE TO CONSECUTIVE LOW GRADE ON BULK SAMPLES. | W49: L04_GHV_051W_ROBBING | X49: BENONGUIL 3 | Y49: ADDITIONAL SOURCE OF GOOD ORE. APPROVED ON JULY 22, 2020 AND STILL ON-GOING CLEANING. Start robbing Sill on August 20 2020. Stopped on Sept 18,2020 already mined out.
K50: L04_JV_054W_DW | L50: SHEPHERD X 2 | M50: REPLACEMENT OF L04 JVSPLIT 058W RAISE. APPROVED ON MARCH 28, 2019/ STOPPED ON MAY 29, 2019 DUE TO CONSECUTIVE LOW GRADE CUT SAMPLES | N50: L04_JV_049W_RAISE | O50: SHEPHERD X 1 | P50: REPLACEMENT OF L04 JV 051W RAISE. APPROVED ON NOV 20, 2018. TEMP. STOPPED ON DECEMBER 10, 2018 AS PER WANCOG. RESUMED ON JANUARY 16, 2019 TO TARGET LOW DIPPING VEIN. TEMP STOPPED AND TRANSFER TO TAÑEZA 8 FROM DUHIG 3 DUE TO GOOD PERFORMANCE OF FORMER TEAM LEADER APPROVED ON MARCH 11,2019. RESUMED ON MARCH 13, 2019 AND TRANSFER FROM TANEZA 8 TO SHEPHERD X 1 (CAPUYAN).STOPPED ON APRIL 7, 2019 ALREADY REACHED THE RECOMMENDED STRIKE LENGTH. | W50: L04_GHV_057W_ROBBING | X50: BAÑEZ 5 | Y50: ADDITIONAL GOOD SOURCE OF GOOD ORE. APPROVED ON SEPTEMBER 07,2020.RENAMED ON SEPT. 22 2020 FROM L04_JV_057W_ROBBING TO L04_GHV_057W_ROBBING. TEMPORARY STOPPED TO PRIORIZE RAISE ON SEPT. 24 2020.
K51: L04_CTV5_017E_DE | L51: CABCAD 1 | M51: REPLACEMENT OF L04 JV 034E DE. APPROVED ON SEPTEMBER 26,2018. TEMPORARY STOPPED ON DECEMBER 6,2018 TO PRIORITIZED ACTIVE STOPE PREP. RESUMED ON JANUARY 28, 2019. TEMP. STOPPED ON FEB. 7, 2019 DUE TO ABSENTEEISM OF MEN RESULTING TO ABANDONMENT OF WP. RESUMED ON FEB 21, 2019; AS PER MEMO BY SCS. TEMPORARY STOPPED ON 3/6/19 DUE TO LACK OF MANPOWER. RESUMED ON APRIL 15, 2019. STOPPED ON APRIL 30, 2019 BECAUSE THIS WAS CUT BY FAULT. | N51: L04_JV_058W_RAISE | O51: SHEPHERD X 2 | P51: ADDITIONAL VERTICAL DEVELOPMENT. APPROVED ON 2/14/19. TRANSFER FROM DUHIG TO SHEPHERD X 2 (CAPUYAN) STARTING ON MARCH 13, 2019.STOP ON APR 4, 2019-LTS. | W51: L04_CV_001E_ROBBING | X51: MARTINEZ RON. 1 | Y51: REPLACEMENT OF L04_JV_053W_RAISE. APPROVED ON MARCH 26 2020. RESUMED ON JULY 11, 2020 FOR CLEANING. START ROBBING ON JULY 14, 2020. STOPPED ON JULY 23, 2020 TO DRIVE WINZE. RESUMED ON SEPT. 2 2020. Stopped on Sept 26, 2020 already done beraking pillars.
K52: L04_RYV_007W_DW | L52: ANDILAB 1 | M52: REPLACEMENT OF L04 NONE 007W XCS.APPROVED ON OCTOBER 24, 2018. STOPPED ON JAN 8. 2019 DUE TO CONSECUTIVE LOW ASSAY GRADE. | N52: L04_NV_020W_RAISE | O52: ANDILAB 1 | P52: REPLACEMENT OF L04 NV 017W DW, APPROVED ON 5/3/19-SDNC.STOPPED ON JUNE 13, 2019 DUE TO CONSECTUVIE LOW ASSAY GRADE. | W52: L04_JV_055W_ROBBING | X52: MARTINEZ, RONALD | Y52: REPLACEMENT OF L04_NONE_025W_XCN. APPROVED ON SEPT. 8 2020. stopped on OCT 12 2020 ALREADY REACHED THE RECOMMENDED STRIKE LENGTH / CROWN PILLAR
K53: L04_JV_049W_DW | L53: DUHIG 3 | M53: REPLACEMENT OF L04 JV 049W RAISE. APPROVED ON DECEMBER 10, 2018. STOPPED ON JANUARY 11, 2019 ALREADY REACHED THE DESIRED STRIKE LENGTH. | N53: L04_GHVFW_024E_RAISE | O53: LERIO 5 | P53: REPLACEMENT OF L04 JV 22W DE, APPROVED ON MAR 5, 2018 AS PER LTS. STOPPED DUE TO LEVEL GEO MEMO ON APRIL 20, 2018. REPLACEMENT OF L04 GHVDW 015E DE ON MAY 30, 2019. STOPPED ON JUNE 10, 2019 DUE TO PINCHED OUT OF VEIN AFTER 2 BLASTS. | W53: L04_CV_013W_ROBBING | X53: MARTINEZ RONALD | Y53: REPLACEMENT OF L04 JV 058W DW. APPROVED ON NOVEMBER 17 2020. STARTED MAINLINECLEANING ON NOV. 28 2020. CONVERTED TO CROWN ON NOV 26 2020. Stopped on Dec 1 2020.
K54: L04_JVSPLIT_012W_DE | L54: MARTINEZ DN 1 | M54: REPLACEMENT OF L04_RYV_011E_DE. APPROVED ON FEB. 6, 2019. STOPPED ON FEB 25, 2019 ALREADY BREAKTHROUGH. | N54: L04_CV_009W_RAISE | O54: MARTINEZ DN 1 | P54: REPLACEMENT OF L04 CV 008W DE. APPROVED ON JUNE 10, 2019.STOPPED DUE TO PINCHED OUT VIEN ON JULY 3, 2019 | W54: L04_JV_056W_ROBBING | X54: MARTINEZ, RON.2 | Y54: REPLACEMENT OF L04_JV_056W_RAISE. APPROVED ON SEPT. 16 2020. ON NOVEMBER 9 2020 STOPPED CROWN & CONVERTED TO SILL PILLAR. MINED OUT JAN 07 2021
K55: L04_JV_003E_DE | L55: CABONITA 1 | M55: REPLACEMENT OF L04 NONE 6W XCN. APPROVED ON JUNE 16, 2018.RENAMED FROM EDV 9W TO NV 9W ON JULY 5, 2018/LTS.TEMPORARY STOPPED DUE TO LACK OF MANPOWER.APPROVED ON SEPTEMBER 18, 2018. TEMPORARY STOPPED ON OCTOBER 10,2018 TO PRIORITIZE L04 NONE 002E XCN. RESUMED ON NOVEMBER 17, 2018.TEMPORARY STOPPED DUE TO INSUFFICIENT MANPOWER ON FEBRUARY 5, 2019. RESUMED ON FEBRUARY 20,2019 AND AT THE SAME TIME TRANSFER FROM ASIS 1 TO CABONITA 1. STOPPED ON MARCH 12, 2019 DUE TO PINCHED OUT OF VEIN. | N55: L04_GHVFW_019E_RAISE | O55: LERIO 5 | P55: REPLACEMENT OF L04 JV 010W STOPE. APPROVED ON FEB. 5, 2019. MZC. TEMPORARY STOPPED ON MARCH 1, 2019. DUE TO CONSECUTIVE LOW ASSAY GRADE. RESUMED ON 6/10/2019 TO CONDUCT INCLINED RAISE FOR EXPLORATORY PURPOSES AND TRANSFER FROM CABONITA 1 TO LERIO 5. STOPPED ON JULY 13, 2019 OFF VEIN. | W55: L04_CTV_025E_ROBBING | X55: MARTINEZ DN 4 | Y55: ADDITIONAL SOURCE OF GOOD ORE. APPROVED ON AUGUST 26 2020. MINED OUT JAN 7, 2021
K56: L04_GHVSPLIT_055W_DW | L56: DUHIG 1 | M56: REPLACEMENT OF L04 NONE 055W XCS. APPROVED ON MARCH 27, 2019.STOP ON 4/9/19-SDNC, PINCHED-OUT VEIN. | N56: L04_CV_011W_RAISE | O56: MARTINEZ DN 1 | P56: REPLACEMENT OF L04_CV_009W_RAISE APPROVED ON JULY 4, 2019.STOPPED ON JULY 11, 2019 ALREADY BREAK THRU. | W56: L04_CTV_019W_ROBBING | X56: SHEPHERD W | Y56: REPLACEMENT OF L04_CTV_019W_DE. Sept. 30 2020 -TOPSLICE CONVERTED TO SILL ON NOV. 28 2020. Stopped due to poor vein mineralization
K57: L04_GHVFW_007E_DE | L57: COMAINGKING 1 | M57: REPLACEMENT OF L04 GHVFW 006E WINZE. APPROVED ON NOV 6, 2018. TRANSFER TO COMAINGKING FROM OY-YOY ON 2/5/19. RENAMED FROM L04 GHVFW 006E DE TO L04 GHVFW 007E DE TO AVOID MISCHARGING. TEMP. STOPPED ON MARCH 20, 2019 TO PRIORITIZE L04 GHVFW 008E WINZE STOPE PREP. RESUMED ON MARCH 29, 2019.STOP ON 4/10/19-LTS, TO PRIORITIZE 7E DW. | N57: L04_JV_016W_RAISE | O57: SHEPHERD X2 | P57: REPLACEMENT OF L04 JVSPLIT 053W RAISE. APPROVED ON MAY 30, 2019.TEMPORARY STOPPED ON JUNE 3, 2019 ON-GOING ML CLEANING. RESUME ON JUNE 13, 2019. STOPPED INCLINED RAISE ON JULY 14, 2019. | W57: L04_CTVSPLIT_010E_ROBBING | X57: MARTINEZ DN 3 | Y57: ADDITIONAL SOURCE OF GOOD ORE. APPROVED ON AUGUST 28 2020. Stopped sill on Nov 26 2020 change heading from sill to crown. Stopped on Jan 14, 2021 reached the mining length for crown pillar
K58: L04_CV_008W_DE | L58: MARTINEZ DN 1 | M58: ADDITIONAL HORIZONTAL DEVELOPMENT. APPROVED ON MARCH 21, 2019.STOPPED ON APRIL 23, 2019 ALREADY BREAKTHROUGH. | N58: L04_CTV_016W_RAISE | O58: SHEPHERD X2 | P58: REPLACEMENT OF L04_CTV_016W_STOPE. APPROVED ON JANUARY 15, 2020. STOPPED ON FEB. 12 2020 DUE TO VEIN PINCHED OUT. | W58: L04_GHV_045W_ROBBING | X58: MARTINEZ RONALD | Y58: ADDITIONAL SOURCE OF GOOD ORE. APPROVED ON DEC. 8 2020. Mined out Jan 15, 2020
K59: L04_GHVFW_013E_DW | L59: LERIO 6 | M59: ADDITIONAL HORIZONTAL DEVELOPMENT. APPROVED ON 3/6/19. TRANSFER TO TAÑEZA 10 FROM PARAGUYA 4 DUE TO GOOD PERFORMANCE OF FORMER TEAM LEADER APPROVED ON MARCH 11,2019. TEMP. STOPPED ON MARCH 11, 2019 DUE TO TRANSITION PERIOD. RESUMED ON APRIL 15, 2019. TRANSFER FROM TANEZA 10 TO LERIO 6. STOPPED ON APRIL 30, 2019 DUE TO 6 METERS OFF VEIN CUT BY FAULT. | N59: L04_CTVSPLIT_021W_RAISE | O59: MARTINEZ, DN 2 | P59: REPLACEMENT OF L04_CTVSPLIT_021W_DE. APPROVED ON FEBRUARY 12 2020. STOPPED ON FEB 28 2020 DUE TO PINCHED OUT VEIN TO 0.05M @ MOST CURRENT BACK | W59: L04_CV_015W_ROBBING | X59: MARTINEZ, RONALD 1 | Y59: RENAME FROM L04 CV 014W ROBBING TO AVOID MISCHARGING.APPROVED ON FEB.11,2021. Transfer from BAÑEZ 5 TO MARTINEZ, RONALD 1 on March 1,2021 start blasting sill pillar.STOPPED ON MARCH 3, 2021 DUE TO UNSAFE CONDITION.
K60: L04_NV_017W_DW | L60: ANDILAB 1 | M60: ADDITIONAL HORIZONTAL DEVELOPMENT. APPROVED ON MARCH 20, 2019. STOPPED ON MAY 2, 2019 DUE TO PINCHED OUT OF VEIN. | N60: L04_CTVSPLIT_022W_RAISE | O60: MARTINEZ, DN 2 | P60: REPLACEMENT OF L04_CTVSPLIT_022W_RAISE. APPROVED ON MARCH 16 2020. STOPPED ON MARCH 19 2020 DUE TO CONSECUTIVE LOW ASSAY GRADE ONCUT SAMPLE/BULK SAMPLE | W60: L04_JV_012W_ROBBING | X60: ANDILAB 1 | Y60: REPLACEMENT OF L04_JV_012W_DW. APPROVED ON OCT. 6 2020.TEMP STOPPED ON MARCH 20, 2021.
K61: L04_CTV5_022E_DE | L61: ANDILAB 2 | M61: ADDITIONAL HORIZONTAL DEVELOPMENT. APPROVED ON JUNE 17, 2019. MZC. RENAMED FROM L04 CTV5 032E DE TO L04 CTV5 022E DE FOR PROPER POSITIONING. TEMP. STOPPED ON JUNE 20, 2019 DUE TO ABSENTEESIM OF MEN RESULTING TO ABANDONMENT OF WORKPLACE AS PER TAN. | N61: L04_JVFW_023E_RAISE | O61: MANZANO 2 | P61: REPLACEMENT OF L04_JVFW_023E_DE. APPROVED ON FEB. 24 2020. TEMPORARY STOPPED ON FEB 25 2020 DUE TO LACK OF MANPOWER (OPERATION MEMO). RESUMED ON MARCH 3 2020 SAME TIME transferred to SHEPHERD AA from AF. TRANSFER FROM SHEPHERD AA TO MANZANO 2 ON JUNE 4, 2020. STOPPED ON JULY 23, 2020 DUE TO LOW CONSECUTIVE ASSAY GRADE. | W61: L04_JV_055W_ROBBING | X61: MARTINEZ, RON 2 | Y61: REPLACEMENT OF L04 JVS 024E DW.APPROVED ON FEB 15. 2021. ROBBING SILL PILLAR. Stopped on April 8,2021 already finished heading.
... K78: L04_JVSPLIT_022W_DW | L78: CABONITA 1 | M78: REPLACEMENT OF L04_NONE_023E_XCN APPROVED ON NOV 13, 2019.TEMP STOPPED TO DRIVE EASTERN ON NOV 22, 2019. | N78: L03_JV_014W_RAISE | O78: FERNANDEZ, RM | P78: REPLACEMENT OF L03_NONE_016W_XCN. APPROVED ON OCTOBER 15, 2024. STOPPED ON DECEMBER 9, 2024. ALREADY REACHED RECOMMENDED SLOPE HT. FOR WINZE STOPE PREP. | W78: L04_JV_024W_ROBBING | X78: SHEPHERD AL | Y78: REPLACEMENT OF L04_CV_003E_RAISE. APPROVED ON APRIL 26, 2022. SILL (A1).STOPPED ON MAY 7, 2022 DUE TO LOW CONSECUTIVE ASSAY GRADE
K79: L04_CTV_008W_DW | L79: NOCOS 3 | M79: ADDITIONAL HORIZONTAL DEVELOPMENT ON L03. APPROVED SEPT. 6, 2019. STOPPED ON DEC 4, 2019 DUE TO PINCHED OUT VEIN. | W79: L04_GHVHW_053W_ROBBING | X79: NOCOS 1 | Y79: REPLACEMENT OF L04_GHVHW_052W_ROBBING APPROVED ON MAY 6, 2022. SILL PILLAR.MARKING OF PILLARS.ON MAY,6,2022.STOPPED ON MAY 21 2022 DUE TO LOW GRADE AND REDISTRIBUTION OF MANPOWER.
K80: L04_JVSPLIT_034E_DE | L80: CABONITA 3 | M80: REPLACEMENT OF L04_NONE_034E_XCN. APPROVED ON NOV 22, 2019. STOPPED ON DEC 7, 2019 DUE TO CONSECUTIVE LOW ASSAY GRADES ON CUT SAMPLES /BULK SAMPLES | W80: L04_JV_026W_ROBBING | X80: MARTINEZ DN 1 | Y80: REPLACEMENT OF L04 GHVSPLIT 041W WINZE. APPROVED ON OCT 25, 2021, SILL PILLAR.STOPPED ON MAY 21 2022 DUE TO LOW GRADE AND REDISTRIBUTION OF MANPOWER TO 10E WINZE.
K81: L04_JVSPLIT_022W_DE | L81: CABONITA 1 | M81: REPLACEMENT OF L04_JVSPLIT_022W_DW APPROVED ON NOV 22, 2019. STOPPED ON DEC 7, 2019 DUE TO CONSECUTIVE LOW ASAY GRADES ON CUT SAMPLES/BULK SAMPLES. | W81: L04_CV_015W_ROBBING | X81: SHEPHERD AQ 2 | Y81: ADDITIONAL SOURCE OF GOOD ORE. APPROVED ON JANUARY 22 2021. CLEANING AND SECONDARY BLASTING OF BOULDERS ALONG HAULAGE AREA.CHANGE WORK HEADING INTO L04 CV 015W ROBBING.APPROVED ON FEB.11,2021.RESUMED ON APRIL 16, 2021.RENAMED FROM 14W TO 15W ROBBING ON APRIL 20, 2021. Temporary stopped on May 11,2021 due to lack of manpower.RESUMED ON JUNE 23 2021 AT THE SAME TIME TRANSFER FROM BANEZ TO MARTINEZ RONALD. TEMP. STOPPED ON JULY 14, 2021 AS PER LM.RESUMED ON JULY 21, 2021 2ND SHIFT.STOPPED ON JANUARY 23,2022 DUE TO CONSECUTIVE LOW ASSAY GRADE.RESUMED ON MARCH 17, 2022 AS WELL AS TRANSFERRED FROM MARTINEZ RONALD TO SHEPGERD AQ 2. SILL.STOPPED ON MAY 21 2022 DUE TO LOW GRADE AND REDISTRIBUTION OF MANPOWER.
K82: L04_GHVFW_018E_DW | L82: MARTINEZ RON. 1 | M82: REPLACEMENT OF L04_CV_003W_ROBBING. APPROVED ON OCT. 30, 2019. TEMP. STOPPED NOV. 1, 2019. | W82: L04_GHVFW_018E_ROBBING | X82: SHEPHERD AL 1 | Y82: REPLACEMENT OF L04_GHVFW_019E_ROBBING. APPROVED ON MAY 27 2022. SILL.STOPPED ON JUNE 16, 2022 DUE TO CONSECUTIVE LOW ASSAY GRADES ON CUT SAMPLES/BULK SAMPLES.
K83: L04_JVSPLIT_023E_DW | L83: SHEPHERD AA2 | M83: REPLACEMENT OF L04_JVSPLIT_022E_DE, APPROVED ON DECEMBER 7, 2019. Transfer from CABONITA 2 TO SHEPHERD AA2 former team leader will transfer to Level 8 effective on January 16,2020. STOPPED ON JANUARY 22 2020 DUE TO CONSECUTIVE LOW ASSAY GRADES ON CUT SAMPLES / BULK SAMPLE. | W83: L04_GHVSPLIT_027W_ROBBING | X83: MARTINEZ, RON 2 | Y83: ADDITIONAL SOURCE OF GOOD ORE. APPROVED ON MARCH 16, 2022. TEMPORARILY STOPPED DUE TO LACK OF MANPOWER ON APRIL 23, 2022.RESUMED ON APRIL 26, 2022 AS WELL AS TRANSFERRED FROMSHEPHERD AQ 3 TO ANDILAB 1.RENAMED FROM L04_GHVFW_027W_ROBBING TO L04_GHVSPLIT_027W_ROBBING ON MAY 3, 2022.TRANSFERRED FROM ANDILAB 1 TO MARTINEZ, RON 2 ON MAY 23 2022.CONVERTED TO SILL ON MAY 26 2022. FINISHED ROBBING ON JUNE 14, 2022.
K84: L04_CTV_016W_DW | L84: NOCOS 1 | M84: REPLACEMENT OF L04 CTV 016W WINZE. APPROVED ON OCT. 15, 2019.STOPPED ON NOV 14, 2019 DUE TO BREAKTHROUGH TOWARDS OLD STOPE.RESUMED ON NOV 20, 2019. STOPPED ON JANUARY 23 2020 DUE TO CONSECUTIVE LOW ASSAY GRADE ON CUT SAMPLES/ BULK SAMPLE. | W84: L04_GHVFW_031W_ROBBING | X84: SHEPHERD AQ 2 | Y84: REPLACEMENT OF L04_CV_004W_ROBBING. APPROVED ON MAY 3, 2022. SILL.TRANSFERRED FRAM MARTINEZ RON 2 TO SHEPHERD AQ 2 ON MAY 23 2022. STOPPED ON JUNE 18, 2022, ALREADY REACHED THE RECOMMENDED STRIKE LENGTH/CROWN PILLAR.
K85: L04_GHVFW_017E_DW | L85: COMAINGKING 4 | M85: REPLACEMENT OF L04_CV_003W_ROBBING. APPROVED ON OCT. 30, 2019. TEMP. STOPPED NOV. 1, 2019. RESUMED ON JANUARY 15, 2020 THE SAME TIME RENAMED FROM 18E TO 17E DE. TRANSFERRED TO COMAINGKING 4 FROM CABCAD 1 ON JANUARY 15, 2020. STOPPED ON FEB 5, 2020 DUE TO PINCHED OUT OF VEIN. | W85: L03_RYV_003W_DE | X85: FERNANDEZ, REX | Y85: REHAB MAINLINE FOR FUTURE ROBBING. APPROVED ON JUNE 29, 2022. STOPPED ON JULY 16, 2022.no advance not yet started.
K86: L04_GHVFW_017E_DE | L86: COMAINGKING 4 | M86: REPLACEMENT OF L04 CTV5 016E WINZE. APPROVED ON MAY 25,2019. INTERMEDIATE SUBLEVEL. TEMP. STOPPED ON JUNE 23, 2019 DUE TO ABSENTEEISM OF MEN RESULTING TO ABANDONMENT OF WORKPLACE. RESUMED OPERATION ON JUNE 28, 2019. STILL TEMPORARY STOPPED AS PER SCS. STOPPED ON OCT, 30 2019. | W86: L04_GHVFW_024W_ROBBING | X86: SHEPHERD AQ 2 | Y86: REPLACEMENT OF L04_GHVFW_031W_ROBBING. APPROVED ON JUNE 21, 2022. SILL.FINISHED HEADING ON JULY 18, 2022.
K87: L04_GHVFW_015E_DE | L87: LERIO 6 | M87: REPLACEMENT OF L04 NONE 015E XCS.APPROVED ON OCTOBER 25, 2018. TEMP. STOPPED ON DECEMBER 19, 2018 DUE TO ABSENTEEISM OF MEN RESULTING TO ABANDONMENT OF WP. RESUMED ON JANUARY 10, 2019 AS PER RAESPENIDO. TRANSFER TO TAÑEZA 10 FROM PARAGUYA 3 DUE TO GOOD PERFORMANCE OF FORMER TEAM LEADER APPROVED ON MARCH 11,2019. TEMP. STOPPED ON MARCH 11, 2019 DUE TO TRANSITION PERIOD. RESUMED ON MAY 17, 2019 AND TRANSFER FROM PARAGUYA TO LERIO 6/ TEMPORARY STOPPED ON MAY 28, 2019DUE TO CONSECUTIVE LOW GRADE CUT SAMPLES | W87: L04_CV_003E_ROBBING | X87: MARTINEZ, RON 1 | Y87: REPLACEMENT OF L04_CV_005E_DW. APPROVED ON JULY 18, 2022. TEMPORARY STOPPED ON JULY 31,2022 DUE TO ABSENTEEISM OF CREW. RESUMED ON AUGUST 2,2022 AT THE SAME TIME TRANSFER FROM SHEPHERD AL TO MARTINEZ, RONALD.STOPPED ON AUGUST 8, 2022.
K88: L04_CTV_008W_DE | L88: NOCOS 3 | M88: REPLACEMENT OF L04 CTV 008W DW. APPROVED ON DECEMBER. 7, 2019. STOPPED ON FEBRUARY 13 2020 DUE TO CONSECUTIVE LOW ASSAY GRADES ON CUT SAMPLES. | W88: L04_CV_004W_ROBBING | X88: MARTINEZ, RON 2 | Y88: ON-GOING CLEANING FOR REGRADING. LM WILL NOTIFY THE MINE ENGINEERING ONCE THE CLEANING WILL BE FINISHED. APPROVED ON MARCH 18, 2022. STOPPED ON MAY 2, 2022, ALREADY REACHED ITS RECOMMENDED STRIKE LENGTH.
K89: L04_CTV_016W_DW | L89: NOCOS 1 | M89: REPLACEMENT OF L04 CTV 016W WINZE. APPROVED ON OCT. 15, 2019.STOPPED ON NOV 14, 2019 DUE TO BREAKTHROUGH TOWARDS OLD STOPE.RESUMED ON NOV 20, 2019. STOPPED ON JANUARY 23 2020 DUE TO CONSECUTIVE LOW ASSAY GRADE ON CUT SAMPLES/ BULK SAMPLE.RESUMED ON FEB 4, 2020. STOPPED ON FEBRUARY 13 2020 DUE TO CONSECUTIVE LOW ASSAY GRADES ON CUT SAMPLES/ BULK SAMPLES. | W89: L04_GHVFW_016E_ROBBING | X89: SHEPHERD AL 1 | Y89: REPLACEMENT OF L04_GHVFW_018E_ROBBING. APPROVED ON JUNE 18, 2022. SILL.STOPPED ON AUGUST 17, 2022 ALREADY REACHED THE RECOMMENDED STRIKE LENGTH/CROWN PILLAR.
K90: L04_JVFW_023E_DE | L90: SHEPHERD AF | M90: REPLACEMENT OF L04_JVFW_023E_DE. APPROVED ON JANUARY 22, 2020. TRANSFERRED FROM SHEPHERD AA2 TO BAKAKON ON JANUARY 24 2020. TEMPORARY STOPPED ON FEBRUARY 13 2020 DUE TO ABSENTEEISM OF MEN RESULTING TO ABANDONMENT OF WORKPLACE. RESUMED ON FEBRUARY 14 2020. TRANSFERRED FROM BAKAKON TO SHEPHERD AF ON FEBRUARY 19 2020. STOPPED ON FEB 25 2020 DUE TO CONSECUTIVE LOW ASSAY GRADE ON CUT SAMPLES/ BULK SAMPLE. | W90: L04_CV_004W_ROBBING | X90: SHEPHERD AL 1 | Y90: REPLACEMENT OF L04_GHVFW_016E_ROBBING APPROVED ON AUGUST 11, 2022. SILL.FROM AUGUST 11-20, 2022 CATEGORIZED AS A3 (SILL, MUCKING OLD MUCK) AND ON AUGUST 21, 2022 START ROBBING ON SILL NEW MUCK WITH MUCKING MACHINE (A1).STOPPED ON AUGUST 26, 2022 DUE TO CONSECUTIVE LOW ASSAY GRADE.
... K141: L03_JV_015W_DE_ISL | L141: FERNANDEZ, RM 6 | M141: REPLACEMENT OF L03_JV_014W_WINZE. APPROVBD ON MAY 11, 2024.TEMPORARY STOPPED ON AUGUST 06, 2024. 3RD SHIFT TO PRIORITIZE L03_CTV_010W_RAISE.RESUMED ON AUGUST 12, 2024.STOPPED ON AUGUST 23, 2024. HEADING IS PROJECTED TO BREAKTHROUGH TO AN OLD STOPE. CURRENT FACE ALSO EXHIBITS POOR VEIN MINERALIZATION. | W141: L03_GHV_052E_ROBBING | X141: FERNANDEZ | Y141: ADDITIONAL WORKPLACE OF LEVEL 03. APPROVED ON NOVEMBER 25, 2025. TEMPORARY STOPPED ON DECEMBER 06, 2025, DUE TO INACCESSIBILITY OF MAINLINE CAUSED BY COLLAPSED PORTION AT 5W RAISE. RESUMED FOR OPERATIONS ON FEBRUARY 10, 2026. THE MAINLINE REHAB IS NOW FINISHED AND SAFE.STOPPED ON MAY 6, 2026. ALREADY FINISHED HEADING. MANPOWER WILL BE ASSIGNED TO CLEAN FOR THE BACK UP ROBBING.
K142: L03_JV_015W_DW_ISL | L142: FERNANDEZ, RM 6 | M142: REPLACEMENT OF L03_JV_015W_DE_ISL. APPROVED ON AUGUST 23, 2024. STOPPED ON NOVEMBER 04, 2024. ALREADY RECOMMENDED STRIKE LENGTH.
A186: SUBTOTAL | B186: =COUNTA(B4:B185)-43 -> 1 | E186: =COUNTA(E4:E185)-43 -> 1 | H186: =COUNTA(H4:H185)-44 -> 1 | K186: =COUNTA(K4:K185)-139 -> 0 | N186: =COUNTA(N4:N185)-74 -> 1 | Q186: =COUNTA(Q4:Q185)-46 -> 0 | T186: =COUNTA(T4:T185)-29 -> 0 | W186: =COUNTA(W5:W185)-126 -> 11 | Z186: =SUBTOTAL(9,B186:Y186) -> 15
A187: LEVEL 5 | B187: L05_DPVE_053E_WINZE STOPE PREP | C187: LERIO 1 | D187: REPLACEMENT OF L05_DPVE_053E_DW_ISL, APPROVED ON NOVEMBER 4, 2023.TEMPORARILY STOPPED ON NOVEMBER 11, 2023 FOR SAFETY EVALUATION. RESUMED ON NOVEMBER 13, 2023, AFTER FURTHER SAFETY EVALUATION. | E187: L05_DPVE_053E_WINZE STOPE | F187: LERIO 1 | G187: REPLACEMENT OF L05_DPVE_053E_WINZE STOPE PREP. APPROVED ON DECEMBER 17, 2023.TEMPORARILY STOPPED ON JANUARY 10, 2024. MANPOWER TRANSFERRED TO LOWER LEVEL. | H187: L05_GHVSPLIT_030W_STOPE | I187: SHEPHERD BB 2 | J187: REPLACEMENT OF L05_GHVSPLIT_030W_STOPE PREP APPROVED ON OCTOBER 24, 2023.TEMPORARY STOPPED ON DECEMBER 6, 2023 DUE TO UNSAFE CONDITION OF THE WORKPLACE BASED ON THE JOINT EVALUATION AND ASSESSMENT OF THE CONCERNED DEPARTMENTS AFTER THE EARTHQUAKE INCIDENT.RESUMED ON DECEMBER 13, 2023.STOPPED BREAKING ON FEBRUARY 01, 2024. DUE TO LOW GRADE ON 3 CONSECUTIVE FLOORS. TO BE CONVERTED TO PULLOUT CLEANING.STOPPED ON FEBRUARY 15, 2024. ALREADY MINED-OUT AT 103% PULL-OUT ATTAINMENT. | K187: L05_DPVE_053E_DW_ISL | L187: LERIO 1 | M187: REPLACEMENT OF L05_DPVE_053E_DE_ISL. APPROVED OCTOBER 23, 2023.STOPPED ON NOVEMBER 4, 2023, CONVERTED TO STOPE PREP. | N187: L05_GHVSPLIT_031W_RAISE | O187: SHEPHERD BB 2 | P187: REPLACEMENT OF L05_GHVSPLIT_031W_DE APPROVED ON APRIL 28, 2023.TEMPORARY STOPPED ON JUNE 8, 2023 DUE TO THE UNAVAILABIILITY OF AGSAO SHAFT.RESUMED ON OCTOBER 02, 2023. AS WELL AS CHANGED TEAM LEADER FROM PANCIT, NOEL 1 TO SHEPHERD BB 2.STOPPED ON OCTOBER 03, 2023. MEMO TO BE FOLLOWED. | Q187: L05_DPVE_046E_WINZE | R187: SHEPHERD AY | S187: REPLACEMENT OF L05_DPVE_049E_ROBBING APPROVED ON MAY 2, 2023.TEMPORARY STOPPED ON JUNE 8, 2023 DUE TO THE UNAVAILABIILITY OF AGSAO SHAFT.RESUMED ON DECEMBER 6, 2023 AS WELL AS CHANGE TL FROM PANCIT, NOEL 5 TO SHEPHERD AY.TEMPORARILY STOPPED ON JANUARY 10, 2024. MANPOWER TRANSFERRED TO LOWER LEVEL. | T187: L05_NONE_030E_XCN | U187: SHEPHERD AF 1 | V187: TARGETING DRILLING INTERCEPT. APPROVED ON FEB. 28, 2023. TEMPORARY STOPPED ON MARCH 10, 2023 DUE TO NO WASTE PASS.RESUMED ON APRIL 17, 2023.STOPPED ON MAY 06, 2023. ALREADY REACHED THE TARGETTED DRILL INTERCEPT. | W187: L05_NONE_033E_XCN | X187: FERNANDEZ | Y187: VENTILATION PROJECT. APPROVED ON JANUARY 11, 2025. STOPPED ON FEBRUARY 25, 2025. FINISH HEADING
B188: L05_GHVSPLIT_030W_STOPE PREP | C188: SHEPHERD BB 2 | D188: REPLACEMENT OF L05_GHVSPLIT_031W_RAISE. APPROVED ON OCTOBER 03, 2023.STOPPED ON OCTOBER 24, 2023. | E188: L05_GHVSPLIT_030W_STOPE | F188: SHEPHERD BB 2 | G188: REPLACEMENT OF L05_GHVSPLIT_030W_STOPE PREP APPROVED ON OCTOBER 24, 2023.TEMPORARY STOPPED ON DECEMBER 6, 2023 DUE TO UNSAFE CONDITION OF THE WORKPLACE BASED ON THE JOINT EVALUATION AND ASSESSMENT OF THE CONCERNED DEPARTMENTS AFTER THE EARTHQUAKE INCIDENT.RESUMED ON DECEMBER 13, 2023.STOPPED BREAKING ON FEBRUARY 01, 2024. DUE TO LOW GRADE ON 3 CONSECUTIVE FLOORS. TO BE CONVERTED TO PULLOUT CLEANING. | H188: L05_DPVE_035E_WINZE STOPE | I188: PANCIT, NOEL 2 | J188: CONVERTED TO PULLOUT CLEANING. APPROVED ON APRIL 20, 2023.STOPPED ON JUNE 5, 2023. ALREADY MINED OUT. | K188: L05_DPVE_053E_DE_ISL | L188: LERIO 1 | M188: REPLACEMENT OF L05_DPVE_053E_DW_ISL APPROVED ON JUNE 1, 2023.TEMPORARY STOPPED ON JUNE 8, 2023 DUE TO THE UNAVAILABILITY OF AGSAO SHAFT.RESUMED ON OCTOBER 02, 2023. AS WELL AS CHANGED TEAM LEADER FROM SHEPHERD AF 1 TO LERIO 2.-STOPPED ON OCTOBER 22, 2023 DUE TO PINCHED OUT VEIN AND WITH NO ASSAY GRADE IMPROVEMENT. | N188: L05_JV_003W_RAISE | O188: PANCIT, NOEL 5 | P188: REPLACEMENT OF L05_JV_001W_DW APPROVED ON MAY 25, 2023.TEMPORARY STOPPED ON JUNE 8, 2023 DUE TO THE UNAVAILABIILITY OF AGSAO SHAFT. | Q188: L05_DPVE_053E_WINZE | R188: SHEPHERD AF 1 | S188: REPLACEMENT OF L05 DPVE 052E ROBBING. APPROVED ON MAR 11, 2023.STOPPED ON MAY 22, 2023, ALREADY REACHED THE RECOMMENDED SLOPE HEIGHT, CONVERTED TO ISL. | T188: L05_NONE_049E_XCN | U188: PANCIT, NOEL 4 | V188: TARGETING DPVE WITH 5-6METERS REMAINING. APPROVED ON FEBRUARY 22, 2023.STOPPED ON MARCH 6, 2023. ALREADY INTERCEPTED THE TARGETED VEIN. | W188: L05_NONE_032E_RAISE | X188: PMC MINERS 1 | Y188: VENTILATION PURPOSES FOR EAST PRIMARY EXHAUST PROJECT. APPROVED ON JANUARY 23,2023.STOPPED ON OCTOBER 16, 2023 ALREADY MADE A BREAKTHROUGH AND DONE WIDENING.
B189: L05_DPVE_050E_STOPE PREP | C189: PANCIT, NOEL 5 | D189: ADDITIONAL SOURCE OF STOPE ORE. APPROVED ON MARCH 20, 2023.STOPPED ON APRIL 03, 2023. CONVERTED TO STOPE BREAKING. | E189: L05_DPVE_050E_STOPE | F189: PANCIT, NOEL 5 | G189: REPLACEMENT OF L05_DPVE_050E_STOPE PREP. APPROVED ON APRIL 03, 2023.STOPPED ON MAY 02, 2023. DUE TO CONSECUTIVE LOW ASSAY GRADE, | H189: L05_DPVE_043E_WINZE STOPE | I189: PANCIT, NOEL 3 | J189: REPLACEMENT OF L05_DPVE_043E_WINZE STOPE PREP APPROVED ON OCTOBER 20, 2022. CONVERTED TO ACTIVE BREAKING.RECOMMENDED FOR IPR AT 10TH FLOOR APPROVED ON DECEMBER 22, 2022.STOPPED BREAKING ON FEBRUARY 2, 2023, CONVERTED TO STOPE PULL OUT CLEANING ON FEBRUARY 2, 2023. STOPPED ON FEBRUARY 25, 2023 DUE TO CONSECUTIVE LOW GRADE ON SAMPLES. | K189: L05_JV_001W_DW | L189: PANCIT, NOEL 5 | M189: REPLACEMENT OF L05 JV 005W ROBBING. APPROVED ON MAY 17, 2023. TRASNFERRED FROM PARAN 1 TO PANCIT, NOEL 5 STARTING ON MAY 22, 2023.STOPPED ON JUNE 6, 2023. DUE TO PINCHED OUT VEIN. | N189: L05_DPVE_052E_RAISE | O189: PANCIT, NOEL 5 | P189: REPLACEMENT OF L05_DPVE_050E_STOPE APPROVED ON MAY 2, 2023.TEMPORARILY STOPPED ON MAY 05, 2023 DUE TO UNAVAILABILITY OF MUCKING MACHINE.RESUMED ON MAY 10, 2023.STOPPED ON MAY 23, 2023. ALREADY REACHED THE RECOMMENDED STRIKE LENGTH AND CONSECUTIVE LOW ASSAY GRADE. | Q189: L05_JVSPLIT_010W_WINZE | R189: SHEPHERD AF 1 | S189: ADDITIONAL FILL-WINZE IN LEVEL 5. APPROVED ON 2/10/2023.STOPPED ON FEB 16, 2023 ALREADY HIT THE ELEVATION FOR FILL WINZE. | T189: L05_NONE_050E_XCN | U189: PARAN 2 | V189: REPLACEMENT OF L05_DPVE_033E_DW. APPROVED ON JANUARY 24,2023.STOPPED ON FEBRUARY 8, 2023 ALREADY REACHED THE DRILL INTERCEPT. | W189: L05_GHVFW_002W_ROBBING | X189: BAYOBAY 1 | Y189: REPLACEMENT OF L05_GHVFW_001E_ROBBING APPROVED ON MAR 20, 2023. SILL PILLAR. STOPPED ON APRIL 13, 2023 DUE TO CONSECUTIVE LOW ASSAY GRADE.
B190: L05_JV_005W_WINZE_STOPE PREP | C190: PARAN 1 | D190: REPLACEMENT OF L05_JV_004W_DE_ISL. APPROVED ON FEB. 28, 2023.STOPPED ON MARCH 13 2023. COMPLETED STOPE PREP. | E190: L05_JV_005W_WINZE STOPE | F190: PARAN 1 | G190: REPLACEMENT OF L05_JV_005W_WINZE_STOPE PREP. APPROVED ON MARCH 13 2023. WINZE STOPE BREAKING.STOPPED BREAKING ON APRIL 28, 2023, AT THE SAME TIME CONVERTED TO PULLOUT CLEANING, NO TRAVERSE DUE TO ITS UNSAFE CONDITION.STOPPED ON MAY 08, 2023. MINED OUT. | H190: L05_JV_020E_STOPE | I190: PANCIT, NOEL 1 | J190: REPLACEMENT OF L05_JV_020E_STOPE , CONVERTED TO ACTIVE PULLOUT ON NOVEMBER 16, 2022.STOPPED ON NOVEMBER 23, 2022 DUE TO CONSECUTIVE LOW ASSAY GRADE @ 120% PULLOUT MC. | K190: L05_GHVSPLIT_034W_DW | L190: BAYOBAY | M190: ADDITIONAL HORIZONTAL DEVELOPMENT. APPROVED ON APRIL 17, 2023.RENAMED FROM L05_GHVSPLIT_055E_DW TO L05_GHVSPLIT_034W_DW FOR PROPER NAMING ON APRIL 19, 2023.STOPPED ON APRIL 27, 2023 HOLE OUT TO OLD ROBBING AREA. | N190: L05_DPVE_045E_RAISE | O190: SHEPHERD AF 2 | P190: REPLACEMENT OF L05_GHVFW_010E_RAISE. APPROVED ON JANUARY 17, 2023.TRANSFER FROM SHEPHERD AQ 4 TO SHEPHERD AF 2 ON JANUARY 17,2023.STOPPED ON FEBRUARY 5, 2023 DUE TO VEIN DISPLACEMENT BY NORTHWEST TRENDING FAULT. | Q190: L05_JV_004W_WINZE | R190: PARAN 1 | S190: REPLACEMENT OF L05_JVSPLIT_016W_WINZE STOPE APPROVED ON NOVEMBER 16, 2022.STOPPED ON JANUARY 23, 2023, BREAKTHROUGH TO AN OLD STOPE | T190: L05_NONE_035E_XCS | U190: SAMBERE | V190: TO TARGET DRILLING INTERCEPT.APPROVED ON 8/20/2021. TEMPORARY STOPPED ON AUG. 25, 2021 DUE TO PROBLEM ON TRAMMING CONGESTION AS THERE WAS ON-GOING ADVANCEMENT AT L05 DPVE 034E WINZE. resumed on September 8, 2021. TEMPORARY STOPPED ON SEPTEMBER 18, 2021 DUE TO INSUFFICIENT MANPOWER. MANPOWER ON THIS WP WILL BER MERGED TO L05 DPVE 043E STOPE PREP. RESUMED ON OCT 8 2021. TRANSFER FROM BAYOBAY TO SAMBERE.STOPPED ON OCT 26, 2021, CONVERTED TO ON VEIN DRIVE | W190: L05_JV_004W_ROBBING | X190: PARAN 3 | Y190: REPLACEMENT OF L05_JV_006W_ROBBING, APPROVED ON MAR 21, 2023. SILL PILLAR.STOPPED ON MARCH 29, 2023 MINED OUT.
B191: L05_DPVE_035E_WINZE STOPE PREP | C191: PANCIT, NOEL 2 | D191: REPLACEMENT OF L05_DPVE_034E_DE_ISL APPROVED ON JANUARY 11, 2023.STOPPED ON FEB. 2, 2023 TO CONVERT STOPE BREAKING. | E191: L05_DPVE_035E_WINZE STOPE | F191: PANCIT, NOEL 2 | G191: REPLACEMENT OF L05_DPVE_035E_WINZE STOPE PREP. APPROVED ON FEB. 2, 2023.STOPPED BREAKING ON APRIL 20, 2023. AT THE SAME TIME CONVERTED TO STOPE PULL-OUT AND TRAVERSED ON THE SAME DAY. | H191: L05_JVSPLIT_016W_WINZE STOPE | I191: PARAN 1 | J191: REPLACEMENT OF L05_JVSPLIT_016W_WINZE_STOPE PREP. CONVERTED TO ACTIVE BREAKING APPROVED ON OCTOBER 22, 2022.STOPPED BREAKING ON NOVEMBER 11, 2022.PUL-OUT ON NOVEMBER 11, 2022. WAITING FOR STOPE TRAVERSE.MINED OUT ON NOVEMBER 15, 2022. | K191: L05_JV_004W_DW_ISL | L191: PARAN 1 | M191: REPLACEMENT OF L05_JV_004W_WINZE. APPROVED ON JANUARY 24,2023.STOPPED ON FEBRUARY 2, 2023, TO PRIORITIZE DRIFT EAST. | N191: L05_GHVFW_010E_RAISE | O191: SHEPHERD AQ 4 | P191: REPLACEMENT OF L05 JVSPLIT 030W RAISE. APPROVED ON DEC 14, 2022.RENAMED FROM L05_DPVE_010W_RAISE TO L05_GHVFW_010E_RAISE APPROVED ON DECEMBER 16, 2022 FOR PROPER NAMING.STOPPED ON JANUARY 17, 2023 DUE TO BREAKTHROUGH AT OLD STOPE. | Q191: L05_DPVE_051E_WINZE | R191: FERNANDEZ, RG 3 | S191: REPLACEMENT OF L05_DPVE_051E_STOPE. APPROVED ON JAN. 26, 2022.TEMPORARY STOPPED ON APRIL 29, 2022 AS PER ADVISED BY MGT ALL DPVE AT L05. PERMANENTLY STOPPED ON JULY 20,2022 ALREADY CONVERTED TO ISL. | T191: L05_NONE_033E_XCN | U191: PANCIT, NOEL 2 | V191: TO DO DOUBLETROW. APPROVED ON AUG. 25, 2021. STOPPED ON SEPTEMBER 9,2021. | W191: L05_NONE_028E_XCS | X191: PARAN 2 | Y191: TARGETING THE DRILLING INTERCEPT. APPROVED ON SEPTEMBER 20, 2022.TEMPORARY STOPPED ON SEPT 20, 2022 REHAB MAINLINE.RESUMED ON OCTOBER 3,2022.SPECIAL PROJECT FOR VENTILATION PURPOSES.STOPPED ON JANUARY 13, 2023 ALREADY FINISHED
B192: L05_DPVE_048E_WINZE STOPE PREP | C192: FERNANDEZ, RG 1 | D192: REPLACEMENT OF L05_DPVE_051E_DW_ISL APPROVED ON NOVEMBER 22, 2022.STOPPED AND CONVERT TO STOPE BREAKING ON DEC. 8, 2022. | E192: L05_DPVE_048E_WINZE STOPE | F192: PANCIT, NOEL 5, | G192: REPLACEMENT OF L05_DPVE_048E_WINZE STOPE PREP. APPROVED ON DEC. 8, 2022.CHANGE TEAM LEADER FROM FERNANDEZ, RG 1 TO PANCIT, NOEL 5, FERNANDEZ WAS DEMOTED FROM TL TO MINER, AND PANCIT NOEL WILL ASSUME THE RESPONSIBILITIES OF FERNANDEZ APPROVED ON FEBRUARY 22, 2023.STOPPED ON MARCH 7, 2023 DUE TO CONSECUTIVE LOW ASSAY GRADES. | H192: L05_DPVE_034E_WINZE STOPE | I192: PANCIT, NOEL 2 | J192: REPLACEMENT OF L05_DPVE_034E_DW_ISL. APPROVED ON MARCH 21,2022. RECOMMENDED FOR ACTIVE STOPE BREAKING. APPROVED ON APRIL 22, 2022.TEMPORARY STOPPED ON APRIL 29, 2022 AS PER ADVISED BY MGT ALL DPVE AT L05.RESUMED ON JUNE 29, 2022. STOPPED ON SEPTEMBER 23,2022 ALREADY DONE BREAKING AT THE SAME TIME CONVERT TO PULL-OUT CLEANING.STOPPED ON OCTOBER 26, 2022. ALREADY MINED OUT WITH 99% PULL OUT MC. | K192: L05_DPVE_033E_DW | L192: PARAN 2 | M192: REPLACEMENT OF L05_NONE_028E_XCS APPROVED ON JANUARY 13, 2023.STOPPED ON JANUARY 19, 2023 DUE TO UNSAFE CONDITION OF THE WORKING PLACE. | N192: L05_DPVE_034E_DE_ISL | O192: PANCIT, NOEL 2 | P192: REPLACEMENT OF L05_DPVE_034E_WINZE STOPE APPROVED ON OCTOBER 26, 2022.TEMPORARY STOPPED ON NOVEMBER 10, 2022 TO PRIORITIZED DW.RESUMED ON NOVEMBER 23, 2022.STOPPED ON DECEMBER 22, 2022 DUE TO CONSECUTIVE LOW ASSAY GRADE. | Q192: L05_DPVE_034E_WINZE | R192: PANCIT, NOEL 2 | S192: replacement of L05_DPVE_025E_STOPE. Approved on August 21, 2021. STOPPED ON JANUARY 29,2022 DUE TO CONSECUTIVE LOW ASSAY GRADE. | T192: L05_NONE_036E_XCN | U192: PANCIT, NOEL 3 | V192: Target on-vein drive East and West and for ventilation purposes. Approved on July 12, 2021. STOPPED ON AUGUST 16, 2021. | W192: L05_JV_005W_ROBBING | X192: SHEPHERD AF 1 | Y192: REPLACEMENT OF L05_GHVFW_010E_ROBBING. APPROVED ON SEPTEMBER 1, 2022. SILL WITH MUCKING.RENAME FROM L05_JV_011E_ROBBING TO L05_JV_005W_ROBBING. APPROVED ON SEPTEMBER 9, 2022. STOPPED ON OCT. 27 2022 ALREADY MINED OUT
B193: L05_JVSPLIT_016W_WINZE STOPE PREP | C193: PARAN 1 | D193: REPLACEMENT OF L05_JVSPLIT_015W_DW_ISL APPROVED ON JUNE 17, 2022.TEMPORARILY STOPPED ON JUNE 28, 2022 TO PRIORITIZE L05_DPVE_034E_WINZE STOPE.RESUMED ON OCTOBER 14,2022 AT THE SAME TIME TRANSFER FROM PANCIT,NOEL 2 TO PARAN 1.STOPPED ON OCTOBER 22, 2022. CONVERTED TO ACTIVE BREAKING. | E193: L05_DPVE_043E_WINZE STOPE | F193: PANCIT, NOEL 3 | G193: REPLACEMENT OF L05_DPVE_043E_WINZE STOPE PREP APPROVED ON OCTOBER 20, 2022. CONVERTED TO ACTIVE BREAKING.RECOMMENDED FOR IPR AT 10TH FLOOR APPROVED ON DECEMBER 22, 2022.STOPPED BREAKING ON FEBRUARY 2, 2023, CONVERTED TO STOPE PULL OUT CLEANING. | H193: L05_CTV_028E_WINZE STOPE | I193: PARAN 1 | J193: REPLACEMENT OF L05_CTV_026E_WINZE STOPE PREP APPROVED ON AUGUST 15, 2022.CHANGE NAME FROM L05_CTV_026E_WINZE STOPE TO L05_CTV_028E_WINZE STOPE FOR PROPER NAMING APPROVED ON AUGUST 25, 2022. STOPPED BREAKING AND CONVERT TO STOPE PULL OUT ON AUGUST 27, 2022.STOPPED ON AUGUST 30,2022 DECLARED MINED OUT NOTIFIED ON SEPTEMBER 2,2022. | K193: L05_JVSPLIT_033W_DE | L193: SAMBERE 1 | M193: REPLACEMENT OF L05_JVSPLIT_033W_RAISE APPROVED ON SEPTEMBER 14, 2022.RENAMED FROM L05_JVSPLIT_034W_DE TO L05_JVSPLIT_033W_DE ON SEPTEMBER 23,2022 TO AVOID MISCHARGING.TEMPORARY STOPPED ON OCTOBER 11,2022 TO FOLLOW UP RAISE.RESUMED ON OCTOBER 26, 2022.STOPPED ON NOVEMBER 21, 2022, ALREADY REACHED THE RECOMMENDED STRIKE LENGTH | N193: L05_DPVE_040E_RAISE | O193: PANCIT, NOEL 4 | P193: REPLACEMENT OF L05_CTV_010E_DW. APPROVED ON NOVEMBER 22, 2022.STOPPED ON DECEMBER 12, 2022, PINCHED OUT VEIN | Q193: L05_CTV_023W_WINZE | R193: MAPAYO 2 | S193: REPLACEMENT OF L05_CTV_023W_DE. APPROVED ON AUG. 18, 2021. Temporary stopped on August 30, 2021 to prioritize L05 CTV 024W DW.RESUME ON SEPTEMBER 10,2021.SAFETY CONCERN EVALUATION. STOPPED ON OCT 30, 2021 LOW CUT SAMPLE RESULT, CONVERT TO CROWN PILLAR ROBBING. | T193: L05_NONE_051E_XCN | U193: SHEPHERD AD 2 | V193: CROSSCUT TO TARGET RESOURCE BLOCKS. APPROVED ON JUNE 19,2021.STOPPED ON JULY 7,2021 | W193: L05_CTV_035E_ROBBING | X193: BAYOBAY 1 | Y193: REPLACEMENT OF L05_JV_025E_ROBBING APPROVED ON OCTOBER 7, 2022. SILL.STOPPED ON OCTOBER 26, 2022 DUE TO CONSECUTIVE LOW ASSAY GRADE
B194: L05_DPVE_043E_WINZE STOPE PREP | C194: PANCIT, NOEL 3 | D194: REPLACEMENT OF L05_DPVE_044E_DW_ISL. APPROVED ON SEPTEMBER 5, 2022.RENAME FROM L05_DPVE_044E_WINZE_STOPE_PREP. APPROVED ON SEPTEMBER 9, 2022.STOPPED ON OCTOBER 20, 2022, CONVERTED TO ACTIVE BREAKING. | E194: L05_JV_020E_STOPE | F194: PANCIT, NOEL 1 | G194: REPLACEMENT OF L05_JV_020E_STOPE PREP APPROVED ON OCTOBER 18, 2022 CONVERTED TO ACTIVE BREAKING. RECOMMENDED IPR AT 8TH FLOOR ON NOVEMBER 12, 2022.STOPPED ON NOVEMBER 15, 2022, TRAVERSE ON NOVEMBER 16, 2022, CONVERTED TO ACTIVE PULLOUT | H194: L05_JVHW_004E_STOPE | I194: BAYOBAY 2 | J194: REPLACEMENT OF L05 JVHW 004E STOPE PREP, APPROVED ON MAY 28, 2022. STOPPED BREAKING AND CONVERT TO PULL-OUT ON JULY 8, 2022.STOPPED ON JULY 22,2022 ALREADY MINED OUT. | K194: L05_CTV_010E_DW | L194: PANCIT, NOEL 4 | M194: REPLACEMENT OF L05_CTV_009E_DW. APPROVED ON NOVEMBER 8, 2022.STOPPED ON NOVEMBER 22, 2022, ALREADY MADE A BREAKTHROUGH. | N194: L05_JVSPLIT_030W_RAISE | O194: SHEPHERD AQ 4 | P194: REPLACEMENT OF L05_JVSPLIT_033W_DE APPROVED ON NOVEMBER 21, 2022.TRANSFERRED FROM SAMBERE 1 TO SHEPHERD AQ 4. APPROVED ON DEC. 1, 2022.STOPPED ON DEC 14, 2022. DUE TO LOW GRADE.STOPPED ON DECEMBER 14, 2022 ALREADY REACHED THE RECOMMENDED SLOPE LENGTH. | Q194: L05_DPVE_044E_WINZE | R194: PANCIT, NOEL 1 | S194: REPLACEMENT OF L05_DPVE_034E_STOPE. APPROVED ON MAY 14,2021. STOPPED ON SEPTEMBER 7, 2021 | T194: L05_NONE_051E_XCS | U194: SHEPHERD AD 2 | V194: BY PASS FOR BACK-UP ROBBING. APPROVED ON MAY 18,2021.STOPPED ON MAY 26,2021.RESUMED ON JUNE 10 2021.STOPPED ON JUNE 11,2021. | W194: L05_CTV_038E_ROBBING | X194: BAYOBAY 2 | Y194: REPLACEMENT OF L05_CTV_037E_ROBBING. APPROVED ON AUGUST 4,2022. ALREADY DONE PILLAR ROBBING. STOPPED ON SEPT 10, 2022.
B195: L05_DPVE_051E_WINZE STOPE PREP | C195: FERNANDEZ, RG 1 | D195: REPLACEMENT OF L05_DPVE_051E_DE_ISL. APPROVED ON SEPTEMBER 1,2022.STOPPED ON OCTOBER 6, 2022, CONVERTED TO ACTIVE BREAKING. | E195: L05_DPVE_034E_WINZE STOPE | F195: PANCIT, NOEL 2 | G195: REPLACEMENT OF L05_DPVE_034E_DW_ISL. APPROVED ON MARCH 21,2022. RECOMMENDED FOR ACTIVE STOPE BREAKING. APPROVED ON APRIL 22, 2022.TEMPORARY STOPPED ON APRIL 29, 2022 AS PER ADVISED BY MGT ALL DPVE AT L05.RESUMED ON JUNE 29, 2022. STOPPED ON SEPTEMBER 23,2022 ALREADY DONE BREAKING AT THE SAME TIME CONVERT TO PULL-OUT CLEANING. | H195: L05_JV_026E_WINZE STOPE | I195: PANCIT, NOEL 5 | J195: REPLACEMENT OF L05_JV_026E_WINZE STOPE PREP. APPROVED ON APRIL 13,2022.stopped on may 5, 2022.RESUMED ON MAY 10, 2022 AND TRANSFERRED FROM MAPAYO 1 TO PANCIT, NOEL 5. BY MANAGEMENT DECISION MAPAYO WAS TRANSFERRED TO L11. STOPPED ON JUNE 7, 2022 AT THE SAME TIME CONVERTED TO PULL OUT CLEANING. ALREADY TRAVERSED ON JUNE 6,2022.STOPPED ON JUNE 15, 2022 DUE TO CONSECUTIVE LOW ASSAY GRADES ON CUT/BULK SAMPLES. | K195: L05_JVSPLIT_032W_DW | L195: SAMBERE 1 | M195: REPLACEMENT OF L05_NONE_032W_XCN. APPROVED ON JULY 4, 2022.RENAME FROM L05_JVSPLIT_032W_DE TO L05_JVSPLIT_032W_DW ON JULY 25, 2022.TRANSFER FROM SHEPHERD AF TO SAMBERE 1 DUE TO LOW PERFORMING ON JULY 28,2022.TEMPORARY STOPPED ON AUGUST 23, 2022 TO PRIORITIZE L05_JVSPLIT_032W_RAISE. | N195: L05_DPVE_046E_RAISE | O195: BAYOBAY 1 | P195: REPLACEMENT OF L05_DPVE_046E_DW. APPROVED ON NOVEMBER 4, 2022. MANPOWER CAME FROM L05_CTV_035E_ROBBING. STOPPED ON NOVEMBER 29,2022 DUE TO CONSECUTIVE LOW ASSAY GRADE. | Q195: L05_CTV_026E_WINZE | R195: PARAN 1 | S195: REPLACEMENT OF L06_CTV_037E_ROBBING, APPROVED ON JANUARY 14 2021. TEMPORARY STOPPED ON JAN 30, 2021 MANPOWER TRANSFERRED TO OTHER LEVEL. resumed on FEB 1 2021.TEMP. STOPPED ON MARCH 4, 2021 TO PRIORITIZE L05 CTV DW W/A VEIN WIDTH OF 050M @ A GRADE 14.50GPT.RESUMED ON JUNE 2, 2021. it has 4 meters projected vertical distance to btrakthrough the said stope.stopped on july 20, 2021 ALREADY BREAKTHROUGH TO OLD STOPE. | T195: L05_NONE_022E_XCS | U195: SHEPHERD AF 1 | V195: REPLACEMENT OF L05_JV_022E_RAISE. APPROVED ON MAY 14,2021. STOPPED ON MAY 18,2021 ALREADY HIT THE VEIN TARGET. | W195: L05_NONE_015E_SUMP | X195: SHEPHERD AF 1 | Y195: ADDITIONAL ALTERNATIVE SUMP @ L05. APPROVED ON MARCH 31 2022.STOPPED ON SEPTEMBER 2,2022.
B196: L05_CTV_026E_WINZE_STOPE PREP | C196: PARAN 1 | D196: STOPPED ON AUGUST 15, 2022 RECOMMENDED FOR ACTIVE BREAKING.REPLACEMENT OF L05_CTV_028E_RAISE_ISL. APPROVED ON AUGUST 11, 2022.RENAME FROM L05_CTV_024E_WINZE_STOPE PREP TO L05_CTV_026E_WINZE_STOPE PREP ON AUG.12, 2022. | E196: L05_JVHW_006W_STOPE | F196: PANCIT,NOEL 3 | G196: REPLACEMENT OF L05_JVHW_006W_STOPE PREP. APPROVED ON JUNE 17, 2022.STOPPED ON AUGUST 16, 2022, AT THE SAME TIME CONVERTED TO ACTIVE PULLOUT. | H196: L05_DPVE_052E_STOPE | I196: FERNANDEZ, RG 1 | J196: REPLACEMENT OF L05_DPVE_052E_STOPE PREP.APPROVED ON MARCH 10, 2022.RECOMMENDED TO CONVERT TO PULL-OUT CLEANING ON MAY 2, 2022.RECOMMENDED TO CONVERT TO PULL-OUT CLEANING ON MAY 2, 2022.stopped on may 5, 2022 | K196: L05_DPVE_040E_DW | L196: PANCIT, NOEL 1 | M196: REPLACEMENT OF L05_JVFW_031E_RAISE. APPROVED ON JULY 1,2022.STOPPED IN AUGUST 15, 2022, PINCHED OUT VEIN AND DUE TO CONSECUTIVE LOW ASSAY GRADE. | N196: L05_JVSPLIT_032W_RAISE | O196: SAMBERE 1 | P196: REPLACEMENT OF L05_JVSPLIT_033W_DE. APPROVED ON OCTOBER 11,2022.STOPPED ON OCTOBER 25, 2022 PINCHED OUT VEIN. | Q196: L05_CTV_005E_WINZE | R196: SHEPHERD W | S196: ADDITIONAL VERTICAL DEVELOPMENT. APPROVED ON OCT 7 2020. VEIN WAS CUT BY A FAULT STOP ON FEB 15 2021 PROCEED TO ISL | T196: L05_NONE_005W_XCS | U196: FERNANDEZ, REX.4 | V196: BYPASS FOR BACK UP ROBBING. APPROVED ON APRIL 4 2020. STOPPED ON APRIL 7 2020. | W196: L05_JVSPLIT_008W_ROBBING | X196: FERNANDEZ, RG 2 | Y196: REPLACEMENT OF L05_JVSPLIT_008W_DW_ISL. APPROVED ON MARCH 16, 2022. TOPSLICE.TEMPORARY STOPPED ON MARCH 29,2022 LACK OF MANPOWER.RESUMED ON MAY 10, 2022 AT THE SAME TIME TRANSFER TO PANCIT NOEL FROM BAYOBAY.TEMPORARILY STOPPED ON MAY 12 2022. MANPOWER TRANSFER TO 26E WINZE STOPE.RESUMED ON JUNE 29, 2022.CHANGE TEAM LEADER FROM PANCIT, NOEL 4 TO FERNANDEZ, RG 2 ON JUNE 29, 2022.MINED-OUT ON JULY 19, 2022.
B197: L05_JVHW_006W_STOPE PREP | C197: PANCIT,NOEL 3 | D197: REPLACEMENT OF L05_JVHW_006W_RAISE. APPROVED ON MAY 30 2022. STOPE PREP. STOPPED STOPE PREP AND CONVERT TO BREAKING ON JUNE 17, 2022. | E197: L05_JV_026E_WINZE STOPE | F197: PANCIT, NOEL 5 | G197: REPLACEMENT OF L05_JV_026E_WINZE STOPE PREP. APPROVED ON APRIL 13,2022.stopped on may 5, 2022.RESUMED ON MAY 10, 2022 AND TRANSFERRED FROM MAPAYO 1 TO PANCIT, NOEL 5. BY MANAGEMENT DECISION MAPAYO WAS TRANSFERRED TO L11. STOPPED ON JUNE 7, 2022 AT THE SAME TIME CONVERTED TO PULL OUT CLEANING. ALREADY TRAVERSED ON JUNE 6,2022. | H197: L05_DPVE_044E_WINZE STOPE | I197: PANCIT, NOEL 1 | J197: replacement of L05_DPVE_044E_WINZE STOPE ON NOV.24,2021.stopped on march 2, 2022 convert to pull-out cleaning.STOPPED ON MARCH 31 2022. MINED OUT. | K197: L05_GHVFW_010E_DE | L197: FERNANDEZ, RG 2 | M197: EXPLORATORY DRIFT. APPROVED ON JUNE 29, 2022.STOPPED ON JULY 19, 2022 ALREADY REACHED THE RECOMMENDED STRIKE LENGTH. | N197: L05_JVSPLIT_032W_RAISE | O197: SAMBERE 1 | P197: REPLACEMENT OF L05_JVSPLIT_032W_DW. APPROVED ON AUGUST 23, 2022. STOPPED ON SEPTEMBER 5, 2022 MEMO TO FOLLOW. | Q197: L05_CTV_002W_WINZE | R197: MAPAYO 3 | S197: ADDITIONAL VERTICAL DEVELOPMENT. APPROVED ON JUNE 23 2020.Transfer from ANDILAB 1 to MAPAYO 3 on June 30, 2020. stopped on July 28 2020 due to pinched out vein | T197: L05_NONE_037E_XCN | U197: BIHAY 1 | V197: COMMON AREA. APPROVED ON SEPT. 30 2019. CONVERT TO PERMANENT WORKING PLACE TO BIHAY 2 REMARKS CROSSCUT TARGETTING ORE RESOURCE. TEMPORARY STOPPED ON DECEMBER 5, 2019 DUE TO WASTEPASS UNAVAILABILITY. RESUMED ON JANUARY 8 2019. STOPPED ON APRIL 1 2020 DUE TO ALREADY INTERCEPTED TARGET VEIN WITH 1.0M IN WIDTH AND 24.73 IN GRADE | W197: L05_JVFW_015W_ROBBING | X197: COMAINGKING 4 | Y197: REPLACEMENT OF L05_JVFW_015W_WINZE_STOPE. APPROVED ON DEC. 2, 2021.SILL.STOPPED ON MARCH 23 2022. FINISHED HEADING. (OPS MEMO TO FOLLOW)
B198: L05_JVHW_004E_STOPE PREP | C198: BAYOBAY 2 | D198: ADDITIONAL SOURCE OF STOPE ORE AT LEVEL 5. APPROVED ON MAY 13,2022.ALREADY DONE STOPE PREPARATION ON MAY 28, 2022. CONVERT TO STOPE BREAKING. | E198: L05_CTV_027E_WINZE_STOPE | F198: PARAN 1 | G198: REPLACEMENT OF L05_CTV_027E_WINZE_STOPE PREP. STOPE BREAKING. APPROVED ON APRIL 6 2022. JUSTIFICATION FOR ITS LOW DIPPING AT 36 DEGREES FROM ITS FLOOR UP TO ITS CURRENT BACK ON MAY 2, 2022. STOPPED ON JUNE 6,2022 ALREADY MINED OUT. STOPE TRAVERSED ON JUNE 6,2022. | H198: L05_JV_024E_WINZE STOPE | I198: MAPAYO 1 | J198: replacement of L05_JV_024E_WINZE STOPE PREP ON. NOV.24,2021. STOPPED BREAKING AND CONVERTED TO STOPE PULL-OUT ON JAN. 28, 2022 MINED-OUT ON MARCH 6, 2022. | K198: L05_CTV_026E_DW_ISL | L198: PARAN 1 | M198: REPLACEMENT OF L05_CTV_026E_WINZE. APPROVED ON JULY 20, 2021.RENAME FROM L05_CTV_026E_DE_ISL TO L05_CTV_024E_DE_ISL ON SEPT.20,2021. STOPPED ON 9/28/21.resumed on Nov. 6, 2021. Rename from L05_CTV_024E_DE_ISL to L05_CTV_026E_DE_ISL at the same date. THIS WORKHEADING HAS A POSSIBILY TO BREAKTHROUGH AN OLD STOPE. EVALUATED ON 11/23/21. TEMP STOPPED ON JAN 11, 2022 TO CONTINUE BREAKING L05_CTV_026E_WINZE_STOPE.RESUMED ON JUNE 14, 2022 IN REPLACEMENT OF L05_CTV_028E_ROBBING. STOPPED ON JULY 11,2022 DUE TO VEIN PINCHED OUT . | N198: L05_JV_024E_RAISE | O198: FERNANDEZ, RG 2 | P198: REPLACEMENT OF L05_GHVFW_010E_DE. APPROVED ON JULY 21, 2022.STOPPED ON AUGUST 15, 2022, PINCHED OUT VEIN | Q198: L05_CTV_002W_WINZE | R198: MAPAYO 3 | S198: ADDITIONAL VERTICAL DEVELOPMENT. APPROVED ON JUNE 23 2020.Transfer from ANDILAB 1 to MAPAYO 3 on June 30, 2020. stopped on July 28 2020 due to pinched out vein | T198: L05_NONE_015W_XCS | U198: FERNANDEZ RX 6 | V198: APPROVED ON NOV 15, 2019 BY PASS TO ACCESS BACK-UP ROBBING. Temporary stopped on Dec 3, 2019 due to no available waste pass. Resumed On december 11, 2019.STOPPED ON FEB 14 2020 ALREADY BREAKTHROUGH | W198: L05_NONE_014E_XCS | X198: FERNANDEZ RG | Y198: Approved on Dec. 23, 2021. Special project for Dewatering.TRANSFERRED FROM PANCIT, NOEL TO FERNANDEZ RG STARTING ON JAN. 17, 2021.STOPPED ON FEBRUARY 7,2022 ALREADY BREAKTHROUGH.
B199: L05_DPVE_034E_WINZE STOPE PREP | C199: PANCIT, NOEL 2 | D199: REPLACEMENT OF L05_DPVE_034E_DW_ISL. APPROVED ON MARCH 21,2022. STOPPED ON APRIL 22, 2022 AND CONVERTED TO WINZE STOPE BREAKING . | E199: L05_DPVE_052E_STOPE | F199: FERNANDEZ, RG 1 | G199: REPLACEMENT OF L05_DPVE_052E_STOPE PREP.APPROVED ON MARCH 10, 2022.RECOMMENDED TO CONVERT TO PULL-OUT CLEANING ON MAY 2, 2022. | H199: L05_DPVE_043E_STOPE | I199: BAYOBAY 1 | J199: replacement of L05_DPVE_043E_STOPE PREP. converted to stope breaking September 24, 2021. Stopped breaking and converted to pull-out on Feb. 4, 2022.stopped on march 2,2022 | K199: L05_JV_019E_DE | L199: FERNANDEZ, RG 2 | M199: REPLACEMENT OF L05_JV_022E_DW. APPROVED ON MARCH 11, 2022.TEMPORARILY STOPPED ON APRIL 26, 2022 DUE TO RAISE PREPARATION.RESUMED ON MAY 3, 2022. TEMPORARY STOPPED ON JUNE 1,2022 DELAY BY FOLLOW UP RAISE.RESUMED ON JUNE 7 2022 AS REPLACEMENT OF L05_JV_022E_RAISE.STOPPED ON JUNE 20, 2022, PINCHED OUT VEIN. | N199: L05_JVHW_007E_RAISE | O199: SAMBERE 1 | P199: REPLACEMENT OF L05_JVHW_005E_DW. APPROVED ON JULY 11, 2022.STOPPED ON JULY 29,2022 DUE TO VEIN PINCHED OUT. | Q199: L05_JV_031E_WINZE | R199: SAMBERE 1 | S199: REPLACEMENT OF L05_JVHW_038E_ROBBING. APPROVED ON MAY 26 2020.STOPPED ON JULY 23, 2020 CONVERT TO INTERMEDIATE SUB LEVEL. | T199: L05_NONE_028E_XCS | U199: PMC MINERS 1 | V199: FOR VENTILATION MAIN VENTILATION PROJECT. APPROVED ON 6/5/19. stopped on 8/30/19 already finished | W199: L05_CTV_021W_ROBBING | X199: MAPAYO 2 | Y199: REPLACEMENT OF L05 CTV 023W WINZE. APPROVED ON OCT 30, 2021. Renamed from L05_CTV_024W_ROBBING. Starting on Nov. 3, 2021.RENAMED FROM L05_CTV_022W_ROBBING. STARTING NOV. 4, 2021. STOPPED ON NOVEMBER 23, 2021. MINED OUT.
... B209: L05_DPVE_025E_STOPE PREP | C209: PANCIT, NOEL 2 | D209: REPLACEMENT OF L05 DPVE 028E STOPE. APPROVED ON JULY 28, 2021. STOPPED ON AUGUST 12, 2021 CONVERT TO STOPE BREAKING. | E209: L05_CTV_012W_WINZE STOPE | F209: SHEPHERD W | G209: REPLACEMENT OF L05_CTV_012W_WINZE STOPE PREP. APPROVED ON JULY 21 2020. Stopped Breaking and Converted to Pull out Cleaning on August 27 2020. | H209: L05_DPVE_033E_STOPE | I209: PANCIT, NOEL 2 | J209: REPLACEMENT OF L05_DPVE_040E_DE APPROVED JAN 13, 2021 TEMPORARY STOPPED ON JAN 30, 2021 MANPOWER TRANSFERRED TO OTHER LEVEL. Resume on Feb 01, 2021.STOPPED ON 04/06/21 ALREADY CONVERTED TO STOPE BREAKING.CONVERT TO PULL OUT CLEANING APPROVED ON APRIL 22, 2021.STOPPED ON MAY 8,2021. FINISHED PULL-OUT CLEANING.OLD STOPE RESUMPTION OF BREAKING APPROVED ON OCTOBER 24, 2023. SHORTENED THE SLOPE LENGTH IN THE PREVIOUS DESIGN BECAUSE OF HOW THEY INITIALLY DESIGNED THE TIGERWAY DECLINE, AND RESUMED BREAKING THE REMAINING FLOORS THAT ARE MINEABLE. | K209: L05_DPVE_049E_DW | L209: SHEPHERD AD 2 | M209: REPLACEMENT OF L05_DPVE_039E_DW. APPROVED ON JULY 31, 2021. STOPPED ON SEPT. 22, 2021 MADE A BREAKTHROUGH. | N209: L05_DPVE_053E_RAISE | O209: SHEPHERD RG | P209: REPLACEMENT OF L05_DPVE_050E_DE. APPROVED NOV. 4, 2021.STOPPED ON NOV.29,2021 | Q209: L05_GHV_023W_WINZE | R209: BADBADON L. 3 | S209: REPLACEMENT OF L05 GHV 024W WINZE STOPE. APPROVED ON OCT. 30, 2018. TEMPORARY STOPPED ON DECEMBER 1, 2018 DUE TO LACK OF MANPOWER AS PER PJVELOZ. RESUMED ON JANUARY 9, 2019. STOPPED ON MARCH 12,2019 DUE TO PINCHED OUT OF VEIN. | T209: L05_NONE_032W_XCN | U209: SHEPHERD AF | V209: TARGET DRILLHOLE L5-242-001. APPROVED ON JULY 3, 2022.TEMP. STOPPED ON JULY 4, 2022. | W209: L05_NONE_028W_RAISE | X209: PMC MINERS 2 | Y209: SPECIAL PROJECT FOR VENTILATION PURPOSES. APPROVED ON MAY 20,2019. TRANSFER FROM ESPADA 2 TO DAGAMAC1 ON JUNE 24, 2019.TEMP. STOPPED ON JULY 3, 2019 FORMER TEAM LEADER SURRENDER THE WORK. RESUMED ON JULY 22,2019 AT THE SAME TIME TRANSFER FROM DAGAMAC 1 TO COMAINGKING 2. STOPPED ON OCTOBER 7, 2019. RESUMED ON OCT. 16, 2019 IN THE SAME TIME TRANSFER FROM COMAINGKING 2 TO DAGAMAC. TRANSFERRED ON MARCH 31 2020 FROM DAGAMAC TO PMC MINERS 2 DUE TO LACK OF MAN POWER. Stopped on November 13,2020.
B210: L05_JV_022E_STOPE PREP | C210: SHEPHERD AF 1 | D210: REPLACEMENT OF L05_JV_022E_DE APPROVED ON JUNE 11, 2021.STOPPED ON JULY 15, 2021 AT THE SAME TIME CONVERTED TO STOPE BREAKING. | E210: L05_CTV_039E_WINZE STOPE | F210: SHEPHERD Z.2 | G210: L05_CTV_039E_WINZE STOPE PREP. APPROVED ON JUNE 23 2020 CONVERTED TO ACTIVE BREAKING.Stopped on July 27 2020 recommended for Pull-out Cleaning. | H210: L05_DPVE_034E_STOPE | I210: PANCIT, NOEL 1 | J210: REPLACEMENT OF L05_DPVE_034E_STOPE PREP.APPROVED ON APRIL 5, 2021.CONVERT TO PULL OUT CLEANING APPROVED ON APRIL 22, 2021.STOPPED ON MAY 8,2021 FINISHED PULL-OUT CLEANING. RESUMED ON MAY 9,2021. STOPPED ON MAY 14,2021. | K210: L05_JVSPLIT_036E_DE | L210: PANCIT, NOEL 3 | M210: REPLACEMENT OF L05_JVSPLIT_036E_DW APPROVED ON AUGUST 25, 2021.STOPPED ON SEPTEMBER 14,2021. | N210: L05_DPVE_042E_RAISE | O210: SHEPHERD AD 1 | P210: REPLACEMENT OF L05_DPVE_051E_RAISE. APPROVED ON SEPT., 8, 2021. STOPPED ON 10/07/21 DUE TO OFF VEIN. | Q210: L05_GHV_019W_WINZE | R210: BADBADON L.4 | S210: REPLACEMENT OF L05 GHV 022W ROBBING. APPROVED ON FEB 26, 20189.PURPOSE FOR ACCESS.STOPPED ON APR 3, 2019. | W210: L05_CTV_037E_ROBBING | X210: SHEPHERD Z | Y210: REPLACEMENT OF L05 CTV 039E DE. APPROVED ON OCT 31 2020. renamed from L05 CTV 040E ROBBING TO 037E ROBBING on NOV 14 2020 TO AVOID MISCHARGING. Stopped on Dec 28 2020 already mined out.
B211: L05_DPVE_047E_STOPE PREP | C211: BAYOBAY 1 | D211: REPLACEMENT OF L05 DPVE 047E RAISE APPROVED ON JUNE 11,2021.STOPPED ON JULY 12, 2021 NOTIFIED ON JULY 14, 2021. RECOMMENDED FOR STOPE BREAKING. | E211: L05_GHV_035W_STOPE | F211: FERNANDEZ RX 5 | G211: REPLACEMENT OF L05_GHV_035W_STOPE PREP APPROVED ON NOV 12, 2019 CONVERT TO ACTIVE BREAKING. STOPPED ON MARCH 6 2020 MADE A BREAKTHROUGH CONVERTED TO PULL OUT CLEANING. | H211: L05_DPVE_041E_STOPE | I211: BAYOBAY 1 | J211: REPLACEMENT OF L05_DPVE_041E_STOPE PREP. APPROVED ON SEPT. 09 2020. convert to pull out cleaning on November 19,2020 due to exclusion zone at the decline TEMPORARY STOPPED ON JAN 30, 2021 MANPOWER TRANSFERRED TO L05 012W SUMP CHAMBER | K211: L05_CTV_023W_DE | L211: MAPAYO 2 | M211: REPLACMENT OF L05 CTV 033W ROBBING. APPROVED ON AUGUST 6, 2021. STOPPED ON AUGUST 18, 2021. RESUME ON SEPTEMBER 1, 2021.STOPPED ON SEPT.10,2021. | N211: L05_JVSPLIT_036E_RAISE | O211: PANCIT, NOEL 4 | P211: REPLACEMENT OF L05_JVSPLIT_036E_DE. APPROVED ON SEPTEMBER 15, 2022. STOPPED ON 9/30/21 . MADE A BREAKTHROUGH. | Q211: L05_GHVFW_029W_WINZE | R211: OY-YOY 1 | S211: REPLACEMENT OF L05 CV 005W WINZE. APPROVED ON MAR 27, 2019.STOPPED ON JUNE 4, 2019 | W211: L05_CTV_039E_ROBBING | X211: SHEPHERD Z.2 | Y211: REPLACEMENT OF L05_CTV_039E_WINZE STOPE.APPROVED ON AUGUST 14, 2020. Stopped on Sept. 15 2020 already mined out.
B212: L05_JV_027E_WINZE STOPE PREP | C212: MAPAYO 1 | D212: REPLACEMENT OF L05_JV_027E_RAISE. APPROVED ON MAY 24,2021.STOPPED ON JUNE 29,2021 AT THE SAME TIME CONVERTED TO STOPE BREAKING. | E212: L05_CV_004W_WINZE STOPE | F212: SHEPHERD L | G212: REPLACEMENT OF L05_CV_004W_WINZE STOPE PREP.APPROVED ON JULY 29, 2019-LTS.TEMPORARY STOPPED ON SEPT 25, 2019 DUE TO DIFECTED AIR HOIST. RESUMED ON OCTOBER 3, 2019. STOPPED AND CONVERT TO ACTIVE PULL-OUT CLEANING ON OCT 18, 2019 | H212: L05_CTV_012W_WINZE STOPE | I212: SHEPHERD W | J212: REPLACEMENT OF L05_CTV_012W_WINZE STOPE PREP. APPROVED ON JULY 21 2020. Stopped Breaking and Converted to Pull out Cleaning on August 27 2020. STOPPED ON 11/6/2020, ALREADY MINED OUT | K212: L05_JVSPLIT_036E_DW | L212: PANCIT, NOEL 3 | M212: REPLACEMENT OF L05_NONE_036E_XCN. APPROVED ON AUG. 18, 2021. STOPPED ON AUGUST 25, 2021. DUE TO PINCHED OUT VEIN. | N212: L05_DPVE_025E_RAISE | O212: PANCIT, NOEL 3 | P212: replacement of L05_DPVE_025E_DW. Approved on June 25, 2021. STOPPED ON JULY 8, 2021 VEIN PINCHED OUT. | Q212: L05_GHV_027W_WINZE | R212: OY-YOY 1 | S212: REPLACEMENT OF L05 GHV 029W WINZE.APPROVED ON JUNE 4, 2019.RENAMED ON JUNE 21, 2019 FROM L05_GHV_028W_WINZE TO L05 GHV 027W WINZE TO AVOID MISCHARGING TO L05 NONE 028W RAISE.TEMP. STOPPED ON JULY 18, 2019 TO PRIORITIZED THE CROWN PILLAR. | W212: L05_CTV_045W_ROBBING | X212: PMC MINERS 1 | Y212: ADDITIONAL SOURCE OF GOOD ORE. APPROVED ON MARCH 6 2020. STOPPED ON APRIL 6 2020 DUE TO CONSECUTIVE LOW ASSAY GRADE ON CUT SAMPLE / BULK SAMPLES.RESUME ON JULY 9, 2020 AT THE SAME TIME TRANSFERRED TO PMC MINER 1.STOPPED ON JULY 27 2020 TO FINISHED HEADING.
B213: L05_CTV_015E_WINZE STOPE PREP | C213: SHEPHERD AM 1 | D213: REPLACEMENT OF L05_CTV_013E_WINZE STOPE. APPROVED ON 1/5/2020- rename from 14E TEMPORARY STOPPED ON JAN 20, MANPOWER MERGED WITH L05 CTV 013W RAISE.RESUME ON 2/3/2021. temporary stopped on 3/6/21 due to insuffient manpower. Resume on April 14,2021 at the same time transfer from SHEPHERD W TO SHEPHERD AM. STOPPED ON APRIL 30,2021 CONVERT TO ACTIVE BREAKING. | E213: L05_NV_009E_STOPE | F213: BIHAY 2 | G213: REPLACEMENT OF L05 NV 008E STOPE PREP. APPROVED ON JUNE 6,2019. RENAMED FROM L05_NV_008E_STOPE TO L05 NV 009E STOPE TO AVOID MISCHARGING TO LEVEL 4 GHVFW 008E WINZE STOPE ON JUNE 21, 2019. STOPPED BREAKING ON AUGUST 15, 2019 AND IN SAME TIME CONVERT TO PULL OUT CLEANING DUE TO PINCHED OUT OF VEIN. | H213: L05_CV_009E_STOPE | I213: SHEPHERD AD | J213: REPLACEMENT OF L05 CV 009E RAISE. APPROVED ON JANUARY 11, 2019. MZC. CONVERTED TO BREAKING JANUARY 17, 2019.STOP BREAKING/CONVERTED TO PULL-OUT ON 4/8/19-SDNC. STOPPED ON APRIL 15,2019 DUE TO LOW GRADE AS PER LEVEL GEOLOGIST. Resumed on September 25,2020 to pull out remaining old muck at the same time transfer from CAYABAS 1 TO SHEPHERD AD. STOPPED ON OCT. 10 2020 ALREADY MINED OUT. | K213: L05_DPVE_035E_DE | L213: BAYOBAY 2 | M213: ADDITIONAL HORIZONTAL DEVELOPMENT. APPROVED ON AUG. 18, 2021. TEMPORARY STOPPED ON 8/20/2021 | N213: L05_DPVE_030E_RAISE | O213: SHEPHERD AB 1 | P213: REPLACEMENT OF L05_DPVE_030E_DE.APPROVED ON JUNE 2, 2021.STOPPED ON JUNE 28, 2021 DUE TO INSUFFICIENT OF MANPOWER/ABSENTEEISM OF MEN RESULTING TO ABANDONMENT OF WORKPLACE. | Q213: L05_CTV_011W_WINZE | R213: OY-YOY 1 | S213: EXPLORATORY WINZE FOR TOPSLICE OR WIZE STOPE APPROVED ON JUNE 27, 2019. STOPPED ON SEPTEMBER 1,2019 DUE TO CONSECUTIVE LOW ASSAY GRADES ON CUT SAMPLES/BULK SAMPLES. | W213: L05_JV_018E_ROBBING | X213: SHEPHERD W | Y213: REPLACEMENT OF L05_JV_018E_RAISE. APPROVED ON MAY 28, 2020. STOPPED ON JUNE 24 2020 FINISHED HEADING.
B214: L05_JV_031E_WINZE STOPE PREP | C214: SAMBERE 1 | D214: REPLACEMENT OF L05_JV_031E_RAISE.APPROVED ON NOV. 30 2020. TEMPORARY STOPPED ON JAN 30, 2021 MANPOWER TRANSFERRED TO OTHER LEVEL.resumed on April 7, 2021.TEMPORARY STOPPED ON APRIL 7,2021 SINGLE ENTRY. Resumed on April 9,2021.STOPPED ON APRIL 15, 2021 CONVERT TO BREAKING. | E214: L05_CV_004W_STOPE | F214: ALMEDORA 1 | G214: REPLACEMENT OF L05 CV 004W STOPE PREP.APPROVED ON MAY 30, 2019. STOPPED ON JUNE 21, 2019 DUE TO CONSECUTIVE LOW ASSAY CUT/BULK SAMPLE. | H214: L05_CTV_008W_STOPE | I214: SHEPHERD AD | J214: REPLACEMENT OF L05 CTV 008W RAISE. APPROVED ON NOVEMBER 29,2018. CONVERTED TO BREAKING ON JANUARY 25, 2019.CONVERTED TO PULL-OUT ON 4/9/19-LTS. CONTROL PULL-OUT ATLEAST 12-15 MC/DAY DUE TO LOW CONSECUTIVE ASSAY GRADE. STOPPED ON MAY 6,2019 DUE TO CONSECUTIVE LOW ASSAY GRADE.RESUMED PULL OUT ON AUGUST 14,2020 AT THE SAME TIME TRANSFER FROM SHEPHERD P TO SHEPHERD AF.Temporary stopped on Sept. 8,2020 due to lack of manpower. resumed on Sept 11,2020 at the same time transfer from SHEPHERD AF TO SHEPHERD AD. ON SEPTEMBER 24 2020, Stopped on September 24, 2020 stope to be open must be L05 CV 009E STOPE misdeclaration of Level Geologist of old stope pull out to be resume. | K214: L05_JV_022E_DE | L214: SHEPHERD AF 1 | M214: REPLACEMENT OF L05_NONE_022E_XCS. APPROVED ON MAY 18,2021.STOPPED ON JUNE 9, 2021 OFF-VEIN DUE TO SUB-PERPENDICULAR.resumed on June 10,2021 (2nd shift) notified on June 11,2021.STOPPED ON JUNE 11,2021 ALREADY BREAKTHROUGH | N214: L05_DPVE_047E_RAISE | O214: BAYOBAY 1 | P214: Replacement of L05_DPVE_045E_RAISE. Approved on May 2, 2021.STOPPED ON JUNE 11,2021 CONVERT TO STOPE PREP. RESUME ON AUGUST 17, 2021 STOPPED ON AUGUST 20, 2021. | Q214: L05_JV_001E_WINZE | R214: OY-YOY 1 | S214: REPLACEMENT OF L05_CTV_043W_WINZE. APPROVED ON NOV. 7, 2019. Temporary stopped on Nov 11,2019 surrender team leader | W214: L05_NONE_028E_RAISE | X214: DAGAMAC 2 | Y214: REPLACEMENT OF L05_NONE_028E_RAISE APPROVED ON NOV. 18, 2019. TEMPORARY STOPPED ON MARCH 9 2020. RESUMED ON MARCH 15 2020. Temporary stopped on May 26,2020.
B215: L05_JVFW_014W_WINZE STOPE PREP | C215: SHEPHERD AB | D215: REPLACEMENT OF L05_JVHW_014W_RAISE. APPROVED ON OCT. 6 2020. STOPPED ON NOV. 21 2020 CONVERTED TO ACTIVE BREAKING. | E215: L05_GHV_040W_WINZE STOPE | F215: COMAINGKING 1 | G215: REPLACEMENT OF L05 GHV 040W WINZE STOPE PREP. APPROVED ON MARCH 14,2019.ALREADY REACHED THE DESIGNED PILLAR. CONVERT TO PULL OUT CLEANING ON MAY 30, 2019. | H215: L05_CTV_039E_WINZE STOPE | I215: SHEPHERD Z.2 | J215: L05_CTV_039E_WINZE STOPE PREP. APPROVED ON JUNE 23 2020 CONVERTED TO ACTIVE BREAKING.Stopped on July 27 2020 recommended for Pull-out Cleaning . Stopped on august 13 2020 already mined out. | K215: L05_JV_031E_DW_ISL | L215: SAMBERE 1 | M215: REPLACEMENT OF L05_JV_031E_DE.APPROVED ON AUG. 14, 2020.STOPPED ON OCT 15 2020.ALREADY REACH RECOMMENDEND STRIKE LENGTH.RESUMED ON MAY 22,2021.STOPPED ON JUNE 10, 2021 PINCHED OUT VEIN. | N215: L05_JV_027E_RAISE_ISL | O215: MAPAYO 1 | P215: REPLACEMENT OF L05_JV_027E_DE.APPROVED ON APRIL 29, 2021. STOPPED ON MAY 24,2021 CONVERT TO STOPE PREPARATION. | Q215: L05_CV_003W_WINZE | R215: OY-YOY 1 | S215: REPLACEMENT OF L05_GHV_044W_WINZE. APPROVED ON NOV. 4, 2019.STOPPED ON NOV 9, 2019 ALREADY BREAK THRU. | W215: L05_GHVFW_022W_ROBBING | X215: FERNANDEZ R | Y215: APPROVED ON NOV. 6, 2019 REPLACEMENT OF L05_GHV_010W_RAISE.STOPPED ON NOV 16, 2019 ALREADY REACHED THE RECOMMENDED STRIKE LENGTH/CROWN PILLAR.
B216: L05_CTV_013E_WINZE STOPE PREP | C216: SHEPHERD W | D216: REPLACEMENT OF L05_CTV_013E_DE. APPROVED ON OCT. 4 2020. STOPPED ON NOV. 10 2020 CONVERTED TO ACTIVE BREAKING. | E216: L05_JVFW_005E_WINZE STOPE | F216: DAVOCOL ROW 1 | G216: REPLACEMENT OF L05 JVFW 005E DE. APPROVED ON DECEMBER 3, 2018. MZC. TEMP STOPPED ON FEB 23, 2019 DUE TO INCOMING HEADING FROM LEVEL 6; MEMO RECEIVED GEO. RESUMED AT THE SAME TIME CONVERTED TO BREAKING ON MAR 27, 2019. TEMPORARY STOPPED ON APRIL 16,2019 DUE TO LACK OF MANPOWER. Stopped Permanently on February 7,2020 as per Level Geologist Zabate. | H216: L05_GHV_035W_STOPE | I216: FERNANDEZ RX 5 | J216: REPLACEMENT OF L05_GHV_035W_STOPE PREP APPROVED ON NOV 12, 2019 CONVERT TO ACTIVE BREAKING. STOPPED ON MARCH 6 2020 MADE A BREAKTHROUGH CONVERTED TO PULL OUT CLEANING. Stopped on march 28 2020 already finished. | K216: L05_DPVE_030E_DE | L216: SHEPHERD AB 1 | M216: additional horizontal development. approved on April 7, 2021.RENAMED FROM 32E TO L05_DPVE_030E_DE.APPROVED ON APRIL 16, 2021. STOPPED ON JUNE 1,2021 DUE TO VEIN PINCHED OUT. | N216: L05_DPVE_046E_RAISE | O216: SHEPHERD AF 1 | P216: ADDITIONAL VERTICAL DEVELOPMENT APPROVED ON APRIL 5, 2021.STOPPED ON APRIL 17, 2021 MANPOWER ISSUE TRANSFER TO 5E DW.RESUMED ON APRIL 20, 2021 AT THE SAME TIME TRANSFER FROM PARAN TO SHEPHERD AF.STOPPED ON MAY 6, 2021 ALREADY REACH THE RECOMMENDED STRIKE LENGTH. | Q216: L05_NV_009E_WINZE | R216: ESPADA 1 | S216: REPLACEMENT OF L05_GHV_046W_DW. APPROVED ON OCT 29, 2019. STOPPED ON DECEMBER 16, 2019 DUE CONSECUTIVELY PRODUCING BELOW CUT OFF GRADE DUE TO POOR VEIN MINIRALIZATION. | W216: L05_JV_020E_ROBBING | X216: BIHAY 2 | Y216: ADDITIONAL SOURCE OF GOOD ORE. APPROVED ON SEPT. 9, 2019. CLEANING IS STILL ON-GOING FOR THE CHARGING OF EXPLOSIVES. START ROBBING OF SILL ON SEPT 10, 2019. CHANGE STATUS ON OCT. 10 2019 TOPSLICE TO SILL PILAR. Stopped on oct 29, 2019 already mined out.
B217: L05_DPVE_041E_STOPE PREP | C217: BAYOBAY 1 | D217: REPLACEMENT OF L05_DPVE_041E_RAISE. APPROVED ON AUG. 4 2020. STOPPED ON SEPT. 9 2020 CONVERTED TO ACTIVE BREAKING STOPE. | E217: L05_JV_018E_STOPE | F217: BALDO 2 | G217: REPLACEMENT OF L05 JV 018E STOPE PREP ON DECEMBER 13, 2018. STOPPED ON MARCH 7,2019 3RD SHIFT ALREADY REACHED THE LEVEL 4 ELEVATION AT THE SAME TIME CONVERT TO PULL-OUT CLEANING. | H217: L05_CTV_013E_STOPE | I217: BALDO 2 | J217: REPLACEMENT OF L05_CTV_013E_STOPE_PREP APPROVED ON NOV 6, 2019. TRANSFERRED ON DEC. 23 2019 FROM BALDO 2 TO FERNANDEZ RX 2. TRANSFERRED ON JANUARY 6, 2020 FROM FERNANDEZ RX 2 TO BALDO 2.CONVERTED TO PULL OUT CLEANING ON FEB 3, 2020. STOPPED ON MARCH 5 2020 ALREADY MINED OUT | K217: L05_JV_027E_DE | L217: MAPAYO 1 | M217: REPLACEMENT OF L05_JV_028E_WINZE. APPROVED ON FEB 5 2021.THE VEINS LATERAL EXTENSION TOWARDS EAST CONTINUES TO PINCHED TO 0.10M VEIN WIDTH DUE TO PARALLEL & CROSS-CUTTING FAULT.STOPPED ON APRIL 24, 2021. OFF VEIN. | N217: L05_DPVE_034E_RAISE | O217: PANCIT NOEL 3 | P217: ADDITIONAL VERTICAL DEVELOPMENT. APPROVED ON SEPT. 29 2020. stopped on DECEMBER 2 2020 DUE TO ALREADY REACHED THE RECOMMENDED TARGET. | Q217: L05_CTV_043W_WINZE | R217: OY-YOY 1 | S217: REPLACEMENT OF L05 GHV 030W WINZE STOPE.APPROVED ON JUNE 19, 2019. TEMP. STOPPED ON JULY 18, 2019 TO PRIORITZED CROWN PILLAR.CHANGE TEAM LEADER FROM AMAC 2 TO OY-YOY ON AUGUST 13, 2019 ON THE SAME TIME RESUMED.TEMP. STOPPED ON NOV. 7, 2019. RESUMED ON DEC 2, 2019. STOPPED ON JANUARY 16 2020 DUE TO CONSECUTIVE PRODUCING BELOW CUT OFF GRADE. | W217: L05_GHV_012W_ROBBING | X217: FERNANDEZ RX 4 | Y217: REPLACEMENT OF L05 CTV 009E ROBBING. APPROVED ON FEB 26, 2019. STOPED ON JULY 8, 2019 DUE TO UNSAFE CONDITION.
B218: L05_JV_029E_STOPE PREP | C218: SHEPHERD AF | D218: REPLACEMENT OF L05_JV_029E_RAISE.APPROVED ON JULY 10, 2020. STOPPED ON AUGUST 25 2020 CONVERTED TO ACTIVE BREAKING. | E218: L05_GHV_030W_WINZE STOPE | F218: AMAC 2 | G218: REPLACEMENT OF L05 GHV 030W WINZE STOPE PREP. APRROVED ON SEPTEMBER 14, 2018. STOPPED BREAKING AND CONVERT TO STOPE CLEANING. | H218: L05_CV_004W_WINZE STOPE | I218: SHEPHERD L | J218: REPLACEMENT OF L05_CV_004W_WINZE STOPE PREP.APPROVED ON JULY 29, 2019-LTS.TEMPORARY STOPPED ON SEPT 25, 2019 DUE TO DIFECTED AIR HOIST. RESUMED ON OCTOBER 3, 2019. STOPPED AND CONVERT TO ACTIVE PULL-OUT CLEANING ON OCT 18, 2019. STOPPED ON NOV 18, 2019 ALREADY FINISHED PULL-OUT. | K218: L05_DPVE_042E_DW | L218: PANCIT, NOEL 3 | M218: REPLACEMENT OF L05_DPVE_042E_DE. APPROVED ON JUNE 3 2020.TRANSFER FROM PMC MINERS 1 TO PANCIT, NOEL 3 FORMER TEAM WAS TRANSFERRED TO SPECIAL PROJECT ON AUGUST 17 ,2020. TEMP. STOPPED ON SEPT. 16 2020 STOPE PREP ONGOING. Resumed on sept. 28 2020. Temporary stopped on November 28,2020 to do follow up raise. resumed on 12/2/20. temporary stopped on Dec 26 2020 to prioritized dpve 034e stope prep | N218: L05_CTV_027W_RAISE | O218: SHEPHERD AD 3 | P218: ADDITIONAL VERTICAL DEVELOPMENT. APPROVED ON SEPT. 28 2020. RENAMED FROM 29W TO 027W RAISE ON OCT. 22 2020. STOPPED ON NOV 9 2020 DUE TO CONSECUTIVE LOW ASSAY GRADE ON CUT SAMPLES /BULK SAMPLE. | Q218: L05_CTV_037E_WINZE | R218: OY-YOY 1 | S218: FILL WINZE TO BE CONNECTED TO OLD STOPE OF LEVEL 7.APPROVED ON NOV 28, 2019. Stopped on Nov. 30, 2019. | W218: L05_CV_023W_ROBBING | X218: PANCIT 6 | Y218: ADDITIONAL, APPROVED ON APRIL 20, 2018/SDNC. TEMPORARY STOPPED BREAKING ON MAY 7, 2018 TO DO MAINLINE CLEANING. RESUMED ON MAY 22, 2018. TEMPORARY STOPPED ON SEPT. 1, 2018; CONVERTED TO STOPE BREAKING. RESUMED ON FEBRUARY 6, 2019. TEMPORARY STOPPED ON MAR 21, 2019 TO PRIORITIZE L5 CV 21W DW AS ACCESS. RESUMED ON MAR 28, 2019. STOPPED BREAKING THE SILL PILLAR ON JUNE 29, 2019.
B219: L05_CTV_039E_WINZE STOPE PREP | C219: SHEPHERD Z.2 | D219: REPLACEMENT OF L05_CTV_039E_DE. APPROVED ON JUNE 8 2020. STOPPED ON JUNE 23 2020 CONVERTED TO ACTIVE BREAKING | E219: L05_GHV_032W_STOPE | F219: ESPADA 1 | G219: REPLACEMENT OF L05 GHV 032W STOPE PREP. APPROVED ON MARCH 21, 2019. CONVERTED TO PULL OUT CLEANING ON MAR 27, 2019 | H219: L05_NV_009E_STOPE | I219: BIHAY 2 | J219: REPLACEMENT OF L05 NV 008E STOPE PREP. APPROVED ON JUNE 6,2019. RENAMED FROM L05_NV_008E_STOPE TO L05 NV 009E STOPE TO AVOID MISCHARGING TO LEVEL 4 GHVFW 008E WINZE STOPE ON JUNE 21, 2019. STOPPED BREAKING ON AUGUST 15, 2019 AND IN SAME TIME CONVERT TO PULL OUT CLEANING DUE TO PINCHED OUT OF VEIN. STOPPED ON AUGUST 30, 2019 DUE TO CONSECUTIVE LOW ASSAY GRADES ON CUT SAMPLES. | K219: L05_CTV_039E_DE | L219: SHEPHERD Z.2 | M219: REPLACEMENT OF L05_CTV_039E_WINZE. APPROVED ON APRIL 6 2020.STOPPED ON MAY 19 2020 DUE TO PINCHED OUT VEIN. Resumed on May 29,2020.Stopped on May 30 2020. intercepted to an Old Raise. Resumed on June 2 2020. STOPPED ON JUNE 8 2020 TO PROCEED STOPE PREP. Resumed on Sept. 15 2020. Stopped on Oct 31 2020.Already finished ISL. Temporary stopped on December 22,2020 delay due to stope prep. | N219: L05_GHV_033W_RAISE | O219: SHEPHERD AD 2 | P219: REPLACMENT OF L05 GHV 033W ROBBING. APPROVED ON AUGUST 20,2020. STOPPEDON OCT 5 2020 ALREADY MADE A BREAK THROUGH. resumed on Oct 8 2020 to do inclined raise at East side. STOPPED ON OCT. 23 2020 ALREADY BREAKTHROUGH | Q219: L05_GHVFW_012W_WINZE | R219: BADBADON L 8 | S219: REPLACEMENT OF L05 JV 025W DW.APPROVED ON JULY 3, 2019. STOPPED ON SEPT. 16, 2019 DUE TO CONSECUTIVE LOW ASSAY GRADE.RESUMED ON NOV 8, 2019.TEMP STOPPED ON NOV. 26, 2019 DUE TO DIFFECTIVE AIR HOST. RESUMED ON JANUARY 7, 2020. STOPPED ON JANUARY 27 2020 DUE TO CONSECUTIVELY PRODUCING BELOW CUT OFF GRADE DUE TO POOR VEIN MINIRALIZATION. | W219: L05_EDV_001E_ROBBING | X219: SHEPHERD P | Y219: ADDITIONAL PRODUCTION.APPROVED ON APRIL 1, 2019. CONVERT TO SILL PILLAR ROBBING ON MAY 9,2019. STOPPED ON JUNE 11, 2019 DUE TO ALREADY FINISHED ROBBING THE SILL PILLAR.
B220: L05_CTV_006E_STOPE PREP | C220: CAYABAS 2 | D220: REPLACEMENT OF L05_CTV_006E_RAISE. APPROVED ON DECEMBER 6, 2019. STOPPED RECOMMENDED FOR ACTIVE STOPE BREAKING ON JANUARY 8 2020. | E220: L05_CTV_008W_STOPE | F220: SHEPHERD P | G220: REPLACEMENT OF L05 CTV 008W RAISE. APPROVED ON NOVEMBER 29,2018. CONVERTED TO BREAKING ON JANUARY 25, 2019.CONVERTED TO PULL-OUT ON 4/9/19-LTS. | H220: L05_GHV_034W_STOPE | I220: FERNANDEZ RX 5 | J220: REPLACEMENT OF L05_GHV_034W_STOPE PREP ON JUNE 17, 2019.STOPPED ON AUGUST 15, 2019 CONVERT TO PULL-OUT CLEANING. STOPPED ON AUGUST 24, 2019 ALREADY MINE OUT. | K220: L05_CTV_030W_DE | L220: SHEPHERD AF.3 | M220: REPLACEMENT OF L05_CV_030W_WINZE. APPROVED ON MARCH 10 2020. TRANSFERRED FROM ESPADA 1 TO NOCOS 1 ON MAY 26 2020. TEMPORARY STOPPED ON JUNE 12 2020. RESUMED ON JUNE 18 2020. TEMPORARY STOPPED ON JUNE 22 2020 REHAB HEAD ROOM AND AIR HOIST AREA. Resume on June 29 2020. TEMPORARY STOPPED ON JULY 4 2020 DUE TO DEFCTED AIRHOIST.resumed on August 6,2020 at the same time transfer from NOCOS 1 TO SHEPHERD AF 3. RENAMED ON SEPT. 23 2020 FROM L05_CV_030W_DE TO L05_CTV_030W_DE. stopped on OCt 21 2020. approaching to 30e VENT RAISE EXCLUSION ZONE | N220: L05_DPVE_036E_RAISE | O220: PANCIT NOEL 1 | P220: REPLACEMENT OF L05_DPVE_038E_RAISE. APPROVED ON AUG. 6 2020. temporary stopped on August 11 2020 not yet started.Resumed on August 12,2020. Stopped on September 15,2020 off vein, cut by fault | Q220: L05_CV_010E_WINZE | R220: SHEPHERD L | S220: REPLACEMENT OF L05 CV 005W WINZE.APPROVED ON JANUARY 23, 2019.STOPPED DUE TO LOW ASSAY GRADE ON MARCH 18, 2019. REPLACEMENT OF L05_CV_004W_ROBBING. APPROVED ON JANUARY 24 2020. Stopped on February 1,2020 due to unsafe condition convert to intermediate sublevel. | W220: L05_GHV_022W_ROBBING | X220: BADBADON L.4 | Y220: ADDITIONAL SOURCE OF GOOD ORE.APPROVED ON SEPTEMBER 11, 2018.TEMP.STOP FEB 22, 2019 TO PRIORITIZE SINKING MEMO FROM OPS. RESUMED ON JUNE 10,2019. TOPSLICE.STOPPED ON JUNE 11, 2019 DUE TO UNSAFE CONDITION.
B221: L05_JV_033E_STOPE PREP | C221: CAYABAS 1 | D221: REPLACEMENT OF L05_JV_033E_DW APPROVED ON NOV 19, 2019. STOPPED ON DECEMBER 13, 2019 CONVERT TO ACTIVE BREAKING. | E221: L05_JVFW_012W_STOPE | F221: FERNANDEZ RX 3 | G221: REPLACEMENT OF L05 JVFW 012W STOPE PREP. APPROVED ON MAY 12,2019. STOPPED ON JULY 19, 2019 DUE TO PINCHING OUT THE VEIN CONVERT TO PULL-OUT CLEANING. | H221: L05_JVFW_012W_STOPE | I221: FERNANDEZ RX 3 | J221: REPLACEMENT OF L05 JVFW 012W STOPE PREP. APPROVED ON MAY 12,2019. STOPPED ON JULY 19, 2019 DUE TO PINCHING OUT THE VEIN CONVERT TO PULL-OUT CLEANING. STOPPED ON AUGUST 20, 2019 DUE TO ALREADY MINED OUT. | K221: L05_CTV_002W_DW | L221: MAPAYO 3 | M221: REPLACEMENT OF L05_CTV_002W_DW.APPROVED ON AUG. 14, 2020. TEMPORARY STOPPED ON AUGUST 25 2020. Resumed on Sept. 8 2020. STOPPED ON SEPT. 29 2020 DUE TO LOW GRADE. | N221: L05_DPVE_037E_RAISE | O221: PMC MINERS 2 | P221: ADDITIONAL INCLINED RAISE DEVOPMENT. APPROVED ON JULY 29 2020. stopped on August 17 2020 due to lack of manpower. | Q221: L05_CV_002W_WINZE | R221: GEMENTIZA 1 | S221: FILL WINZE TO BE CONNECTED TO OLD STOPE APPROVED ON JULY 10, 2019. STOPPED ON AUGUST 13, 2019 DUE TO ALREEADY CONNECTED TOWARDS L06_CV_2W_STOPE. RESUMED ON DECEMBER 4, 2019 IN THE SAME TIME TRANSFERRED FROM FERNADEZ RX.4 TO GEMENTIZA 1. TEMPORARY stopped on January 23 2020 due to incapable to operate the heading. | W221: L05_JV_016W_ROBBING | X221: FERNANDEZ RX 3 | Y221: REPLACEMENT OF L05 NONE 015W XCN APPROVED ON NOVEMBER 8, 2018.TEMP. STOPPED ON GOING MAINLINE CLEANING ON NOVEMBER 16, 2018. RESUMED ON NOVEMBER 29, 2018 AS PER JRABOSA. STOPPED ON JANUARY 11, 2019 DUE TO PINED-OUT OF VEIN.
... B233: L05_NV_008E_STOPE PREP | C233: BIHAY 2 | D233: REPLACEMENT OF L05 NV 008E RAISE. APPROVED ON MAY 15,2019.STOPPED CONVERT TO ACTIVE BREAKING ON JUNE 6, 2019. | E233: L05_JV_031E_WINZE STOPE | F233: SAMBERE 1 | G233: REPLACEMENT OF L05_JV_031E_WINZE STOPE PREP APPROVED ON APRIL 14, 2021. Stopped on breaking on May 11,2021 convert to pull out cleaning already reached the recommended pillar. | H233: L05_CTV_013E_WINZE STOPE | I233: SHEPHERD W | J233: REPLACEMENT OF L05 CTV 013E WINZE STOPE PREP. APPROVED ON NOV. 11 2020. Stopped breaking on Dec. 4 2020 converted to pull out cleaning. Stopped on January 5 2021 already mined out. | K233: L05_GHVSPLIT_030E_DW | L233: CAYABAS 1 | M233: REPLACEMENT OF L05 NONE 026E XCN. APPROVED ON DECEMBER 4, 2018. STOPPED ON JAN 9, 2019 | N233: L05_CTV_009W_RAISE | O233: SHEPHERD P | P233: REPLACEMENT OF L05 CTV 007W STOPE PREP. APPROVED ON MARCH 26, 2019. INCLINED RAISE.STOP ON 4/11/19-LTS, LOW ASSAY GRADE RESULT. | Q233: L05_CTV_012W_WINZE | R233: SHEPHERD AF 2 | S233: ADDITIONAL VERTICAL DEVELOPMENT. APPROVED ON MARCH 13, 2023. FILL WINZE. STOPPED ON APRIL 14, 2023, AT 13 METER ELEVATION BUT DID NOT BREAKTHROUGH YET. | W233: L05_CV_001W_ROBBING | X233: ALMEDORA 1 | Y233: ADDITIONAL PRODUCTION TONNAGE. APPROVED ON 3/25/19. STOPPED ON 5/27/19-LOC, ALREADY FINISHED.
B234: L05_GHV_034W_STOPE PREP | C234: FERNANDEZ RX 5 | D234: REPLACEMENT OF L05 GHV 034W RAISE. APPROVED ON MAY 10,2019. TEMPORARY STOPPED ON MAY 11,2019 DUE TO UNAVAILABILITY IF MUCKING MACHINE. RESUMED ON MAY 15,2019. STOPPED ON JUNE 17, 2019 CONVERTED TO ACTIVE BREAKING. | E234: L05_CTV_015E_WINZE STOPE | F234: SHEPHERD AM 1 | G234: replacement of L05_CTV_015E_WINZE STOPE PREP. Approved on April 30, 2021.STOPPED ON MAY 13, 2021 CONVERT TO PULL OUT CLEANING. | H234: L05_DPVE_038E_STOPE | I234: PANCIT NOEL 1 | J234: REPLACEMENT OF L05_DPVE_038E_STOPE PREP. APPROVED ON OCT. 10 2020. Convert to pull out cleaning on November 19,2020 due to exclusion zone at the decline. STOPPED ON JAN 5 2021, ALREADY MINED OUT. | K234: L05_GHV_037W_DE | L234: COMAINGKING 1 | M234: REPLACEMENT OF L05 GHV 038W DW. APPROVED ON JANUARY 20,2019. STOPPED ON JANUARY 30, 2019 DUE TO PINCHED OUT OF VEIN. | N234: L05_RYV_025E_RAISE | O234: ALMEDORA 2 | P234: REPLACEMENT OF L05 CV 003W STOPE PREP. APPROVED ON MARCH 26, 2019.STOP ON 4/9/19-LTS, VEIN PINCH OUT. | W234: L05_JVFW_006E_ROBBING | X234: DAVOCOL ROW 2 | Y234: ADDITIONAL PRODUCTION.APPROVED ON APRIL 1, 2019. TEMPORARY STOPPED ON APRIL 18,2019 TO PRIORITIZED EXPLORATORY CROSSCUT. RESUMED ON JUNE 8, 2019. STOPPED BREAKING ON JUNE 29, 2019
B235: L05_GHVFW_029W_WINZE STOPE PREP | C235: COMAINGKING 1 | D235: REPLACEMENT OF L05_GHVFW_029W_DW. APPROVED ON AUGUST 15, 2019. STOPPED ON NOV. 4, 2019 DUE TO COSECUTIVE LOW ASSAY GRADES ON CUT SAMPLES/BULK SAMPLES/PINCHED OUT VAIN. | E235: L05_JV_029E_STOPE | F235: PANCIT, NOEL 3 | G235: REPLACEMENT OF L05_JV_029E_STOPE PREP. APPROVED ON AUGUST 25 2020. TRANSFERRED FROM SHEPHERD AF TO PANCIT NOEL 2 ON NOV. 12 2020. TRANSFERRED FROM PANCIT NOEL 2 TO SHEPHERD MINERS AK ON NOV. 27 2020. TEMPOPRARY STOPPED ON FEB 01, 2021 MANPOWER TRANSFERRED TO LEVEL 7. RESUME ON APRIL 5, 2021.TRANSFERRED FROM SHEPHERD AK1 TO PANCIT NOEL ON 4/29/2021. STOPPED ON MAY 14,2021 DUE TO UNSAFE CONDITION CONVERT TO PULL OUT CLEANING. | H235: L05_JV_031E_WINZE STOPE | I235: SAMBERE 1 | J235: REPLACEMENT OF L05_JV_031E_WINZE STOPE PREP APPROVED ON APRIL 14, 2021. Stopped on breaking on May 11,2021 convert to pull out cleaning already reached the recommended pillar. STOPPED ON MAY 22,2021 ALREADY MINED OUT. | K235: L05_NV_011E_DW | L235: BIHAY 1 | M235: REPLACEMENT OF L05 CTV 029E RAISE. APPROVED ON 1-8-2019. TRANSFER FROM ALMEDORA TO BIHAY 1, APPROVED ON JAN 31, 2019. STOPPED ON FEBRUARY 20,2019 ALREADY REACHED THE TARGET VEIN REPLACED BY L05 NV 010E DW. | N235: L05_CTV_007W_RAISE | O235: SHEPHERD P 1 | P235: ADDITIONAL VERTICAL DEVELOPMENT. INCLINED RAISE. APPROVED ON FEB 21, 2019. MZC. TEMP. STOPPED ON MARCH 8, 2019 DUE TO HIT AN OLD ROCKBOLT THAT COMES FROM OLD DRILLING CHAMBER AND TO RESURVEY THE RAISE IN ORDER TO KNOW THE ELEVATION AND PILLAR FROM OLD DRILLING CHAMBER. | W235: L05_CV_003E_ROBBING | X235: ALMEDORA 1 | Y235: REPLACEMENT OF L05_CV_001W_ROBBING ON JUNE 7, 2019. STOPPED BREAKING THE CROWN PILLAR ANG HAULING OF BROKEN MATERIALS ON JUNE 29, 2019.
B236: L05_CTV_013E_STOPE PREP | C236: BALDO 2 | D236: REPLACEMENT OF L05_CTV_013E_RAISE.APPROVED ON SEPT. 16, 2019.STOPPED ON NOV. 6, 2019 CONVERTED TO STOPE BREAKING. | E236: L05_JV_032E_WINZE STOPE | F236: SAMBERE 1 | G236: REPLACEMENT OF L05_JV_032E_WINZE STOPE PREP.APPROVED ON JULY 16, 2021.STOPPED ON JULY 26, 2021 CONVERT TO PULL OUT. | H236: L05_CTV_015E_WINZE STOPE | I236: SHEPHERD AM 1 | J236: replacement of L05_CTV_015E_WINZE STOPE PREP. Approved on April 30, 2021.convert to pull out cleaning on may 13, 2021.STOPPED ON JUNE 2, 2021 FINISHED HEADINGS. | K236: L05_GHVSPLIT_029W_DW | L236: ESPADA 1 | M236: REPLACEMENT OF L05 GHVS 030W DW. APPROVED ON FEB. 22, 2019. MZC. STOPPED ON MARCH 11,2019 DUE TO VEIN PINCHED OUT. | N236: L05_JVHW_007E_RAISE | O236: BALDO 1 | P236: REPLACEMENT OF L05 JVHW 007E DE. APPROVED ON NOVEMBER 26,2018. STOPPED ON JANUARY 25, 2019 DUE TO VEIN PINCHED OUT. | W236: L05_NV_002E_ROBBING | X236: BALDO 2 | Y236: REPLACE OF L05 NV 007E RAISE ON MAY 22, 2019.CONVERT TO SILL PILLAR ON JUNE 10, 2019. STOPPED ON JUNE 27, 2019 DUE TO ALREADY MINE OUT.
B237: L05_GHVSPLIT_032W_WINZE STOPE PREP | C237: BADBADON L2 | D237: REPLACEMENT OF L05_GHVSPLIT_033W_DE. APPROVED ON SEPT 13, 2019. RENAMED ON SEPT 19, 2019 FROM L05_GHVSPLIT_032E_WINZE STOPE PREP TO L05_GHVSPLIT_032W_WINZE STOPE PREP.RECOMMENDED TO CONVERT ACTIVE BREAKING ON NOV. 6 2019. | E237: L05_JV_027E_WINZE STOPE | F237: MAPAYO 1 | G237: REPLACEMENT OF L05_JV_027E_RAISE. APPROVED ON MAY 24,2021.STOPPED ON JUNE 29,2021 AT THE SAME TIME CONVERTED TO STOPE BREAKING. STOPPED ON AUGUST 18, 2021 CONVERTED TO PULL OUT. | H237: L05_JV_029E_STOPE | I237: PANCIT, NOEL 3 | J237: REPLACEMENT OF L05_JV_029E_STOPE PREP. APPROVED ON AUGUST 25 2020. TRANSFERRED FROM SHEPHERD AF TO PANCIT NOEL 2 ON NOV. 12 2020. TRANSFERRED FROM PANCIT NOEL 2 TO SHEPHERD MINERS AK ON NOV. 27 2020. TEMPOPRARY STOPPED ON FEB 01, 2021 MANPOWER TRANSFERRED TO LEVEL 7. RESUME ON APRIL 5, 2021.TRANSFERRED FROM SHEPHERD AK1 TO PANCIT NOEL ON 4/29/2021. STOPPED ON MAY 14,2021 DUE TO UNSAFE CONDITION CONVERT TO PULL OUT CLEANING.STOPPED ON JUNE 11, 2021 ALREADY MINED OUT. | K237: L05_JVFW_006E_DE | L237: DAVOCOL ROW 1 | M237: REPLACEMENT OF L05 JVFW 005E WINZE STOPE PREP. APPROVED ON FEB 27, 2019.STOPPED DUE TO CUT BY FAULT ON MARCH 23, 2019 | N237: L05_GHVSPLIT_030E_RAISE | O237: CAYABAS 1 | P237: REPLACEMENT OF L05_GHVSPLIT_030E_DW. APPROVED ON JAN 10, 2019.STOPPED CONNECTED TO OLD STOPE ON JANUARY 23, 2019 | W237: L05_CTV_038W_ROBBING | X237: BADBADON L.4 | Y237: REPLACEMENT OF L05 GHW 022W ROBBING ON JUNE 11, 2019. HANDMUCKING ACTIVITY AS PER LEOMAR FRAGINAL. STOPPED ON JULY 4, 2019 DUE TO CONSECUTIE LOW ASSAY GRADES ON CUT SAMPLES/BUK SAMPES.
B238: L05_CTV_012W_WINZE STOPE PREP | C238: SHEPHERD W | D238: REPLACEMENT OF L05_CTV_012W_RAISE. APPROVED ON JUNE 17 2020. STOPPED ON JULY 21 2020 CONVERTED TO ACTIVE BREAKING | E238: L05_DPVE_047E_STOPE | F238: BAYOBAY 1 | G238: REPLACEMENT OF L05_DPVE_047E_STOPE.APPROVED ON JULY 12, 2021. THIS WORKHEADING AS STOPE BRK. IS BELOW THE OLD INCLINED RAISE EVAL. ON AUGUST 12, 2021.STOPPED ON AUGUST 17,2021 UNSAFE CONDITION | H238: L05_DPVE_025E_STOPE | I238: PANCIT, NOEL 2 | J238: RESUMED PULL-OUT ON AUG. 25, 2021. Temporary stopped Aug 25 | K238: L05_GHVHW_042W_DE | L238: FERNANDEZ RX 5 | M238: REPLACEMENT OF L05 JV 014W ROBBING.APPROVED ON FEBRUARY 19, 2019. TEMP STOPPED ON 2/26/19 TO EVALUATE FURTHER SINCE DRIVE IS WITHIN THE EXCLUSION ZONE OF BAGUIO SHAFT. RESUMED ON FEBRUARY 28,2019. STOPPED ON MARCH 22, 2019. | N238: L05_GHV_032W_RAISE | O238: ESPADA 1 | P238: REPLACEMENT OF L05_CTV3_051W_STOPE APPROVED ON JAN 9, 2019. STOPPED ON FEBRUARY 5,2019 DUE TO BREAKTHROUGH. | W238: L05_EDV_008W_ROBBING | X238: SHEPHERD P2 | Y238: ADDITIONAL GOOD SOURCE OF ORE APPROVED ON JUNE 27, 2019. STOPPED ON JULY 10, 2019 DUE TO CONSECUTIVE LOW ASSAY GRADE.
B239: L05_DPVE_038E_STOPE PREP | C239: PANCIT NOEL 1 | D239: REPLACEMENT OF L05_DPVE_036E_RAISE. APPROVED ON SEPT. 16 2020. STOPPED ON OCT. 1 2020 CONVERTED TO ACTIVE BREAKING. | E239: L05_DPVE_025E_STOPE | F239: PANCIT, NOEL 2 | G239: REPLACEMENT OF L05 DPVE 028E STOPE. APPROVED ON JULY 28, 2021. CONVERT TO STOPE BREAKING ON AUGUST 12, 2021. STOPPED ON AUGUST 21, 2021 DUE TO VERY UNSAFE CONDITION, GEOTECH EVALUATES THE STOPE. | H239: L05_DPVE_047E_STOPE | I239: BAYOBAY 1 | J239: REPLACEMENT OF L05_DPVE_047E_STOPE.APPROVED ON JULY 12, 2021. THIS WORKHEADING AS STOPE BRK. IS BELOW THE OLD INCLINED RAISE EVAL. ON AUGUST 12, 2021.STOPPED ON AUGUST 17,2021 UNSAFE CONDITION.CONVERTO TO PULL-OUT CLEANING STARTING ON 8/20/2021. stopped on Sept. 8, 2021 | K239: L05_JVSPLIT_005E_DW | L239: DAVOCOL ROW 1 | M239: REPLACEMENT OF L05 JVFW 006E DE.APPROVED ON MARCH 23, 2019. STOPPED ON MAR 27, 2019. NO FURTHER VIEN TARGET | N239: L05_NV_005W_RAISE | O239: SHEPHERD P 1 | P239: REPLACEMENT OF L05 NONE 008E XCS.APPROVED ON JANUARY 23, 2019. RENAMED FROM L05 NV 004W RAISE. ON JAN 24, 2019. STOPPED ON FEB 21, 2019; LOW GRADE; MEMO RECEIVED. | W239: L05_CV_006W_ROBBING | X239: CAYABAS 1 | Y239: REPLACEMENT OF L05 JV 7E ROBBING, APPROVED ON 5/30/19-LOC.CONVERTED TO SILL PILLAR ON AUGUST 13, 2019. STOPPED ON SEPT 13, 2019 ALREADY REACHED THE RECOMMENDED STRIKE LENGTH.
B240: L05_DPVE_034E_STOPE PREP | C240: PANCIT, NOEL 3 | D240: REPLACEMENT OF L05_DPVE_042E_DW APPROVED ON DEC 21, 2020. Temporary stop on Feb 01, 2021 to resume L05_DPVE_033E_STOPE PREP & due to group will temporary assign at level 9 until agsao shaft resume its opearation.-resumed on March 25, 2021.STOPPED ON APRIL 5, 2021 CONVERT TO BREAKING. | E240: L05_CTV_037W_STOPE | F240: SHEPHERD AD 2 | G240: REPLACEMENT L05_CTV_037W_STOPE PREP. APPROVED ON SEPTEMBER 11, 2021.TEMPORARY STOPPED ON OCT 16, 2021 TO PRIORITIZE L05_JV_022E_STOPE. | H240: L05_CTV_026E_WINZE_STOPE | I240: PARAN 1 | J240: REPLACEMENT OF L05 CTV 026E DW, APPROVED ON JAN 11, 2022.CONVERT TO PULL-OUT CLEANING ON MARCH 5, 2022.MINED OUT ON MARCH 9 2022 | K240: L05_CV_021W_DW | L240: PANCIT 6 | M240: REPLACEMENT OF L05 CV 21W ROBBING .SERVES AS BYPASS TO ACCESS THE L05 CV 023W ROBBING. APPROVED ON MAR 21, 2019. STOPPED ON MAR 28, 2019. | N240: L05_GHV_025W_RAISE | O240: BADBADON L. 1 | P240: REPLACEMENT OF L05 NONE 027W XCN. APPROVED ON FEB 22, 2019. MZC.STOPPED ON FEB 27,2019. BREAKTHROUGH TO GHV 21W STOPE | W240: L05_JVFW_003E_ROBBING | X240: DAVOCOL ROW 2 | Y240: ADDITIONAL PRODUCTION.APPROVED ON APRIL 1, 2019. TEMPORARY STOPPED ON APRIL 18,2019 TO PRIORITIZED EXPLORATORY CROSSCUT. RESUMED ON JUNE 8, 2019. STOPPED BREAKING ON JUNE 29, 2019 RESUMED ON JULY 1,2019 CONVERT TO SILL PILLAR ROBBING. RENAMED FROM L05 JVFW 006E ROBBING TO L05 JVFW 003E ROBBING; TO AVOID MISCHARGING WITH L05 CV 006W ROBBING. STOPPED SILL PILLAR ON SEPT 9, 2019 PROCEED TO TOPSLICE. stopped on 9/26/09 already finished robbing crown pillar
B241: L05_DPVE_033E_STOPE PREP | C241: PANCIT, NOEL 3 | D241: REPLACEMENT OF L05_DPVE_040E_DE APPROVED JAN 13, 2021 TEMPORARY STOPPED ON JAN 30, 2021 MANPOWER TRANSFERRED TO OTHER LEVEL. Resume on Feb 01, 2021.STOPPED ON 04/06/21 CONVERTED TO BREAKING | E241: L05_JVSPLIT_036E_STOPE | F241: PANCIT, NOEL 4 | G241: REPLACEMENT OF L05_JVSPLIT_036E_STOPE PREP APPROVED ON OCT.9,2021.STOPPED ON OCT.15,2021.ALREADY DONE IPR, RESUMED ON OCT 19, 2021.STOPPED BREAKING, BREAKTHROUGH TO AN OLD STOP, CONVERT TO PULL OUT CLEANING OCT 27, 2021. | H241: L05_JVHW_006W_STOPE | I241: PANCIT,NOEL 3 | J241: REPLACEMENT OF L05_JVHW_006W_STOPE PREP. APPROVED ON JUNE 17, 2022.STOPPED ON AUGUST 16, 2022, AT THE SAME TIME CONVERTED TO ACTIVE PULLOUT.APPROVED ON AUGUST 16, 2022. STOPPED AND MINED-OUT ON AUGUST 27, 2022 WITH 96% PULL-OUT MC. | K241: L05_CV_007W_DW | L241: CAYABAS 2 | M241: ADDITTIONAL HORIZONTAL DEVELOPMENT. APPROVED ON FEB 25, 2019. MZC. TRANSFER FROM BIHAY 1 TO CAYABAS 2 APPROVED ON MARCH 12,2019. TRANSFER FROM CAYABAS 2 TO ESPADA 1 FORMER TL WILL TAKE OVER THE DEVELOPMENT RAISE. TRANSFER FROM ESPADA 1 TO CAYABAS 2 ON APRIL 2,2019 DUE TO LACK OF MANPOWER OF MR. ESPADA.STOP ON 4/5/19-LTS, DUE TO VEIN PINCH OUT. | N241: L05_CV_003W_RAISE | O241: ALMEDORA 2 | P241: REPLACEMENT OF L05 CV 002E STOPE.APPROVED ON JANUARY 23, 2019. RENAMED FROM L05 CV 003E RAISE. STOPPED ON MARCH 8, 2019 ALREADY CONNECTED TO THE OLD RAISE. | W241: L05_JV_027W_ROBBING | X241: BADBADON L4 | Y241: REPLACEMENT OF L05_NONE_027W_XCS.APPROVED ON AUGUST 3, 2019. STOPPED ON AUGUST 24, 2019 TOPSLICE CONVERTED TO SILL PILLAR. STOPPED ON OCTOBER 4, 2019 ALREADY BREAK THE RECOMMENDED STRIKE LENGTH OF SILL PILLAR TO ROBBING.
B242: L05_GHV_023W_WINZE STOPE PREP | C242: SHEPHERD AF | D242: ADDITIONAL SOURCE OF GOOD ORE. APPROVED ON SEPT. 8 2020. TEMPORARY STOPPED ON NOV 10 2020, DUE TO INSUFFICIENT MANPOWER.RESUMED ON 12/8/20.RECOMMENDED FOR ACTIVE STOPE BREAKING APPROVED ON 3/2/21 | E242: L05_JVFW_015W_WINZE_STOPE | F242: COMAINGKING 4 | G242: REPLACEMENT OF L05 JVFW 015W stope prep. CONVERT TO STOPE BREAKING ON SEPTEMBER 5, 2021. STOPPED ON NOV. 4, 2021 CONVERTED TO PULL OUT. | H242: L05_JV_005W_WINZE STOPE | I242: PARAN 1 | J242: STOPPED BREAKING ON APRIL 28, 2023, AT THE SAME TIME CONVERTED TO PULLOUT CLEANING, NO TRAVERSE DUE TO ITS UNSAFE CONDITION.STOPPED ON MAY 08, 2023. MINED OUT. | K242: L05_GHVHW_051W_DE | L242: PANCIT 9 | M242: REPLACEMENT OF L05 CV 011W ROBBING.APPROVED ON MARCH 8, 2019.STOP ON 4/8/19-SDNC, NO FURTHER VEIN TARGET. | N242: L05_JVFW_012W_RAISE | O242: FERNANDEZ RX 3 | P242: REPLACEMENT OF L05 JV 016W ROBBING.APPROVED ON JANUARY 17, 2019.STOPPED CONVERT TO STOPE PREP ON MARCH 18, 2019 | W242: L05_GHV_010W_ROBBING | X242: FERNANDEZ RX 6 | Y242: TO RECOVER REMAINING PILLARS,APPROVED ON FEB 17 2016.TRANSFERRED FROM FERNANDEZ, ROM TO FERNANDEZ, REX. ON AUG 1,2016. TEMPORARY STOPPED ON NOVEMBER 6, 2017 DUE TO LOW GRADE AS PER MEMO OF LEVEL GEOLOGIST. STOPPED ON NOV.08,2017 AS PER MG EDEZA (LOW GRADE).RESUMED ON APRIL 11, 2018/LTS. SAME TL. TEMPORARY STOPPED ON 10/2/18 TO EXCAVATE L05 GHV 018W RAISE (INCLINE RAISE) AS AN OREPASS FOR THE REMAINING PILLAR OF GHV 010W ROBBING. RESUMED ON NOV. 8, 2018. STOPPED ON SEPT. 12,2019. RESUMED ON 9/26/19. STOPPED ON OCTOBER 4, 2019 DUE TO UNSAFE CONDITION.
B243: L05_DPVE_028E_STOPE PREP | C243: PANCIT, NOEL 2 | D243: REPLACEMENT OF L05_DPVE_028E_RAISE. APPROVED ON MAY 24,2021.recommended o strictly charged broken material into waste from these dutes. STOPPED ON JUNE 11,2021 CONVERT TO ACTIVE BREAKING. | E243: L05_DPVE_025E_WINZE STOPE | F243: SHEPHERD AF 2 | G243: REPLACEMENT OF L05_DPVE_025E_WINZE STOPE PREP ON MARCH 9, 2022.STOPPED ON MARCH 15, 2022 DUE TO LOW CONSECUTIVE ASSAY GRADE | K243: L05_NV_010E_DW | L243: BIHAY 1 | M243: REPLACEMENT OF L05 NV 011E DW. APPROVED ON FEB 21, 2019. STOPPED ON APRIL 15,2019 DUE TO PINCHED OUT VEIN. | N243: L05_CV_004W_RAISE | O243: ALMEDORA 1 | P243: ADDITIONAL VERTICAL DEVELOPMENT. APPROVED ON FEB 21, 2019..STOPPED ALREADY REACHED THE RECOMMENDED STRIKE LENGTH ON MARCH 19, 2019 | W243: L05_GHV_023W_ROBBING | X243: BADBADON L4 | Y243: ADDITIONAL SOURCE OF GOOD ORE. APPROVED ON AUGUST 2, 2019. TEMPORARY STOPPED ON AUGUST 15, 2019 DUE TO SURRENDERED TEAM LEADER. RESUMED ON AUGUST 27, 2019 AT THE SAME TIME TRANSFERRED FROM AMAC 2 TO SHEPHERD P2. transferred from Shepherd P2 to Badbadon L4 on Oct 3, 2019.TEMP STOPPED ON NOV 8, 2019 TO PRIORITIZED CLEANING OF L05_GHV_023W_WINZE.
B244: L05_JV_032E_WINZE STOPE PREP | C244: SAMBERE 1 | D244: replacement of L05 JV 032E RAISE ISL. APPROVED ON JUNE 25, 2021.STOPPED ON JULY 14, 2021.AT THE SAME TIME CONVERT TO STOPE BREAKING. | E244: L05_JVHW_004E_STOPE | F244: BAYOBAY 2 | G244: REPLACEMENT OF L05 JVHW 004E STOPE PREP, APPROVED ON MAY 28, 2022. STOPPED BREAKING AND CONVERT TO PULL-OUT ON JULY 8, 2022. | K244: L05_GHV_019W_DE | L244: BADBADON L.4 | M244: REPLACEMENT OF L05 GHV 19W WINZE APPROVED ON APR 3 2018/LTS.STOP ON 4/26/19-LOC. | N244: L05_JVSPLIT_006E_RAISE | O244: BALDO 1 | P244: ADDITIONAL VERTICAL DEVELOPMENT. APPROVED ON JANUARY 30, 2019. MZC. TEMPORARY STOPPED ON FEBRUARY 6,2019 DUE TO MANPOWER PROBLEM AND AVAILABILITY OF MUCKING MACHINE.RESUME ON 2/11/19. STOPPED DUE TO VEIN PINCH-OUT 4/10/19-LTS. | W244: L05_CTV_002W_ROBBING | X244: FERNANDEZ RX 4 | Y244: ADDITIONAL PRODUCTION. APPROVED ON SEPTEMBER 4, 2019.STOPPED ON NOV 27, 2019 ALREADY MINED OUT.
B245: L05_DPVE_043E_STOPE PREP | C245: BAYOBAY 1 | D245: Replacement of L05_DPVE_043E_RAISE. Approved on Sept. 6, 2021.stopped on sept.24,2021 converted to breajing | E245: L05_CTV_028E_WINZE STOPE | F245: PARAN 1 | G245: REPLACEMENT OF L05_CTV_026E_WINZE STOPE PREP APPROVED ON AUGUST 15, 2022.CHANGE NAME FROM L05_CTV_026E_WINZE STOPE TO L05_CTV_028E_WINZE STOPE FOR PROPER NAMING APPROVED ON AUGUST 25, 2022. STOPPED BREAKING AND CONVERT TO STOPE PULL OUT ON AUGUST 27, 2022. | K245: L05_GHV_023W_DE | L245: BADBADON L. 3 | M245: REPLACMENT OF L05 GHV 023W WINZE. APPROVED ON MARCH 14,2019. STOP ON 5/7/19 DUE TO VEIN PINCHED OUT. | N245: L05_CV_006W_RAISE | O245: CAYABAS 2 | P245: ADDITIONAL VERTICAL DEVELOPMENT.APPROVED ON MARCH 30, 2019.STOPPED PINCHED OUT VIEN ON APRIL22, 2019 | W245: L05_CTV_015E_ROBBING | X245: SHEPHERD Z1 | Y245: REPLACEMENT OF L05_CTV_015E RAISE APPORVED ON JULY 31, 2019.-LTS. STOPPED TOPSLICE AND CONVERTED TO SILL PILLAR ON SEPT 4, 2019 WITH ONLY 10 METERS TO ROB. Already done robbing pillar stopped on Sept 11, 2019. RESUMED ON OCT. 10 2019 TO DRIVE TOPSLICE ROBBING. TRANSFERRED FROM SHEPHERD P 2 TO SHEPHERD Z1 BY MANAGEMENT ON OCT 23, 2019.STOPPED ON NOV 26, 2019 DUE TO UNSAFE CONDITION
B246: L05_JVSPLIT_036E_STOPE PREP | C246: PANCIT, NOEL 4 | D246: REPLACEMENT OF L05 JVSPLIT 036E RAISE. APPROVED ON OCT 1, 2021.STOPPED ON OCT.9,2021 | E246: L05_JVSPLIT_016W_WINZE STOPE | F246: PARAN 1 | G246: REPLACEMENT OF L05_JVSPLIT_016W_WINZE_STOPE PREP. CONVERTED TO ACTIVE BREAKING APPROVED ON OCTOBER 22, 2022.STOPPED BREAKING ON NOVEMBER 11, 2022. | K246: L05_NV_012E_DE | L246: BIHAY 1 | M246: REPLACEMENT OF L05 NV 010E DW. APPROVED ON APRIL 15,2019. STOPPED ON MAY 9,2019 TO AVOID BREAKTHROUGH AT 8E SHAFT. | N246: L05_NV_007E_RAISE | O246: BALDO 2 | P246: REPLACEMENT OF L05 JVFW 45E ROBBING, APPROVED ON 4/8/19-LTS. STOPPED ON MAY 6,2019 CONNECTED TO OLD STOPE. | W246: L05_GHV_030W_ROBBING | X246: COMAINGKING 2 | Y246: REPLACEMENT OF L05 NONE 038W XCN. APPROVED ON DECEMBER 4, 2019. STOPPED ON DEEMBER 9, 2019 DUE TO CONSECUTIVE LOW ASSAY GRADES ON CUT SAMPLES/ BULK SAMPLES.
B247: L05_JV_026E_WINZE STOPE PREP | C247: MAPAYO 1 | D247: REPLACEMENT OF L05_JVSPLIT_024E_DW_ISL. APPROVED ON MARCH 25,2022. STOPPED ON APRIL 13,2022 ALREADY FINISHED. | E247: L05_DPVE_051E_WINZE STOPE | F247: FERNANDEZ, RG 1 | G247: REPLACEMENT OF L05_DPVE_051E_WINZE STOPE PREP, CONVERTED TO ACTIVE BREAKING ON OCTOBER 6, 2022.TEMPORARRY STOPPED BREAKING ON OCT 27, 2022. DUE TO CONSECUTIVE LOW GRADE RESULT. NO PULL OUT OF MINE CARS. TO BE DONE YET.RESUMED ON NOVEMBER 11, 2022, TO CONDUCT IPR.TEMPORARILY STOPPED ON NOVEMBER 24, 2022 ALREADY FINISHED IPR. | K247: L05_CV_004W_DW | L247: SHEPHERD L | M247: REPLACEMENT OF L05 CV 004W WINZE . APPROVED ON MAR 28, 2019.TEMPORARY STOPPED ON JUNE 4, 2019.STOPPED ALREADY CONVERTED TO L05_CV_5W_WINZE STOPE PREP ON JUNE 4, 2019 | N247: L05_NV_008E_RAISE | O247: BIHAY 2 | P247: ADDITIONAL VERTICAL DEVELOPMENT.APPROVED ON MARCH 11, 2019. STOPPED ON MAY 14,2019 CONVERT TO STOPE PREPARATION. | W247: L05_DPVE_021E_ROBBING | X247: SHEPHERD Z.1 | Y247: ADDITIONAL PRODUCTION TONNAGE. APPROVED ON DECEMBER 2, 2019. STOPPED ON DECEMBER 11, 2019 DUE TO CONSECUTIVELY PRODUCING BELOW CUT OFF GRADE .
...

Sheet Final List
A1: ="ACTIVE WORKINGPLACES "&UPPER(TEXT(TODAY(),"mmmm")&" "&TEXT(TODAY(),"yyyy")) -> ACTIVE WORKINGPLACES JUNE 2026 | L1: z | V1: ROBBING PILLARS | W1: PRIORITY DRIFT | X1: PRIORITY RAISE | Y1: PRIORITY WINZE | Z1: PRIORITY XC | AC1: Infra Segregation
A2: STOPES | H2: DEVELOPMENT_(HORIZONTAL/VERTICAL) | P2: INFRA | R2: COLOR CODING | AC2: (For Dashboard)
B3: STOPE PREP | C3: TEAMLEADER | D3: BREAKING | E3: TEAMLEADER | F3: PULL_OUT | G3: TEAMLEADER | H3: DRIFT | I3: TEAMLEADER | J3: RAISE | K3: TEAMLEADER | L3: WINZE | M3: TEAMLEADER | N3: CROSSCUT | O3: TEAMLEADER | P3: PROJECT | Q3: TEAMLEADER | AC3: =IFERROR(INDEX(LIST2!$F:$F,MATCH(P3,LIST2!J:J,0),1),"")
A4: LEVEL 3 | P4: L03_GHV_053W_ROBBING | Q4: FERNANDEZ 6 | T4: WP W/ NO MAP | V4: =IF((RIGHT(P4,7)="ROBBING"),"ROBBING","") -> ROBBING | AC4: =IFERROR(INDEX(LIST2!$F:$F,MATCH(P4,LIST2!J:J,0),1),"") -> RobS 79
P5: L03_NONE_047E_MAINLINE CLEANING | Q5: FERNANDEZ | T5: TRANSFERED TEAM LEADER | V5: =IF((RIGHT(P5,7)="ROBBING"),"ROBBING","") | AC5: =IFERROR(INDEX(LIST2!$F:$F,MATCH(P5,LIST2!J:J,0),1),"") -> Dhoz 71
T6: NEW WP W/ MAP | V6: =IF((RIGHT(P6,7)="ROBBING"),"ROBBING","") | AC6: =IFERROR(INDEX(LIST2!$F:$F,MATCH(P6,LIST2!J:J,0),1),"")
T7: TEMP. STOPPED | V7: =IF((RIGHT(P7,7)="ROBBING"),"ROBBING","") | AC7: =IFERROR(INDEX(LIST2!$F:$F,MATCH(P7,LIST2!J:J,0),1),"")
T8: STOPPED | V8: =IF((RIGHT(P8,7)="ROBBING"),"ROBBING","") | AC8: =IFERROR(INDEX(LIST2!$F:$F,MATCH(P8,LIST2!J:J,0),1),"")
V9: =IF((RIGHT(P9,7)="ROBBING"),"ROBBING","") | AC9: =IFERROR(INDEX(LIST2!$F:$F,MATCH(P9,LIST2!J:J,0),1),"")
V10: =IF((RIGHT(P10,7)="ROBBING"),"ROBBING","") | AC10: =IFERROR(INDEX(LIST2!$F:$F,MATCH(P10,LIST2!J:J,0),1),"")
V11: =IF((RIGHT(P11,7)="ROBBING"),"ROBBING","") | AC11: =IFERROR(INDEX(LIST2!$F:$F,MATCH(P11,LIST2!J:J,0),1),"")
A13: SUBTOTAL | B13: =COUNTA(B4:B10) -> 0 | D13: =COUNTA(D4:D10) -> 0 | F13: =COUNTA(F4:F10) -> 0 | H13: =COUNTA(H4:H10) -> 0 | J13: =COUNTA(J4:J10) -> 0 | L13: =COUNTA(L4:L10) -> 0 | N13: =COUNTA(N4:N10) -> 0 | P13: =COUNTA(P4:P11) -> 2 | R13: =COUNTIF(V4:V10,"ROBBING") -> 1 | S13: ='FINAL LIST WITH REMARKS'!Z186 -> 15 | T13: =SUM(B13:Q13) -> 2 | U13: ='For Explo'!J26 -> 2 | V13: =COUNTIF(V4:V11,"ROBBING") -> 1 | W13: =COUNTA(W4:W10) -> 0 | X13: =COUNTA(X4:X10) -> 0 | Y13: =COUNTA(Y4:Y10) -> 0 | Z13: =COUNTA(Z4:Z10) -> 0 | AC13: =IFERROR(INDEX(LIST2!$F:$F,MATCH(P13,LIST2!J:J,0),1),"")
A14: LEVEL 4 | V14: =IF((RIGHT(P14,7)="ROBBING"),"ROBBING","") | W14: TOP | X14: TOP | Y14: TOP | Z14: TOP | AC14: =IFERROR(INDEX(LIST2!$F:$F,MATCH(P14,LIST2!J:J,0),1),"")
V15: =IF((RIGHT(P15,7)="ROBBING"),"ROBBING","") | W15: TOP | X15: TOP | Y15: TOP | AC15: =IFERROR(INDEX(LIST2!$F:$F,MATCH(P15,LIST2!J:J,0),1),"")
V16: =IF((RIGHT(P16,7)="ROBBING"),"ROBBING","") | AC16: =IFERROR(INDEX(LIST2!$F:$F,MATCH(P16,LIST2!J:J,0),1),"")
V17: =IF((RIGHT(P17,7)="ROBBING"),"ROBBING","") | AC17: =IFERROR(INDEX(LIST2!$F:$F,MATCH(P17,LIST2!J:J,0),1),"")
V18: =IF((RIGHT(P18,7)="ROBBING"),"ROBBING","") | AC18: =IFERROR(INDEX(LIST2!$F:$F,MATCH(P18,LIST2!J:J,0),1),"")
V19: =IF((RIGHT(P19,7)="ROBBING"),"ROBBING","") | AC19: =IFERROR(INDEX(LIST2!$F:$F,MATCH(P19,LIST2!J:J,0),1),"")
V20: =IF((RIGHT(P20,7)="ROBBING"),"ROBBING","") | AC20: =IFERROR(INDEX(LIST2!$F:$F,MATCH(P20,LIST2!J:J,0),1),"")
V21: =IF((RIGHT(P21,7)="ROBBING"),"ROBBING","") | AC21: =IFERROR(INDEX(LIST2!$F:$F,MATCH(P21,LIST2!J:J,0),1),"")
V22: =IF((RIGHT(P22,7)="ROBBING"),"ROBBING","") | AC22: =IFERROR(INDEX(LIST2!$F:$F,MATCH(P22,LIST2!J:J,0),1),"")
V23: =IF((RIGHT(P23,7)="ROBBING"),"ROBBING","") | AC23: =IFERROR(INDEX(LIST2!$F:$F,MATCH(P23,LIST2!J:J,0),1),"")
V24: =IF((RIGHT(P24,7)="ROBBING"),"ROBBING","") | AC24: =IFERROR(INDEX(LIST2!$F:$F,MATCH(P24,LIST2!J:J,0),1),"")
V25: =IF((RIGHT(P25,7)="ROBBING"),"ROBBING","") | AC25: =IFERROR(INDEX(LIST2!$F:$F,MATCH(P25,LIST2!J:J,0),1),"")
V26: =IF((RIGHT(P26,7)="ROBBING"),"ROBBING","") | AC26: =IFERROR(INDEX(LIST2!$F:$F,MATCH(P26,LIST2!J:J,0),1),"")
V27: =IF((RIGHT(P27,7)="ROBBING"),"ROBBING","") | AC27: =IFERROR(INDEX(LIST2!$F:$F,MATCH(P27,LIST2!J:J,0),1),"")
... V30: =IF((RIGHT(P30,7)="ROBBING"),"ROBBING","") | AC30: =IFERROR(INDEX(LIST2!$F:$F,MATCH(P30,LIST2!J:J,0),1),"")
A31: SUBTOTAL | B31: =COUNTA(B14:B30) -> 0 | D31: =COUNTA(D14:D30) -> 0 | F31: =COUNTA(F14:F30) -> 0 | H31: =COUNTA(H14:H30) -> 0 | J31: =COUNTA(J14:J30) -> 0 | L31: =COUNTA(L14:L30) -> 0 | N31: =COUNTA(N14:N30) -> 0 | P31: =COUNTA(P14:P30) -> 0 | R31: =COUNTIF(V14:V30,"ROBBING") -> 0 | S31: ='FINAL LIST WITH REMARKS'!Z186 -> 15 | T31: =SUM(B31:Q31) -> 0 | U31: ='For Explo'!J72 -> 0 | V31: =COUNTIF(V14:V30,"ROBBING") -> 0 | W31: =COUNTA(W14:W30) -> 2 | X31: =COUNTA(X14:X30) -> 2 | Y31: =COUNTA(Y14:Y30) -> 2 | Z31: =COUNTA(Z14:Z30) -> 1 | AC31: =IFERROR(INDEX(LIST2!$F:$F,MATCH(P31,LIST2!J:J,0),1),"")
A32: LEVEL 5 | V32: =IF((RIGHT(P32,7)="ROBBING"),"ROBBING","") | W32: TOP | X32: TOP | Y32: TOP | AC32: =IFERROR(INDEX(LIST2!$F:$F,MATCH(P32,LIST2!J:J,0),1),"")
V33: =IF((RIGHT(P33,7)="ROBBING"),"ROBBING","") | AC33: =IFERROR(INDEX(LIST2!$F:$F,MATCH(P33,LIST2!J:J,0),1),"")
V34: =IF((RIGHT(P34,7)="ROBBING"),"ROBBING","") | AC34: =IFERROR(INDEX(LIST2!$F:$F,MATCH(P34,LIST2!J:J,0),1),"")
V35: =IF((RIGHT(P35,7)="ROBBING"),"ROBBING","") | AC35: =IFERROR(INDEX(LIST2!$F:$F,MATCH(P35,LIST2!J:J,0),1),"")
V36: =IF((RIGHT(P36,7)="ROBBING"),"ROBBING","") | AC36: =IFERROR(INDEX(LIST2!$F:$F,MATCH(P36,LIST2!J:J,0),1),"")
V37: =IF((RIGHT(P37,7)="ROBBING"),"ROBBING","") | AC37: =IFERROR(INDEX(LIST2!$F:$F,MATCH(P37,LIST2!J:J,0),1),"")
V38: =IF((RIGHT(P38,7)="ROBBING"),"ROBBING","") | AC38: =IFERROR(INDEX(LIST2!$F:$F,MATCH(P38,LIST2!J:J,0),1),"")
V39: =IF((RIGHT(P39,7)="ROBBING"),"ROBBING","") | AC39: =IFERROR(INDEX(LIST2!$F:$F,MATCH(P39,LIST2!J:J,0),1),"")
V40: =IF((RIGHT(P40,7)="ROBBING"),"ROBBING","") | AC40: =IFERROR(INDEX(LIST2!$F:$F,MATCH(P40,LIST2!J:J,0),1),"")
V41: =IF((RIGHT(P41,7)="ROBBING"),"ROBBING","") | AC41: =IFERROR(INDEX(LIST2!$F:$F,MATCH(P41,LIST2!J:J,0),1),"")
V42: =IF((RIGHT(P42,7)="ROBBING"),"ROBBING","") | AC42: =IFERROR(INDEX(LIST2!$F:$F,MATCH(P42,LIST2!J:J,0),1),"")
V43: =IF((RIGHT(P43,7)="ROBBING"),"ROBBING","") | AC43: =IFERROR(INDEX(LIST2!$F:$F,MATCH(P43,LIST2!J:J,0),1),"")
V44: =IF((RIGHT(P44,7)="ROBBING"),"ROBBING","") | AC44: =IFERROR(INDEX(LIST2!$F:$F,MATCH(P44,LIST2!J:J,0),1),"")
... V49: =IF((RIGHT(P49,7)="ROBBING"),"ROBBING","") | AC49: =IFERROR(INDEX(LIST2!$F:$F,MATCH(P49,LIST2!J:J,0),1),"")
A50: SUBTOTAL | B50: =COUNTA(B32:B49) -> 0 | D50: =COUNTA(D32:D49) -> 0 | F50: =COUNTA(F32:F49) -> 0 | H50: =COUNTA(H32:H49) -> 0 | J50: =COUNTA(J32:J49) -> 0 | L50: =COUNTA(L32:L49) -> 0 | N50: =COUNTA(N32:N49) -> 0 | P50: =COUNTA(P32:P49) -> 0 | R50: =COUNTIF(V32:V49,"ROBBING") -> 0 | S50: ='FINAL LIST WITH REMARKS'!Z402 -> 3 | T50: =SUM(B50:Q50) -> 0 | U50: ='For Explo'!J115 -> 0 | V50: =COUNTIF(V32:V49,"ROBBING") -> 0 | W50: =COUNTA(W32:W49) -> 1 | X50: =COUNTA(X32:X49) -> 1 | Y50: =COUNTA(Y32:Y49) -> 1 | Z50: =COUNTA(Z32:Z49) -> 0 | AC50: =IFERROR(INDEX(LIST2!$F:$F,MATCH(P50,LIST2!J:J,0),1),"")
A51: LEVEL 6 | V51: =IF((RIGHT(P51,7)="ROBBING"),"ROBBING","") | W51: TOP | X51: TOP | Y51: TOP | AC51: =IFERROR(INDEX(LIST2!$F:$F,MATCH(P51,LIST2!J:J,0),1),"")
V52: =IF((RIGHT(P52,7)="ROBBING"),"ROBBING","") | W52: SILL | X52: SILL | AC52: =IFERROR(INDEX(LIST2!$F:$F,MATCH(P52,LIST2!J:J,0),1),"")
V53: =IF((RIGHT(P53,7)="ROBBING"),"ROBBING","") | W53: TOP | X53: TOP | AC53: =IFERROR(INDEX(LIST2!$F:$F,MATCH(P53,LIST2!J:J,0),1),"")
V54: =IF((RIGHT(P54,7)="ROBBING"),"ROBBING","") | W54: SILL | X54: SILL | AC54: =IFERROR(INDEX(LIST2!$F:$F,MATCH(P54,LIST2!J:J,0),1),"")
V55: =IF((RIGHT(P55,7)="ROBBING"),"ROBBING","") | W55: TOP | X55: TOP | AC55: =IFERROR(INDEX(LIST2!$F:$F,MATCH(P55,LIST2!J:J,0),1),"")
V56: =IF((RIGHT(P56,7)="ROBBING"),"ROBBING","") | AC56: =IFERROR(INDEX(LIST2!$F:$F,MATCH(P56,LIST2!J:J,0),1),"")
V57: =IF((RIGHT(P57,7)="ROBBING"),"ROBBING","") | AC57: =IFERROR(INDEX(LIST2!$F:$F,MATCH(P57,LIST2!J:J,0),1),"")
V58: =IF((RIGHT(P58,7)="ROBBING"),"ROBBING","") | AC58: =IFERROR(INDEX(LIST2!$F:$F,MATCH(P58,LIST2!J:J,0),1),"")
V59: =IF((RIGHT(P59,7)="ROBBING"),"ROBBING","") | AC59: =IFERROR(INDEX(LIST2!$F:$F,MATCH(P59,LIST2!J:J,0),1),"")
V60: =IF((RIGHT(P60,7)="ROBBING"),"ROBBING","") | AC60: =IFERROR(INDEX(LIST2!$F:$F,MATCH(P60,LIST2!J:J,0),1),"")
V61: =IF((RIGHT(P61,7)="ROBBING"),"ROBBING","") | AC61: =IFERROR(INDEX(LIST2!$F:$F,MATCH(P61,LIST2!J:J,0),1),"")
V62: =IF((RIGHT(P62,7)="ROBBING"),"ROBBING","") | AC62: =IFERROR(INDEX(LIST2!$F:$F,MATCH(P62,LIST2!J:J,0),1),"")
V63: =IF((RIGHT(P63,7)="ROBBING"),"ROBBING","") | AC63: =IFERROR(INDEX(LIST2!$F:$F,MATCH(P63,LIST2!J:J,0),1),"")
V64: =IF((RIGHT(P64,7)="ROBBING"),"ROBBING","") | AC64: =IFERROR(INDEX(LIST2!$F:$F,MATCH(P64,LIST2!J:J,0),1),"")
V65: =IF((RIGHT(P65,7)="ROBBING"),"ROBBING","") | AC65: =IFERROR(INDEX(LIST2!$F:$F,MATCH(P65,LIST2!J:J,0),1),"")
V66: =IF((RIGHT(P66,7)="ROBBING"),"ROBBING","") | AC66: =IFERROR(INDEX(LIST2!$F:$F,MATCH(P66,LIST2!J:J,0),1),"")
V67: =IF((RIGHT(P67,7)="ROBBING"),"ROBBING","") | AC67: =IFERROR(INDEX(LIST2!$F:$F,MATCH(P67,LIST2!J:J,0),1),"")
V68: =IF((RIGHT(P68,7)="ROBBING"),"ROBBING","") | AC68: =IFERROR(INDEX(LIST2!$F:$F,MATCH(P68,LIST2!J:J,0),1),"")
A69: SUBTOTAL | B69: =COUNTA(B51:B68) -> 0 | D69: =COUNTA(D51:D55) -> 0 | F69: =COUNTA(F51:F68) -> 0 | H69: =COUNTA(H51:H68) -> 0 | J69: =COUNTA(J51:J68) -> 0 | L69: =COUNTA(L51:L68) -> 0 | N69: =COUNTA(N51:N68) -> 0 | P69: =COUNTA(P51:P68) -> 0 | R69: =COUNTIF(V51:V68,"ROBBING") -> 0 | S69: ='FINAL LIST WITH REMARKS'!Z676 -> 0 | T69: =SUM(B69:Q69) -> 0 | U69: ='For Explo'!J158 -> 0 | V69: =COUNTIF(V51:V68,"ROBBING") -> 0 | W69: =COUNTA(W51:W68) -> 5 | X69: =COUNTA(X51:X68) -> 5 | Y69: =COUNTA(Y51:Y68) -> 1 | Z69: =COUNTA(Z51:Z68) -> 0 | AC69: =IFERROR(INDEX(LIST2!$F:$F,MATCH(P69,LIST2!J:J,0),1),"")
A70: LEVEL 7 | P70: L07_NONE_035E_XCS | Q70: PMC MINERS | V70: =IF((RIGHT(P70,7)="ROBBING"),"ROBBING","") | W70: TOP | X70: TOP | Y70: TOP | AC70: =IFERROR(INDEX(LIST2!$F:$F,MATCH(P70,LIST2!J:J,0),1),"") -> Dhoz 71
V71: =IF((RIGHT(P71,7)="ROBBING"),"ROBBING","") | W71: TOP | X71: TOP | Y71: TOP | AC71: =IFERROR(INDEX(LIST2!$F:$F,MATCH(P71,LIST2!J:J,0),1),"")
V72: =IF((RIGHT(P72,7)="ROBBING"),"ROBBING","") | W72: TOP | X72: TOP | AC72: =IFERROR(INDEX(LIST2!$F:$F,MATCH(P72,LIST2!J:J,0),1),"")
V73: =IF((RIGHT(P73,7)="ROBBING"),"ROBBING","") | AC73: =IFERROR(INDEX(LIST2!$F:$F,MATCH(P73,LIST2!J:J,0),1),"")
V74: =IF((RIGHT(P74,7)="ROBBING"),"ROBBING","") | AC74: =IFERROR(INDEX(LIST2!$F:$F,MATCH(P74,LIST2!J:J,0),1),"")
V75: =IF((RIGHT(P75,7)="ROBBING"),"ROBBING","") | AC75: =IFERROR(INDEX(LIST2!$F:$F,MATCH(P75,LIST2!J:J,0),1),"")
V76: =IF((RIGHT(P76,7)="ROBBING"),"ROBBING","") | AC76: =IFERROR(INDEX(LIST2!$F:$F,MATCH(P76,LIST2!J:J,0),1),"")
V77: =IF((RIGHT(P77,7)="ROBBING"),"ROBBING","") | AC77: =IFERROR(INDEX(LIST2!$F:$F,MATCH(P77,LIST2!J:J,0),1),"")
V78: =IF((RIGHT(P78,7)="ROBBING"),"ROBBING","") | AC78: =IFERROR(INDEX(LIST2!$F:$F,MATCH(P78,LIST2!J:J,0),1),"")
V79: =IF((RIGHT(P79,7)="ROBBING"),"ROBBING","") | AC79: =IFERROR(INDEX(LIST2!$F:$F,MATCH(P79,LIST2!J:J,0),1),"")
V80: =IF((RIGHT(P80,7)="ROBBING"),"ROBBING","") | AC80: =IFERROR(INDEX(LIST2!$F:$F,MATCH(P80,LIST2!J:J,0),1),"")
V81: =IF((RIGHT(P81,7)="ROBBING"),"ROBBING","") | AC81: =IFERROR(INDEX(LIST2!$F:$F,MATCH(P81,LIST2!J:J,0),1),"")
V82: =IF((RIGHT(P82,7)="ROBBING"),"ROBBING","") | AC82: =IFERROR(INDEX(LIST2!$F:$F,MATCH(P82,LIST2!J:J,0),1),"")
V83: =IF((RIGHT(P83,7)="ROBBING"),"ROBBING","") | AC83: =IFERROR(INDEX(LIST2!$F:$F,MATCH(P83,LIST2!J:J,0),1),"")
V84: =IF((RIGHT(P84,7)="ROBBING"),"ROBBING","") | AC84: =IFERROR(INDEX(LIST2!$F:$F,MATCH(P84,LIST2!J:J,0),1),"")
... V87: =IF((RIGHT(P87,7)="ROBBING"),"ROBBING","") | AC87: =IFERROR(INDEX(LIST2!$F:$F,MATCH(P87,LIST2!J:J,0),1),"")
A88: SUBTOTAL | B88: =COUNTA(B70:B87) -> 0 | D88: =COUNTA(D70:D87) -> 0 | F88: =COUNTA(F70:F87) -> 0 | H88: =COUNTA(H70:H87) -> 0 | J88: =COUNTA(J70:J87) -> 0 | L88: =COUNTA(L70:L87) -> 0 | N88: =COUNTA(N70:N87) -> 0 | P88: =COUNTA(P70:P87) -> 1 | R88: =COUNTIF(V70:V87,"ROBBING") -> 0 | S88: ='FINAL LIST WITH REMARKS'!Z936 -> 5 | T88: =SUM(B88:Q88) -> 1 | U88: ='For Explo'!J201 -> 1 | V88: =COUNTIF(V70:V87,"ROBBING") -> 0 | W88: =COUNTA(W70:W87) -> 3 | X88: =COUNTA(X70:X87) -> 3 | Y88: =COUNTA(Y70:Y87) -> 2 | Z88: =COUNTA(Z70:Z87) -> 0 | AC88: =IFERROR(INDEX(LIST2!$F:$F,MATCH(P88,LIST2!J:J,0),1),"")
A89: LEVEL 8 | B89: L08_JV_020E_STOPE PREP | C89: CAPUYAN | D89: L08_JV_021E_STOPE | E89: CAPUYAN | H89: L08_DPVE_032E_DW_ISL_A | I89: FERNANDEZ | L89: L08_DPVE_014W_WINZE | M89: NITRO CN | N89: L08_NONE_043W_XCN | O89: CAPUYAN | P89: L08_GHV_006E_ROBBING | Q89: FERNANDEZ | V89: =IF((RIGHT(P89,7)="ROBBING"),"ROBBING","") -> ROBBING | W89: TOP | X89: TOP | Z89: SILL | AC89: =IFERROR(INDEX(LIST2!$F:$F,MATCH(P89,LIST2!J:J,0),1),"") -> RobS 79
B90: L08_JV_019E_STOPE PREP | C90: FERNANDEZ 7 | D90: L08_DPVE_039E_WINZE_STOPE | E90: CANTAGO 4 | L90: L08_GHVHW_016E_WINZE | M90: CANTAGO | P90: L08_GHV_017W_ROBBING | Q90: NITRO CQ | V90: =IF((RIGHT(P90,7)="ROBBING"),"ROBBING","") -> ROBBING | W90: TOP | X90: TOP | Z90: SILL | AC90: =IFERROR(INDEX(LIST2!$F:$F,MATCH(P90,LIST2!J:J,0),1),"") -> RobS 79
B91: L08_JV_026E_WINZE STOPE PREP | C91: NITRO CM | D91: L08_JV_049E_WINZE_STOPE | E91: CANTAGO 3 | P91: L08_GHV_002W_ROBBING | Q91: NITRO CQ | V91: =IF((RIGHT(P91,7)="ROBBING"),"ROBBING","") -> ROBBING | W91: TOP | X91: TOP | Z91: SILL | AC91: =IFERROR(INDEX(LIST2!$F:$F,MATCH(P91,LIST2!J:J,0),1),"") -> RobS 79
P92: L08_NONE_034E_WIDENING | Q92: CAPUYAN 1 | V92: =IF((RIGHT(P92,7)="ROBBING"),"ROBBING","") | W92: TOP | X92: TOP | AC92: DVA 73
P93: L08_GHV_012W_ROBBING | Q93: FERNANDEZ 5 | V93: =IF((RIGHT(P93,7)="ROBBING"),"ROBBING","") -> ROBBING | X93: TOP | Z93: SILL | AC93: =IFERROR(INDEX(LIST2!$F:$F,MATCH(P93,LIST2!J:J,0),1),"") -> RobS 79
P94: L08_JV_022E_MAINLINE CLEANING | Q94: CAPUYAN | V94: =IF((RIGHT(P94,7)="ROBBING"),"ROBBING","") | X94: TOP | AC94: Dhoz 71
P95: L08_NONE_038E_ALIMAK_RAISE | Q95: PMC MINERS | V95: =IF((RIGHT(P95,7)="ROBBING"),"ROBBING","") | X95: TOP | AC95: DVA 73
P96: L08_JV_023E_ROBBING | Q96: CAPUYAN | V96: =IF((RIGHT(P96,7)="ROBBING"),"ROBBING","") -> ROBBING | Z96: TOP | AC96: RobC 80
V97: =IF((RIGHT(P97,7)="ROBBING"),"ROBBING","") | Z97: SILL
V98: =IF((RIGHT(P98,7)="ROBBING"),"ROBBING","")
V99: =IF((RIGHT(P99,7)="ROBBING"),"ROBBING","")
V100: =IF((RIGHT(P100,7)="ROBBING"),"ROBBING","")
V101: =IF((RIGHT(P101,7)="ROBBING"),"ROBBING","")
V102: =IF((RIGHT(P102,7)="ROBBING"),"ROBBING","")
V103: =IF((RIGHT(P103,7)="ROBBING"),"ROBBING","") | AC103: =IFERROR(INDEX(LIST2!$F:$F,MATCH(P103,LIST2!J:J,0),1),"")
V104: =IF((RIGHT(P104,7)="ROBBING"),"ROBBING","") | AC104: =IFERROR(INDEX(LIST2!$F:$F,MATCH(P104,LIST2!J:J,0),1),"")
V105: =IF((RIGHT(P105,7)="ROBBING"),"ROBBING","") | AC105: =IFERROR(INDEX(LIST2!$F:$F,MATCH(P105,LIST2!J:J,0),1),"")
V106: =IF((RIGHT(P106,7)="ROBBING"),"ROBBING","") | AC106: =IFERROR(INDEX(LIST2!$F:$F,MATCH(P106,LIST2!J:J,0),1),"")
V107: =IF((RIGHT(P107,7)="ROBBING"),"ROBBING","") | AC107: =IFERROR(INDEX(LIST2!$F:$F,MATCH(P107,LIST2!J:J,0),1),"")
V108: =IF((RIGHT(P108,7)="ROBBING"),"ROBBING","") | AC108: =IFERROR(INDEX(LIST2!$F:$F,MATCH(P108,LIST2!J:J,0),1),"")
V109: =IF((RIGHT(P109,7)="ROBBING"),"ROBBING","") | AC109: =IFERROR(INDEX(LIST2!$F:$F,MATCH(P109,LIST2!J:J,0),1),"")
...

Sheet For Sir ECB
A3: Breakdown | B3: Count | E3: ='Final List'!A1 -> ACTIVE WORKINGPLACES JUNE 2026
A4: Drift | B4: =I19-COUNTIF('Final List'!$H$14:$H$220,"*ISL*") -> 20
A5: Crosscut | B5: =L19 -> 7
A6: Intermediate Sublevel | B6: =COUNTIF('Final List'!$H$14:$H$220,"*ISL*") -> 4 | E6: LEVEL | F6: STOPE PREP | G6: BREAKING | H6: PULL-OUT | I6: DRIFT | J6: RAISE | K6: WINZE | L6: CROSSCUT | M6: SPECIAL PROJECT | N6: ROBBING | O6: SUM | P6: ISL | Q6: TOPSLICE | R6: SILL
A7: Shrink Stope Prep | B7: ='Final List'!B252-COUNTIF('Final List'!B14:B192,"*WINZE*") -> 7 | E7: L03 | F7: =CONTROLLER!P4 -> 0 | G7: =CONTROLLER!Q4 -> 0 | H7: =CONTROLLER!R4 -> 0 | I7: =CONTROLLER!S4 -> 0 | J7: =CONTROLLER!T4 -> 0 | K7: =CONTROLLER!U4 -> 0 | L7: =CONTROLLER!V4 -> 0 | M7: =CONTROLLER!W4 -> 1 | N7: =CONTROLLER!X4 -> 1 | O7: =SUM(F7:N7) -> 2 | P7: =COUNTIFS('Final List'!$H$14:$H$191,"*ISL*",'Final List'!$H$14:$H$191,"*L03*") -> 0 | Q7: =COUNTIFS('Final List'!$AC$4:$AC$252,"RobC 80",'Final List'!$P$4:$P$252,"*L03*") -> 0 | R7: =N7-Q7 -> 1
A8: Shrink Stope Breaking | B8: ='Final List'!D252-COUNTIF('Final List'!D14:D220,"*WINZE*") -> 20 | E8: L04 | F8: =CONTROLLER!P5 -> 0 | G8: =CONTROLLER!Q5 -> 0 | H8: =CONTROLLER!R5 -> 0 | I8: =CONTROLLER!S5 -> 0 | J8: =CONTROLLER!T5 -> 0 | K8: =CONTROLLER!U5 -> 0 | L8: =CONTROLLER!V5 -> 0 | M8: =CONTROLLER!W5 -> 0 | N8: =CONTROLLER!X5 -> 0 | O8: =SUM(F8:N8) -> 0 | P8: =COUNTIFS('Final List'!$H$14:$H$191,"*ISL*",'Final List'!$H$14:$H$191,"*L04*") -> 0 | Q8: =COUNTIFS('Final List'!$AC$4:$AC$252,"RobC 80",'Final List'!$P$4:$P$252,"*L04*") -> 0 | R8: =N8-Q8 -> 0
A9: Shrink Stope Pullout | B9: ='Final List'!F252-COUNTIF('Final List'!F14:F220,"*WINZE*") -> 2 | E9: L05 | F9: =CONTROLLER!P6 -> 0 | G9: =CONTROLLER!Q6 -> 0 | H9: =CONTROLLER!R6 -> 0 | I9: =CONTROLLER!S6 -> 0 | J9: =CONTROLLER!T6 -> 0 | K9: =CONTROLLER!U6 -> 0 | L9: =CONTROLLER!V6 -> 0 | M9: =CONTROLLER!W6 -> 0 | N9: =CONTROLLER!X6 -> 0 | O9: =SUM(F9:N9) -> 0 | P9: =COUNTIFS('Final List'!$H$14:$H$191,"*ISL*",'Final List'!$H$14:$H$191,"*L05*") -> 0 | Q9: =COUNTIFS('Final List'!$AC$4:$AC$252,"RobC 80",'Final List'!$P$4:$P$252,"*L05*") -> 0 | R9: =N9-Q9 -> 0
A10: Winze Stope Prep | B10: =COUNTIF('Final List'!B14:B220,"*WINZE*") -> 1 | E10: L06 | F10: =CONTROLLER!P7 -> 0 | G10: =CONTROLLER!Q7 -> 0 | H10: =CONTROLLER!R7 -> 0 | I10: =CONTROLLER!S7 -> 0 | J10: =CONTROLLER!T7 -> 0 | K10: =CONTROLLER!U7 -> 0 | L10: =CONTROLLER!V7 -> 0 | M10: =CONTROLLER!W7 -> 0 | N10: =CONTROLLER!X7 -> 0 | O10: =SUM(F10:N10) -> 0 | P10: =COUNTIFS('Final List'!$H$14:$H$191,"*ISL*",'Final List'!$H$14:$H$191,"*L06*") -> 0 | Q10: =COUNTIFS('Final List'!$AC$4:$AC$252,"RobC 80",'Final List'!$P$4:$P$252,"*L06*") -> 0 | R10: =N10-Q10 -> 0
A11: Winze Stope Breaking | B11: =COUNTIF('Final List'!D14:D220,"*WINZE*") -> 4 | E11: L07 | F11: =CONTROLLER!P8 -> 0 | G11: =CONTROLLER!Q8 -> 0 | H11: =CONTROLLER!R8 -> 0 | I11: =CONTROLLER!S8 -> 0 | J11: =CONTROLLER!T8 -> 0 | K11: =CONTROLLER!U8 -> 0 | L11: =CONTROLLER!V8 -> 0 | M11: =CONTROLLER!W8 -> 1 | N11: =CONTROLLER!X8 -> 0 | O11: =SUM(F11:N11) -> 1 | P11: =COUNTIFS('Final List'!$H$14:$H$191,"*ISL*",'Final List'!$H$14:$H$191,"*L07*") -> 0 | Q11: =COUNTIFS('Final List'!$AC$4:$AC$252,"RobC 80",'Final List'!$P$4:$P$252,"*L07*") -> 0 | R11: =N11-Q11 -> 0
A12: Winze Stope Pullot | B12: =COUNTIF('Final List'!F14:F220,"*WINZE*") -> 0 | E12: L08 | F12: =CONTROLLER!P9 -> 3 | G12: =CONTROLLER!Q9 -> 3 | H12: =CONTROLLER!R9 -> 0 | I12: =CONTROLLER!S9 -> 1 | J12: =CONTROLLER!T9 -> 0 | K12: =CONTROLLER!U9 -> 2 | L12: =CONTROLLER!V9 -> 1 | M12: =CONTROLLER!W9 -> 3 | N12: =CONTROLLER!X9 -> 5 | O12: =SUM(F12:N12) -> 18 | P12: =COUNTIFS('Final List'!$H$14:$H$191,"*ISL*",'Final List'!$H$14:$H$191,"*L08*") -> 1 | Q12: =COUNTIFS('Final List'!$AC$4:$AC$252,"RobC 80",'Final List'!$P$4:$P$252,"L08*") -> 1 | R12: =N12-Q12 -> 4
A13: Raise | B13: =J19+COUNTIF('Final List'!$J$14:$J$220,"*NR*")-COUNTIF('Final List'!$J$14:$J$220,"*ISL*") -> 9 | E13: L09 | F13: =CONTROLLER!P10 -> 0 | G13: =CONTROLLER!Q10 -> 1 | H13: =CONTROLLER!R10 -> 0 | I13: =CONTROLLER!S10 -> 2 | J13: =CONTROLLER!T10 -> 0 | K13: =CONTROLLER!U10 -> 0 | L13: =CONTROLLER!V10 -> 0 | M13: =CONTROLLER!W10 -> 1 | N13: =CONTROLLER!X10 -> 7 | O13: =SUM(F13:N13) -> 11 | P13: =COUNTIFS('Final List'!$H$14:$H$191,"*ISL*",'Final List'!$H$14:$H$191,"*L09*") -> 2 | Q13: =COUNTIFS('Final List'!$AC$4:$AC$252,"RobC 80",'Final List'!$P$4:$P$252,"*L09*") -> 1 | R13: =N13-Q13 -> 6
A14: Raise_ISL | B14: =COUNTIF('Final List'!$J$14:$J$220,"*ISL*") -> 0 | E14: L10 | F14: =CONTROLLER!P11 -> 0 | G14: =CONTROLLER!Q11 -> 3 | H14: =CONTROLLER!R11 -> 0 | I14: =CONTROLLER!S11 -> 1 | J14: =CONTROLLER!T11 -> 0 | K14: =CONTROLLER!U11 -> 0 | L14: =CONTROLLER!V11 -> 1 | M14: =CONTROLLER!W11 -> 1 | N14: =CONTROLLER!X11 -> 1 | O14: =SUM(F14:N14) -> 7 | P14: =COUNTIFS('Final List'!$H$14:$H$191,"*ISL*",'Final List'!$H$14:$H$191,"*L10*") -> 0 | Q14: =COUNTIFS('Final List'!$AC$4:$AC$252,"RobC 80",'Final List'!$P$4:$P$252,"*L10*") -> 0 | R14: =N14-Q14 -> 1
A15: Winze | B15: =K19 -> 7 | E15: L11 | F15: =CONTROLLER!P12 -> 0 | G15: =CONTROLLER!Q12 -> 6 | H15: =CONTROLLER!R12 -> 0 | I15: =CONTROLLER!S12 -> 5 | J15: =CONTROLLER!T12 -> 2 | K15: =CONTROLLER!U12 -> 3 | L15: =CONTROLLER!V12 -> 0 | M15: =CONTROLLER!W12 -> 0 | N15: =CONTROLLER!X12 -> 0 | O15: =SUM(F15:N15) -> 16 | P15: =COUNTIFS('Final List'!$H$14:$H$191,"*ISL*",'Final List'!$H$14:$H$191,"*L11*") -> 0 | Q15: =COUNTIFS('Final List'!$AC$4:$AC$252,"RobC 80",'Final List'!$P$4:$P$252,"*L11*") -> 0 | R15: =N15-Q15 -> 0
A16: Robbing Sill | B16: =COUNTIF('Final List'!$AC$4:$AC$220,"RobS 79") -> 12 | E16: L12 | F16: =CONTROLLER!P13 -> 3 | G16: =CONTROLLER!Q13 -> 4 | H16: =CONTROLLER!R13 -> 0 | I16: =CONTROLLER!S13 -> 4 | J16: =CONTROLLER!T13 -> 1 | K16: =CONTROLLER!U13 -> 0 | L16: =CONTROLLER!V13 -> 1 | M16: =CONTROLLER!W13 -> 1 | N16: =CONTROLLER!X13 -> 0 | O16: =SUM(F16:N16) -> 14 | P16: =COUNTIFS('Final List'!$H$14:$H$191,"*ISL*",'Final List'!$H$14:$H$191,"*L12*") -> 1 | Q16: =COUNTIFS('Final List'!$AC$4:$AC$252,"RobC 80",'Final List'!$P$4:$P$252,"*L12*") -> 0 | R16: =N16-Q16 -> 0
A17: Robbing Crown | B17: =COUNTIF('Final List'!$AC$5:$AC$221,"RobC 80") -> 2 | E17: L425 | F17: =CONTROLLER!P14 -> 2 | G17: =CONTROLLER!Q14 -> 7 | H17: =CONTROLLER!R14 -> 2 | I17: =CONTROLLER!S14 -> 6 | J17: =CONTROLLER!T14 -> 5 | K17: =CONTROLLER!U14 -> 2 | L17: =CONTROLLER!V14 -> 2 | M17: =CONTROLLER!W14 -> 0 | N17: =CONTROLLER!X14 -> 0 | O17: =SUM(F17:N17) -> 26 | P17: =COUNTIFS('Final List'!$H$14:$H$191,"*ISL*",'Final List'!$H$14:$H$191,"*L425*") -> 0 | Q17: =COUNTIFS('Final List'!$AC$4:$AC$252,"RobC 80",'Final List'!$P$4:$P$252,"*L425*") -> 0 | R17: =N17-Q17 -> 0
A18: Special Projects | B18: =COUNTIF('Final List'!$AC$4:$AC$250,"Dhoz 71")+COUNTIF('Final List'!$AC$4:$AC$250,"DVR 72")+COUNTIF('Final List'!$AC$4:$AC$250,"DVS 75")+COUNTIF('Final List'!$AC$4:$AC$250,"DVA 73")+COUNTIF('Final List'!$AC$4:$AC$250,"DVW 74") -> 8 | E18: L460 | F18: =CONTROLLER!P15 -> 0 | G18: =CONTROLLER!Q15 -> 0 | H18: =CONTROLLER!R15 -> 0 | I18: =CONTROLLER!S15 -> 5 | J18: =CONTROLLER!T15 -> 1 | K18: =CONTROLLER!U15 -> 0 | L18: =CONTROLLER!V15 -> 2 | M18: =CONTROLLER!W15 -> 0 | N18: =CONTROLLER!X15 -> 0 | O18: =SUM(F18:N18) -> 8 | P18: =COUNTIFS('Final List'!$H$14:$H$191,"*ISL*",'Final List'!$H$14:$H$191,"*L425*") -> 0 | Q18: =COUNTIFS('Final List'!$AC$4:$AC$252,"RobC 80",'Final List'!$P$4:$P$252,"*L425*") -> 0 | R18: =N18-Q18 -> 0
A19: Total | B19: =IF(SUM(B4:B18)=O19,SUM(B4:B18),"CHECK") -> 103 | E19: SUM | F19: =SUM(F7:F18) -> 8 | G19: =SUM(G7:G18) -> 24 | H19: =SUM(H7:H18) -> 2 | I19: =SUM(I7:I18) -> 24 | J19: =SUM(J7:J18) -> 9 | K19: =SUM(K7:K18) -> 7 | L19: =SUM(L7:L18) -> 7 | M19: =SUM(M7:M18) -> 8 | ... R19: =SUM(R7:R18) -> 12
E21: TOTAL | F21: =SUM(F19:N19) -> 103
E24: TOTAL WORK AREAS - DASHBOARD DATA (RSS)
E25: DATE | F25: STOPE PREP | G25: STOPE BREAKING | H25: STOPE PULL OUT | I25: WINZE STOPE | J25: DRIFT | K25: RAISE | L25: WINZE | M25: TIMBERMEN | N25: CLEANERS | O25: Work Place ratio | P25: Total WP
E26: =RIGHT(E3,9) -> JUNE 2026 | F26: ='Final List'!B252-COUNTIF('Final List'!B4:B250,"PREP") -> 8 | G26: ='Final List'!D252-COUNTIF('Final List'!D4:D250,"*WINZE*")+COUNTIF('Final List'!$AC$4:$AC$250,"RobS 79") -> 32 | H26: ='Final List'!F252-COUNTIF('Final List'!F4:F250,"STOPE") -> 2 | I26: =COUNTIF('Final List'!D4:D252,"*WINZE*")+COUNTIF('Final List'!$H$4:$H$250,"*ISL*")+COUNTIF('Final List'!$AC$4:$AC$250,"RobC 80")+COUNTIF('Final List'!$J$4:$J$250,"*ISL*") -> 10 | J26: =I19+L19-COUNTIF('Final List'!$H$4:$H$252,"*ISL*")+COUNTIF('Final List'!$AC$4:$AC$252,"Dhoz 71") -> 32 | K26: =J19+COUNTIF('Final List'!$AC$4:$AC$252,"DVR 72")-COUNTIF('Final List'!$J$4:$J$252,"*ISL*") -> 9 | L26: =K19+COUNTIF('Final List'!$AC$4:$AC$250,"DVS 75")+COUNTIF('Final List'!$AC$4:$AC$250,"DVW 74") -> 7 | O26: {='LEVEL QUOTA'!W18:W20} -> 0.51006221 | P26: =IF(F21=SUM(F26:L26),F21,"Check") -> Check
O27: 0
O28: 0

Sheet LIST2
A1: REMINDER: PLEASE SA PAG ENCODE DINHI, COPY-PASTE VALUES LANG JUD FROM COLUMN I TO COLUMN J. | F1: MINE CODE | G1: CONTRACTOR 1 | H1: CONTRACTOR 2 | J1: DROP DOWN ANG FORMULA SA GREEN COLUMNS / Copy Values | K1: STOPE PREP | L1: BREAKING MATCH | M1: PULLOUT MATCH | N1: DRIFT MATCH | O1: RAISE MATCH | P1: WINZE MATCH | Q1: XCUT MATCH | R1: SP MATCH | S1: CHECK NON | T1: .S OR L | V1: FINAL TEAM LEADER | W1: STATUS | X1: I | Y1: S
B2: L10 | C2: DPVE | D2: 099E | E2: STOPE | F2: =IF(OR(E2="XCN",E2="DE",E2="DW",E2="DN",E2="XCS",E2="XCE",E2="XCW",E2="SUMP",E2="BYPASS",E2="CHAMBER",E2="DRAIN HOLE",E2="DRILLING CHAMBER",E2="DE_ISL",E2="DW_ISL",E2="REHAB"),"Dhoz 71",IF(OR(E2="RAISE",E2="RAISE_ISL"),"DVR 72",IF(E2="ALIMAK","DVA 73",IF(E2="WINZE","DVW 74",IF(E2="SHAFT","DVS 75",IF(AND(E2="WINZE STOPE",T2="S"),"RobC 80",IF(AND(E2="STOPE",T2="S"),"StpS 77",IF(AND(E2="WINZE STOPE",T2="L"),"RobC 80",IF(AND(E2="STOPE",T2="L"),"StpL 78",IF(AND(E2="WINZE STOPE PREP",T2="S"),"RobC 80",IF(AND(E2="STOPE PREP",T2="S"),"StpS 77",IF(AND(E2="WINZE STOPE PREP",T2="L"),"RobC 80",IF(AND(E2="STOPE PREP",T2="L"),"StpL 78",IF(AND(E2="ROBBING",T2="L"),"RobC 80",IF(AND(E2="ROBBING",T2="S"),"RobS 79",0))))))))))))))) -> StpS 77 | G2: OLIVEROS 2 | I2: =CONCATENATE(B2,"_",C2,"_",D2,"_",E2) -> L10_DPVE_099E_STOPE | J2: L10_DPVE_099E_STOPE | K2: =IFERROR(MATCH(J2,'Final List'!$B$4:$B$252,0),0) -> 0 | L2: =IFERROR(MATCH(J2,'Final List'!$D$4:$D$252,0),0) -> 0 | M2: =IFERROR(MATCH(J2,'Final List'!$F$4:$F$251,0),0) -> 0 | N2: =IFERROR(MATCH(J2,'Final List'!$H$4:$H$252,0),0) -> 0 | O2: =IFERROR(MATCH(J2,'Final List'!$J$4:$J$252,0),0) -> 0 | P2: =IFERROR(MATCH(J2,'Final List'!$L$4:$L$252,0),0) -> 0 | Q2: =IFERROR(MATCH(J2,'Final List'!$N$4:$N$252,0),0) -> 0 | R2: =IFERROR(MATCH(J2,'Final List'!$P$4:$P$252,0),0) -> 0 | S2: =SUM(K2:R2) -> 0 | T2: S | V2: =IF(H2="",G2,H2) -> OLIVEROS 2 | W2: BRK
B3: L10 | C3: GHVSPLIT | D3: 073E | E3: STOPE | F3: =IF(OR(E3="XCN",E3="DE",E3="DW",E3="DN",E3="XCS",E3="XCE",E3="XCW",E3="SUMP",E3="BYPASS",E3="CHAMBER",E3="DRAIN HOLE",E3="DRILLING CHAMBER",E3="DE_ISL",E3="DW_ISL",E3="REHAB"),"Dhoz 71",IF(OR(E3="RAISE",E3="RAISE_ISL"),"DVR 72",IF(E3="ALIMAK","DVA 73",IF(E3="WINZE","DVW 74",IF(E3="SHAFT","DVS 75",IF(AND(E3="WINZE STOPE",T3="S"),"RobC 80",IF(AND(E3="STOPE",T3="S"),"StpS 77",IF(AND(E3="WINZE STOPE",T3="L"),"RobC 80",IF(AND(E3="STOPE",T3="L"),"StpL 78",IF(AND(E3="WINZE STOPE PREP",T3="S"),"RobC 80",IF(AND(E3="STOPE PREP",T3="S"),"StpS 77",IF(AND(E3="WINZE STOPE PREP",T3="L"),"RobC 80",IF(AND(E3="STOPE PREP",T3="L"),"StpL 78",IF(AND(E3="ROBBING",T3="L"),"RobC 80",IF(AND(E3="ROBBING",T3="S"),"RobS 79",0))))))))))))))) -> StpS 77 | G3: SHEPHERD BB 1 | I3: =CONCATENATE(B3,"_",C3,"_",D3,"_",E3) -> L10_GHVSPLIT_073E_STOPE | J3: L10_GHVSPLIT_073E_STOPE | K3: =IFERROR(MATCH(J3,'Final List'!$B$4:$B$252,0),0) -> 0 | L3: =IFERROR(MATCH(J3,'Final List'!$D$4:$D$252,0),0) -> 0 | M3: =IFERROR(MATCH(J3,'Final List'!$F$4:$F$251,0),0) -> 0 | N3: =IFERROR(MATCH(J3,'Final List'!$H$4:$H$252,0),0) -> 0 | O3: =IFERROR(MATCH(J3,'Final List'!$J$4:$J$252,0),0) -> 0 | P3: =IFERROR(MATCH(J3,'Final List'!$L$4:$L$252,0),0) -> 0 | Q3: =IFERROR(MATCH(J3,'Final List'!$N$4:$N$252,0),0) -> 0 | R3: =IFERROR(MATCH(J3,'Final List'!$P$4:$P$252,0),0) -> 0 | S3: =SUM(K3:R3) -> 0 | T3: S | V3: =IF(H3="",G3,H3) -> SHEPHERD BB 1 | W3: PO
B4: L10 | C4: GHVSPLIT | D4: 030E | E4: STOPE | F4: =IF(OR(E4="XCN",E4="DE",E4="DW",E4="DN",E4="XCS",E4="XCE",E4="XCW",E4="SUMP",E4="BYPASS",E4="CHAMBER",E4="DRAIN HOLE",E4="DRILLING CHAMBER",E4="DE_ISL",E4="DW_ISL",E4="REHAB"),"Dhoz 71",IF(OR(E4="RAISE",E4="RAISE_ISL"),"DVR 72",IF(E4="ALIMAK","DVA 73",IF(E4="WINZE","DVW 74",IF(E4="SHAFT","DVS 75",IF(AND(E4="WINZE STOPE",T4="S"),"RobC 80",IF(AND(E4="STOPE",T4="S"),"StpS 77",IF(AND(E4="WINZE STOPE",T4="L"),"RobC 80",IF(AND(E4="STOPE",T4="L"),"StpL 78",IF(AND(E4="WINZE STOPE PREP",T4="S"),"RobC 80",IF(AND(E4="STOPE PREP",T4="S"),"StpS 77",IF(AND(E4="WINZE STOPE PREP",T4="L"),"RobC 80",IF(AND(E4="STOPE PREP",T4="L"),"StpL 78",IF(AND(E4="ROBBING",T4="L"),"RobC 80",IF(AND(E4="ROBBING",T4="S"),"RobS 79",0))))))))))))))) -> StpS 77 | G4: LARGO 2 | I4: =CONCATENATE(B4,"_",C4,"_",D4,"_",E4) -> L10_GHVSPLIT_030E_STOPE | J4: L10_GHVSPLIT_030E_STOPE | K4: =IFERROR(MATCH(J4,'Final List'!$B$4:$B$252,0),0) -> 0 | L4: =IFERROR(MATCH(J4,'Final List'!$D$4:$D$252,0),0) -> 0 | M4: =IFERROR(MATCH(J4,'Final List'!$F$4:$F$251,0),0) -> 0 | N4: =IFERROR(MATCH(J4,'Final List'!$H$4:$H$252,0),0) -> 0 | O4: =IFERROR(MATCH(J4,'Final List'!$J$4:$J$252,0),0) -> 0 | P4: =IFERROR(MATCH(J4,'Final List'!$L$4:$L$252,0),0) -> 0 | Q4: =IFERROR(MATCH(J4,'Final List'!$N$4:$N$252,0),0) -> 0 | R4: =IFERROR(MATCH(J4,'Final List'!$P$4:$P$252,0),0) -> 0 | S4: =SUM(K4:R4) -> 0 | T4: S | V4: =IF(H4="",G4,H4) -> LARGO 2 | W4: PO
B5: L09 | C5: JVSPLIT | D5: 073E | E5: WINZE STOPE | F5: =IF(OR(E5="XCN",E5="DE",E5="DW",E5="DN",E5="XCS",E5="XCE",E5="XCW",E5="SUMP",E5="BYPASS",E5="CHAMBER",E5="DRAIN HOLE",E5="DRILLING CHAMBER",E5="DE_ISL",E5="DW_ISL",E5="REHAB"),"Dhoz 71",IF(OR(E5="RAISE",E5="RAISE_ISL"),"DVR 72",IF(E5="ALIMAK","DVA 73",IF(E5="WINZE","DVW 74",IF(E5="SHAFT","DVS 75",IF(AND(E5="WINZE STOPE",T5="S"),"RobC 80",IF(AND(E5="STOPE",T5="S"),"StpS 77",IF(AND(E5="WINZE STOPE",T5="L"),"RobC 80",IF(AND(E5="STOPE",T5="L"),"StpL 78",IF(AND(E5="WINZE STOPE PREP",T5="S"),"RobC 80",IF(AND(E5="STOPE PREP",T5="S"),"StpS 77",IF(AND(E5="WINZE STOPE PREP",T5="L"),"RobC 80",IF(AND(E5="STOPE PREP",T5="L"),"StpL 78",IF(AND(E5="ROBBING",T5="L"),"RobC 80",IF(AND(E5="ROBBING",T5="S"),"RobS 79",0))))))))))))))) -> RobC 80 | G5: PANSIT, NORMAN 2 | I5: =CONCATENATE(B5,"_",C5,"_",D5,"_",E5) -> L09_JVSPLIT_073E_WINZE STOPE | J5: L09_JVSPLIT_073E_WINZE STOPE | K5: =IFERROR(MATCH(J5,'Final List'!$B$4:$B$252,0),0) -> 0 | L5: =IFERROR(MATCH(J5,'Final List'!$D$4:$D$252,0),0) -> 0 | M5: =IFERROR(MATCH(J5,'Final List'!$F$4:$F$251,0),0) -> 0 | N5: =IFERROR(MATCH(J5,'Final List'!$H$4:$H$252,0),0) -> 0 | O5: =IFERROR(MATCH(J5,'Final List'!$J$4:$J$252,0),0) -> 0 | P5: =IFERROR(MATCH(J5,'Final List'!$L$4:$L$252,0),0) -> 0 | Q5: =IFERROR(MATCH(J5,'Final List'!$N$4:$N$252,0),0) -> 0 | R5: =IFERROR(MATCH(J5,'Final List'!$P$4:$P$252,0),0) -> 0 | S5: =SUM(K5:R5) -> 0 | T5: S | V5: =IF(H5="",G5,H5) -> PANSIT, NORMAN 2 | W5: WPO
B6: L09 | C6: JVSPLIT | D6: 048E | E6: WINZE STOPE PREP | F6: =IF(OR(E6="XCN",E6="DE",E6="DW",E6="DN",E6="XCS",E6="XCE",E6="XCW",E6="SUMP",E6="BYPASS",E6="CHAMBER",E6="DRAIN HOLE",E6="DRILLING CHAMBER",E6="DE_ISL",E6="DW_ISL",E6="REHAB"),"Dhoz 71",IF(OR(E6="RAISE",E6="RAISE_ISL"),"DVR 72",IF(E6="ALIMAK","DVA 73",IF(E6="WINZE","DVW 74",IF(E6="SHAFT","DVS 75",IF(AND(E6="WINZE STOPE",T6="S"),"RobC 80",IF(AND(E6="STOPE",T6="S"),"StpS 77",IF(AND(E6="WINZE STOPE",T6="L"),"RobC 80",IF(AND(E6="STOPE",T6="L"),"StpL 78",IF(AND(E6="WINZE STOPE PREP",T6="S"),"RobC 80",IF(AND(E6="STOPE PREP",T6="S"),"StpS 77",IF(AND(E6="WINZE STOPE PREP",T6="L"),"RobC 80",IF(AND(E6="STOPE PREP",T6="L"),"StpL 78",IF(AND(E6="ROBBING",T6="L"),"RobC 80",IF(AND(E6="ROBBING",T6="S"),"RobS 79",0))))))))))))))) -> RobC 80 | G6: SHEPHERD AF 1 | I6: =CONCATENATE(B6,"_",C6,"_",D6,"_",E6) -> L09_JVSPLIT_048E_WINZE STOPE PREP | J6: L09_JVSPLIT_048E_WINZE STOPE PREP | K6: =IFERROR(MATCH(J6,'Final List'!$B$4:$B$252,0),0) -> 0 | L6: =IFERROR(MATCH(J6,'Final List'!$D$4:$D$252,0),0) -> 0 | M6: =IFERROR(MATCH(J6,'Final List'!$F$4:$F$251,0),0) -> 0 | N6: =IFERROR(MATCH(J6,'Final List'!$H$4:$H$252,0),0) -> 0 | O6: =IFERROR(MATCH(J6,'Final List'!$J$4:$J$252,0),0) -> 0 | P6: =IFERROR(MATCH(J6,'Final List'!$L$4:$L$252,0),0) -> 0 | Q6: =IFERROR(MATCH(J6,'Final List'!$N$4:$N$252,0),0) -> 0 | R6: =IFERROR(MATCH(J6,'Final List'!$P$4:$P$252,0),0) -> 0 | S6: =SUM(K6:R6) -> 0 | T6: S | V6: =IF(H6="",G6,H6) -> SHEPHERD AF 1 | W6: WPREP
B7: L08 | C7: DPVE | D7: 029E | E7: WINZE STOPE | F7: =IF(OR(E7="XCN",E7="DE",E7="DW",E7="DN",E7="XCS",E7="XCE",E7="XCW",E7="SUMP",E7="BYPASS",E7="CHAMBER",E7="DRAIN HOLE",E7="DRILLING CHAMBER",E7="DE_ISL",E7="DW_ISL",E7="REHAB"),"Dhoz 71",IF(OR(E7="RAISE",E7="RAISE_ISL"),"DVR 72",IF(E7="ALIMAK","DVA 73",IF(E7="WINZE","DVW 74",IF(E7="SHAFT","DVS 75",IF(AND(E7="WINZE STOPE",T7="S"),"RobC 80",IF(AND(E7="STOPE",T7="S"),"StpS 77",IF(AND(E7="WINZE STOPE",T7="L"),"RobC 80",IF(AND(E7="STOPE",T7="L"),"StpL 78",IF(AND(E7="WINZE STOPE PREP",T7="S"),"RobC 80",IF(AND(E7="STOPE PREP",T7="S"),"StpS 77",IF(AND(E7="WINZE STOPE PREP",T7="L"),"RobC 80",IF(AND(E7="STOPE PREP",T7="L"),"StpL 78",IF(AND(E7="ROBBING",T7="L"),"RobC 80",IF(AND(E7="ROBBING",T7="S"),"RobS 79",0))))))))))))))) -> RobC 80 | G7: CARIKITAN 1 | I7: =CONCATENATE(B7,"_",C7,"_",D7,"_",E7) -> L08_DPVE_029E_WINZE STOPE | J7: L08_DPVE_029E_WINZE STOPE | K7: =IFERROR(MATCH(J7,'Final List'!$B$4:$B$252,0),0) -> 0 | L7: =IFERROR(MATCH(J7,'Final List'!$D$4:$D$252,0),0) -> 0 | M7: =IFERROR(MATCH(J7,'Final List'!$F$4:$F$251,0),0) -> 0 | N7: =IFERROR(MATCH(J7,'Final List'!$H$4:$H$252,0),0) -> 0 | O7: =IFERROR(MATCH(J7,'Final List'!$J$4:$J$252,0),0) -> 0 | P7: =IFERROR(MATCH(J7,'Final List'!$L$4:$L$252,0),0) -> 0 | Q7: =IFERROR(MATCH(J7,'Final List'!$N$4:$N$252,0),0) -> 0 | R7: =IFERROR(MATCH(J7,'Final List'!$P$4:$P$252,0),0) -> 0 | S7: =SUM(K7:R7) -> 0 | T7: S | V7: =IF(H7="",G7,H7) -> CARIKITAN 1 | W7: WPO
B8: L08 | C8: JVSPLIT | D8: 074E | E8: WINZE STOPE | F8: =IF(OR(E8="XCN",E8="DE",E8="DW",E8="DN",E8="XCS",E8="XCE",E8="XCW",E8="SUMP",E8="BYPASS",E8="CHAMBER",E8="DRAIN HOLE",E8="DRILLING CHAMBER",E8="DE_ISL",E8="DW_ISL",E8="REHAB"),"Dhoz 71",IF(OR(E8="RAISE",E8="RAISE_ISL"),"DVR 72",IF(E8="ALIMAK","DVA 73",IF(E8="WINZE","DVW 74",IF(E8="SHAFT","DVS 75",IF(AND(E8="WINZE STOPE",T8="S"),"RobC 80",IF(AND(E8="STOPE",T8="S"),"StpS 77",IF(AND(E8="WINZE STOPE",T8="L"),"RobC 80",IF(AND(E8="STOPE",T8="L"),"StpL 78",IF(AND(E8="WINZE STOPE PREP",T8="S"),"RobC 80",IF(AND(E8="STOPE PREP",T8="S"),"StpS 77",IF(AND(E8="WINZE STOPE PREP",T8="L"),"RobC 80",IF(AND(E8="STOPE PREP",T8="L"),"StpL 78",IF(AND(E8="ROBBING",T8="L"),"RobC 80",IF(AND(E8="ROBBING",T8="S"),"RobS 79",0))))))))))))))) -> RobC 80 | G8: VILLARANTE 1 | I8: =CONCATENATE(B8,"_",C8,"_",D8,"_",E8) -> L08_JVSPLIT_074E_WINZE STOPE | J8: L08_JVSPLIT_074E_WINZE STOPE | K8: =IFERROR(MATCH(J8,'Final List'!$B$4:$B$252,0),0) -> 0 | L8: =IFERROR(MATCH(J8,'Final List'!$D$4:$D$252,0),0) -> 0 | M8: =IFERROR(MATCH(J8,'Final List'!$F$4:$F$251,0),0) -> 0 | N8: =IFERROR(MATCH(J8,'Final List'!$H$4:$H$252,0),0) -> 0 | O8: =IFERROR(MATCH(J8,'Final List'!$J$4:$J$252,0),0) -> 0 | P8: =IFERROR(MATCH(J8,'Final List'!$L$4:$L$252,0),0) -> 0 | Q8: =IFERROR(MATCH(J8,'Final List'!$N$4:$N$252,0),0) -> 0 | R8: =IFERROR(MATCH(J8,'Final List'!$P$4:$P$252,0),0) -> 0 | S8: =SUM(K8:R8) -> 0 | T8: S | V8: =IF(H8="",G8,H8) -> VILLARANTE 1 | W8: WPO
B9: L05 | C9: DPVE | D9: 053E | E9: WINZE STOPE | F9: =IF(OR(E9="XCN",E9="DE",E9="DW",E9="DN",E9="XCS",E9="XCE",E9="XCW",E9="SUMP",E9="BYPASS",E9="CHAMBER",E9="DRAIN HOLE",E9="DRILLING CHAMBER",E9="DE_ISL",E9="DW_ISL",E9="REHAB"),"Dhoz 71",IF(OR(E9="RAISE",E9="RAISE_ISL"),"DVR 72",IF(E9="ALIMAK","DVA 73",IF(E9="WINZE","DVW 74",IF(E9="SHAFT","DVS 75",IF(AND(E9="WINZE STOPE",T9="S"),"RobC 80",IF(AND(E9="STOPE",T9="S"),"StpS 77",IF(AND(E9="WINZE STOPE",T9="L"),"RobC 80",IF(AND(E9="STOPE",T9="L"),"StpL 78",IF(AND(E9="WINZE STOPE PREP",T9="S"),"RobC 80",IF(AND(E9="STOPE PREP",T9="S"),"StpS 77",IF(AND(E9="WINZE STOPE PREP",T9="L"),"RobC 80",IF(AND(E9="STOPE PREP",T9="L"),"StpL 78",IF(AND(E9="ROBBING",T9="L"),"RobC 80",IF(AND(E9="ROBBING",T9="S"),"RobS 79",0))))))))))))))) -> RobC 80 | G9: LERIO 1 | I9: =CONCATENATE(B9,"_",C9,"_",D9,"_",E9) -> L05_DPVE_053E_WINZE STOPE | J9: L05_DPVE_053E_WINZE STOPE | K9: =IFERROR(MATCH(J9,'Final List'!$B$4:$B$252,0),0) -> 0 | L9: =IFERROR(MATCH(J9,'Final List'!$D$4:$D$252,0),0) -> 0 | M9: =IFERROR(MATCH(J9,'Final List'!$F$4:$F$251,0),0) -> 0 | N9: =IFERROR(MATCH(J9,'Final List'!$H$4:$H$252,0),0) -> 0 | O9: =IFERROR(MATCH(J9,'Final List'!$J$4:$J$252,0),0) -> 0 | P9: =IFERROR(MATCH(J9,'Final List'!$L$4:$L$252,0),0) -> 0 | Q9: =IFERROR(MATCH(J9,'Final List'!$N$4:$N$252,0),0) -> 0 | R9: =IFERROR(MATCH(J9,'Final List'!$P$4:$P$252,0),0) -> 0 | S9: =SUM(K9:R9) -> 0 | T9: S | V9: =IF(H9="",G9,H9) -> LERIO 1 | W9: WBRK
B10: L04 | C10: CTV | D10: 010W | E10: WINZE STOPE | F10: =IF(OR(E10="XCN",E10="DE",E10="DW",E10="DN",E10="XCS",E10="XCE",E10="XCW",E10="SUMP",E10="BYPASS",E10="CHAMBER",E10="DRAIN HOLE",E10="DRILLING CHAMBER",E10="DE_ISL",E10="DW_ISL",E10="REHAB"),"Dhoz 71",IF(OR(E10="RAISE",E10="RAISE_ISL"),"DVR 72",IF(E10="ALIMAK","DVA 73",IF(E10="WINZE","DVW 74",IF(E10="SHAFT","DVS 75",IF(AND(E10="WINZE STOPE",T10="S"),"RobC 80",IF(AND(E10="STOPE",T10="S"),"StpS 77",IF(AND(E10="WINZE STOPE",T10="L"),"RobC 80",IF(AND(E10="STOPE",T10="L"),"StpL 78",IF(AND(E10="WINZE STOPE PREP",T10="S"),"RobC 80",IF(AND(E10="STOPE PREP",T10="S"),"StpS 77",IF(AND(E10="WINZE STOPE PREP",T10="L"),"RobC 80",IF(AND(E10="STOPE PREP",T10="L"),"StpL 78",IF(AND(E10="ROBBING",T10="L"),"RobC 80",IF(AND(E10="ROBBING",T10="S"),"RobS 79",0))))))))))))))) -> RobC 80 | G10: MARTINEZ, DN 3 | I10: =CONCATENATE(B10,"_",C10,"_",D10,"_",E10) -> L04_CTV_010W_WINZE STOPE | J10: L04_CTV_010W_WINZE STOPE | K10: =IFERROR(MATCH(J10,'Final List'!$B$4:$B$252,0),0) -> 0 | L10: =IFERROR(MATCH(J10,'Final List'!$D$4:$D$252,0),0) -> 0 | M10: =IFERROR(MATCH(J10,'Final List'!$F$4:$F$251,0),0) -> 0 | N10: =IFERROR(MATCH(J10,'Final List'!$H$4:$H$252,0),0) -> 0 | O10: =IFERROR(MATCH(J10,'Final List'!$J$4:$J$252,0),0) -> 0 | P10: =IFERROR(MATCH(J10,'Final List'!$L$4:$L$252,0),0) -> 0 | Q10: =IFERROR(MATCH(J10,'Final List'!$N$4:$N$252,0),0) -> 0 | R10: =IFERROR(MATCH(J10,'Final List'!$P$4:$P$252,0),0) -> 0 | S10: =SUM(K10:R10) -> 0 | T10: S | V10: =IF(H10="",G10,H10) -> MARTINEZ, DN 3 | W10: WPO
B11: L04 | C11: CTV | D11: 021W | E11: WINZE STOPE | F11: =IF(OR(E11="XCN",E11="DE",E11="DW",E11="DN",E11="XCS",E11="XCE",E11="XCW",E11="SUMP",E11="BYPASS",E11="CHAMBER",E11="DRAIN HOLE",E11="DRILLING CHAMBER",E11="DE_ISL",E11="DW_ISL",E11="REHAB"),"Dhoz 71",IF(OR(E11="RAISE",E11="RAISE_ISL"),"DVR 72",IF(E11="ALIMAK","DVA 73",IF(E11="WINZE","DVW 74",IF(E11="SHAFT","DVS 75",IF(AND(E11="WINZE STOPE",T11="S"),"RobC 80",IF(AND(E11="STOPE",T11="S"),"StpS 77",IF(AND(E11="WINZE STOPE",T11="L"),"RobC 80",IF(AND(E11="STOPE",T11="L"),"StpL 78",IF(AND(E11="WINZE STOPE PREP",T11="S"),"RobC 80",IF(AND(E11="STOPE PREP",T11="S"),"StpS 77",IF(AND(E11="WINZE STOPE PREP",T11="L"),"RobC 80",IF(AND(E11="STOPE PREP",T11="L"),"StpL 78",IF(AND(E11="ROBBING",T11="L"),"RobC 80",IF(AND(E11="ROBBING",T11="S"),"RobS 79",0))))))))))))))) -> RobC 80 | G11: MARTINEZ, DN 2 | I11: =CONCATENATE(B11,"_",C11,"_",D11,"_",E11) -> L04_CTV_021W_WINZE STOPE | J11: L04_CTV_021W_WINZE STOPE | K11: =IFERROR(MATCH(J11,'Final List'!$B$4:$B$252,0),0) -> 0 | L11: =IFERROR(MATCH(J11,'Final List'!$D$4:$D$252,0),0) -> 0 | M11: =IFERROR(MATCH(J11,'Final List'!$F$4:$F$251,0),0) -> 0 | N11: =IFERROR(MATCH(J11,'Final List'!$H$4:$H$252,0),0) -> 0 | O11: =IFERROR(MATCH(J11,'Final List'!$J$4:$J$252,0),0) -> 0 | P11: =IFERROR(MATCH(J11,'Final List'!$L$4:$L$252,0),0) -> 0 | Q11: =IFERROR(MATCH(J11,'Final List'!$N$4:$N$252,0),0) -> 0 | R11: =IFERROR(MATCH(J11,'Final List'!$P$4:$P$252,0),0) -> 0 | S11: =SUM(K11:R11) -> 0 | T11: S | V11: =IF(H11="",G11,H11) -> MARTINEZ, DN 2 | W11: WPO
B12: L04 | C12: CTV | D12: 020W | E12: ROBBING | F12: =IF(OR(E12="XCN",E12="DE",E12="DW",E12="DN",E12="XCS",E12="XCE",E12="XCW",E12="SUMP",E12="BYPASS",E12="CHAMBER",E12="DRAIN HOLE",E12="DRILLING CHAMBER",E12="DE_ISL",E12="DW_ISL",E12="REHAB"),"Dhoz 71",IF(OR(E12="RAISE",E12="RAISE_ISL"),"DVR 72",IF(E12="ALIMAK","DVA 73",IF(E12="WINZE","DVW 74",IF(E12="SHAFT","DVS 75",IF(AND(E12="WINZE STOPE",T12="S"),"RobC 80",IF(AND(E12="STOPE",T12="S"),"StpS 77",IF(AND(E12="WINZE STOPE",T12="L"),"RobC 80",IF(AND(E12="STOPE",T12="L"),"StpL 78",IF(AND(E12="WINZE STOPE PREP",T12="S"),"RobC 80",IF(AND(E12="STOPE PREP",T12="S"),"StpS 77",IF(AND(E12="WINZE STOPE PREP",T12="L"),"RobC 80",IF(AND(E12="STOPE PREP",T12="L"),"StpL 78",IF(AND(E12="ROBBING",T12="L"),"RobC 80",IF(AND(E12="ROBBING",T12="S"),"RobS 79",0))))))))))))))) -> RobS 79 | G12: NOCOS 1 | I12: =CONCATENATE(B12,"_",C12,"_",D12,"_",E12) -> L04_CTV_020W_ROBBING | J12: L04_CTV_020W_ROBBING | K12: =IFERROR(MATCH(J12,'Final List'!$B$4:$B$252,0),0) -> 0 | L12: =IFERROR(MATCH(J12,'Final List'!$D$4:$D$252,0),0) -> 0 | M12: =IFERROR(MATCH(J12,'Final List'!$F$4:$F$251,0),0) -> 0 | N12: =IFERROR(MATCH(J12,'Final List'!$H$4:$H$252,0),0) -> 0 | O12: =IFERROR(MATCH(J12,'Final List'!$J$4:$J$252,0),0) -> 0 | P12: =IFERROR(MATCH(J12,'Final List'!$L$4:$L$252,0),0) -> 0 | Q12: =IFERROR(MATCH(J12,'Final List'!$N$4:$N$252,0),0) -> 0 | R12: =IFERROR(MATCH(J12,'Final List'!$P$4:$P$252,0),0) -> 0 | S12: =SUM(K12:R12) -> 0 | T12: S | V12: =IF(H12="",G12,H12) -> NOCOS 1 | W12: SILL
B13: L04 | C13: JV | D13: 055W | E13: ROBBING | F13: =IF(OR(E13="XCN",E13="DE",E13="DW",E13="DN",E13="XCS",E13="XCE",E13="XCW",E13="SUMP",E13="BYPASS",E13="CHAMBER",E13="DRAIN HOLE",E13="DRILLING CHAMBER",E13="DE_ISL",E13="DW_ISL",E13="REHAB"),"Dhoz 71",IF(OR(E13="RAISE",E13="RAISE_ISL"),"DVR 72",IF(E13="ALIMAK","DVA 73",IF(E13="WINZE","DVW 74",IF(E13="SHAFT","DVS 75",IF(AND(E13="WINZE STOPE",T13="S"),"RobC 80",IF(AND(E13="STOPE",T13="S"),"StpS 77",IF(AND(E13="WINZE STOPE",T13="L"),"RobC 80",IF(AND(E13="STOPE",T13="L"),"StpL 78",IF(AND(E13="WINZE STOPE PREP",T13="S"),"RobC 80",IF(AND(E13="STOPE PREP",T13="S"),"StpS 77",IF(AND(E13="WINZE STOPE PREP",T13="L"),"RobC 80",IF(AND(E13="STOPE PREP",T13="L"),"StpL 78",IF(AND(E13="ROBBING",T13="L"),"RobC 80",IF(AND(E13="ROBBING",T13="S"),"RobS 79",0))))))))))))))) -> RobS 79 | G13: MARTINEZ, RON 2 | I13: =CONCATENATE(B13,"_",C13,"_",D13,"_",E13) -> L04_JV_055W_ROBBING | J13: L04_JV_055W_ROBBING | K13: =IFERROR(MATCH(J13,'Final List'!$B$4:$B$252,0),0) -> 0 | L13: =IFERROR(MATCH(J13,'Final List'!$D$4:$D$252,0),0) -> 0 | M13: =IFERROR(MATCH(J13,'Final List'!$F$4:$F$251,0),0) -> 0 | N13: =IFERROR(MATCH(J13,'Final List'!$H$4:$H$252,0),0) -> 0 | O13: =IFERROR(MATCH(J13,'Final List'!$J$4:$J$252,0),0) -> 0 | P13: =IFERROR(MATCH(J13,'Final List'!$L$4:$L$252,0),0) -> 0 | Q13: =IFERROR(MATCH(J13,'Final List'!$N$4:$N$252,0),0) -> 0 | R13: =IFERROR(MATCH(J13,'Final List'!$P$4:$P$252,0),0) -> 0 | S13: =SUM(K13:R13) -> 0 | T13: S | V13: =IF(H13="",G13,H13) -> MARTINEZ, RON 2 | W13: SILL
B14: L04 | C14: JVHW | D14: 014E | E14: WINZE STOPE | F14: =IF(OR(E14="XCN",E14="DE",E14="DW",E14="DN",E14="XCS",E14="XCE",E14="XCW",E14="SUMP",E14="BYPASS",E14="CHAMBER",E14="DRAIN HOLE",E14="DRILLING CHAMBER",E14="DE_ISL",E14="DW_ISL",E14="REHAB"),"Dhoz 71",IF(OR(E14="RAISE",E14="RAISE_ISL"),"DVR 72",IF(E14="ALIMAK","DVA 73",IF(E14="WINZE","DVW 74",IF(E14="SHAFT","DVS 75",IF(AND(E14="WINZE STOPE",T14="S"),"RobC 80",IF(AND(E14="STOPE",T14="S"),"StpS 77",IF(AND(E14="WINZE STOPE",T14="L"),"RobC 80",IF(AND(E14="STOPE",T14="L"),"StpL 78",IF(AND(E14="WINZE STOPE PREP",T14="S"),"RobC 80",IF(AND(E14="STOPE PREP",T14="S"),"StpS 77",IF(AND(E14="WINZE STOPE PREP",T14="L"),"RobC 80",IF(AND(E14="STOPE PREP",T14="L"),"StpL 78",IF(AND(E14="ROBBING",T14="L"),"RobC 80",IF(AND(E14="ROBBING",T14="S"),"RobS 79",0))))))))))))))) -> RobC 80 | G14: COMAINGKING 3 | I14: =CONCATENATE(B14,"_",C14,"_",D14,"_",E14) -> L04_JVHW_014E_WINZE STOPE | J14: L04_JVHW_014E_WINZE STOPE | K14: =IFERROR(MATCH(J14,'Final List'!$B$4:$B$252,0),0) -> 0 | L14: =IFERROR(MATCH(J14,'Final List'!$D$4:$D$252,0),0) -> 0 | M14: =IFERROR(MATCH(J14,'Final List'!$F$4:$F$251,0),0) -> 0 | N14: =IFERROR(MATCH(J14,'Final List'!$H$4:$H$252,0),0) -> 0 | O14: =IFERROR(MATCH(J14,'Final List'!$J$4:$J$252,0),0) -> 0 | P14: =IFERROR(MATCH(J14,'Final List'!$L$4:$L$252,0),0) -> 0 | Q14: =IFERROR(MATCH(J14,'Final List'!$N$4:$N$252,0),0) -> 0 | R14: =IFERROR(MATCH(J14,'Final List'!$P$4:$P$252,0),0) -> 0 | S14: =SUM(K14:R14) -> 0 | T14: L | V14: =IF(H14="",G14,H14) -> COMAINGKING 3 | W14: WPO
B15: L05 | C15: NONE | D15: 018E | E15: CHAMBER | F15: =IF(OR(E15="XCN",E15="DE",E15="DW",E15="DN",E15="XCS",E15="XCE",E15="XCW",E15="SUMP",E15="BYPASS",E15="CHAMBER",E15="DRAIN HOLE",E15="DRILLING CHAMBER",E15="DE_ISL",E15="DW_ISL",E15="REHAB"),"Dhoz 71",IF(OR(E15="RAISE",E15="RAISE_ISL"),"DVR 72",IF(E15="ALIMAK","DVA 73",IF(E15="WINZE","DVW 74",IF(E15="SHAFT","DVS 75",IF(AND(E15="WINZE STOPE",T15="S"),"RobC 80",IF(AND(E15="STOPE",T15="S"),"StpS 77",IF(AND(E15="WINZE STOPE",T15="L"),"RobC 80",IF(AND(E15="STOPE",T15="L"),"StpL 78",IF(AND(E15="WINZE STOPE PREP",T15="S"),"RobC 80",IF(AND(E15="STOPE PREP",T15="S"),"StpS 77",IF(AND(E15="WINZE STOPE PREP",T15="L"),"RobC 80",IF(AND(E15="STOPE PREP",T15="L"),"StpL 78",IF(AND(E15="ROBBING",T15="L"),"RobC 80",IF(AND(E15="ROBBING",T15="S"),"RobS 79",0))))))))))))))) -> Dhoz 71 | G15: MARTINEZ, ROGER 1 | H15: SHEPHERD AD 2 | I15: =CONCATENATE(B15,"_",C15,"_",D15,"_",E15) -> L05_NONE_018E_CHAMBER | J15: L05_NONE_018E_CHAMBER | K15: =IFERROR(MATCH(J15,'Final List'!$B$4:$B$252,0),0) -> 0 | L15: =IFERROR(MATCH(J15,'Final List'!$D$4:$D$252,0),0) -> 0 | M15: =IFERROR(MATCH(J15,'Final List'!$F$4:$F$251,0),0) -> 0 | N15: =IFERROR(MATCH(J15,'Final List'!$H$4:$H$252,0),0) -> 0 | O15: =IFERROR(MATCH(J15,'Final List'!$J$4:$J$252,0),0) -> 0 | P15: =IFERROR(MATCH(J15,'Final List'!$L$4:$L$252,0),0) -> 0 | Q15: =IFERROR(MATCH(J15,'Final List'!$N$4:$N$252,0),0) -> 0 | R15: =IFERROR(MATCH(J15,'Final List'!$P$4:$P$252,0),0) -> 0 | S15: =SUM(K15:R15) -> 0 | V15: =IF(H15="",G15,H15) -> SHEPHERD AD 2 | W15: SP
B16: L05 | C16: CTV | D16: 032W | E16: WINZE STOPE | F16: =IF(OR(E16="XCN",E16="DE",E16="DW",E16="DN",E16="XCS",E16="XCE",E16="XCW",E16="SUMP",E16="BYPASS",E16="CHAMBER",E16="DRAIN HOLE",E16="DRILLING CHAMBER",E16="DE_ISL",E16="DW_ISL",E16="REHAB"),"Dhoz 71",IF(OR(E16="RAISE",E16="RAISE_ISL"),"DVR 72",IF(E16="ALIMAK","DVA 73",IF(E16="WINZE","DVW 74",IF(E16="SHAFT","DVS 75",IF(AND(E16="WINZE STOPE",T16="S"),"RobC 80",IF(AND(E16="STOPE",T16="S"),"StpS 77",IF(AND(E16="WINZE STOPE",T16="L"),"RobC 80",IF(AND(E16="STOPE",T16="L"),"StpL 78",IF(AND(E16="WINZE STOPE PREP",T16="S"),"RobC 80",IF(AND(E16="STOPE PREP",T16="S"),"StpS 77",IF(AND(E16="WINZE STOPE PREP",T16="L"),"RobC 80",IF(AND(E16="STOPE PREP",T16="L"),"StpL 78",IF(AND(E16="ROBBING",T16="L"),"RobC 80",IF(AND(E16="ROBBING",T16="S"),"RobS 79",0))))))))))))))) -> RobC 80 | G16: SHEPHERD AF 1 | I16: =CONCATENATE(B16,"_",C16,"_",D16,"_",E16) -> L05_CTV_032W_WINZE STOPE | J16: L05_CTV_032W_WINZE STOPE | K16: =IFERROR(MATCH(J16,'Final List'!$B$4:$B$252,0),0) -> 0 | L16: =IFERROR(MATCH(J16,'Final List'!$D$4:$D$252,0),0) -> 0 | M16: =IFERROR(MATCH(J16,'Final List'!$F$4:$F$251,0),0) -> 0 | N16: =IFERROR(MATCH(J16,'Final List'!$H$4:$H$252,0),0) -> 0 | O16: =IFERROR(MATCH(J16,'Final List'!$J$4:$J$252,0),0) -> 0 | P16: =IFERROR(MATCH(J16,'Final List'!$L$4:$L$252,0),0) -> 0 | Q16: =IFERROR(MATCH(J16,'Final List'!$N$4:$N$252,0),0) -> 0 | R16: =IFERROR(MATCH(J16,'Final List'!$P$4:$P$252,0),0) -> 0 | S16: =SUM(K16:R16) -> 0 | T16: S | V16: =IF(H16="",G16,H16) -> SHEPHERD AF 1 | W16: WBRK
B17: L05 | C17: JVFW | D17: 014W | E17: WINZE STOPE | F17: =IF(OR(E17="XCN",E17="DE",E17="DW",E17="DN",E17="XCS",E17="XCE",E17="XCW",E17="SUMP",E17="BYPASS",E17="CHAMBER",E17="DRAIN HOLE",E17="DRILLING CHAMBER",E17="DE_ISL",E17="DW_ISL",E17="REHAB"),"Dhoz 71",IF(OR(E17="RAISE",E17="RAISE_ISL"),"DVR 72",IF(E17="ALIMAK","DVA 73",IF(E17="WINZE","DVW 74",IF(E17="SHAFT","DVS 75",IF(AND(E17="WINZE STOPE",T17="S"),"RobC 80",IF(AND(E17="STOPE",T17="S"),"StpS 77",IF(AND(E17="WINZE STOPE",T17="L"),"RobC 80",IF(AND(E17="STOPE",T17="L"),"StpL 78",IF(AND(E17="WINZE STOPE PREP",T17="S"),"RobC 80",IF(AND(E17="STOPE PREP",T17="S"),"StpS 77",IF(AND(E17="WINZE STOPE PREP",T17="L"),"RobC 80",IF(AND(E17="STOPE PREP",T17="L"),"StpL 78",IF(AND(E17="ROBBING",T17="L"),"RobC 80",IF(AND(E17="ROBBING",T17="S"),"RobS 79",0))))))))))))))) -> RobC 80 | G17: MAPAYO NOEL | H17: SHEPHERD AB 1 | I17: =CONCATENATE(B17,"_",C17,"_",D17,"_",E17) -> L05_JVFW_014W_WINZE STOPE | J17: L05_JVFW_014W_WINZE STOPE | K17: =IFERROR(MATCH(J17,'Final List'!$B$4:$B$252,0),0) -> 0 | L17: =IFERROR(MATCH(J17,'Final List'!$D$4:$D$252,0),0) -> 0 | M17: =IFERROR(MATCH(J17,'Final List'!$F$4:$F$251,0),0) -> 0 | N17: =IFERROR(MATCH(J17,'Final List'!$H$4:$H$252,0),0) -> 0 | O17: =IFERROR(MATCH(J17,'Final List'!$J$4:$J$252,0),0) -> 0 | P17: =IFERROR(MATCH(J17,'Final List'!$L$4:$L$252,0),0) -> 0 | Q17: =IFERROR(MATCH(J17,'Final List'!$N$4:$N$252,0),0) -> 0 | R17: =IFERROR(MATCH(J17,'Final List'!$P$4:$P$252,0),0) -> 0 | S17: =SUM(K17:R17) -> 0 | T17: S | V17: =IF(H17="",G17,H17) -> SHEPHERD AB 1 | W17: WPO
B18: L06 | C18: GHV | D18: 026E | E18: RAISE | F18: =IF(OR(E18="XCN",E18="DE",E18="DW",E18="DN",E18="XCS",E18="XCE",E18="XCW",E18="SUMP",E18="BYPASS",E18="CHAMBER",E18="DRAIN HOLE",E18="DRILLING CHAMBER",E18="DE_ISL",E18="DW_ISL",E18="REHAB"),"Dhoz 71",IF(OR(E18="RAISE",E18="RAISE_ISL"),"DVR 72",IF(E18="ALIMAK","DVA 73",IF(E18="WINZE","DVW 74",IF(E18="SHAFT","DVS 75",IF(AND(E18="WINZE STOPE",T18="S"),"RobC 80",IF(AND(E18="STOPE",T18="S"),"StpS 77",IF(AND(E18="WINZE STOPE",T18="L"),"RobC 80",IF(AND(E18="STOPE",T18="L"),"StpL 78",IF(AND(E18="WINZE STOPE PREP",T18="S"),"RobC 80",IF(AND(E18="STOPE PREP",T18="S"),"StpS 77",IF(AND(E18="WINZE STOPE PREP",T18="L"),"RobC 80",IF(AND(E18="STOPE PREP",T18="L"),"StpL 78",IF(AND(E18="ROBBING",T18="L"),"RobC 80",IF(AND(E18="ROBBING",T18="S"),"RobS 79",0))))))))))))))) -> DVR 72 | G18: REBOTE, JONATHAN 1 | I18: =CONCATENATE(B18,"_",C18,"_",D18,"_",E18) -> L06_GHV_026E_RAISE | J18: L06_GHV_026E_RAISE | K18: =IFERROR(MATCH(J18,'Final List'!$B$4:$B$252,0),0) -> 0 | L18: =IFERROR(MATCH(J18,'Final List'!$D$4:$D$252,0),0) -> 0 | M18: =IFERROR(MATCH(J18,'Final List'!$F$4:$F$251,0),0) -> 0 | N18: =IFERROR(MATCH(J18,'Final List'!$H$4:$H$252,0),0) -> 0 | O18: =IFERROR(MATCH(J18,'Final List'!$J$4:$J$252,0),0) -> 0 | P18: =IFERROR(MATCH(J18,'Final List'!$L$4:$L$252,0),0) -> 0 | Q18: =IFERROR(MATCH(J18,'Final List'!$N$4:$N$252,0),0) -> 0 | R18: =IFERROR(MATCH(J18,'Final List'!$P$4:$P$252,0),0) -> 0 | S18: =SUM(K18:R18) -> 0 | V18: =IF(H18="",G18,H18) -> REBOTE, JONATHAN 1 | W18: INC
B19: L06 | C19: CTV | D19: 002W | E19: STOPE | F19: =IF(OR(E19="XCN",E19="DE",E19="DW",E19="DN",E19="XCS",E19="XCE",E19="XCW",E19="SUMP",E19="BYPASS",E19="CHAMBER",E19="DRAIN HOLE",E19="DRILLING CHAMBER",E19="DE_ISL",E19="DW_ISL",E19="REHAB"),"Dhoz 71",IF(OR(E19="RAISE",E19="RAISE_ISL"),"DVR 72",IF(E19="ALIMAK","DVA 73",IF(E19="WINZE","DVW 74",IF(E19="SHAFT","DVS 75",IF(AND(E19="WINZE STOPE",T19="S"),"RobC 80",IF(AND(E19="STOPE",T19="S"),"StpS 77",IF(AND(E19="WINZE STOPE",T19="L"),"RobC 80",IF(AND(E19="STOPE",T19="L"),"StpL 78",IF(AND(E19="WINZE STOPE PREP",T19="S"),"RobC 80",IF(AND(E19="STOPE PREP",T19="S"),"StpS 77",IF(AND(E19="WINZE STOPE PREP",T19="L"),"RobC 80",IF(AND(E19="STOPE PREP",T19="L"),"StpL 78",IF(AND(E19="ROBBING",T19="L"),"RobC 80",IF(AND(E19="ROBBING",T19="S"),"RobS 79",0))))))))))))))) -> StpS 77 | G19: BAÑEZ 2 | I19: =CONCATENATE(B19,"_",C19,"_",D19,"_",E19) -> L06_CTV_002W_STOPE | J19: L06_CTV_002W_STOPE | K19: =IFERROR(MATCH(J19,'Final List'!$B$4:$B$252,0),0) -> 0 | L19: =IFERROR(MATCH(J19,'Final List'!$D$4:$D$252,0),0) -> 0 | M19: =IFERROR(MATCH(J19,'Final List'!$F$4:$F$251,0),0) -> 0 | N19: =IFERROR(MATCH(J19,'Final List'!$H$4:$H$252,0),0) -> 0 | O19: =IFERROR(MATCH(J19,'Final List'!$J$4:$J$252,0),0) -> 0 | P19: =IFERROR(MATCH(J19,'Final List'!$L$4:$L$252,0),0) -> 0 | Q19: =IFERROR(MATCH(J19,'Final List'!$N$4:$N$252,0),0) -> 0 | R19: =IFERROR(MATCH(J19,'Final List'!$P$4:$P$252,0),0) -> 0 | S19: =SUM(K19:R19) -> 0 | T19: S | V19: =IF(H19="",G19,H19) -> BAÑEZ 2 | W19: PO
B20: L06 | C20: JVFW | D20: 037E | E20: WINZE | F20: =IF(OR(E20="XCN",E20="DE",E20="DW",E20="DN",E20="XCS",E20="XCE",E20="XCW",E20="SUMP",E20="BYPASS",E20="CHAMBER",E20="DRAIN HOLE",E20="DRILLING CHAMBER",E20="DE_ISL",E20="DW_ISL",E20="REHAB"),"Dhoz 71",IF(OR(E20="RAISE",E20="RAISE_ISL"),"DVR 72",IF(E20="ALIMAK","DVA 73",IF(E20="WINZE","DVW 74",IF(E20="SHAFT","DVS 75",IF(AND(E20="WINZE STOPE",T20="S"),"RobC 80",IF(AND(E20="STOPE",T20="S"),"StpS 77",IF(AND(E20="WINZE STOPE",T20="L"),"RobC 80",IF(AND(E20="STOPE",T20="L"),"StpL 78",IF(AND(E20="WINZE STOPE PREP",T20="S"),"RobC 80",IF(AND(E20="STOPE PREP",T20="S"),"StpS 77",IF(AND(E20="WINZE STOPE PREP",T20="L"),"RobC 80",IF(AND(E20="STOPE PREP",T20="L"),"StpL 78",IF(AND(E20="ROBBING",T20="L"),"RobC 80",IF(AND(E20="ROBBING",T20="S"),"RobS 79",0))))))))))))))) -> DVW 74 | G20: SAMBERE 1 | H20: GUNAY 3 | I20: =CONCATENATE(B20,"_",C20,"_",D20,"_",E20) -> L06_JVFW_037E_WINZE | J20: L06_JVFW_037E_WINZE | K20: =IFERROR(MATCH(J20,'Final List'!$B$4:$B$252,0),0) -> 0 | L20: =IFERROR(MATCH(J20,'Final List'!$D$4:$D$252,0),0) -> 0 | M20: =IFERROR(MATCH(J20,'Final List'!$F$4:$F$251,0),0) -> 0 | N20: =IFERROR(MATCH(J20,'Final List'!$H$4:$H$252,0),0) -> 0 | O20: =IFERROR(MATCH(J20,'Final List'!$J$4:$J$252,0),0) -> 0 | P20: =IFERROR(MATCH(J20,'Final List'!$L$4:$L$252,0),0) -> 0 | Q20: =IFERROR(MATCH(J20,'Final List'!$N$4:$N$252,0),0) -> 0 | R20: =IFERROR(MATCH(J20,'Final List'!$P$4:$P$252,0),0) -> 0 | S20: =SUM(K20:R20) -> 0 | V20: =IF(H20="",G20,H20) -> GUNAY 3 | W20: FW
B21: L07 | C21: GHV | D21: 028W | E21: DE | F21: =IF(OR(E21="XCN",E21="DE",E21="DW",E21="DN",E21="XCS",E21="XCE",E21="XCW",E21="SUMP",E21="BYPASS",E21="CHAMBER",E21="DRAIN HOLE",E21="DRILLING CHAMBER",E21="DE_ISL",E21="DW_ISL",E21="REHAB"),"Dhoz 71",IF(OR(E21="RAISE",E21="RAISE_ISL"),"DVR 72",IF(E21="ALIMAK","DVA 73",IF(E21="WINZE","DVW 74",IF(E21="SHAFT","DVS 75",IF(AND(E21="WINZE STOPE",T21="S"),"RobC 80",IF(AND(E21="STOPE",T21="S"),"StpS 77",IF(AND(E21="WINZE STOPE",T21="L"),"RobC 80",IF(AND(E21="STOPE",T21="L"),"StpL 78",IF(AND(E21="WINZE STOPE PREP",T21="S"),"RobC 80",IF(AND(E21="STOPE PREP",T21="S"),"StpS 77",IF(AND(E21="WINZE STOPE PREP",T21="L"),"RobC 80",IF(AND(E21="STOPE PREP",T21="L"),"StpL 78",IF(AND(E21="ROBBING",T21="L"),"RobC 80",IF(AND(E21="ROBBING",T21="S"),"RobS 79",0))))))))))))))) -> Dhoz 71 | G21: FERNANDEZ 2 | I21: =CONCATENATE(B21,"_",C21,"_",D21,"_",E21) -> L07_GHV_028W_DE | J21: L07_GHV_028W_DE | K21: =IFERROR(MATCH(J21,'Final List'!$B$4:$B$252,0),0) -> 0 | L21: =IFERROR(MATCH(J21,'Final List'!$D$4:$D$252,0),0) -> 0 | M21: =IFERROR(MATCH(J21,'Final List'!$F$4:$F$251,0),0) -> 0 | N21: =IFERROR(MATCH(J21,'Final List'!$H$4:$H$252,0),0) -> 0 | O21: =IFERROR(MATCH(J21,'Final List'!$J$4:$J$252,0),0) -> 0 | P21: =IFERROR(MATCH(J21,'Final List'!$L$4:$L$252,0),0) -> 0 | Q21: =IFERROR(MATCH(J21,'Final List'!$N$4:$N$252,0),0) -> 0 | R21: =IFERROR(MATCH(J21,'Final List'!$P$4:$P$252,0),0) -> 0 | S21: =SUM(K21:R21) -> 0 | V21: =IF(H21="",G21,H21) -> FERNANDEZ 2 | W21: D-2
B22: L07 | C22: CTV | D22: 015E | E22: DW | F22: =IF(OR(E22="XCN",E22="DE",E22="DW",E22="DN",E22="XCS",E22="XCE",E22="XCW",E22="SUMP",E22="BYPASS",E22="CHAMBER",E22="DRAIN HOLE",E22="DRILLING CHAMBER",E22="DE_ISL",E22="DW_ISL",E22="REHAB"),"Dhoz 71",IF(OR(E22="RAISE",E22="RAISE_ISL"),"DVR 72",IF(E22="ALIMAK","DVA 73",IF(E22="WINZE","DVW 74",IF(E22="SHAFT","DVS 75",IF(AND(E22="WINZE STOPE",T22="S"),"RobC 80",IF(AND(E22="STOPE",T22="S"),"StpS 77",IF(AND(E22="WINZE STOPE",T22="L"),"RobC 80",IF(AND(E22="STOPE",T22="L"),"StpL 78",IF(AND(E22="WINZE STOPE PREP",T22="S"),"RobC 80",IF(AND(E22="STOPE PREP",T22="S"),"StpS 77",IF(AND(E22="WINZE STOPE PREP",T22="L"),"RobC 80",IF(AND(E22="STOPE PREP",T22="L"),"StpL 78",IF(AND(E22="ROBBING",T22="L"),"RobC 80",IF(AND(E22="ROBBING",T22="S"),"RobS 79",0))))))))))))))) -> Dhoz 71 | G22: UDLOS 1 | H22: TURRA 1 | I22: =CONCATENATE(B22,"_",C22,"_",D22,"_",E22) -> L07_CTV_015E_DW | J22: L07_CTV_015E_DW | K22: =IFERROR(MATCH(J22,'Final List'!$B$4:$B$252,0),0) -> 0 | L22: =IFERROR(MATCH(J22,'Final List'!$D$4:$D$252,0),0) -> 0 | M22: =IFERROR(MATCH(J22,'Final List'!$F$4:$F$251,0),0) -> 0 | N22: =IFERROR(MATCH(J22,'Final List'!$H$4:$H$252,0),0) -> 0 | O22: =IFERROR(MATCH(J22,'Final List'!$J$4:$J$252,0),0) -> 0 | P22: =IFERROR(MATCH(J22,'Final List'!$L$4:$L$252,0),0) -> 0 | Q22: =IFERROR(MATCH(J22,'Final List'!$N$4:$N$252,0),0) -> 0 | R22: =IFERROR(MATCH(J22,'Final List'!$P$4:$P$252,0),0) -> 0 | S22: =SUM(K22:R22) -> 0 | V22: =IF(H22="",G22,H22) -> TURRA 1 | W22: ISL
